Workbook

Sheet IN x Localidad NATI
A1: Programas provinciales - Dirección General de Vivienda
A2: Ingreso de Datos
C3: LOCALIDAD: | D3: Olaeta | E3: ⬅️ solamente ELEGIR LOCALIDAD
C4: DEPARTAMENTO: | D4: =IFERROR(VLOOKUP($D$3,'Base TOTAL'!A:AJ,2,0), "Sin dato") -> Juárez Celman
C5: Datos actuales | D5: Modificar/Ingresar nuevo dato
A6: PROGRAMA PROVINCIAL DE CORDÓN CUNETA Y ADOQUINES - LEY Nº 11089
B7: EXPEDIENTE N° | C7: =LET(res, IFERROR(VLOOKUP($D$3,'Base TOTAL'!A:AJ,3,0),""), IF(res="", "Sin datos", res)) -> 0423-080117/2026
B8: N° Orden | C8: =LET(res, IFERROR(VLOOKUP($D$3,'Base TOTAL'!A:AJ,4,0),""), IF(res="", "Sin datos", res)) -> 42
B9: MUNICIPIO / COMUNA | C9: =LET(res, IFERROR(VLOOKUP($D$3,'Base TOTAL'!A:AJ,5,0),""), IF(res="", "Sin datos", res)) -> M
B10: INTENDENTE / PRESIDENTE COMUNAL | C10: =LET(res, IFERROR(VLOOKUP($D$3,'Base TOTAL'!A:AJ,6,0),""), IF(res="", "Sin datos", res)) -> Gaston Bravo
B11: N° TELÉFONO M/C | C11: =LET(res, IFERROR(VLOOKUP($D$3,'Base TOTAL'!A:AJ,7,0),""), IF(res="", "Sin datos", res)) -> 3586543232
B12: CORREO ELECTRÓNICO | C12: =LET(res, IFERROR(VLOOKUP($D$3,'Base TOTAL'!A:AJ,8,0),""), IF(res="", "Sin datos", res)) -> arquitecturaolaeta@gmail.com
B13: CONTACTO TÉCNICO de M/C | C13: =LET(res, IFERROR(VLOOKUP($D$3,'Base TOTAL'!A:AJ,9,0),""), IF(res="", "Sin datos", res)) -> arquitecturaolaeta@gmail.com
A14: CONVENIO | B14: MONTO CONVENIO | C14: =LET(res, IFERROR(VLOOKUP($D$3,'Base TOTAL'!A:AJ,10,0),""), IF(res="", "Sin datos", res)) -> 180000000
B15: Cordón Cuneta (ml) | C15: =LET(res, IFERROR(VLOOKUP($D$3,'Base TOTAL'!A:AJ,11,0),""), IF(res="", "Sin datos", res)) -> 496
B16: Adoquinado (m2) | C16: =LET(res, IFERROR(VLOOKUP($D$3,'Base TOTAL'!A:AJ,12,0),""), IF(res="", "Sin datos", res)) -> 3200
A17: DOCUMENTACIÓN A PRESENTAR por Municipio / Comuna | B17: 1 | C17: =LET(res, IFERROR(VLOOKUP($D$3,'Base TOTAL'!A:AJ,13,0),""), IF(res="", "Sin datos", res)) -> A corregir por M/C
B18: 2 | C18: =LET(res, IFERROR(VLOOKUP($D$3,'Base TOTAL'!A:AJ,14,0),""), IF(res="", "Sin datos", res)) -> Completo OK
B19: 3 | C19: =LET(res, IFERROR(VLOOKUP($D$3,'Base TOTAL'!A:AJ,15,0),""), IF(res="", "Sin datos", res)) -> Completo OK
B20: 4 | C20: =LET(res, IFERROR(VLOOKUP($D$3,'Base TOTAL'!A:AJ,16,0),""), IF(res="", "Sin datos", res)) -> A corregir por M/C
B21: Descripción General | C21: =LET(res, IFERROR(VLOOKUP($D$3,'Base TOTAL'!A:AJ,17,0),""), IF(res="", "Sin datos", res)) -> A corregir por M/C
B22: Memoria Técnica | C22: =LET(res, IFERROR(VLOOKUP($D$3,'Base TOTAL'!A:AJ,18,0),""), IF(res="", "Sin datos", res)) -> A corregir por M/C
B23: Plazo de Ejecución | C23: =LET(res, IFERROR(VLOOKUP($D$3,'Base TOTAL'!A:AJ,19,0),""), IF(res="", "Sin datos", res)) -> Completo OK
B24: Cómputo y Presupuesto | C24: =LET(res, IFERROR(VLOOKUP($D$3,'Base TOTAL'!A:AJ,20,0),""), IF(res="", "Sin datos", res)) -> Completo OK
B25: Cronograma Avance Obra | C25: =LET(res, IFERROR(VLOOKUP($D$3,'Base TOTAL'!A:AJ,21,0),""), IF(res="", "Sin datos", res)) -> Completo OK
B26: Planimetría | C26: =LET(res, IFERROR(VLOOKUP($D$3,'Base TOTAL'!A:AJ,22,0),""), IF(res="", "Sin datos", res)) -> Completo OK
B27: Perfil Calzada | C27: =LET(res, IFERROR(VLOOKUP($D$3,'Base TOTAL'!A:AJ,23,0),""), IF(res="", "Sin datos", res)) -> A corregir por M/C
B28: Detalle de Cordón Cuneta | C28: =LET(res, IFERROR(VLOOKUP($D$3,'Base TOTAL'!A:AJ,24,0),""), IF(res="", "Sin datos", res)) -> Completo OK
B29: Detalle de Badén | C29: =LET(res, IFERROR(VLOOKUP($D$3,'Base TOTAL'!A:AJ,25,0),""), IF(res="", "Sin datos", res)) -> Completo OK
B30: Paquete estr. Calzada | C30: =LET(res, IFERROR(VLOOKUP($D$3,'Base TOTAL'!A:AJ,26,0),""), IF(res="", "Sin datos", res)) -> Completo OK
B31: 5 | C31: =LET(res, IFERROR(VLOOKUP($D$3,'Base TOTAL'!A:AJ,27,0),""), IF(res="", "Sin datos", res)) -> A corregir por M/C
B32: 6 | C32: =LET(res, IFERROR(VLOOKUP($D$3,'Base TOTAL'!A:AJ,28,0),""), IF(res="", "Sin datos", res)) -> Completo OK
B33: 7 | C33: =LET(res, IFERROR(VLOOKUP($D$3,'Base TOTAL'!A:AJ,29,0),""), IF(res="", "Sin datos", res)) -> Completo OK
B34: 8 | C34: =LET(res, IFERROR(VLOOKUP($D$3,'Base TOTAL'!A:AJ,30,0),""), IF(res="", "Sin datos", res)) -> Completo OK
B35: 9 | C35: =LET(res, IFERROR(VLOOKUP($D$3,'Base TOTAL'!A:AJ,31,0),""), IF(res="", "Sin datos", res)) -> A corregir por M/C
B36: ESTADO DEL EXPEDIENTE DE LA LOCALIDAD | C36: =LET(res, IFERROR(VLOOKUP($D$3,'Base TOTAL'!A:AJ,32,0),""), IF(res="", "Sin datos", res)) -> En CURSO en DGV
A37: OBSERVACIONES | C37: =LET(res, IFERROR(VLOOKUP($D$3,'Base TOTAL'!A:AJ,33,0),""), IF(res="", "Sin datos", res)) -> 13/7/2026: Comunicaciòn con la arq. a cargo. Se hacen observaciones sobre doc. tècnica a corregir. 08/7/2026: Se envìa al municipio (por Email) las correcciones que deben realizar. 03/7/2026: Presentan documentaciòn en Evaluaciòn. 19/6/26: El municipio presenta documentación a corregir y completar. Se envía INSTRUCTIVO de la documentación legar y técnica requerida. 5/6/26: Ingresa Nota Ministerio Gobierno autorizando financiamiento.
A38: EXPEDIENTE RADICADO EN: | B38: FECHA | C38: =LET(res, IFERROR(VLOOKUP($D$3,'Base TOTAL'!A:AJ,34,0),""), IF(res="", "Sin datos", res)) -> 46192
B39: REPARTICIÓN | C39: =LET(res, IFERROR(VLOOKUP($D$3,'Base TOTAL'!A:AJ,35,0),""), IF(res="", "Sin datos", res)) -> Técnica DGV
A40: PROGRAMA CÓRDOBA HOGAR - LEY Nº 8663
B41: EXPEDIENTE N°
B42: N° Orden
B43: MUNICIPIO / COMUNA
B44: INTENDENTE / PRESIDENTE COMUNAL
B45: N° TELÉFONO M/C
B46: CORREO ELECTRÓNICO
B47: CONTACTO TÉCNICO de M/C
A48: CONVENIO | B48: MONTO CONVENIO
B49: Cantidad de Viviendas

Sheet IN x Localidad PABLO
A1: Programas provinciales - Dirección General de Vivienda
A2: Ingreso de Datos
C3: LOCALIDAD: | D3: Las Playas | E3: ⬅️ solamente ELEGIR LOCALIDAD
C4: DEPARTAMENTO: | D4: =IFERROR(VLOOKUP($D$3,'Base TOTAL'!A:AJ,2,0), "Sin dato") -> Cruz del Eje
C5: Datos actuales | D5: Modificar/Ingresar nuevo dato
A6: PROGRAMA PROVINCIAL DE CORDÓN CUNETA Y ADOQUINES - LEY Nº 11089
B7: EXPEDIENTE N° | C7: =LET(res, IFERROR(VLOOKUP($D$3,'Base TOTAL'!A:AJ,3,0),""), IF(res="", "Sin datos", res)) -> 0423-079112/2026
B8: N° Orden | C8: =LET(res, IFERROR(VLOOKUP($D$3,'Base TOTAL'!A:AJ,4,0),""), IF(res="", "Sin datos", res)) -> 8
B9: MUNICIPIO / COMUNA | C9: =LET(res, IFERROR(VLOOKUP($D$3,'Base TOTAL'!A:AJ,5,0),""), IF(res="", "Sin datos", res)) -> C
B10: INTENDENTE / PRESIDENTE COMUNAL | C10: =LET(res, IFERROR(VLOOKUP($D$3,'Base TOTAL'!A:AJ,6,0),""), IF(res="", "Sin datos", res)) -> MARÍA DANIELA GODOY
B11: N° TELÉFONO M/C | C11: =LET(res, IFERROR(VLOOKUP($D$3,'Base TOTAL'!A:AJ,7,0),""), IF(res="", "Sin datos", res)) -> (3549) 46-8032
B12: CORREO ELECTRÓNICO | C12: =LET(res, IFERROR(VLOOKUP($D$3,'Base TOTAL'!A:AJ,8,0),""), IF(res="", "Sin datos", res)) -> Danielagodoy79@gmail.com
B13: CONTACTO TÉCNICO de M/C | C13: =LET(res, IFERROR(VLOOKUP($D$3,'Base TOTAL'!A:AJ,9,0),""), IF(res="", "Sin datos", res)) -> Ing. Bracamonte 3521401659 ---ingbracamontegustavo@gmail.com
A14: CONVENIO | B14: MONTO CONVENIO | C14: =LET(res, IFERROR(VLOOKUP($D$3,'Base TOTAL'!A:AJ,10,0),""), IF(res="", "Sin datos", res)) -> 200000000
B15: Cordón Cuneta (ml) | C15: =LET(res, IFERROR(VLOOKUP($D$3,'Base TOTAL'!A:AJ,11,0),""), IF(res="", "Sin datos", res)) -> Sin datos
B16: Adoquinado (m2) | C16: =LET(res, IFERROR(VLOOKUP($D$3,'Base TOTAL'!A:AJ,12,0),""), IF(res="", "Sin datos", res)) -> 3922.22
A17: DOCUMENTACIÓN A PRESENTAR por Municipio / Comuna | B17: 1 | C17: =LET(res, IFERROR(VLOOKUP($D$3,'Base TOTAL'!A:AJ,13,0),""), IF(res="", "Sin datos", res)) -> A corregir por M/C
B18: 2 | C18: =LET(res, IFERROR(VLOOKUP($D$3,'Base TOTAL'!A:AJ,14,0),""), IF(res="", "Sin datos", res)) -> Completo OK
B19: 3 | C19: =LET(res, IFERROR(VLOOKUP($D$3,'Base TOTAL'!A:AJ,15,0),""), IF(res="", "Sin datos", res)) -> Completo OK
B20: 4 | C20: =LET(res, IFERROR(VLOOKUP($D$3,'Base TOTAL'!A:AJ,16,0),""), IF(res="", "Sin datos", res)) -> A corregir por M/C
B21: Descripción General | C21: =LET(res, IFERROR(VLOOKUP($D$3,'Base TOTAL'!A:AJ,17,0),""), IF(res="", "Sin datos", res)) -> A corregir por M/C
B22: Memoria Técnica | C22: =LET(res, IFERROR(VLOOKUP($D$3,'Base TOTAL'!A:AJ,18,0),""), IF(res="", "Sin datos", res)) -> A corregir por M/C
B23: Plazo de Ejecución | C23: =LET(res, IFERROR(VLOOKUP($D$3,'Base TOTAL'!A:AJ,19,0),""), IF(res="", "Sin datos", res)) -> A corregir por M/C
B24: Cómputo y Presupuesto | C24: =LET(res, IFERROR(VLOOKUP($D$3,'Base TOTAL'!A:AJ,20,0),""), IF(res="", "Sin datos", res)) -> A corregir por M/C
B25: Cronograma Avance Obra | C25: =LET(res, IFERROR(VLOOKUP($D$3,'Base TOTAL'!A:AJ,21,0),""), IF(res="", "Sin datos", res)) -> Sin Presentar
B26: Planimetría | C26: =LET(res, IFERROR(VLOOKUP($D$3,'Base TOTAL'!A:AJ,22,0),""), IF(res="", "Sin datos", res)) -> A corregir por M/C
B27: Perfil Calzada | C27: =LET(res, IFERROR(VLOOKUP($D$3,'Base TOTAL'!A:AJ,23,0),""), IF(res="", "Sin datos", res)) -> A corregir por M/C
B28: Detalle de Cordón Cuneta | C28: =LET(res, IFERROR(VLOOKUP($D$3,'Base TOTAL'!A:AJ,24,0),""), IF(res="", "Sin datos", res)) -> Sin Presentar
B29: Detalle de Badén | C29: =LET(res, IFERROR(VLOOKUP($D$3,'Base TOTAL'!A:AJ,25,0),""), IF(res="", "Sin datos", res)) -> Sin Presentar
B30: Paquete estr. Calzada | C30: =LET(res, IFERROR(VLOOKUP($D$3,'Base TOTAL'!A:AJ,26,0),""), IF(res="", "Sin datos", res)) -> A corregir por M/C
B31: 5 | C31: =LET(res, IFERROR(VLOOKUP($D$3,'Base TOTAL'!A:AJ,27,0),""), IF(res="", "Sin datos", res)) -> Completo OK
B32: 6 | C32: =LET(res, IFERROR(VLOOKUP($D$3,'Base TOTAL'!A:AJ,28,0),""), IF(res="", "Sin datos", res)) -> Completo OK
B33: 7 | C33: =LET(res, IFERROR(VLOOKUP($D$3,'Base TOTAL'!A:AJ,29,0),""), IF(res="", "Sin datos", res)) -> Completo OK
B34: 8 | C34: =LET(res, IFERROR(VLOOKUP($D$3,'Base TOTAL'!A:AJ,30,0),""), IF(res="", "Sin datos", res)) -> Completo OK
B35: 9 | C35: =LET(res, IFERROR(VLOOKUP($D$3,'Base TOTAL'!A:AJ,31,0),""), IF(res="", "Sin datos", res)) -> Completo OK
B36: ESTADO DEL EXPEDIENTE DE LA LOCALIDAD | C36: =LET(res, IFERROR(VLOOKUP($D$3,'Base TOTAL'!A:AJ,32,0),""), IF(res="", "Sin datos", res)) -> En CURSO en DGV
A37: OBSERVACIONES | C37: =LET(res, IFERROR(VLOOKUP($D$3,'Base TOTAL'!A:AJ,33,0),""), IF(res="", "Sin datos", res)) -> 13-7-2026: Se recibe de la intend. doc. por whast y se solicita que se envie en base a instructivo y por E mail. 13-7-2026: Se llamo al ing. quien avisa que el viernes enviò la doc. a la municip y mañana la envian firmada 13/7/2026: Se solicita informen còmo van con la documentaciòn a presentar. 29/6/2026: Se enviaron por Email las observaciones A corregir por la comuna 26/6/26: Se envían las observaciones a corregir por el ing. Se aguardan las observaciones del area Legales........22/6/26: El ing. se comunica con el àrea tècnica: Se le envìa el Instructivo de la documentaciòn legal y tècnica a presentar. 19/6/26: Sin respuesta del ing. a cargo, se envìa nuevamente el instructivo a la Pres. comunal. 11/6/26: Se solicita corregir documentación presentada. SE LE ENVIÓ LOS 9 REQUISITOS PARA PARTICIPAR EN EL PROGRAMA
A38: EXPEDIENTE RADICADO EN: | B38: FECHA | C38: =LET(res, IFERROR(VLOOKUP($D$3,'Base TOTAL'!A:AJ,34,0),""), IF(res="", "Sin datos", res)) -> 46139
B39: REPARTICIÓN | C39: =LET(res, IFERROR(VLOOKUP($D$3,'Base TOTAL'!A:AJ,35,0),""), IF(res="", "Sin datos", res)) -> Técnica DGV
A40: PROGRAMA CÓRDOBA HOGAR - LEY Nº 8663
B41: EXPEDIENTE N°
B42: N° Orden
B43: MUNICIPIO / COMUNA
B44: INTENDENTE / PRESIDENTE COMUNAL
B45: N° TELÉFONO M/C
B46: CORREO ELECTRÓNICO
B47: CONTACTO TÉCNICO de M/C
A48: CONVENIO | B48: MONTO CONVENIO
B49: Cantidad de Viviendas

Sheet IN x Localidad H
A1: Programas provinciales - Dirección General de Vivienda
A2: Ingreso de Datos
C3: LOCALIDAD: | D3: Villa Sarmiento | E3: ⬅️ solamente ELEGIR LOCALIDAD
C4: DEPARTAMENTO: | D4: =IFERROR(VLOOKUP($D$3,'Base TOTAL'!A:AJ,2,0), "Sin dato") -> General Roca
C5: Datos actuales | D5: Modificar/Ingresar nuevo dato
A6: PROGRAMA PROVINCIAL DE CORDÓN CUNETA Y ADOQUINES - LEY Nº 11089
B7: EXPEDIENTE N° | C7: =LET(res, IFERROR(VLOOKUP($D$3,'Base TOTAL'!A:AJ,3,0),""), IF(res="", "Sin datos", res)) -> 0423-079096/2026
B8: N° Orden | C8: =LET(res, IFERROR(VLOOKUP($D$3,'Base TOTAL'!A:AJ,4,0),""), IF(res="", "Sin datos", res)) -> 14
B9: MUNICIPIO / COMUNA | C9: =LET(res, IFERROR(VLOOKUP($D$3,'Base TOTAL'!A:AJ,5,0),""), IF(res="", "Sin datos", res)) -> C
B10: INTENDENTE / PRESIDENTE COMUNAL | C10: =LET(res, IFERROR(VLOOKUP($D$3,'Base TOTAL'!A:AJ,6,0),""), IF(res="", "Sin datos", res)) -> OSVALDO ESTRADA
B11: N° TELÉFONO M/C | C11: =LET(res, IFERROR(VLOOKUP($D$3,'Base TOTAL'!A:AJ,7,0),""), IF(res="", "Sin datos", res)) -> (3583) 43-0074
B12: CORREO ELECTRÓNICO | C12: =LET(res, IFERROR(VLOOKUP($D$3,'Base TOTAL'!A:AJ,8,0),""), IF(res="", "Sin datos", res)) -> _
B13: CONTACTO TÉCNICO de M/C | C13: =LET(res, IFERROR(VLOOKUP($D$3,'Base TOTAL'!A:AJ,9,0),""), IF(res="", "Sin datos", res)) -> rojobufa@gmail.com
A14: CONVENIO | B14: MONTO CONVENIO | C14: =LET(res, IFERROR(VLOOKUP($D$3,'Base TOTAL'!A:AJ,10,0),""), IF(res="", "Sin datos", res)) -> 210000000
B15: Cordón Cuneta (ml) | C15: =LET(res, IFERROR(VLOOKUP($D$3,'Base TOTAL'!A:AJ,11,0),""), IF(res="", "Sin datos", res)) -> 1530
B16: Adoquinado (m2) | C16: =LET(res, IFERROR(VLOOKUP($D$3,'Base TOTAL'!A:AJ,12,0),""), IF(res="", "Sin datos", res)) -> 1575
A17: DOCUMENTACIÓN A PRESENTAR por Municipio / Comuna | B17: 1 | C17: =LET(res, IFERROR(VLOOKUP($D$3,'Base TOTAL'!A:AJ,13,0),""), IF(res="", "Sin datos", res)) -> Completo OK
B18: 2 | C18: =LET(res, IFERROR(VLOOKUP($D$3,'Base TOTAL'!A:AJ,14,0),""), IF(res="", "Sin datos", res)) -> Completo OK
B19: 3 | C19: =LET(res, IFERROR(VLOOKUP($D$3,'Base TOTAL'!A:AJ,15,0),""), IF(res="", "Sin datos", res)) -> A corregir por M/C
B20: 4 | C20: =LET(res, IFERROR(VLOOKUP($D$3,'Base TOTAL'!A:AJ,16,0),""), IF(res="", "Sin datos", res)) -> A corregir por M/C
B21: Descripción General | C21: =LET(res, IFERROR(VLOOKUP($D$3,'Base TOTAL'!A:AJ,17,0),""), IF(res="", "Sin datos", res)) -> Completo OK
B22: Memoria Técnica | C22: =LET(res, IFERROR(VLOOKUP($D$3,'Base TOTAL'!A:AJ,18,0),""), IF(res="", "Sin datos", res)) -> Completo OK
B23: Plazo de Ejecución | C23: =LET(res, IFERROR(VLOOKUP($D$3,'Base TOTAL'!A:AJ,19,0),""), IF(res="", "Sin datos", res)) -> Sin Presentar
B24: Cómputo y Presupuesto | C24: =LET(res, IFERROR(VLOOKUP($D$3,'Base TOTAL'!A:AJ,20,0),""), IF(res="", "Sin datos", res)) -> Completo OK
B25: Cronograma Avance Obra | C25: =LET(res, IFERROR(VLOOKUP($D$3,'Base TOTAL'!A:AJ,21,0),""), IF(res="", "Sin datos", res)) -> Completo OK
B26: Planimetría | C26: =LET(res, IFERROR(VLOOKUP($D$3,'Base TOTAL'!A:AJ,22,0),""), IF(res="", "Sin datos", res)) -> A corregir por M/C
B27: Perfil Calzada | C27: =LET(res, IFERROR(VLOOKUP($D$3,'Base TOTAL'!A:AJ,23,0),""), IF(res="", "Sin datos", res)) -> Sin Presentar
B28: Detalle de Cordón Cuneta | C28: =LET(res, IFERROR(VLOOKUP($D$3,'Base TOTAL'!A:AJ,24,0),""), IF(res="", "Sin datos", res)) -> Completo OK
B29: Detalle de Badén | C29: =LET(res, IFERROR(VLOOKUP($D$3,'Base TOTAL'!A:AJ,25,0),""), IF(res="", "Sin datos", res)) -> Completo OK
B30: Paquete estr. Calzada | C30: =LET(res, IFERROR(VLOOKUP($D$3,'Base TOTAL'!A:AJ,26,0),""), IF(res="", "Sin datos", res)) -> Completo OK
B31: 5 | C31: =LET(res, IFERROR(VLOOKUP($D$3,'Base TOTAL'!A:AJ,27,0),""), IF(res="", "Sin datos", res)) -> Completo OK
B32: 6 | C32: =LET(res, IFERROR(VLOOKUP($D$3,'Base TOTAL'!A:AJ,28,0),""), IF(res="", "Sin datos", res)) -> Completo OK
B33: 7 | C33: =LET(res, IFERROR(VLOOKUP($D$3,'Base TOTAL'!A:AJ,29,0),""), IF(res="", "Sin datos", res)) -> Completo OK
B34: 8 | C34: =LET(res, IFERROR(VLOOKUP($D$3,'Base TOTAL'!A:AJ,30,0),""), IF(res="", "Sin datos", res)) -> Completo OK
B35: 9 | C35: =LET(res, IFERROR(VLOOKUP($D$3,'Base TOTAL'!A:AJ,31,0),""), IF(res="", "Sin datos", res)) -> Completo OK
B36: ESTADO DEL EXPEDIENTE DE LA LOCALIDAD | C36: =LET(res, IFERROR(VLOOKUP($D$3,'Base TOTAL'!A:AJ,32,0),""), IF(res="", "Sin datos", res)) -> En CURSO en DGV
A37: OBSERVACIONES | C37: =LET(res, IFERROR(VLOOKUP($D$3,'Base TOTAL'!A:AJ,33,0),""), IF(res="", "Sin datos", res)) -> 03-07-2026 Completar: - Pto. 3 en Declarac. Jurada y.... Se deberà colocar las Geo Referenc. en los domicilios que figuren como (calle Publica sin Numero y tambien en los de Zona Rural) - En la Memoria pto. 3 colocar PLAZO de OBRA (Ver instruct.) -En ambas PLANIM. Generales colocar (Geo Referenc. y Medidas generales Largo y ancho de las calles del proyecto). - Presentar DETALLE Perfil Transversal de Calzada) Ver instructivo. - 30/6/2026: Se solicito por email envien imagen de DNI y CBU con mas definicion. el resto de la documentación esta completa. 19-06-2026- Se solicita al arq. Buffa ( 1CBU Y2 DNI borrosos + 3Sobre las Planim. Gral coloque las Geo Refer de los 3 sectores de obra + 4 faltan Perfil transv de calzada ) 12-06-2026 Se pidio al arq. R.Buffa estos faltantes + Georef. en pl. gral. --RTA.: 11-06-2026 de esta correc. solo faltan en TECNICA (agregar cortes transv. de calz. + detalle de paquete estr. de calz + detalles de cordones cun y badenes lo demas correcto) + en LEG ( en Nota contad pto 5 cambiar el plazo a 180 dias) -22-06-2026 - 04-06-2026 - Deben completar (Pto 4- graficos Detalles de Perfiles transv. de calzada + detalle graf. de cordon cuneta + secc transv. de de vaden + Pto. Nª 9 Acta de proclamac cantidad de votos?..Preguntar a Natalia) Ya ajustó los montos… Pasó $236.529.986,60 y debe ser de $210.000.000 - Debe cambiar Nota Inicial, dice plazo obra 365 días y debe decir 180 días El 29/05/26 ingresa nva. Nota digi 0697832111-126 (La parte técnica ya está ok - Pero falta cambiar: Plazo de Obra, en Nota inicial) YA LO CAMBIÓ Y ENVIÓ 29/5/26 El 26/05/26 se recibe nueva documentación. ¡Se excede del monto estipulado! Debe calcular ENVIÓ DOCUMENTACIÓN PARA SER ANALIZADA. El 12/5/26 se envía correcciones técnicas y documentación gráfica y planillas modelo, para realizar nueva presentación.
A38: EXPEDIENTE RADICADO EN: | B38: FECHA | C38: =LET(res, IFERROR(VLOOKUP($D$3,'Base TOTAL'!A:AJ,34,0),""), IF(res="", "Sin datos", res)) -> 46139
B39: REPARTICIÓN | C39: =LET(res, IFERROR(VLOOKUP($D$3,'Base TOTAL'!A:AJ,35,0),""), IF(res="", "Sin datos", res)) -> Técnica DGV
A40: PROGRAMA CÓRDOBA HOGAR - LEY Nº 8663
B41: EXPEDIENTE N°
B42: N° Orden
B43: MUNICIPIO / COMUNA
B44: INTENDENTE / PRESIDENTE COMUNAL
B45: N° TELÉFONO M/C
B46: CORREO ELECTRÓNICO
B47: CONTACTO TÉCNICO de M/C
A48: CONVENIO | B48: MONTO CONVENIO
B49: Cantidad de Viviendas

Sheet IN x Localidad BETINA
A1: Programas provinciales - Dirección General de Vivienda
A2: Ingreso de Datos
C3: LOCALIDAD: | D3: Los Reartes | E3: ⬅️ solamente ELEGIR LOCALIDAD
C4: DEPARTAMENTO: | D4: =IFERROR(VLOOKUP($D$3,'Base TOTAL'!A:AJ,2,0), "Sin dato") -> Calamuchita
C5: Datos actuales | D5: Modificar/Ingresar nuevo dato
A6: PROGRAMA PROVINCIAL DE CORDÓN CUNETA Y ADOQUINES - LEY Nº 11089
B7: EXPEDIENTE N° | C7: =LET(res, IFERROR(VLOOKUP($D$3,'Base TOTAL'!A:AJ,3,0),""), IF(res="", "Sin datos", res)) -> 0423-080115/2026
B8: N° Orden | C8: =LET(res, IFERROR(VLOOKUP($D$3,'Base TOTAL'!A:AJ,4,0),""), IF(res="", "Sin datos", res)) -> 39
B9: MUNICIPIO / COMUNA | C9: =LET(res, IFERROR(VLOOKUP($D$3,'Base TOTAL'!A:AJ,5,0),""), IF(res="", "Sin datos", res)) -> Sin datos
B10: INTENDENTE / PRESIDENTE COMUNAL | C10: =LET(res, IFERROR(VLOOKUP($D$3,'Base TOTAL'!A:AJ,6,0),""), IF(res="", "Sin datos", res)) -> Sin datos
B11: N° TELÉFONO M/C | C11: =LET(res, IFERROR(VLOOKUP($D$3,'Base TOTAL'!A:AJ,7,0),""), IF(res="", "Sin datos", res)) -> Sin datos
B12: CORREO ELECTRÓNICO | C12: =LET(res, IFERROR(VLOOKUP($D$3,'Base TOTAL'!A:AJ,8,0),""), IF(res="", "Sin datos", res)) -> inesramello@losreartes.gob.ar
B13: CONTACTO TÉCNICO de M/C | C13: =LET(res, IFERROR(VLOOKUP($D$3,'Base TOTAL'!A:AJ,9,0),""), IF(res="", "Sin datos", res)) -> Ing. Martin Gallo 351-6645348 Mail: martingallo2012@gmail.com
A14: CONVENIO | B14: MONTO CONVENIO | C14: =LET(res, IFERROR(VLOOKUP($D$3,'Base TOTAL'!A:AJ,10,0),""), IF(res="", "Sin datos", res)) -> 100000000
B15: Cordón Cuneta (ml) | C15: =LET(res, IFERROR(VLOOKUP($D$3,'Base TOTAL'!A:AJ,11,0),""), IF(res="", "Sin datos", res)) -> 418
B16: Adoquinado (m2) | C16: =LET(res, IFERROR(VLOOKUP($D$3,'Base TOTAL'!A:AJ,12,0),""), IF(res="", "Sin datos", res)) -> 1379
A17: DOCUMENTACIÓN A PRESENTAR por Municipio / Comuna | B17: 1 | C17: =LET(res, IFERROR(VLOOKUP($D$3,'Base TOTAL'!A:AJ,13,0),""), IF(res="", "Sin datos", res)) -> En Evaluaciòn Jurìdico
B18: 2 | C18: =LET(res, IFERROR(VLOOKUP($D$3,'Base TOTAL'!A:AJ,14,0),""), IF(res="", "Sin datos", res)) -> En Evaluaciòn Jurìdico
B19: 3 | C19: =LET(res, IFERROR(VLOOKUP($D$3,'Base TOTAL'!A:AJ,15,0),""), IF(res="", "Sin datos", res)) -> En Evaluaciòn Jurìdico
B20: 4 | C20: =LET(res, IFERROR(VLOOKUP($D$3,'Base TOTAL'!A:AJ,16,0),""), IF(res="", "Sin datos", res)) -> A corregir por M/C
B21: Descripción General | C21: =LET(res, IFERROR(VLOOKUP($D$3,'Base TOTAL'!A:AJ,17,0),""), IF(res="", "Sin datos", res)) -> A corregir por M/C
B22: Memoria Técnica | C22: =LET(res, IFERROR(VLOOKUP($D$3,'Base TOTAL'!A:AJ,18,0),""), IF(res="", "Sin datos", res)) -> A corregir por M/C
B23: Plazo de Ejecución | C23: =LET(res, IFERROR(VLOOKUP($D$3,'Base TOTAL'!A:AJ,19,0),""), IF(res="", "Sin datos", res)) -> A corregir por M/C
B24: Cómputo y Presupuesto | C24: =LET(res, IFERROR(VLOOKUP($D$3,'Base TOTAL'!A:AJ,20,0),""), IF(res="", "Sin datos", res)) -> A corregir por M/C
B25: Cronograma Avance Obra | C25: =LET(res, IFERROR(VLOOKUP($D$3,'Base TOTAL'!A:AJ,21,0),""), IF(res="", "Sin datos", res)) -> A corregir por M/C
B26: Planimetría | C26: =LET(res, IFERROR(VLOOKUP($D$3,'Base TOTAL'!A:AJ,22,0),""), IF(res="", "Sin datos", res)) -> A corregir por M/C
B27: Perfil Calzada | C27: =LET(res, IFERROR(VLOOKUP($D$3,'Base TOTAL'!A:AJ,23,0),""), IF(res="", "Sin datos", res)) -> A corregir por M/C
B28: Detalle de Cordón Cuneta | C28: =LET(res, IFERROR(VLOOKUP($D$3,'Base TOTAL'!A:AJ,24,0),""), IF(res="", "Sin datos", res)) -> A corregir por M/C
B29: Detalle de Badén | C29: =LET(res, IFERROR(VLOOKUP($D$3,'Base TOTAL'!A:AJ,25,0),""), IF(res="", "Sin datos", res)) -> A corregir por M/C
B30: Paquete estr. Calzada | C30: =LET(res, IFERROR(VLOOKUP($D$3,'Base TOTAL'!A:AJ,26,0),""), IF(res="", "Sin datos", res)) -> A corregir por M/C
B31: 5 | C31: =LET(res, IFERROR(VLOOKUP($D$3,'Base TOTAL'!A:AJ,27,0),""), IF(res="", "Sin datos", res)) -> En Evaluaciòn Jurìdico
B32: 6 | C32: =LET(res, IFERROR(VLOOKUP($D$3,'Base TOTAL'!A:AJ,28,0),""), IF(res="", "Sin datos", res)) -> En Evaluaciòn Jurìdico
B33: 7 | C33: =LET(res, IFERROR(VLOOKUP($D$3,'Base TOTAL'!A:AJ,29,0),""), IF(res="", "Sin datos", res)) -> En Evaluaciòn Jurìdico
B34: 8 | C34: =LET(res, IFERROR(VLOOKUP($D$3,'Base TOTAL'!A:AJ,30,0),""), IF(res="", "Sin datos", res)) -> En Evaluaciòn Jurìdico
B35: 9 | C35: =LET(res, IFERROR(VLOOKUP($D$3,'Base TOTAL'!A:AJ,31,0),""), IF(res="", "Sin datos", res)) -> En Evaluaciòn Jurìdico
B36: ESTADO DEL EXPEDIENTE DE LA LOCALIDAD | C36: =LET(res, IFERROR(VLOOKUP($D$3,'Base TOTAL'!A:AJ,32,0),""), IF(res="", "Sin datos", res)) -> En CURSO en DGV
A37: OBSERVACIONES | C37: =LET(res, IFERROR(VLOOKUP($D$3,'Base TOTAL'!A:AJ,33,0),""), IF(res="", "Sin datos", res)) -> 03/7/2026: Presentan documentación en evaluaciòn. 22/6/26:Comunicaciòn con la pres. comunal. Se envìa Instructivo de la documentaciòn legal y tècnica requerida al munic. y al profesional. . 5/6/26: Ingresa Nota Ministerio Gobierno autorizando financiamiento.
A38: EXPEDIENTE RADICADO EN: | B38: FECHA | C38: =LET(res, IFERROR(VLOOKUP($D$3,'Base TOTAL'!A:AJ,34,0),""), IF(res="", "Sin datos", res)) -> Sin datos
B39: REPARTICIÓN | C39: =LET(res, IFERROR(VLOOKUP($D$3,'Base TOTAL'!A:AJ,35,0),""), IF(res="", "Sin datos", res)) -> Sin datos
A40: PROGRAMA CÓRDOBA HOGAR - LEY Nº 8663
B41: EXPEDIENTE N°
B42: N° Orden
B43: MUNICIPIO / COMUNA
B44: INTENDENTE / PRESIDENTE COMUNAL
B45: N° TELÉFONO M/C | E45: ,
B46: CORREO ELECTRÓNICO
B47: CONTACTO TÉCNICO de M/C
A48: CONVENIO | B48: MONTO CONVENIO
B49: Cantidad de Viviendas

Sheet REP Depart.
A1: OBRA: "EJECUCIÒN DE CORDÒN CUNETA Y ADOQUINADO"
A2: PROGRAMA: "PROVINCIAL DE CORDÒN CUNETA Y ADOQUINES" - LEY Nº 11.089
A3: INFORME DEPARTAMENTO | B3: =TODAY() -> 46216
A4: DEPARTAMENTO: | B4: Marcos Juárez
A5: Cantidad de localidades afectadas | B5: =COUNTIF('Base TOTAL'!B:B, $B$4) -> 10
A6: TRAMITE PRE-OBRA
A7: MONTO TOTAL: | B7: =SUMIF('Base TOTAL'!B:B, $B$4, 'Base TOTAL'!J:J) -> 1420000000
A8: ='Base TOTAL'!K3 -> Cordón Cuneta (ml) | B8: =SUMIF('Base TOTAL'!B:B, $B$4, 'Base TOTAL'!K:K) -> 889
A9: ='Base TOTAL'!L3 -> Adoquinado (m2) | B9: =SUMIF('Base TOTAL'!B:B, $B$4, 'Base TOTAL'!L:L) -> 4520.9
A10: ='Base TOTAL'!AF3 -> ESTADO DEL EXPEDIENTE DE LA LOCALIDAD
A11: =IFERROR(__xludf.DUMMYFUNCTION("SORT(FILTER('Base TOTAL'!A:A, 'Base TOTAL'!B:B = B4))"),"Arias") -> Arias | B11: =IFERROR(VLOOKUP($A11,'Base TOTAL'!A:AJ,32,0), "-") -> En CURSO en DGV
A12: =IFERROR(__xludf.DUMMYFUNCTION("""COMPUTED_VALUE"""),"Camilo Aldao") -> Camilo Aldao | B12: =IFERROR(VLOOKUP($A12,'Base TOTAL'!A:AJ,32,0), "-") -> COMPLETO en DGV
A13: =IFERROR(__xludf.DUMMYFUNCTION("""COMPUTED_VALUE"""),"Capitán General Bernardo O'Higgins") -> Capitán General Bernardo O'Higgins | B13: =IFERROR(VLOOKUP($A13,'Base TOTAL'!A:AJ,32,0), "-") -> En CURSO en DGV
A14: =IFERROR(__xludf.DUMMYFUNCTION("""COMPUTED_VALUE"""),"Cavanagh") -> Cavanagh | B14: =IFERROR(VLOOKUP($A14,'Base TOTAL'!A:AJ,32,0), "-") -> En CURSO en DGV
A15: =IFERROR(__xludf.DUMMYFUNCTION("""COMPUTED_VALUE"""),"Colonia Barge") -> Colonia Barge | B15: =IFERROR(VLOOKUP($A15,'Base TOTAL'!A:AJ,32,0), "-") -> A INICIAR en DGV
A16: =IFERROR(__xludf.DUMMYFUNCTION("""COMPUTED_VALUE"""),"Colonia Italiana") -> Colonia Italiana | B16: =IFERROR(VLOOKUP($A16,'Base TOTAL'!A:AJ,32,0), "-") -> COMPLETO en DGV
A17: =IFERROR(__xludf.DUMMYFUNCTION("""COMPUTED_VALUE"""),"Cruz Alta") -> Cruz Alta | B17: =IFERROR(VLOOKUP($A17,'Base TOTAL'!A:AJ,32,0), "-") -> A INICIAR en DGV
A18: =IFERROR(__xludf.DUMMYFUNCTION("""COMPUTED_VALUE"""),"General Baldissera") -> General Baldissera | B18: =IFERROR(VLOOKUP($A18,'Base TOTAL'!A:AJ,32,0), "-") -> A INICIAR en DGV
A19: =IFERROR(__xludf.DUMMYFUNCTION("""COMPUTED_VALUE"""),"General Roca") -> General Roca | B19: =IFERROR(VLOOKUP($A19,'Base TOTAL'!A:AJ,32,0), "-") -> COMPLETO en DGV
A20: =IFERROR(__xludf.DUMMYFUNCTION("""COMPUTED_VALUE"""),"Saira") -> Saira | B20: =IFERROR(VLOOKUP($A20,'Base TOTAL'!A:AJ,32,0), "-") -> A INICIAR en DGV
B21: =IFERROR(VLOOKUP($A21,'Base TOTAL'!A:AJ,32,0), "-") -> -
B22: =IFERROR(VLOOKUP($A22,'Base TOTAL'!A:AJ,32,0), "-") -> -
B23: =IFERROR(VLOOKUP($A23,'Base TOTAL'!A:AJ,32,0), "-") -> -
B24: =IFERROR(VLOOKUP($A24,'Base TOTAL'!A:AJ,32,0), "-") -> -
B25: =IFERROR(VLOOKUP($A25,'Base TOTAL'!A:AJ,32,0), "-") -> -
B26: =IFERROR(VLOOKUP($A26,'Base TOTAL'!A:AJ,32,0), "-") -> -
B27: =IFERROR(VLOOKUP($A27,'Base TOTAL'!A:AJ,32,0), "-") -> -
B28: =IFERROR(VLOOKUP($A28,'Base TOTAL'!A:AJ,32,0), "-") -> -
B29: =IFERROR(VLOOKUP($A29,'Base TOTAL'!A:AJ,32,0), "-") -> -
B30: =IFERROR(VLOOKUP($A30,'Base TOTAL'!A:AJ,32,0), "-") -> -
B31: =IFERROR(VLOOKUP($A31,'Base TOTAL'!A:AJ,32,0), "-") -> -
B32: =IFERROR(VLOOKUP($A32,'Base TOTAL'!A:AJ,32,0), "-") -> -
... B50: =IFERROR(VLOOKUP($A50,'Base TOTAL'!A:AJ,32,0), "-") -> -
A51: fin del listado

Sheet REP Loc.
A1: OBRA: "EJECUCIÒN DE CORDÒN CUNETA Y ADOQUINADO"
A2: PROGRAMA: "PROVINCIAL DE CORDÒN CUNETA Y ADOQUINES" - LEY Nº 11.089
A3: INFORME LOCALIDAD | B3: =TODAY() -> 46216
A4: LOCALIDAD: | B4: Guanaco Muerto
A5: DEPARTAMENTO: | B5: =IFERROR(VLOOKUP($B$4,'Base TOTAL'!A:AJ,2,0), "Sin dato") -> Cruz del Eje
A6: TRAMITE PRE-OBRA
A7: Nº EXPEDIENTE 0135- : | B7: =IFERROR(VLOOKUP($B$4,'Base TOTAL'!A:AJ,3,0), "Sin dato") -> 0423-079111/2026
A8: MONTO TOTAL: | B8: =IFERROR(VLOOKUP($B$4,'Base TOTAL'!A:AJ,10,0), "Sin dato") -> 50000000
A9: ='Base TOTAL'!K3 -> Cordón Cuneta (ml) | B9: 440
A10: ='Base TOTAL'!L3 -> Adoquinado (m2) | B10: =IFERROR(VLOOKUP($B$4,'Base TOTAL'!A:AJ,12,0), "Sin dato")
A11: Estado de la documentación
A12: 1- Nota Solicitud de Financiamiento | B12: =IFERROR(VLOOKUP($B$4,'Base TOTAL'!A:AJ,13,0), "Sin dato") -> Sin Presentar
A13: 2- Ordenanza y Decreto/ Resolución comunal | B13: =IFERROR(VLOOKUP($B$4,'Base TOTAL'!A:AJ,14,0), "Sin dato") -> Sin Presentar
A14: 3- DDJJ compromiso de ejecuciòn obra | B14: =IFERROR(VLOOKUP($B$4,'Base TOTAL'!A:AJ,15,0), "Sin dato") -> Sin Presentar
A15: 4- Proyecto, Planos, Còmputo y Presupuesto | B15: =IFERROR(VLOOKUP($B$4,'Base TOTAL'!A:AJ,16,0), "Sin dato") -> A corregir por M/C
A16: Descripción General | B16: =IFERROR(VLOOKUP($B$4,'Base TOTAL'!A:AJ,17,0), "Sin dato") -> A corregir por M/C
A17: Memoria Técnica | B17: =IFERROR(VLOOKUP($B$4,'Base TOTAL'!A:AJ,18,0), "Sin dato") -> A corregir por M/C
A18: Plazo de Ejecución | B18: =IFERROR(VLOOKUP($B$4,'Base TOTAL'!A:AJ,19,0), "Sin dato") -> A corregir por M/C
A19: Cómputo y Presupuesto | B19: =IFERROR(VLOOKUP($B$4,'Base TOTAL'!A:AJ,20,0), "Sin dato") -> A corregir por M/C
A20: Cronograma Avance Obra | B20: =IFERROR(VLOOKUP($B$4,'Base TOTAL'!A:AJ,21,0), "Sin dato") -> A corregir por M/C
A21: Planimetría | B21: =IFERROR(VLOOKUP($B$4,'Base TOTAL'!A:AJ,22,0), "Sin dato") -> A corregir por M/C
A22: Perfil Calzada | B22: =IFERROR(VLOOKUP($B$4,'Base TOTAL'!A:AJ,23,0), "Sin dato") -> A corregir por M/C
A23: Detalle de Cordón Cuneta | B23: =IFERROR(VLOOKUP($B$4,'Base TOTAL'!A:AJ,24,0), "Sin dato") -> A corregir por M/C
A24: Detalle de Badén | B24: =IFERROR(VLOOKUP($B$4,'Base TOTAL'!A:AJ,25,0), "Sin dato") -> A corregir por M/C
A25: Paquete estr. Calzada | B25: =IFERROR(VLOOKUP($B$4,'Base TOTAL'!A:AJ,26,0), "Sin dato") -> A corregir por M/C
A26: 5- Nota a Contaduría Cesiòn Coparticipaciòn | B26: =IFERROR(VLOOKUP($B$4,'Base TOTAL'!A:AJ,27,0), "Sin dato") -> Sin Presentar
A27: 6- Nº CBU de M/C especial para depòsito de fondos | B27: =IFERROR(VLOOKUP($B$4,'Base TOTAL'!A:AJ,28,0), "Sin dato") -> Sin Presentar
A28: 7- Nº CUIT Municipal / Comunal | B28: =IFERROR(VLOOKUP($B$4,'Base TOTAL'!A:AJ,29,0), "Sin dato") -> Sin Presentar
A29: 8- DNI Intendente / Jefe Comunal | B29: =IFERROR(VLOOKUP($B$4,'Base TOTAL'!A:AJ,30,0), "Sin dato") -> Sin Presentar
A30: 9- Acta de Proclamación Int./Pres. Com. | B30: =IFERROR(VLOOKUP($B$4,'Base TOTAL'!A:AJ,31,0), "Sin dato") -> Sin Presentar
A32: ='Base TOTAL'!AG2 -> OBSERVACIONES
A33: =IFERROR(VLOOKUP($B$4,'Base TOTAL'!A:AJ,33,0), "Sin dato") -> 18/6/26: Se envìa Instructivo de documentaciòn legal y tècnica a presentar por M-C. EL 29/04/26 SE LE ENVÍA LOS REQUISITOS, VA A ENVIAR DOCUMENTACIÓN Completó el punto 4. Se le envió el 29/04/26 los restantes items para completar Expte.
A35: EXPEDIENTE RADICADO EN:
A36: ='Base TOTAL'!AH3 -> FECHA | B36: ='Base TOTAL'!AI3 -> REPARTICIÓN
A37: =IFERROR(VLOOKUP($B$4,'Base TOTAL'!A:AJ,34,0), "Sin dato") -> 46139 | B37: =IFERROR(VLOOKUP($B$4,'Base TOTAL'!A:AJ,35,0), "Sin dato") -> Técnica DGV

Sheet REP estado expediente
A1: OBRA: "EJECUCIÒN DE CORDÒN CUNETA Y ADOQUINADO"
A2: PROGRAMA: "PROVINCIAL DE CORDÒN CUNETA Y ADOQUINES" - LEY Nº 11.089
A3: REPORTE | B3: =TODAY() -> 46216
A4: ='Base TOTAL'!AF3 -> ESTADO DEL EXPEDIENTE DE LA LOCALIDAD | C4: COMPLETO en DGV
C5: =COUNTA(C7:C402) -> 396 | D5: ='Base TOTAL'!AH2 -> EXPEDIENTE RADICADO EN:
A6: Localidad | B6: Departamento | D6: ='Base TOTAL'!AH3 -> FECHA | E6: ='Base TOTAL'!AI3 -> REPARTICIÓN
A7: =IFERROR(__xludf.DUMMYFUNCTION("SORT(FILTER('Base TOTAL'!A:A, 'Base TOTAL'!AF:AF = C4))"),"Camilo Aldao") -> Camilo Aldao | B7: =IFERROR(VLOOKUP($A7,'Base TOTAL'!A:AJ,2,0), "-") -> Marcos Juárez | C7: =IFERROR(VLOOKUP($A7,'Base TOTAL'!A:AJ,33,0), "-") -> 13-07-2026 Se recibio doc. completa ordenada en 3 PDF 13-07-2026 Avisa la arqta. Gise, que enviò toda la doc. por mail. NO llego, se dio aviso para su re envio 08-07-2026 Se solicita al arq. la Present. de toda la doc. corregida completa s/ intructivo (Como iniciar el tram.) 07-07-2026 Se recibe doc. para completar pto 9 03/7/2026: Se solicita completen el acta de aceptación del cargo del intendente. 30/6/2026: Expte. PASA A LEGALES 29/6/2026: Documentaciòn en orden para anexar al Expte. y dar curso. - 05-06-2026 - Pto. 4 ( Falta cronograma de avance de obra + En planimetria gral. colocar las Geo referencias de los cuatro sectores de obra) Se solicitan nuevos cambios. COMPLETÓ DOCUMENTACIÓN 01/06/26 - Se pasan las actuaciones a arq. Carlos Viana para enviar a Jurídico Se envían el 26/05/26, nuevas correcciones, se recibe nueva documentación técnica el 29/05/26. 07-07-2026 Se recibe doc. Pto. 9 p/ completar exp. El 26/05/26 se envió correcciones a la parte técnica. Documentación Corregida. Sube a Jurídico El 19/05/26 se recibe documentación corregida para su análisis. El 11/5/26 se logra comunicación con municipalidad. Se pasa por whatsapp la documentación modelo. | D7: =IFERROR(VLOOKUP($A7,'Base TOTAL'!A:AJ,34,0), "-") -> 46205 | E7: =IFERROR(VLOOKUP($A7,'Base TOTAL'!A:AJ,35,0), "-") -> Jurídico DGV
A8: =IFERROR(__xludf.DUMMYFUNCTION("""COMPUTED_VALUE"""),"Colonia Italiana") -> Colonia Italiana | B8: =IFERROR(VLOOKUP($A8,'Base TOTAL'!A:AJ,2,0), "-") -> Marcos Juárez | C8: =IFERROR(VLOOKUP($A8,'Base TOTAL'!A:AJ,33,0), "-") -> 30/6/2026: Expte. PASA A LEGALES 29/6/2026: Documentaciòn en orden para anexar al Expte. y dar curso. 29/6/2026: Documentaciòn en orden para anexar al Expte. y dar curso. 19/6/26: Deben completar y corregir. 18/06/2026 enviaron memoria y doc tecnica corregida segun obervaciones. P- 17-06-2026 Se envìan correg/completar: ( firma y sello del prof. en cada hoja grafic.+ falta perfil transversal de calzada aunque no tenga paq. estr. determinando mat. de relleno) + pto.6 no se enviò imagen, del CBU el enviado tiene imagen parcial cortada) P- 11-06-2026 TEC.:( Faltan Memoria + Planim. con cotas + todos los detalles cortes + Cronogr. de Avances en 6 mese + todo sellado y firm x profes.) 11/6/26: Se solicita nuevamente la documentaciòn tècnica faltante. La arq. completará. P- 08-06-2026 - Pto. Nª 2 Falta Sello y firma del Tesorero o esta borroza Secr. tesor. + Pto. Nª 4 ( Faltan cotas grales de cada manz. en la planialtim. + cortes transv. + detalles + Planilla de avances cronograma de obra + Ubica y Memoria) El 30/04/26 vino la intendente Alejandra Ita a consultar por el Programa. Pregunta por el descuento por copa posterior. | D8: =IFERROR(VLOOKUP($A8,'Base TOTAL'!A:AJ,34,0), "-") -> 46205 | E8: =IFERROR(VLOOKUP($A8,'Base TOTAL'!A:AJ,35,0), "-") -> Jurídico DGV
A9: =IFERROR(__xludf.DUMMYFUNCTION("""COMPUTED_VALUE"""),"General Roca") -> General Roca | B9: =IFERROR(VLOOKUP($A9,'Base TOTAL'!A:AJ,2,0), "-") -> Marcos Juárez | C9: =IFERROR(VLOOKUP($A9,'Base TOTAL'!A:AJ,33,0), "-") -> Completó documentación y se elevó a jurídica para su estudio. COMPLETO. CON V°B° DE TÉCNICA. | D9: =IFERROR(VLOOKUP($A9,'Base TOTAL'!A:AJ,34,0), "-") -> 46205 | E9: =IFERROR(VLOOKUP($A9,'Base TOTAL'!A:AJ,35,0), "-") -> Tribunal de Cuentas
A10: =IFERROR(__xludf.DUMMYFUNCTION("""COMPUTED_VALUE"""),"La Paz") -> La Paz | B10: =IFERROR(VLOOKUP($A10,'Base TOTAL'!A:AJ,2,0), "-") -> San Javier | C10: =IFERROR(VLOOKUP($A10,'Base TOTAL'!A:AJ,33,0), "-") -> 08-07-2026 Se solicita al arq. la Present. de toda la doc. corregida completa s/ intructivo (Como iniciar el tram.) y Se resaltan completar detalles en esta present. ( Pto 2 que lleve ademas las firmas y sellos del tesorero e intend. + en Ptol 3 En la declar. Jurada si es el domic. real esquina sacar el S/N si no colocar las georef del mismo + en la Memoria Pto 3 plazo colocar s/ instruc. ) 30/6/2026: Expte. PASA A LEGALES 29/6/2026: Documentaciòn en orden para anexar al Expte. y dar curso. /// 23-06-2026 - Completo toda la doc. ( se recibe detalle de baden) 22-06-2026 - Solo falta detalle de baden se lo pedimos y le enviamos modelo al arq. Adrian RTA.: Enviado 19/6/26: Se solicita al arq. que presenta la documentaciòn a la mayor brevedad. 12-06-2026 -- Se solicita al arq. Adrian actualiz. correcc. -RTAS.: 11-06-2026 TEC.: ( solo falta det. baden ancho + paquete estruct. de calz + Geo ref. en Pl.gral) 04-06-2026 - Se tilda al Pto. Nª 4 (para que se modifique la unidad del cordon cun. a ml en el CM) EL 28/04/26 SE LE ENVÍA LOS REQUISITOS, VA A ENVIAR DOCUMENTACIÓN | D10: =IFERROR(VLOOKUP($A10,'Base TOTAL'!A:AJ,34,0), "-") -> 46205 | E10: =IFERROR(VLOOKUP($A10,'Base TOTAL'!A:AJ,35,0), "-") -> Jurídico DGV
A11: =IFERROR(__xludf.DUMMYFUNCTION("""COMPUTED_VALUE"""),"La Población") -> La Población | B11: =IFERROR(VLOOKUP($A11,'Base TOTAL'!A:AJ,2,0), "-") -> San Javier | C11: =IFERROR(VLOOKUP($A11,'Base TOTAL'!A:AJ,33,0), "-") -> 08-07-2026 Se solicita al arq. la Present. de toda la doc. corregida completa s/ intructivo (Como iniciar el tram.) 03-07-2026 Se reciben correcciones 03/7/2026: Se solicita al arq. corregir las observaciones (Faltan Georeferencias) 2026-07-01 Se solicito al arq. el complet. de geo ref en nota 3 y la firma del intend. en nota de ampliac. de doc. de georef. 2026-06-30 Se recibe modificacion parrafo Nota 5 solicitado al arq. --EXP. COMPLETO- 2026-06-30 Se recibe envio de Geo ref y se solicita modif. parrafo en nota 5 29/6/2026: Se reitera pedido de Geo-Ref. en Planim. Gral. 8/6/26 PASA DE AREA TECNICA A LEGALES // S-3-6-2026 Se observò desde Jurìdica falta en Punto Nª2 (son 3 firmas y falta..+ monto en la parte escrita) 3/6/2026 Se envió documentacion completa digital por email y lo recibiò Jurídica. COMPLETÓ documentación. Subió a Jurídico. Está en la Privada desde el 28/05/26 EL 20/05/26 SE APRUEBA LA PARTE TÉCNICA. SE SUBE A JURÍDICO PARA SU PROSECUCIÓN. EL 20/04/2026 LA COMUNA ENVÍA DOCUMENTACIÓN. FALTA INFO TÉCNICA. SE SOLICITA COMPLETAR LA MISMA. EL 14/04/26 SE CONTACTÓ AL PRESIDENTE COMUNAL - | D11: =IFERROR(VLOOKUP($A11,'Base TOTAL'!A:AJ,34,0), "-") -> 46199 | E11: =IFERROR(VLOOKUP($A11,'Base TOTAL'!A:AJ,35,0), "-") -> Técnica DGV
A12: =IFERROR(__xludf.DUMMYFUNCTION("""COMPUTED_VALUE"""),"Los Hornillos") -> Los Hornillos | B12: =IFERROR(VLOOKUP($A12,'Base TOTAL'!A:AJ,2,0), "-") -> San Javier | C12: =IFERROR(VLOOKUP($A12,'Base TOTAL'!A:AJ,33,0), "-") -> 8/6/26 PASA DE AREA TECNICA A LEGALES // P- 04-06-2026 - Se tilda al Pto. Nª 4 (para que se modifique la unidad del cordon cun. a ml en el Comp Metrico) EL 28/04/26 SE LE ENVÍA LOS REQUISITOS, VA A ENVIAR DOCUMENTACIÓNP- 3/6/2026 Se envió documentacion completa digital por email y lo recibiò Jurídica. EN CONDICIONES. EN LA PRIVADA DESDE 28/05/26 El 26/05/2026 se envía toda la Documentación completa con las correcciones ya corregidas por parte de la Comuna. El 26/5/26 se envía a Jurídico todo completo El 20/05/26 se aprueba la parte técnica, sube a jurídico. El 7/5/26 se envía escaneo de docum. Técnica para corregir, también se envía modelo de avance de obra por 6 meses. El 7/5/26 se solicitó corregir el punto 4 (doc. técnica) y se solicita cambio y corrección de Nota inicial. Presentó el 30/04/26 toda la documentación. El cómputo y presupuesto se pasa en $240.991-Se pide que se corrija. | D12: =IFERROR(VLOOKUP($A12,'Base TOTAL'!A:AJ,34,0), "-") -> 46199 | E12: =IFERROR(VLOOKUP($A12,'Base TOTAL'!A:AJ,35,0), "-") -> Tribunal de Cuentas
A13: =IFERROR(__xludf.DUMMYFUNCTION("""COMPUTED_VALUE"""),"San Javier y Yacanto") -> San Javier y Yacanto | B13: =IFERROR(VLOOKUP($A13,'Base TOTAL'!A:AJ,2,0), "-") -> San Javier | C13: =IFERROR(VLOOKUP($A13,'Base TOTAL'!A:AJ,33,0), "-") -> 03/7/2026: Se solicita al arq. y por Email municipio, corregir las observaciones (Faltan Georeferencias) 01-07-2026 - Se solicita al arq. Las Geo-Referenc. y la modicific. de la Nota Pto. 5 sacar ante ult. parrafo. 9/6/26 PASA DE AREA TECNICA A LEGALES. -04-06-2026 -(En Pto. 1 Nota Financ sacar la expres. vereda peinada y colocar tambien medida del cordòn en ml + en el Pto. 4 en el Comp. Metr. poner la medida del cordòn cunet. en ml) 3/6/2026 Se envió documentacion completa digital por email y fue recibida por Jurídica. COMPLETÓ documentación. Subió a Jurídico. Está en la Privada desde el 28/05/26 El 05/05/26 presentó la documentación, se exede en el montoasignado de $200.000.000 en $304.840 (se lo llama para que cambie) EL 16/04/26 VINO PERSONALMENTE EL INTENDENTE, MOSTRANDO INTERÉS. EL 14/04/26 SE CONTACTÓ AL INTENDENTE. | D13: =IFERROR(VLOOKUP($A13,'Base TOTAL'!A:AJ,34,0), "-") -> 46203 | E13: =IFERROR(VLOOKUP($A13,'Base TOTAL'!A:AJ,35,0), "-") -> Técnica DGV
A14: =IFERROR(__xludf.DUMMYFUNCTION("""COMPUTED_VALUE"""),"Tuclame") -> Tuclame | B14: =IFERROR(VLOOKUP($A14,'Base TOTAL'!A:AJ,2,0), "-") -> Cruz del Eje | C14: =IFERROR(VLOOKUP($A14,'Base TOTAL'!A:AJ,33,0), "-") -> COMPLETÓ documentación. Subió a Jurídico Con V°B°. EN LA PRIVADA DESDE 19/05/26 ENVIÓ LA DOCUMENTACIÓN. ESTÁS COMPLETA, SÓLO DEBE CORREGIR CRONOGRAMA DE INVERSIONES. COMPLETO. CON V°B° DE TÉCNICA | D14: =IFERROR(VLOOKUP($A14,'Base TOTAL'!A:AJ,34,0), "-") -> 46205 | E14: =IFERROR(VLOOKUP($A14,'Base TOTAL'!A:AJ,35,0), "-") -> Tribunal de Cuentas
A15: =IFERROR(__xludf.DUMMYFUNCTION("""COMPUTED_VALUE"""),"Villa Valeria") -> Villa Valeria | B15: =IFERROR(VLOOKUP($A15,'Base TOTAL'!A:AJ,2,0), "-") -> General Roca | C15: =IFERROR(VLOOKUP($A15,'Base TOTAL'!A:AJ,33,0), "-") -> 03/7/2026: PASO A LEGALES 10/6/2026 COMPLETÓ documentación. Subió a Jurídico Con V°B°. ARCHIVADO EL 13/05/26 El 12/5/26 se le envía "devolución" con correcciones de la documentación técnica presentada. COMPLETO. PASADO CON V°B° DE TÉCNICA. EL 30/04/26, EL INTENDENTE ENVÍA DOCUMENTACIÓN, QUE ESTÁ SIENDO ANALIZADA. DEBE COMPLETAR PUNTO 4, DE DOC. TÉCN. | D15: =IFERROR(VLOOKUP($A15,'Base TOTAL'!A:AJ,34,0), "-") -> 02/072026 | E15: =IFERROR(VLOOKUP($A15,'Base TOTAL'!A:AJ,35,0), "-") -> Tribunal de Cuentas
B16: =IFERROR(VLOOKUP($A16,'Base TOTAL'!A:AJ,2,0), "-") -> - | C16: =IFERROR(VLOOKUP($A16,'Base TOTAL'!A:AJ,33,0), "-") -> - | D16: =IFERROR(VLOOKUP($A16,'Base TOTAL'!A:AJ,34,0), "-") -> - | E16: =IFERROR(VLOOKUP($A16,'Base TOTAL'!A:AJ,35,0), "-") -> -
B17: =IFERROR(VLOOKUP($A17,'Base TOTAL'!A:AJ,2,0), "-") -> - | C17: =IFERROR(VLOOKUP($A17,'Base TOTAL'!A:AJ,33,0), "-") -> - | D17: =IFERROR(VLOOKUP($A17,'Base TOTAL'!A:AJ,34,0), "-") -> - | E17: =IFERROR(VLOOKUP($A17,'Base TOTAL'!A:AJ,35,0), "-") -> -
B18: =IFERROR(VLOOKUP($A18,'Base TOTAL'!A:AJ,2,0), "-") -> - | C18: =IFERROR(VLOOKUP($A18,'Base TOTAL'!A:AJ,33,0), "-") -> - | D18: =IFERROR(VLOOKUP($A18,'Base TOTAL'!A:AJ,34,0), "-") -> - | E18: =IFERROR(VLOOKUP($A18,'Base TOTAL'!A:AJ,35,0), "-") -> -
B19: =IFERROR(VLOOKUP($A19,'Base TOTAL'!A:AJ,2,0), "-") -> - | C19: =IFERROR(VLOOKUP($A19,'Base TOTAL'!A:AJ,33,0), "-") -> - | D19: =IFERROR(VLOOKUP($A19,'Base TOTAL'!A:AJ,34,0), "-") -> - | E19: =IFERROR(VLOOKUP($A19,'Base TOTAL'!A:AJ,35,0), "-") -> -
B20: =IFERROR(VLOOKUP($A20,'Base TOTAL'!A:AJ,2,0), "-") -> - | C20: =IFERROR(VLOOKUP($A20,'Base TOTAL'!A:AJ,33,0), "-") -> - | D20: =IFERROR(VLOOKUP($A20,'Base TOTAL'!A:AJ,34,0), "-") -> - | E20: =IFERROR(VLOOKUP($A20,'Base TOTAL'!A:AJ,35,0), "-") -> -
B21: =IFERROR(VLOOKUP($A21,'Base TOTAL'!A:AJ,2,0), "-") -> - | C21: =IFERROR(VLOOKUP($A21,'Base TOTAL'!A:AJ,33,0), "-") -> - | D21: =IFERROR(VLOOKUP($A21,'Base TOTAL'!A:AJ,34,0), "-") -> - | E21: =IFERROR(VLOOKUP($A21,'Base TOTAL'!A:AJ,35,0), "-") -> -
B22: =IFERROR(VLOOKUP($A22,'Base TOTAL'!A:AJ,2,0), "-") -> - | C22: =IFERROR(VLOOKUP($A22,'Base TOTAL'!A:AJ,33,0), "-") -> - | D22: =IFERROR(VLOOKUP($A22,'Base TOTAL'!A:AJ,34,0), "-") -> - | E22: =IFERROR(VLOOKUP($A22,'Base TOTAL'!A:AJ,35,0), "-") -> -
B23: =IFERROR(VLOOKUP($A23,'Base TOTAL'!A:AJ,2,0), "-") -> - | C23: =IFERROR(VLOOKUP($A23,'Base TOTAL'!A:AJ,33,0), "-") -> - | D23: =IFERROR(VLOOKUP($A23,'Base TOTAL'!A:AJ,34,0), "-") -> - | E23: =IFERROR(VLOOKUP($A23,'Base TOTAL'!A:AJ,35,0), "-") -> -
B24: =IFERROR(VLOOKUP($A24,'Base TOTAL'!A:AJ,2,0), "-") -> - | C24: =IFERROR(VLOOKUP($A24,'Base TOTAL'!A:AJ,33,0), "-") -> - | D24: =IFERROR(VLOOKUP($A24,'Base TOTAL'!A:AJ,34,0), "-") -> - | E24: =IFERROR(VLOOKUP($A24,'Base TOTAL'!A:AJ,35,0), "-") -> -
B25: =IFERROR(VLOOKUP($A25,'Base TOTAL'!A:AJ,2,0), "-") -> - | C25: =IFERROR(VLOOKUP($A25,'Base TOTAL'!A:AJ,33,0), "-") -> - | D25: =IFERROR(VLOOKUP($A25,'Base TOTAL'!A:AJ,34,0), "-") -> - | E25: =IFERROR(VLOOKUP($A25,'Base TOTAL'!A:AJ,35,0), "-") -> -
B26: =IFERROR(VLOOKUP($A26,'Base TOTAL'!A:AJ,2,0), "-") -> - | C26: =IFERROR(VLOOKUP($A26,'Base TOTAL'!A:AJ,33,0), "-") -> - | D26: =IFERROR(VLOOKUP($A26,'Base TOTAL'!A:AJ,34,0), "-") -> - | E26: =IFERROR(VLOOKUP($A26,'Base TOTAL'!A:AJ,35,0), "-") -> -
B27: =IFERROR(VLOOKUP($A27,'Base TOTAL'!A:AJ,2,0), "-") -> - | C27: =IFERROR(VLOOKUP($A27,'Base TOTAL'!A:AJ,33,0), "-") -> - | D27: =IFERROR(VLOOKUP($A27,'Base TOTAL'!A:AJ,34,0), "-") -> - | E27: =IFERROR(VLOOKUP($A27,'Base TOTAL'!A:AJ,35,0), "-") -> -
... B501: =IFERROR(VLOOKUP($A501,'Base TOTAL'!A:AJ,2,0), "-") -> - | C501: =IFERROR(VLOOKUP($A501,'Base TOTAL'!A:AJ,33,0), "-") -> - | D501: =IFERROR(VLOOKUP($A501,'Base TOTAL'!A:AJ,34,0), "-") -> - | E501: =IFERROR(VLOOKUP($A501,'Base TOTAL'!A:AJ,35,0), "-") -> -

Sheet Base TOTAL
A1: PROGRAMA PROVINCIAL DE CORDÓN CUNETA Y ADOQUINES - LEY Nº 11089 - AREA TECNICA - DIRECCIÓN GENERAL DE VIVENDA - MINISTERIO DE COOPERATIVAS Y MUTUALES - GOBIERNO DE CÒRDOBA
A2: LOCALIDAD / PROYECTO | B2: DEPARTAMENTO | C2: EXPEDIENTE N° | D2: N° Orden | E2: MUNICIPIO / COMUNA | F2: INTENDENTE / PRESIDENTE COMUNAL | G2: N° TELÉFONO M/C | H2: CORREO ELECTRÓNICO | I2: CONTACTO TÉCNICO de M/C | J2: CONVENIO | M2: DOCUMENTACIÓN A PRESENTAR por Municipio / Comuna | AG2: OBSERVACIONES | AH2: EXPEDIENTE RADICADO EN:
J3: MONTO CONVENIO | K3: Cordón Cuneta (ml) | L3: Adoquinado (m2) | M3: 1 | N3: 2 | O3: 3 | P3: 4 | Q3: Descripción General | R3: Memoria Técnica | S3: Plazo de Ejecución | T3: Cómputo y Presupuesto | U3: Cronograma Avance Obra | V3: Planimetría | W3: Perfil Calzada | X3: Detalle de Cordón Cuneta | Y3: Detalle de Badén | Z3: Paquete estr. Calzada | AA3: 5 | AB3: 6 | AC3: 7 | AD3: 8 | AE3: 9 | AF3: ESTADO DEL EXPEDIENTE DE LA LOCALIDAD | AH3: FECHA | AI3: REPARTICIÓN
A4: =COUNTA(A6:A55) -> 48 | J4: =SUM(J5:J56) -> 7065000000 | K4: =SUM(K5:K56) -> 8202.3 | L4: =SUM(L5:L56) -> 50710.12 | M4: =COUNTIF(M5:M56, "Completo OK") -> 14 | N4: =COUNTIF(N5:N56, "Completo OK") -> 17 | O4: =COUNTIF(O5:O56, "Completo OK") -> 15 | P4: =COUNTIF(P5:P56, "Completo OK") -> 13 | Q4: =COUNTIF(Q5:Q56, "Completo OK") -> 16 | R4: =COUNTIF(R5:R56, "Completo OK") -> 15 | S4: =COUNTIF(S5:S56, "Completo OK") -> 14 | T4: =COUNTIF(T5:T56, "Completo OK") -> 18 | ... AE4: =COUNTIF(AE5:AE56, "Completo OK") -> 16
A6: San Joaquín | B6: Presidente Roque Sáenz Peña | C6: 043-079116/2026 | D6: 1 | E6: C | F6: DANIEL PICCO | G6: (3385) 43-5407 | H6: Danielpicco66@hotmail.com | I6: laurirojas90@gmail.com | J6: 30000000 | K6: 206 | M6: A corregir por M/C | N6: En Evaluaciòn Jurìdico | O6: A corregir por M/C | P6: A corregir por M/C | Q6: Completo OK | R6: A corregir por M/C | S6: A corregir por M/C | T6: Completo OK | U6: Sin Presentar | V6: A corregir por M/C | W6: A corregir por M/C | X6: Completo OK | Y6: A corregir por M/C | Z6: Sin Presentar | AA6: A corregir por M/C | AB6: A corregir por M/C | AC6: En Evaluaciòn Jurìdico | AD6: En Evaluaciòn Jurìdico | AE6: En Evaluaciòn Jurìdico | AF6: En CURSO en DGV | AG6: 25/6/26: Comunicación con int. solicitando presenten correcciones. Se espera respuesta de la ing. a cargo. 19/6/26: Comunicaciòn con la ing. a cargo . Se solcita la presentaciòn a la mayor brevedad posible . 12-06-2026 Solicitar P Georef en Planim. + demas doc.Tec y leg 11/6/26: Se solicita nuevamente la correcciòn de Documentaciòn tècnica.Tiene todos los Items completos, salvo por el 4 (documentación técnica). El 29/5/26 se reclama la documentación firmada EL 19/05/26 PRESENTA PROYECTO CORREGIDO (A EVALUAR). EL 30/4 PRESENTAN NUEVO PRESUPUESTO, A VALOR $30.000.000. DEBE FUNDAMENTAR EL INCREMENTO EN EL MONTO TOTAL EL CÓMPUTO. El 30/04 se recibe y el monto que presenta es menor que el que se le da. Se pide que lo haga llegar al monto asignado El 28/04/26 se le envía documentación técnica modelo. EL 20/04/2026 LA COMUNA ENVÍA DOCUMENTACIÓN. FALTA INFO TÉCNICA. PRESENTA PRESUPUESTO, DE $21.969.370 - FALTA FIRMAS DE ÉSTE. EL 14/04/26 SE CONTACTÓ AL PRESIDENTE COMUNAL - | AH6: 46126 | AI6: Técnica DGV
A7: La Población | B7: San Javier | C7: 0423-079121/2026 | D7: 2 | E7: C | F7: EDUARDO ROMERO | G7: (3544) 58-0485 | H7: _ | I7: Arq. Adriàn Heredia (3544) 434500 Alejandra Castro (011) 6185-9307 | J7: 75000000 | K7: 440 | L7: 870 | M7: Completo OK | N7: Completo OK | O7: Completo OK | P7: Completo OK | Q7: Completo OK | R7: Completo OK | S7: Completo OK | T7: Completo OK | U7: Completo OK | V7: Completo OK | W7: Completo OK | X7: Completo OK | Y7: Completo OK | Z7: Completo OK | AA7: Completo OK | AB7: Completo OK | AC7: Completo OK | AD7: Completo OK | AE7: Completo OK | AF7: COMPLETO en DGV | AG7: 08-07-2026 Se solicita al arq. la Present. de toda la doc. corregida completa s/ intructivo (Como iniciar el tram.) 03-07-2026 Se reciben correcciones 03/7/2026: Se solicita al arq. corregir las observaciones (Faltan Georeferencias) 2026-07-01 Se solicito al arq. el complet. de geo ref en nota 3 y la firma del intend. en nota de ampliac. de doc. de georef. 2026-06-30 Se recibe modificacion parrafo Nota 5 solicitado al arq. --EXP. COMPLETO- 2026-06-30 Se recibe envio de Geo ref y se solicita modif. parrafo en nota 5 29/6/2026: Se reitera pedido de Geo-Ref. en Planim. Gral. 8/6/26 PASA DE AREA TECNICA A LEGALES // S-3-6-2026 Se observò desde Jurìdica falta en Punto Nª2 (son 3 firmas y falta..+ monto en la parte escrita) 3/6/2026 Se envió documentacion completa digital por email y lo recibiò Jurídica. COMPLETÓ documentación. Subió a Jurídico. Está en la Privada desde el 28/05/26 EL 20/05/26 SE APRUEBA LA PARTE TÉCNICA. SE SUBE A JURÍDICO PARA SU PROSECUCIÓN. EL 20/04/2026 LA COMUNA ENVÍA DOCUMENTACIÓN. FALTA INFO TÉCNICA. SE SOLICITA COMPLETAR LA MISMA. EL 14/04/26 SE CONTACTÓ AL PRESIDENTE COMUNAL - | AH7: 46199 | AI7: Técnica DGV
A8: Del Campillo | B8: General Roca | C8: 0423-079098/2026 | D8: 3 | E8: M | F8: CARLA VILLANOVA | G8: (3583) 40-1420 | H8: Carla.villanova480@gmail.com | J8: 200000000 | L8: 7440 | M8: En Evaluaciòn Jurìdico | N8: En Evaluaciòn Jurìdico | O8: En Evaluaciòn Jurìdico | P8: En Evaluaciòn Jurìdico | Q8: Completo OK | R8: Completo OK | S8: Completo OK | T8: Completo OK | U8: Completo OK | V8: A corregir por M/C | W8: Completo OK | X8: Sin Presentar | Y8: Sin Presentar | Z8: A corregir por M/C | AA8: En Evaluaciòn Jurìdico | AB8: En Evaluaciòn Jurìdico | AC8: En Evaluaciòn Jurìdico | AD8: En Evaluaciòn Jurìdico | AE8: En Evaluaciòn Jurìdico | AF8: En CURSO en DGV | AG8: - 22-06-2026 : Comunicaciòn con int. Se espera doc. tècnica y listo para dar continuidad al tràmite. - 19-06-2026 Se solicitan a la intend. Carla los siguientes: (Faltan en Planimetria Gral. las Geo ref. sobre las diferentes ubic. de obra + ampliar sobre la misma los nombres de las calles no se visualizan + corte paquete estr. de la calzada + detalles de baden s/ modelo) - 18-06-2026 Se envian al whats de intendenta y al mail los faltantes, correcciones y Modelo --RTAS.; Se recibe toda la doc. 4/6/2026 CB - VVVVVV 4/6/2026 HS - la documentacion tecnica tiene observaciones en el computo. esperaremos la vuelta desde jurídico. COMPLETÓ documentación. Subió a Jurídico Con V°B°. ARCHIVADO EL 13/05/26 EL 14/04/26 SE CONTACTÓ A LA INTENDENTE, LA CUAL ENVIÓ POSTERIORMENTE DOCUMENTACIÓN. SE SOLICITÓ EL COMPLETAMIENTO DE ITEM 4. COMPLETÓ PASADO CON V°B° TÉCNICA | AH8: 46155 | AI8: Jurídico DGV
A9: San Javier y Yacanto | B9: San Javier | C9: 0423-079118/2026 | D9: 4 | E9: M | F9: SEGUNDO MARTÍN GARCÍA | G9: (3544) 53-4283 | H9: garciam.s078@gmail.com | I9: Arq. Adriàn Heredia (3544) 434500 | J9: 200000000 | L9: 1823 | M9: Completo OK | N9: Completo OK | O9: A corregir por M/C | P9: Completo OK | Q9: Completo OK | R9: Completo OK | S9: Completo OK | T9: Completo OK | U9: Completo OK | V9: A corregir por M/C | W9: Completo OK | X9: Completo OK | Y9: Completo OK | Z9: Completo OK | AA9: Completo OK | AB9: Completo OK | AC9: Completo OK | AD9: Completo OK | AE9: Completo OK | AF9: COMPLETO en DGV | AG9: 03/7/2026: Se solicita al arq. y por Email municipio, corregir las observaciones (Faltan Georeferencias) 01-07-2026 - Se solicita al arq. Las Geo-Referenc. y la modicific. de la Nota Pto. 5 sacar ante ult. parrafo. 9/6/26 PASA DE AREA TECNICA A LEGALES. -04-06-2026 -(En Pto. 1 Nota Financ sacar la expres. vereda peinada y colocar tambien medida del cordòn en ml + en el Pto. 4 en el Comp. Metr. poner la medida del cordòn cunet. en ml) 3/6/2026 Se envió documentacion completa digital por email y fue recibida por Jurídica. COMPLETÓ documentación. Subió a Jurídico. Está en la Privada desde el 28/05/26 El 05/05/26 presentó la documentación, se exede en el montoasignado de $200.000.000 en $304.840 (se lo llama para que cambie) EL 16/04/26 VINO PERSONALMENTE EL INTENDENTE, MOSTRANDO INTERÉS. EL 14/04/26 SE CONTACTÓ AL INTENDENTE. | AH9: 46203 | AI9: Técnica DGV
A10: Cavanagh | B10: Marcos Juárez | C10: 0423-079101/2026 | D10: 55 | E10: M | F10: GUSTAVO DAL BO | G10: (3468) 64-7760 | H10: municavanagh@alejotv.com.ar | I10: richardquinn68@hotmail.com | J10: 300000000 | M10: A corregir por M/C | N10: A corregir por M/C | O10: A corregir por M/C | P10: A corregir por M/C | Q10: Sin Presentar | R10: Sin Presentar | S10: Sin Presentar | T10: Sin Presentar | U10: Sin Presentar | V10: Sin Presentar | W10: Sin Presentar | X10: Sin Presentar | Y10: Sin Presentar | Z10: Sin Presentar | AA10: Completo OK | AB10: Completo OK | AC10: Completo OK | AD10: Completo OK | AE10: Completo OK | AF10: En CURSO en DGV | AG10: 25-6-26: Comunicaciòn con Int. Solicita el Instructivo, se envìa. 10/6/2026: Se envìa doc. al arq. R. Quin para su correcc. x whatss P-10/6/2026: Se solicita al Municipio el contacto del ingeniero para enviar nuevamente lo que deben corregir P- 09-6-2026 Hablar con el intendente para avisar que este Progr. no contempla el asfaltado......-Pto. 1 -corregir nombre del Programa y plazo de ejecucion a 6 meses + Pto. 2 - No tiene el sello y firma de tesorero + Pto. 3 - corregir la denominaciòn del Programa + Pto. 7 el cuil presentado fue el del intend. No de la municipal. ? + 4/6/26:Presentan documentaciòn por Cidi- En evaluaciòn tècnica. EL 14/04/2026 SE CONTACTÓ AL INTENDENTE… QUEDÓ EN HABLAR, NO LO HIZOº | AH10: 46183 | AI10: Técnica DGV
A11: Capitán General Bernardo O'Higgins | B11: Marcos Juárez | C11: 0423-079103/2026 | D11: 6 | E11: M | F11: NORA BESSONE | G11: (3468) 56-1281 | H11: nora_bessone@hotmail.com | I11: muniohiggins@hotmail.com | J11: 200000000 | M11: A corregir por M/C | N11: Completo OK | O11: Completo OK | P11: Sin Presentar | Q11: A corregir por M/C | R11: A corregir por M/C | S11: A corregir por M/C | T11: A corregir por M/C | U11: Completo OK | V11: A corregir por M/C | W11: A corregir por M/C | X11: A corregir por M/C | Y11: A corregir por M/C | Z11: A corregir por M/C | AA11: Completo OK | AB11: Completo OK | AC11: Completo OK | AD11: Completo OK | AE11: Completo OK | AF11: En CURSO en DGV | AG11: 25-6-26: Comunicaciòn con int. y arq. para completen Georeferencia. 19/6/2026 se envian observaciones por email para corregir y completar. 18/6/26: Comunicación con el municipio para enviar Instructivo. EL 16/04/26 SE CONTACTÓ A LA INTENDENTE. EL 29/04/26 NOS VISITÓ Y CONSULTÓ. VA A ENVIAR DOCUMENTACIÓN | AH11: 46192 | AI11: Técnica DGV
A12: La Higuera | B12: Cruz del Eje | C12: 0423-079115/2026 | D12: 7 | E12: C | F12: DANIEL MANZANELLI | G12: (3542) 47-0003 | H12: Comunalahiguera01@gmail.com | I12: Ing. Bracamonte 3521401659 ---ingbracamontegustavo@gmail.com | J12: 100000000 | M12: A corregir por M/C | N12: A corregir por M/C | O12: A corregir por M/C | P12: A corregir por M/C | Q12: A corregir por M/C | R12: A corregir por M/C | S12: A corregir por M/C | T12: A corregir por M/C | U12: A corregir por M/C | V12: A corregir por M/C | W12: A corregir por M/C | X12: A corregir por M/C | Y12: A corregir por M/C | Z12: A corregir por M/C | AA12: Sin Presentar | AB12: Sin Presentar | AC12: Sin Presentar | AD12: Sin Presentar | AE12: Sin Presentar | AF12: En CURSO en DGV | AG12: 13-07-2026 Se llamo al ing. quien avisa que hoy envia doc. a la firma de la comuna y mañana nos envian por mail. 13/7/2026: Se solicita a la comuna y al ing. informen si puedieron avanzar con la documentaciòn. 13/7/2026: Se solicita a la comuna y al ing. informen si puedieron avanzar con la documentaciòn. 30-06-2026 Se reitera actualiz y completar docum. s/ instr. 26/6/2026: holaaaaaa 26/6/26: Se solicita al Ing. que complete la documentaciòn requerida conforme al Instructivo. 24/6/26: Se insiste y se hace un llamado al pres. comunal. Envìa datos por wathsapp. 22/6/26: Se solicita correo electrònico y datos del profesional para enviar instructivo. Sin respuesta 12-05-2026 Se envia las correcciones de la documentac. tecnica y la nota inial ( via whatsapp a Gonzalo Guzman El 30/04/2026 envían documentación de los items 1 a 5 para ver EL MARTES 28/04/26 SE HABLÓ POR TELÉFONO Y POR WHATSAPP, DONDE SE LE ENVIÓ LOS 9 PUNTOS Y SE COMPROMETIÓ EN DAR RESPUESTA. | AH12: 46139 | AI12: Técnica DGV
A13: Las Playas | B13: Cruz del Eje | C13: 0423-079112/2026 | D13: 8 | E13: C | F13: MARÍA DANIELA GODOY | G13: (3549) 46-8032 | H13: Danielagodoy79@gmail.com | I13: Ing. Bracamonte 3521401659 ---ingbracamontegustavo@gmail.com | J13: 200000000 | L13: 3922.22 | M13: A corregir por M/C | N13: Completo OK | O13: Completo OK | P13: A corregir por M/C | Q13: A corregir por M/C | R13: A corregir por M/C | S13: A corregir por M/C | T13: A corregir por M/C | U13: Sin Presentar | V13: A corregir por M/C | W13: A corregir por M/C | X13: Sin Presentar | Y13: Sin Presentar | Z13: A corregir por M/C | AA13: Completo OK | AB13: Completo OK | AC13: Completo OK | AD13: Completo OK | AE13: Completo OK | AF13: En CURSO en DGV | AG13: 13-7-2026: Se recibe de la intend. doc. por whast y se solicita que se envie en base a instructivo y por E mail. 13-7-2026: Se llamo al ing. quien avisa que el viernes enviò la doc. a la municip y mañana la envian firmada 13/7/2026: Se solicita informen còmo van con la documentaciòn a presentar. 29/6/2026: Se enviaron por Email las observaciones A corregir por la comuna 26/6/26: Se envían las observaciones a corregir por el ing. Se aguardan las observaciones del area Legales........22/6/26: El ing. se comunica con el àrea tècnica: Se le envìa el Instructivo de la documentaciòn legal y tècnica a presentar. 19/6/26: Sin respuesta del ing. a cargo, se envìa nuevamente el instructivo a la Pres. comunal. 11/6/26: Se solicita corregir documentación presentada. SE LE ENVIÓ LOS 9 REQUISITOS PARA PARTICIPAR EN EL PROGRAMA | AH13: 46139 | AI13: Técnica DGV
A14: Luyaba | B14: San Javier | C14: 0423-079120/2026 | D14: 9 | E14: C | F14: MAXIMILIANO PEREYRA | G14: (3544) 56-7381 | H14: Hectormaximilianopereyra@gmail.com | I14: Arq. Adriàn Heredia (3544) 434500 | J14: 150000000 | K14: 300 | L14: 2050 | M14: Completo OK | N14: Completo OK | O14: Completo OK | P14: Completo OK | Q14: Completo OK | R14: Completo OK | S14: Completo OK | T14: Completo OK | U14: Completo OK | V14: Completo OK | W14: Completo OK | X14: Completo OK | Y14: Completo OK | Z14: Completo OK | AA14: Completo OK | AB14: Completo OK | AC14: Completo OK | AD14: Completo OK | AE14: Completo OK | AF14: APROBADO por TC | AG14: 8/6/26 PASA DE AREA TECNICA A LEGALES // P -04-06-2026 -(En el Pto. 4 en el Comp. Metr. poner la medida del cordòn cunet. en ml) 3/6/2026 Se envió documentacion completa digital por email y lo recibiò Jurídica. 2/6/2026 corregido pasa a juridico El 27/05/2026 el municipio presentó el total de la información. APROBADA LA PARTE TÉCNICA. Debe corregir y presentar la Nota a Contaduría Gral y la DDJJ con firma clara 19/05/26 se aprueba la Parte Técnica. El 27/05/26 se recibe nueva documentación. 28/05/26 se pide que cambie nota a la contaduría y se le envía la nueva para que firme El 8/5/26 se le envió documentación modelo. Se recibió documenación de parte de la Comuna. La misma está en proceso de estudio y análisis. El | AH14: 46211 | AI14: Aprobado TC
A15: Villa Valeria | B15: General Roca | C15: 0423-079095/2026 | D15: 10 | E15: M | F15: CLAUDIO MELERO | G15: (3583) 43-9116 | H15: _ | J15: 350000000 | L15: 5000 | M15: Completo OK | N15: Completo OK | O15: Completo OK | P15: Completo OK | Q15: Completo OK | R15: Completo OK | S15: Completo OK | T15: Completo OK | U15: Completo OK | V15: Completo OK | W15: Completo OK | X15: Completo OK | Y15: Completo OK | Z15: Completo OK | AA15: Completo OK | AB15: Completo OK | AC15: Completo OK | AD15: Completo OK | AE15: Completo OK | AF15: COMPLETO en DGV | AG15: 03/7/2026: PASO A LEGALES 10/6/2026 COMPLETÓ documentación. Subió a Jurídico Con V°B°. ARCHIVADO EL 13/05/26 El 12/5/26 se le envía "devolución" con correcciones de la documentación técnica presentada. COMPLETO. PASADO CON V°B° DE TÉCNICA. EL 30/04/26, EL INTENDENTE ENVÍA DOCUMENTACIÓN, QUE ESTÁ SIENDO ANALIZADA. DEBE COMPLETAR PUNTO 4, DE DOC. TÉCN. | AH15: 02/072026 | AI15: Tribunal de Cuentas
A16: Villa Huidobro | B16: General Roca | C16: 0423-079097/2026 | D16: 11 | E16: M | F16: ENZO QUIROGA | G16: (2302) 45-3904 | H16: mvhuidobro@gmail.com | I16: arqmariasolcastelli2024@gmail.com | J16: 200000000 | K16: 1100 | M16: Completo OK | N16: Completo OK | O16: Completo OK | P16: Completo OK | Q16: Completo OK | R16: Completo OK | S16: Completo OK | T16: Completo OK | U16: Completo OK | V16: Completo OK | W16: Completo OK | X16: Completo OK | Y16: Completo OK | Z16: Completo OK | AA16: Completo OK | AB16: Completo OK | AC16: Completo OK | AD16: Completo OK | AE16: Completo OK | AF16: En CURSO en DGV | AG16: 08-7-2026 Se recibe por mail la doc. solicitada (solo el Cuil sale borroso mientras que en presentac. ant. sale bien) y se eleva a legales para su revisiòn 07-07-2026 Se tomo contacto con la arqta. Sol Castelli para acordar la presentac. de toda la doc. actualiz de manera ordenada 30-06-26 Se Responde a las dudas planteadas x el profes. x whatss 29/6/2026: Se recibe documentacion y se re envìan las correcciones 24-06-2026 -- Nos desarrollan consultas y se re envian por whats datos a completar y corregir 23-06-26 Se envian correc. 19-06-2026 Pto 6 -Re enviar CBU esta cortada la imag. + TECnica adecuar cronogr. de avance de Ob. a 6 meses y en todo escrito de la memoria que mencione plazos + nota 1 en los datos del pavimento articulado colocar medida en ML Y el Plazo de ejecucion de obra llevarlo a 6 meses + llevar los 6 meses al desarrollo de la planilla del cronogra de avances de obras + en Planim. Gral. colocar las Geo refer. y cotas ancho y largo de calles en desarr. de obra ) 9/6/26: Presentan documentación nuevamente a evaluar . 8/6/26: Se envía Instructivo (Doc. Requerida) a la localidad. El 05/05/26 se envía documentación Modelo que ayuda al completamiento y corrección de la misma. SI BIEN EL MUNPICIPIO CORRIGIÓ Y ENVIÓ CON AJUSTES EL PRESUPUESTO, DEBE ACLARAR ITEMS DE LA PARTE TÉCNICA PARA ADECUAR A MONTO CONFORMADO. | AH16: 46147 | AI16: Técnica DGV
A17: La Paz | B17: San Javier | C17: 0423-079119/2026 | D17: 12 | E17: C | F17: RAMÓN RUFINO FUNES | G17: (3544) 44-0352 | H17: secgoblapaz@gmail.com | I17: Arq. Adriàn Heredia (3544) 434500 | J17: 300000000 | K17: 930 | L17: 2795 | M17: Completo OK | N17: A corregir por M/C | O17: A corregir por M/C | P17: Completo OK | Q17: Completo OK | R17: Completo OK | S17: A corregir por M/C | T17: Completo OK | U17: Completo OK | V17: Completo OK | W17: Completo OK | X17: Completo OK | Y17: Completo OK | Z17: Completo OK | AA17: Completo OK | AB17: Completo OK | AC17: Completo OK | AD17: Completo OK | AE17: A corregir por M/C | AF17: COMPLETO en DGV | AG17: 08-07-2026 Se solicita al arq. la Present. de toda la doc. corregida completa s/ intructivo (Como iniciar el tram.) y Se resaltan completar detalles en esta present. ( Pto 2 que lleve ademas las firmas y sellos del tesorero e intend. + en Ptol 3 En la declar. Jurada si es el domic. real esquina sacar el S/N si no colocar las georef del mismo + en la Memoria Pto 3 plazo colocar s/ instruc. ) 30/6/2026: Expte. PASA A LEGALES 29/6/2026: Documentaciòn en orden para anexar al Expte. y dar curso. /// 23-06-2026 - Completo toda la doc. ( se recibe detalle de baden) 22-06-2026 - Solo falta detalle de baden se lo pedimos y le enviamos modelo al arq. Adrian RTA.: Enviado 19/6/26: Se solicita al arq. que presenta la documentaciòn a la mayor brevedad. 12-06-2026 -- Se solicita al arq. Adrian actualiz. correcc. -RTAS.: 11-06-2026 TEC.: ( solo falta det. baden ancho + paquete estruct. de calz + Geo ref. en Pl.gral) 04-06-2026 - Se tilda al Pto. Nª 4 (para que se modifique la unidad del cordon cun. a ml en el CM) EL 28/04/26 SE LE ENVÍA LOS REQUISITOS, VA A ENVIAR DOCUMENTACIÓN | AH17: 46205 | AI17: Jurídico DGV
A18: Guanaco Muerto | B18: Cruz del Eje | C18: 0423-079111/2026 | D18: 13 | E18: C | F18: MAYCO SORIA | G18: (3549) 44-0455 | H18: maycosoria19@gmail.com | J18: 50000000 | M18: Sin Presentar | N18: Sin Presentar | O18: Sin Presentar | P18: A corregir por M/C | Q18: A corregir por M/C | R18: A corregir por M/C | S18: A corregir por M/C | T18: A corregir por M/C | U18: A corregir por M/C | V18: A corregir por M/C | W18: A corregir por M/C | X18: A corregir por M/C | Y18: A corregir por M/C | Z18: A corregir por M/C | AA18: Sin Presentar | AB18: Sin Presentar | AC18: Sin Presentar | AD18: Sin Presentar | AE18: Sin Presentar | AF18: En CURSO en DGV | AG18: 18/6/26: Se envìa Instructivo de documentaciòn legal y tècnica a presentar por M-C. EL 29/04/26 SE LE ENVÍA LOS REQUISITOS, VA A ENVIAR DOCUMENTACIÓN Completó el punto 4. Se le envió el 29/04/26 los restantes items para completar Expte. | AH18: 46139 | AI18: Técnica DGV
A19: Villa Sarmiento | B19: General Roca | C19: 0423-079096/2026 | D19: 14 | E19: C | F19: OSVALDO ESTRADA | G19: (3583) 43-0074 | H19: _ | I19: rojobufa@gmail.com | J19: 210000000 | K19: 1530 | L19: 1575 | M19: Completo OK | N19: Completo OK | O19: A corregir por M/C | P19: A corregir por M/C | Q19: Completo OK | R19: Completo OK | S19: Sin Presentar | T19: Completo OK | U19: Completo OK | V19: A corregir por M/C | W19: Sin Presentar | X19: Completo OK | Y19: Completo OK | Z19: Completo OK | AA19: Completo OK | AB19: Completo OK | AC19: Completo OK | AD19: Completo OK | AE19: Completo OK | AF19: En CURSO en DGV | AG19: 03-07-2026 Completar: - Pto. 3 en Declarac. Jurada y.... Se deberà colocar las Geo Referenc. en los domicilios que figuren como (calle Publica sin Numero y tambien en los de Zona Rural) - En la Memoria pto. 3 colocar PLAZO de OBRA (Ver instruct.) -En ambas PLANIM. Generales colocar (Geo Referenc. y Medidas generales Largo y ancho de las calles del proyecto). - Presentar DETALLE Perfil Transversal de Calzada) Ver instructivo. - 30/6/2026: Se solicito por email envien imagen de DNI y CBU con mas definicion. el resto de la documentación esta completa. 19-06-2026- Se solicita al arq. Buffa ( 1CBU Y2 DNI borrosos + 3Sobre las Planim. Gral coloque las Geo Refer de los 3 sectores de obra + 4 faltan Perfil transv de calzada ) 12-06-2026 Se pidio al arq. R.Buffa estos faltantes + Georef. en pl. gral. --RTA.: 11-06-2026 de esta correc. solo faltan en TECNICA (agregar cortes transv. de calz. + detalle de paquete estr. de calz + detalles de cordones cun y badenes lo demas correcto) + en LEG ( en Nota contad pto 5 cambiar el plazo a 180 dias) -22-06-2026 - 04-06-2026 - Deben completar (Pto 4- graficos Detalles de Perfiles transv. de calzada + detalle graf. de cordon cuneta + secc transv. de de vaden + Pto. Nª 9 Acta de proclamac cantidad de votos?..Preguntar a Natalia) Ya ajustó los montos… Pasó $236.529.986,60 y debe ser de $210.000.000 - Debe cambiar Nota Inicial, dice plazo obra 365 días y debe decir 180 días El 29/05/26 ingresa nva. Nota digi 0697832111-126 (La parte técnica ya está ok - Pero falta cambiar: Plazo de Obra, en Nota inicial) YA LO CAMBIÓ Y ENVIÓ 29/5/26 El 26/05/26 se recibe nueva documentación. ¡Se excede del monto estipulado! Debe calcular ENVIÓ DOCUMENTACIÓN PARA SER ANALIZADA. El 12/5/26 se envía correcciones técnicas y documentación gráfica y planillas modelo, para realizar nueva presentación. | AH19: 46139 | AI19: Técnica DGV
A20: La Batea | B20: Cruz del Eje | C20: 0423-079110/026 | D20: 15 | E20: C | F20: IVÁN DENIS FARÍAS | G20: (3549) 46-5986 | H20: fariasivandenis@gmail.com | J20: 50000000 | M20: Sin Presentar | N20: Sin Presentar | O20: Sin Presentar | P20: Sin Presentar | Q20: Sin Presentar | R20: Sin Presentar | S20: Sin Presentar | T20: Sin Presentar | U20: Sin Presentar | V20: Sin Presentar | W20: Sin Presentar | X20: Sin Presentar | Y20: Sin Presentar | Z20: Sin Presentar | AA20: Sin Presentar | AB20: Sin Presentar | AC20: Sin Presentar | AD20: Sin Presentar | AE20: Sin Presentar | AF20: A INICIAR en DGV | AG20: 26/6/26: Silvia informa que la localidad NO quiere adherir al Convenio, NO CONTINUAR EL TRÀMITE. 24/6/26:Comunicación con el pres. comunal. Se envía Instructivo de la documentación legal y técnica requerida. El 8/5/26 se le envía documentación modelo para participar en el Programa. Presentó decumentación que está siendo estudiada. | AH20: 46139 | AI20: Técnica DGV
A21: Tuclame | B21: Cruz del Eje | C21: 0423-079113/2026 | D21: 16 | E21: C | F21: GRACIELA DEL VALLE GONZÁLEZ | G21: (3549) 53-7628 | H21: gracieladelvallegonzalez20@gmail.com | J21: 200000000 | K21: 400 | M21: Completo OK | N21: Completo OK | O21: Completo OK | P21: Completo OK | Q21: Completo OK | R21: Completo OK | S21: Completo OK | T21: Completo OK | U21: Completo OK | V21: Completo OK | W21: Completo OK | X21: Completo OK | Y21: Completo OK | Z21: Completo OK | AA21: Completo OK | AB21: Completo OK | AC21: Completo OK | AD21: Completo OK | AE21: Completo OK | AF21: COMPLETO en DGV | AG21: COMPLETÓ documentación. Subió a Jurídico Con V°B°. EN LA PRIVADA DESDE 19/05/26 ENVIÓ LA DOCUMENTACIÓN. ESTÁS COMPLETA, SÓLO DEBE CORREGIR CRONOGRAMA DE INVERSIONES. COMPLETO. CON V°B° DE TÉCNICA | AH21: 46205 | AI21: Tribunal de Cuentas
A22: Colonia Italiana | B22: Marcos Juárez | C22: 0423-079102/2026 | D22: 17 | E22: M | F22: ALEJANDRA SOLEDAD ITA | G22: (3468) 50-1628 | H22: alejandraita26@hotmail.com | J22: 80000000 | K22: 889 | M22: Completo OK | N22: Completo OK | O22: Completo OK | P22: Completo OK | Q22: Completo OK | R22: Completo OK | S22: Completo OK | T22: Completo OK | U22: Completo OK | V22: Completo OK | W22: Completo OK | X22: Completo OK | Y22: Completo OK | Z22: Completo OK | AA22: Completo OK | AB22: Completo OK | AC22: Completo OK | AD22: Completo OK | AE22: Completo OK | AF22: COMPLETO en DGV | AG22: 30/6/2026: Expte. PASA A LEGALES 29/6/2026: Documentaciòn en orden para anexar al Expte. y dar curso. 29/6/2026: Documentaciòn en orden para anexar al Expte. y dar curso. 19/6/26: Deben completar y corregir. 18/06/2026 enviaron memoria y doc tecnica corregida segun obervaciones. P- 17-06-2026 Se envìan correg/completar: ( firma y sello del prof. en cada hoja grafic.+ falta perfil transversal de calzada aunque no tenga paq. estr. determinando mat. de relleno) + pto.6 no se enviò imagen, del CBU el enviado tiene imagen parcial cortada) P- 11-06-2026 TEC.:( Faltan Memoria + Planim. con cotas + todos los detalles cortes + Cronogr. de Avances en 6 mese + todo sellado y firm x profes.) 11/6/26: Se solicita nuevamente la documentaciòn tècnica faltante. La arq. completará. P- 08-06-2026 - Pto. Nª 2 Falta Sello y firma del Tesorero o esta borroza Secr. tesor. + Pto. Nª 4 ( Faltan cotas grales de cada manz. en la planialtim. + cortes transv. + detalles + Planilla de avances cronograma de obra + Ubica y Memoria) El 30/04/26 vino la intendente Alejandra Ita a consultar por el Programa. Pregunta por el descuento por copa posterior. | AH22: 46205 | AI22: Jurídico DGV
A23: Los Hornillos | B23: San Javier | C23: 0423-079117/2026 | D23: 18 | E23: C | F23: CAROLINA CABALLERO | G23: (3544) 41-0108 | H23: _ | I23: Arq. Adriàn Heredia (3544) 434500 Noelia Del Aguila (3544) 40-6139 | J23: 150000000 | K23: 913.3 | L23: 534 | M23: Completo OK | N23: Completo OK | O23: Completo OK | P23: Completo OK | Q23: Completo OK | R23: Completo OK | S23: Completo OK | T23: Completo OK | U23: Completo OK | V23: Completo OK | W23: Completo OK | X23: Completo OK | Y23: Completo OK | Z23: Completo OK | AA23: Completo OK | AB23: Completo OK | AC23: Completo OK | AD23: Completo OK | AE23: Completo OK | AF23: COMPLETO en DGV | AG23: 8/6/26 PASA DE AREA TECNICA A LEGALES // P- 04-06-2026 - Se tilda al Pto. Nª 4 (para que se modifique la unidad del cordon cun. a ml en el Comp Metrico) EL 28/04/26 SE LE ENVÍA LOS REQUISITOS, VA A ENVIAR DOCUMENTACIÓNP- 3/6/2026 Se envió documentacion completa digital por email y lo recibiò Jurídica. EN CONDICIONES. EN LA PRIVADA DESDE 28/05/26 El 26/05/2026 se envía toda la Documentación completa con las correcciones ya corregidas por parte de la Comuna. El 26/5/26 se envía a Jurídico todo completo El 20/05/26 se aprueba la parte técnica, sube a jurídico. El 7/5/26 se envía escaneo de docum. Técnica para corregir, también se envía modelo de avance de obra por 6 meses. El 7/5/26 se solicitó corregir el punto 4 (doc. técnica) y se solicita cambio y corrección de Nota inicial. Presentó el 30/04/26 toda la documentación. El cómputo y presupuesto se pasa en $240.991-Se pide que se corrija. | AH23: 46199 | AI23: Tribunal de Cuentas
A24: General Roca | B24: Marcos Juárez | C24: 0423-079133/2026 | D24: 19 | E24: M | F24: FRANCISCO FACUNDO ISER | G24: (3472) 63-7614 | H24: _ | J24: 240000000 | M24: Completo OK | N24: Completo OK | O24: Completo OK | P24: Completo OK | Q24: Completo OK | R24: Completo OK | S24: Completo OK | T24: Completo OK | U24: Completo OK | V24: Completo OK | W24: Completo OK | X24: Completo OK | Y24: Completo OK | Z24: Completo OK | AA24: Completo OK | AB24: Completo OK | AC24: Completo OK | AD24: Completo OK | AE24: Completo OK | AF24: COMPLETO en DGV | AG24: Completó documentación y se elevó a jurídica para su estudio. COMPLETO. CON V°B° DE TÉCNICA. | AH24: 46205 | AI24: Tribunal de Cuentas
A25: Rosales | B25: Presidente Roque Sáenz Peña | C25: 0423-079114/2026 | D25: 20 | E25: M | F25: ARIEL GUSTAVO PANICHELLI | G25: (3385) 43-0090 | H25: munirosales.cba@gmail.com | I25: Perezrodrigomiguel@gmail.com | J25: 100000000 | M25: En Evaluaciòn Jurìdico | N25: En Evaluaciòn Jurìdico | O25: En Evaluaciòn Jurìdico | P25: A corregir por M/C | Q25: A corregir por M/C | R25: A corregir por M/C | S25: A corregir por M/C | T25: A corregir por M/C | U25: A corregir por M/C | V25: A corregir por M/C | W25: A corregir por M/C | X25: A corregir por M/C | Y25: A corregir por M/C | Z25: A corregir por M/C | AA25: En Evaluaciòn Jurìdico | AB25: En Evaluaciòn Jurìdico | AC25: En Evaluaciòn Jurìdico | AD25: En Evaluaciòn Jurìdico | AE25: En Evaluaciòn Jurìdico | AF25: A INICIAR en DGV | AG25: 07/7/2026: Envìan contacto y correo electrònico del ing. a cargo de la obra. 24/6/26: Se enviò Instructivo .El 8/05/26 se envió documentación modelo para participar. El 11/ envió documentación a analizar | AH25: 46139 | AI25: Técnica DGV
A26: La Cesira | B26: Presidente Roque Sáenz Peña | C26: 0423-079809/2026 | D26: 22 | E26: M | F26: GUILLERMO LEGORBURU | G26: (3382) 672961 | H26: rossettomaxi@gmail.com | J26: 200000000 | L26: 3440 | M26: Completo OK | N26: Completo OK | O26: Completo OK | P26: Completo OK | Q26: Completo OK | R26: Completo OK | S26: Completo OK | T26: Completo OK | U26: Completo OK | V26: Completo OK | W26: Completo OK | X26: Completo OK | Y26: Completo OK | Z26: Completo OK | AA26: Completo OK | AB26: Completo OK | AC26: Completo OK | AD26: Completo OK | AE26: Completo OK | AF26: APROBADO por TC | AG26: 8/6/26 PASA DE AREA TECNICA A LEGALES //3/6/2026 Se envió documentacion completa digital por email y lo recibiò Jurídica. SUBIDA EL 29-05-26 28/5/26, debe cambiar la nota de pedido a la contaduría Gral. y no se ve firma en la declaracion jurada. El 27/05/26 presentó toda la documentación (completa la parte técnica). Debe cambiar la Nota de inicio, corregir Monto y Plazo de Obra. LISTO, Pero ahora, El 27/05/2026 el municipio presentó el total de la información, se solicita que cambie la Nota inicial, con el momto de obra y el plazo de la misma.. EN CONDICIONES Se presentó nuevo Expte. con nuevo monto asignado - Pasó a $200.000.000. | AH26: 46211 | AI26: Aprobado TC
A27: Las Perdices | B27: Tercero Arriba | C27: PEDIR BETI | D27: 23 | E27: M | F27: SERGIO AVALIS | G27: (3534) 234615 | J27: _ | M27: Sin Presentar | N27: Sin Presentar | O27: Sin Presentar | P27: Sin Presentar | Q27: Sin Presentar | R27: Sin Presentar | S27: Sin Presentar | T27: Sin Presentar | U27: Sin Presentar | V27: Sin Presentar | W27: Sin Presentar | X27: Sin Presentar | Y27: Sin Presentar | Z27: Sin Presentar | AA27: Sin Presentar | AB27: Sin Presentar | AC27: Sin Presentar | AD27: Sin Presentar | AE27: Sin Presentar | AF27: A INICIAR en DGV | AG27: 25-6-26: Comunicación con int. Se espera autirización Ministerio Gobierno. El 08/05/26 se realia comunicación telefónica con el intendente. Va a enviar su documentación. SIN EXPEDIENTE. | AH27: 46150 | AI27: _
A28: Colonia Barge | B28: Marcos Juárez | C28: 0423-079784/2026 | D28: 24 | E28: M | F28: SERGIO RODRIGUEZ | G28: (3468) 569782 | H28: Mnina@ccbarge.gob.ar /// nvrodriguez@ccbarge.gob.ar | I28: emanuelmartinatto@gmail.com | J28: 50000000 | M28: Sin Presentar | N28: Sin Presentar | O28: Sin Presentar | P28: Sin Presentar | Q28: Sin Presentar | R28: Sin Presentar | S28: Sin Presentar | T28: Sin Presentar | U28: Sin Presentar | V28: Sin Presentar | W28: Sin Presentar | X28: Sin Presentar | Y28: Sin Presentar | Z28: Sin Presentar | AA28: Sin Presentar | AB28: Sin Presentar | AC28: Sin Presentar | AD28: Sin Presentar | AE28: Sin Presentar | AF28: A INICIAR en DGV | AG28: 24/6/26: Comunicaciòn con la comuna. Se enviò Instructivo. El 11/5/26 se logra comunicación con municipalidad. Se pasa por whatsapp la documentación modelo | AH28: 46153 | AI28: _
A29: Saira | B29: Marcos Juárez | C29: 0423-079781/2026 | D29: 25 | E29: M | F29: EDGAR JORDÁN | G29: (3472) 502676 | H29: nvrodriguez@ccbarge.gob.ar | J29: 150000000 | M29: Sin Presentar | N29: Sin Presentar | O29: Sin Presentar | P29: Sin Presentar | Q29: Sin Presentar | R29: Sin Presentar | S29: Sin Presentar | T29: Sin Presentar | U29: Sin Presentar | V29: Sin Presentar | W29: Sin Presentar | X29: Sin Presentar | Y29: Sin Presentar | Z29: Sin Presentar | AA29: Sin Presentar | AB29: Sin Presentar | AC29: Sin Presentar | AD29: Sin Presentar | AE29: Sin Presentar | AF29: A INICIAR en DGV | AG29: 22/6/26: Se envìa Instructivo. 12/6/26: Se envìa Modelos de doc. tecnica y se avisa que en breve se enviarà el instructivo total del Programa. 10/6/26: Comunicaciòn con municipio para enviar Instructivo de Documentaciòn A presentar. El 11/5/26 se logra comunicación con municipalidad. Se pasa por whatsapp la documentación modelo. Envió documentación pero pide para PAVIMENTO | AH29: 46153 | AI29: _
A30: Camilo Aldao | B30: Marcos Juárez | C30: 0423-079782/2026 | D30: 26 | E30: M | F30: MARIO DOMINGO BACELLI | G30: (3468) 644516 | H30: munca@nodosud.com.ar munca@futurnet.com.ar mariobacelli@hotmail.com | I30: ARQ. GISELA MIRIANI (3468)51-6292 | J30: 100000000 | L30: 3600 | M30: Completo OK | N30: Completo OK | O30: Completo OK | P30: Completo OK | Q30: Completo OK | R30: Completo OK | S30: Completo OK | T30: Completo OK | U30: Completo OK | V30: Completo OK | W30: Completo OK | X30: Sin Presentar | Y30: Sin Presentar | Z30: Completo OK | AA30: Completo OK | AB30: Completo OK | AC30: Completo OK | AD30: Completo OK | AE30: Completo OK | AF30: COMPLETO en DGV | AG30: 13-07-2026 Se recibio doc. completa ordenada en 3 PDF 13-07-2026 Avisa la arqta. Gise, que enviò toda la doc. por mail. NO llego, se dio aviso para su re envio 08-07-2026 Se solicita al arq. la Present. de toda la doc. corregida completa s/ intructivo (Como iniciar el tram.) 07-07-2026 Se recibe doc. para completar pto 9 03/7/2026: Se solicita completen el acta de aceptación del cargo del intendente. 30/6/2026: Expte. PASA A LEGALES 29/6/2026: Documentaciòn en orden para anexar al Expte. y dar curso. - 05-06-2026 - Pto. 4 ( Falta cronograma de avance de obra + En planimetria gral. colocar las Geo referencias de los cuatro sectores de obra) Se solicitan nuevos cambios. COMPLETÓ DOCUMENTACIÓN 01/06/26 - Se pasan las actuaciones a arq. Carlos Viana para enviar a Jurídico Se envían el 26/05/26, nuevas correcciones, se recibe nueva documentación técnica el 29/05/26. 07-07-2026 Se recibe doc. Pto. 9 p/ completar exp. El 26/05/26 se envió correcciones a la parte técnica. Documentación Corregida. Sube a Jurídico El 19/05/26 se recibe documentación corregida para su análisis. El 11/5/26 se logra comunicación con municipalidad. Se pasa por whatsapp la documentación modelo. | AH30: 46205 | AI30: Jurídico DGV
A31: Arias | B31: Marcos Juárez | C31: 0423-079785/2026 | D31: 27 | E31: M | F31: NÉSTOR DEFAGOT DIAZ | G31: (3468) 512149 | H31: njdefagot@hotmail.com.ar | I31: ing.jmaldonado@gmail.com | J31: 100000000 | L31: 920.9 | M31: A corregir por M/C | N31: A corregir por M/C | O31: A corregir por M/C | P31: A corregir por M/C | Q31: A corregir por M/C | R31: A corregir por M/C | S31: A corregir por M/C | T31: A corregir por M/C | U31: Completo OK | V31: A corregir por M/C | W31: Completo OK | X31: A corregir por M/C | Y31: Completo OK | Z31: Completo OK | AA31: A corregir por M/C | AB31: Completo OK | AC31: Completo OK | AD31: Completo OK | AE31: A corregir por M/C | AF31: En CURSO en DGV | AG31: 08/7/2026: Se enviaron observaciones (Email) al municipio y profesional responsable para corregir.. 25-06-2026 - Se enviaron imagenes de las correcc. y re envio del instructivo p/ whats al ing. 24-06-2026 - Se enviaron correcciones por whats al ing. 23/6/2026: la nota de pedido tiene un valor mayor cotizado, 4to parrafo del considerando y art, 4,debe decir:seis meses (6) a partir de efectivizado el primer desembolso, nota a contaduria completar, falta DDJJ y acta de aceptacion del cargo, 22/6/26: Comunicaciòn con Int. y profesional para corregir documentaciòn conforme al instructivo. 19/6/26: Comunicación con Municipio. Docuemtación En Evaluación. 4/6/26:Presentan documentaciòn por Cidi- En evaluaciòn tècnica - El 11/5/26 se logra comunicación con municipalidad. Se pasa por whatsapp la documentación modelo | AH31: 46153 | AI31: Técnica DGV
A32: General Baldissera | B32: Marcos Juárez | C32: 0423-079783/2026 | D32: 28 | E32: M | F32: LUCAS PERASSI | G32: (3468) 512117 | H32: munigbaldissera@gmail.com | I32: ebigi@hotmail.com | J32: 100000000 | M32: Sin Presentar | N32: Sin Presentar | O32: Sin Presentar | P32: Sin Presentar | Q32: Sin Presentar | R32: Sin Presentar | S32: Sin Presentar | T32: Sin Presentar | U32: Sin Presentar | V32: Sin Presentar | W32: Sin Presentar | X32: Sin Presentar | Y32: Sin Presentar | Z32: Sin Presentar | AA32: Sin Presentar | AB32: Sin Presentar | AC32: Sin Presentar | AD32: Sin Presentar | AE32: Sin Presentar | AF32: A INICIAR en DGV | AG32: 24/6/26: Se envía Instructivo de documentación legal y técnica requerida. 22/6/26: Se solicitan correos electrònicos del municipio y profesional a cargo. El 11/5/26 se logra comunicación con municipalidad. Se pasa por whatsapp la documentación modelo | AH32: 46153 | AI32: _
A33: Matorrales | B33: Río Segundo | C33: 0423-079944/2026 | D33: 29 | E33: M | F33: FRANCO CINGOLANI | G33: (3573) 513735 | H33: Munimatorrales@hotmail.com | I33: germangarino@gmail.com | J33: 80000000 | M33: Sin Presentar | N33: Sin Presentar | O33: Sin Presentar | P33: Sin Presentar | Q33: Sin Presentar | R33: Sin Presentar | S33: Sin Presentar | T33: Sin Presentar | U33: Sin Presentar | V33: Sin Presentar | W33: Sin Presentar | X33: Sin Presentar | Y33: Sin Presentar | Z33: Sin Presentar | AA33: Sin Presentar | AB33: Sin Presentar | AC33: Sin Presentar | AD33: Sin Presentar | AE33: Sin Presentar | AF33: A INICIAR en DGV | AG33: 07/7/2026: Se solicita verifiquen el correo de la municipalidad porque NO se puede entregar. El municipio dice que enviaron con error. Se envìa nuevamente el Instructivo al correo correcto. 01/7/2026: Se envìa Instructivo de la documentaciòn legal y tècnica requerida por el Programa. 22/6/26: Comunicaciòn con el municipio para enviar Instructivo. El 26/05/2026 se envía WhatsApp a intendente. El 27/05/2026 se logra la comunicación telefónica. | AH33: 46167 | AI33: _
A34: Embalse | B34: Calamuchita | C34: 0423-079932/2026 | D34: 30 | E34: M | F34: MARIO RIVAROLA | G34: (3571) 526135 | H34: crayanes@gmail.com | I34: jjorgeaquiroga@gmail.com | J34: 200000000 | M34: Completo OK | N34: Completo OK | O34: Completo OK | P34: A corregir por M/C | Q34: A corregir por M/C | R34: A corregir por M/C | S34: A corregir por M/C | T34: Completo OK | U34: Completo OK | V34: A corregir por M/C | W34: Completo OK | X34: Sin Presentar | Y34: Sin Presentar | Z34: Sin Presentar | AA34: Sin Presentar | AB34: Completo OK | AC34: Completo OK | AD34: Completo OK | AE34: A corregir por M/C | AF34: En CURSO en DGV | AG34: 13/7/2026: Se solicita contacto de contador municipio (a cargo del tràmite). 01/7/2026: Se enviaron al municipio y profesional a cargo, las Observaciones A corregir. 01/7/2026: Comunicación con el municipio, presentan documentaciòn A evaluar. 29/6/2026: Comunicaciòn con la Contadora del municipio. Se solicitò la documentaciòn y dijeron que Hoy presentaban. Se aguarda la misma. 19/6/26: Se envía Instructivo de documentación legal y técnica requerida. 11/6/26: Se envìa nuevamente el instructivo Area Tècnica para que corrijan documentaciòn presentada. 10/6/26: Comunicaciòn con municipio para enviar Instructivo de Documentaciòn A presentar. P- Corregir a: $ 200.000.000- en todo lugar donde se denomine el Monto de Obra. + Agregar (cotas) a la Planimetria El 26/05/2026 nos comunicamos telefónicamente con intendente. Se le envía WhatsApp documentación modelo. El 27/05/2026 se recibe documentación de parte de la Municipalidad. El 28/05/26 se envían las correcciones de la parte técnica | AH34: 46167 | AI34: Técnica DGV
A35: Las Varillas | B35: San Justo | C35: 0423-079946/2026 | D35: 31 | E35: M | F35: MAURO DANIELE | G35: (3573) 414656 | H35: maurodanielelv@gmail.com | J35: 400000000 | M35: Sin Presentar | N35: Sin Presentar | O35: Sin Presentar | P35: Sin Presentar | Q35: Sin Presentar | R35: Sin Presentar | S35: Sin Presentar | T35: Sin Presentar | U35: Sin Presentar | V35: Sin Presentar | W35: Sin Presentar | X35: Sin Presentar | Y35: Sin Presentar | Z35: Sin Presentar | AA35: Sin Presentar | AB35: Sin Presentar | AC35: Sin Presentar | AD35: Sin Presentar | AE35: Sin Presentar | AF35: A INICIAR en DGV | AG35: 19/6/26: Se envía Instructivo de documentación legal y técnica requerida. El 26/05/2026 se comunica con el intendente, y se le envía documentación del Programa. El 28/05/2026 se pasa el monto asignado de $400.000.000 | AH35: 46167 | AI35: _
A36: Calchín | B36: Río Segundo | C36: 0423-079943/2026 | D36: 32 | E36: M | F36: CLAUDIO CAON | G36: (3573) 498726 | H36: sg_municalchin@hotmail.com | J36: 50000000 | M36: A corregir por M/C | N36: Sin Presentar | O36: A corregir por M/C | P36: Sin Presentar | Q36: Sin Presentar | R36: Sin Presentar | S36: Sin Presentar | T36: Sin Presentar | U36: Sin Presentar | V36: Sin Presentar | W36: Sin Presentar | X36: Sin Presentar | Y36: Sin Presentar | Z36: Sin Presentar | AA36: A corregir por M/C | AB36: Sin Presentar | AC36: Sin Presentar | AD36: Sin Presentar | AE36: Sin Presentar | AF36: En CURSO en DGV | AG36: 19/6/26: El municipio presenta documentación a corregir y completar. Se envía INSTRUCTIVO de la documentación legal y técnica requerida.El 26/05/2026 se logra la comunicación telefónica con el Intendente. Se le envía documentación modelo por WhatsApp | AH36: 46167 | AI36: Técnica DGV
A37: Villa Parque Santa Ana | B37: Santa María | C37: 0423-079945/2026 | D37: 33 | E37: M | F37: SERGIO CERDA | G37: (351) 2045478 | J37: 150000000 | M37: Sin Presentar | N37: Sin Presentar | O37: Sin Presentar | P37: Sin Presentar | Q37: Sin Presentar | R37: Sin Presentar | S37: Sin Presentar | T37: Sin Presentar | U37: Sin Presentar | V37: Sin Presentar | W37: Sin Presentar | X37: Sin Presentar | Y37: Sin Presentar | Z37: Sin Presentar | AA37: Sin Presentar | AB37: Sin Presentar | AC37: Sin Presentar | AD37: Sin Presentar | AE37: Sin Presentar | AF37: A INICIAR en DGV | AG37: 19/6/26: Se envía Instructivo de documentación legal y técnica requerida. 12/6/26: Comunicaciòn con Sec. Gobierno para dar inicio al tràmite. El 26/05/2026 se logra la comunicación telefónica con el Intendente. Se le envía documentación modelo por WhatsApp | AH37: 46167 | AI37: _
A38: Pozo del Molle | B38: Río Segundo | C38: 0423-079948/2026 | D38: 34 | E38: M | F38: FERNANDO RUIZ DÍAZ | G38: (3534) 227342 | H38: Intendencia@pozodelmolle.gob.ar | J38: 200000000 | M38: Sin Presentar | N38: Sin Presentar | O38: Sin Presentar | P38: Sin Presentar | Q38: Sin Presentar | R38: Sin Presentar | S38: Sin Presentar | T38: Sin Presentar | U38: Sin Presentar | V38: Sin Presentar | W38: Sin Presentar | X38: Sin Presentar | Y38: Sin Presentar | Z38: Sin Presentar | AA38: Sin Presentar | AB38: Sin Presentar | AC38: Sin Presentar | AD38: Sin Presentar | AE38: Sin Presentar | AF38: A INICIAR en DGV | AG38: 01/7/2026: Se envìa Instructivo de la documentaciòn legal y tècnica requerida. 01/7/2026: Comunicación con el municipio solicitando Correos Electrónicos para enviar Instructivo. El 27/05/2026 se logra la comunicación telefónica con el Intendente. Se le envía documentación modelo por WhatsApp | AH38: 46167 | AI38: _
A39: Capilla del Carmen | B39: Río Segundo | C39: 0423-079942/2026 | D39: 35 | E39: M | F39: DANIEL TURINA | G39: (3573) 402343 | H39: municapilladelcarmen@hotmail.com | I39: 3573-465684 lpleita@hotmail.com | J39: 100000000 | L39: 1600 | M39: A corregir por M/C | N39: En Evaluaciòn Jurìdico | O39: En Evaluaciòn Jurìdico | P39: A corregir por M/C | Q39: A corregir por M/C | R39: A corregir por M/C | S39: A corregir por M/C | T39: A corregir por M/C | U39: A corregir por M/C | V39: Sin Presentar | W39: Completo OK | X39: Sin Presentar | Y39: Sin Presentar | Z39: Completo OK | AA39: En Evaluaciòn Jurìdico | AB39: En Evaluaciòn Jurìdico | AC39: En Evaluaciòn Jurìdico | AD39: En Evaluaciòn Jurìdico | AE39: En Evaluaciòn Jurìdico | AF39: En CURSO en DGV | AG39: 30/6/2026: Se enviaron observaciones A Corregir por el Municipio / Se envió nuevamente el Instructivo al arq. a cargo. 29/6/2026: El Municipio presenta Documentaciòn a corregir. Se espera Informe de legales para enviar Observaciones al municipio. 18/6/26: Se envìa Instructivo de documentaciòn legal y tècnica a presentar por M-C. El 27/05/2026 se logra la comunicación telefónica con el Intendente. Se le envía documentación modelo por WhatsApp | AH39: 46169 | AI39: _
A40: Sacanta | B40: San Justo | C40: 0423-080124/2026 | D40: 38 | F40: Mecchia Jose Luis | G40: 3533580162 | H40: Intendente@sacanta.gob.ar | I40: Secretariodegobierno@sacanta.gob.ar | J40: 70000000 | M40: Sin Presentar | N40: Sin Presentar | O40: Sin Presentar | P40: Sin Presentar | Q40: Sin Presentar | R40: Sin Presentar | S40: Sin Presentar | T40: Sin Presentar | U40: Sin Presentar | V40: Sin Presentar | W40: Sin Presentar | X40: Sin Presentar | Y40: Sin Presentar | Z40: Sin Presentar | AA40: Sin Presentar | AB40: Sin Presentar | AC40: Sin Presentar | AD40: Sin Presentar | AE40: Sin Presentar | AF40: A INICIAR en DGV | AG40: 29/6/2026: Se envía nuevamente al municipio (Email) el Instructivo de la documentación legal y técnica requerida. 24/6/26: El Intendente informa que el monto autorizado es de $100 mill. y no $70 como dice la autorización previa. Ya hizo la gestión para que corrijan. /// Se envía Instructivo de la documentación legal y técnica a presentar.....23/6/26: Comunicaciòn con municipio solicitando Correo electrònico. 5/6/26: Ingresa Nota Ministerio Gobierno autorizando financiamiento.
A41: Los Reartes | B41: Calamuchita | C41: 0423-080115/2026 | D41: 39 | H41: inesramello@losreartes.gob.ar | I41: Ing. Martin Gallo 351-6645348 Mail: martingallo2012@gmail.com | J41: 100000000 | K41: 418 | L41: 1379 | M41: En Evaluaciòn Jurìdico | N41: En Evaluaciòn Jurìdico | O41: En Evaluaciòn Jurìdico | P41: A corregir por M/C | Q41: A corregir por M/C | R41: A corregir por M/C | S41: A corregir por M/C | T41: A corregir por M/C | U41: A corregir por M/C | V41: A corregir por M/C | W41: A corregir por M/C | X41: A corregir por M/C | Y41: A corregir por M/C | Z41: A corregir por M/C | AA41: En Evaluaciòn Jurìdico | AB41: En Evaluaciòn Jurìdico | AC41: En Evaluaciòn Jurìdico | AD41: En Evaluaciòn Jurìdico | AE41: En Evaluaciòn Jurìdico | AF41: En CURSO en DGV | AG41: 03/7/2026: Presentan documentación en evaluaciòn. 22/6/26:Comunicaciòn con la pres. comunal. Se envìa Instructivo de la documentaciòn legal y tècnica requerida al munic. y al profesional. . 5/6/26: Ingresa Nota Ministerio Gobierno autorizando financiamiento.
A42: Laboulaye | B42: Presidente Roque Sáenz Peña | C42: 0423-080119/2026 | D42: 40 | H42: sec_opublicas@munilaboulaye.gov.ar | J42: 200000000 | M42: Sin Presentar | N42: Sin Presentar | O42: Sin Presentar | P42: Sin Presentar | Q42: Sin Presentar | R42: Sin Presentar | S42: Sin Presentar | T42: Sin Presentar | U42: Sin Presentar | V42: Sin Presentar | W42: Sin Presentar | X42: Sin Presentar | Y42: Sin Presentar | Z42: Sin Presentar | AA42: Sin Presentar | AB42: Sin Presentar | AC42: Sin Presentar | AD42: Sin Presentar | AE42: Sin Presentar | AF42: A INICIAR en DGV | AG42: 23/6/26: Se solicitan correos electrònicos de municipio y profesional. Se Envìa INSTRUCTIVO de documentaciòn legal y tècnica requerida. 5/6/26: Ingresa Nota Ministerio Gobierno autorizando financiamiento.
A43: Santa Eufemia | B43: Juárez Celman | C43: 0423-080118/2026 | D43: 41 | E43: M | F43: Gisela Barrionuevo | G43: 3584405706 | H43: municipalidadsantaeufemia@gmail.com | I43: muni-staeufemia@hotmail.com.a | J43: 150000000 | K43: 580 | L43: 3101 | M43: En Evaluaciòn Jurìdico | N43: En Evaluaciòn Jurìdico | O43: En Evaluaciòn Jurìdico | P43: En Evaluaciòn Tècnica | Q43: A corregir por M/C | R43: A corregir por M/C | S43: Sin Presentar | T43: A corregir por M/C | U43: Sin Presentar | V43: A corregir por M/C | W43: A corregir por M/C | X43: A corregir por M/C | Y43: A corregir por M/C | Z43: A corregir por M/C | AA43: En Evaluaciòn Jurìdico | AB43: En Evaluaciòn Jurìdico | AC43: En Evaluaciòn Jurìdico | AD43: En Evaluaciòn Jurìdico | AE43: En Evaluaciòn Jurìdico | AF43: En CURSO en DGV | AG43: 08/7/2026: Presentan documentaciòn En evaluaciòn àrea tècnica y legales. 24/6/26 Comunicaciòn con municipio y se envìa Instructivo de documentaciòn legal tècnica requerida. 5/6/26: Ingresa Nota Ministerio Gobierno autorizando financiamiento. | AH43: 46178 | AI43: Técnica DGV
A44: Olaeta | B44: Juárez Celman | C44: 0423-080117/2026 | D44: 42 | E44: M | F44: Gaston Bravo | G44: 3586543232 | H44: arquitecturaolaeta@gmail.com | I44: arquitecturaolaeta@gmail.com | J44: 180000000 | K44: 496 | L44: 3200 | M44: A corregir por M/C | N44: Completo OK | O44: Completo OK | P44: A corregir por M/C | Q44: A corregir por M/C | R44: A corregir por M/C | S44: Completo OK | T44: Completo OK | U44: Completo OK | V44: Completo OK | W44: A corregir por M/C | X44: Completo OK | Y44: Completo OK | Z44: Completo OK | AA44: A corregir por M/C | AB44: Completo OK | AC44: Completo OK | AD44: Completo OK | AE44: A corregir por M/C | AF44: En CURSO en DGV | AG44: 13/7/2026: Comunicaciòn con la arq. a cargo. Se hacen observaciones sobre doc. tècnica a corregir. 08/7/2026: Se envìa al municipio (por Email) las correcciones que deben realizar. 03/7/2026: Presentan documentaciòn en Evaluaciòn. 19/6/26: El municipio presenta documentación a corregir y completar. Se envía INSTRUCTIVO de la documentación legar y técnica requerida. 5/6/26: Ingresa Nota Ministerio Gobierno autorizando financiamiento. | AH44: 46192 | AI44: Técnica DGV
A45: Las Varas | B45: San Justo | C45: 0423-080123/2026 | D45: 43 | E45: M | F45: Fabian Macias | G45: 3533402890 | H45: municipalidaddelasvarasinterno@gmail.com | I45: carolinasirerol@gmail.com | J45: 150000000 | M45: Sin Presentar | N45: Sin Presentar | O45: Sin Presentar | P45: Sin Presentar | Q45: Sin Presentar | R45: Sin Presentar | S45: Sin Presentar | T45: Sin Presentar | U45: Sin Presentar | V45: Sin Presentar | W45: Sin Presentar | X45: Sin Presentar | Y45: Sin Presentar | Z45: Sin Presentar | AA45: Sin Presentar | AB45: Sin Presentar | AC45: Sin Presentar | AD45: Sin Presentar | AE45: Sin Presentar | AF45: A INICIAR en DGV | AG45: 07/7/2026: Se envìa Instructivo y listado de documentaciòn requerida por el Programa. 01/7/2026: Se reitera la solicitud de Correos electrónicos y contactos. Se envìa Instructivo. 24/6/26:Comunicación con el municipio. Hoy es feriado en las Varas (Fiestas Patronales) Ya nos enviaran datos de Correos. 5/6/26: Ingresa Nota Ministerio Gobierno autorizando financiamiento. 24/6/26:Comunicación con el municipio. Hoy es feriado en las Varas (Fiestas Patronales) Ya nos enviaran datos de Correos. 5/6/26: Ingresa Nota Ministerio Gobierno autorizando financiamiento.
A46: Cruz Alta | B46: Marcos Juárez | D46: 44 | E46: M | F46: Agustin Gonzalez | G46: 3513063795 | H46: secretariadegobieno@cruzalta.gob.ar | J46: 100000000 | M46: Sin Presentar | N46: Sin Presentar | O46: Sin Presentar | P46: Sin Presentar | Q46: Sin Presentar | R46: Sin Presentar | S46: Sin Presentar | T46: Sin Presentar | U46: Sin Presentar | V46: Sin Presentar | W46: Sin Presentar | X46: Sin Presentar | Y46: Sin Presentar | Z46: Sin Presentar | AA46: Sin Presentar | AB46: Sin Presentar | AC46: Sin Presentar | AD46: Sin Presentar | AE46: Sin Presentar | AF46: A INICIAR en DGV | AG46: 24/6/26: Se contacta al municipio se envía el Instructivo de documentación legal y técnica requerida. 17/3/26: Ingresa Nota Ministerio Gobierno autorizando financiamiento.
A47: Charras | B47: Juárez Celman | C47: 0423-080116/2026 | D47: 45 | E47: M | F47: Emiliano Rattazzi | G47: 3584329533 | H47: intendente@municipalidadcharras.gob.ar | I47: 3584329533 | J47: 100000000 | L47: 3960 | M47: A corregir por M/C | N47: Completo OK | O47: Completo OK | P47: Completo OK | Q47: Completo OK | R47: Completo OK | S47: Completo OK | T47: Completo OK | U47: Completo OK | V47: Completo OK | W47: Completo OK | X47: Sin Presentar | Y47: Sin Presentar | Z47: Completo OK | AA47: En Evaluaciòn Jurìdico | AB47: Completo OK | AC47: Completo OK | AD47: Completo OK | AE47: Completo OK | AF47: En CURSO en DGV | AG47: 03/7/2026: Presentan documentaciòn nuevamente. 01/7/2026: Se envìan al municipio /profesional las Observaciones a corregir. 30-06-2026 Avisa el int. que envìo doc. por mail 18/6/26: Se envìa Instructivo de documentaciòn legal y tècnica a presentar por M-C. P -17-06-2026 Se corrige envio y se envia por whats al Intend. Emiliano p/ su completam. -RTAS.: 12/6/26: Comunicaciòn con Intendente para dar inicio al tràmite. 5/6/26: Ingresa Nota Ministerio Gobierno autorizando financiamiento. | AH47: 46190 | AI47: Técnica DGV
A48: El Fortín | B48: San Justo | C48: 0423-080122/2026 | D48: 46 | H48: Carlosentesanomap@gmail.com | I48: Ignaciocesarbianchini@gmail.com | J48: 300000000 | M48: Sin Presentar | N48: Sin Presentar | O48: Sin Presentar | P48: Sin Presentar | Q48: Sin Presentar | R48: Sin Presentar | S48: Sin Presentar | T48: Sin Presentar | U48: Sin Presentar | V48: Sin Presentar | W48: Sin Presentar | X48: Sin Presentar | Y48: Sin Presentar | Z48: Sin Presentar | AA48: Sin Presentar | AB48: Sin Presentar | AC48: Sin Presentar | AD48: Sin Presentar | AE48: Sin Presentar | AF48: A INICIAR en DGV | AG48: 29/6/2026: Comunicación con el intendenten. Se envía el Instructivo al arquitecto a cargo 18/6/26: Se envìa Instructivo de documentaciòn legal y tècnica a presentar por M-C. 8/6/26: Se envía Instructivo (Doc. Requerida) a la localidad. 5/6/26: Ingresa Nota Ministerio Gobierno
A49: Alicia | B49: San Justo | C49: 0423-080120/2026 | D49: 47 | E49: M | F49: Bianchini Agustin | G49: 3533405587 | H49: obraspublicasalicia@gmail.com | J49: 200000000 | K49: 0 | L49: 3500 | M49: Sin Presentar | N49: Sin Presentar | O49: Sin Presentar | P49: A corregir por M/C | Q49: A corregir por M/C | R49: A corregir por M/C | S49: A corregir por M/C | T49: A corregir por M/C | U49: A corregir por M/C | V49: Sin Presentar | W49: Sin Presentar | X49: Sin Presentar | Y49: Sin Presentar | Z49: Sin Presentar | AA49: Sin Presentar | AB49: Sin Presentar | AC49: Sin Presentar | AD49: Sin Presentar | AE49: Sin Presentar | AF49: En CURSO en DGV | AG49: 07/7/2026: Comunicaciòn con municipio. Mañana presentaràn documentaciòn para revisiòn legal y tècnica. 26-06-2026 --Se envian ahora tambien por Whatss el instruct. 25-6-26: Presentan documentaciòn incompleta. Se envían las observaciones .Responden que a la brevedad completan. 18/6/26: Se envìa Instructivo de documentaciòn legal y tècnica a presentar por M-C. 5/6/26: Ingresa Nota Ministerio Gobierno autorizando financiamiento.
A50: El Arañado | B50: San Justo | C50: 0423-080121/2026 | D50: 48 | F50: Gudiño Jorge Alino | G50: 3533442747 | H50: Jorgegudino276@gmail.com | I50: ab.alcantaro@gmail.com | J50: 200000000 | M50: Sin Presentar | N50: Sin Presentar | O50: Sin Presentar | P50: Sin Presentar | Q50: Sin Presentar | R50: Sin Presentar | S50: Sin Presentar | T50: Sin Presentar | U50: Sin Presentar | V50: Sin Presentar | W50: Sin Presentar | X50: Sin Presentar | Y50: Sin Presentar | Z50: Sin Presentar | AA50: Sin Presentar | AB50: Sin Presentar | AC50: Sin Presentar | AD50: Sin Presentar | AE50: Sin Presentar | AF50: A INICIAR en DGV | AG50: 24/6/26:Comunicación con el municipio. Se envía Instructivo de la documentación legal y técnica requerida. 5/6/26: Ingresa Nota Ministerio Gobierno autorizando financiamiento.
A51: Villa del Prado | B51: Santa María | C51: 0423-080125/2026 | D51: 49 | E51: C | F51: Ludueña Jose Eduardo | G51: 3547 52-5021 | H51: obrasprivadasvilladelprado@gmail.com | J51: 50000000 | M51: Sin Presentar | N51: Sin Presentar | O51: Sin Presentar | P51: Sin Presentar | Q51: A corregir por M/C | R51: Sin Presentar | S51: Sin Presentar | T51: Sin Presentar | U51: Sin Presentar | V51: A corregir por M/C | W51: Sin Presentar | X51: Sin Presentar | Y51: Sin Presentar | Z51: Sin Presentar | AA51: Sin Presentar | AB51: Sin Presentar | AC51: Sin Presentar | AD51: Sin Presentar | AE51: Sin Presentar | AF51: En CURSO en DGV | AG51: 22/6/26: Se envìa Instructivo de la documentaciòn legal y tècnica requerida. 19/6/25/6/26: Comunicaciòn con el int. Se solicita correo electrònico para enviar instructivo. 5/6/26: Ingresa Nota Ministerio Gobierno autorizando financiamiento.
A52: Deán Funes | H52: melpetete@gmail.com | Q52: Sin Presentar | R52: Sin Presentar | S52: Sin Presentar | T52: Sin Presentar | U52: Sin Presentar | V52: Sin Presentar | W52: Sin Presentar | X52: Sin Presentar | Y52: Sin Presentar | Z52: Sin Presentar | AG52: 29/6/2026: El secretario de la Int. envía número de nota presentada. Nos comunicamos informando que para dar inicio al trámite debemos tener la Autorización del Ministerio de Gobierno. 10/6/26: El Municipio se comunica con Area Tècnica. Localidad Sin Autorizaciòn del Ministerio de Gobierno.
A53: La Laguna | Q53: Sin Presentar | R53: Sin Presentar | S53: Sin Presentar | T53: Sin Presentar | U53: Sin Presentar | V53: Sin Presentar | W53: Sin Presentar | X53: Sin Presentar | Y53: Sin Presentar | Z53: Sin Presentar | AG53: 07/7/2026: El intendente se comunicò para solicitar informaciòn respecto si tiene financiamiento autorizado para el programa.
Q54: Sin Presentar | R54: Sin Presentar | S54: Sin Presentar | T54: Sin Presentar | U54: Sin Presentar | V54: Sin Presentar | W54: Sin Presentar | X54: Sin Presentar | Y54: Sin Presentar | Z54: Sin Presentar
Q55: Sin Presentar | R55: Sin Presentar | S55: Sin Presentar | T55: Sin Presentar | U55: Sin Presentar | V55: Sin Presentar | W55: Sin Presentar | X55: Sin Presentar | Y55: Sin Presentar | Z55: Sin Presentar
Q56: Sin Presentar | R56: Sin Presentar | S56: Sin Presentar | T56: Sin Presentar | U56: Sin Presentar | V56: Sin Presentar | W56: Sin Presentar | X56: Sin Presentar | Y56: Sin Presentar | Z56: Sin Presentar
Q57: Sin Presentar | R57: Sin Presentar | S57: Sin Presentar | T57: Sin Presentar | U57: Sin Presentar | V57: Sin Presentar | W57: Sin Presentar | X57: Sin Presentar | Y57: Sin Presentar | Z57: Sin Presentar
A58: ☝🏻 AGREGAR NUEVAS LOCALIDADES ARRIBA DE ESTA FILA ☝🏻
G62: l

Sheet Resumen
A2: Presupuesto destinado por Localidad
A24: ='Base TOTAL'!AF3 -> ESTADO DEL EXPEDIENTE DE LA LOCALIDAD
A26: A INICIAR en DGV | B26: =COUNTIF('Base TOTAL'!AF:AF, A26) -> 16
A27: En CURSO en DGV | B27: =COUNTIF('Base TOTAL'!AF:AF, A27) -> 19
A28: COMPLETO en DGV | B28: =COUNTIF('Base TOTAL'!AF:AF, A28) -> 9
A29: APROBADO por TC | B29: =COUNTIF('Base TOTAL'!AF:AF, A29) -> 2
A36: Donde esta radicado el expediente por áreas dentro de la repartición
A38: Técnica DGV | B38: =COUNTIF('Base TOTAL'!AI:AI, A38) -> 18
A39: Jurídico DGV | B39: =COUNTIF('Base TOTAL'!AI:AI, A39) -> 4
A40: Económico DGV | B40: =COUNTIF('Base TOTAL'!AI:AI, A40) -> 0
A41: Privada DGV | B41: =COUNTIF('Base TOTAL'!AI:AI, A41) -> 0
A42: Tribunal de Cuentas | B42: =COUNTIF('Base TOTAL'!AI:AI, A42) -> 4
A43: Aprobado TC | B43: =COUNTIF('Base TOTAL'!AI:AI, A43) -> 2
A48: Proyecto, Planos, Còmputo y Presupuesto - Estado
A50: Sin Presentar | B50: =COUNTIF('Base TOTAL'!P:P, A50) -> 18
A51: En Evaluaciòn Tècnica | B51: =COUNTIF('Base TOTAL'!P:P, A51) -> 1
A52: A corregir por M/C | B52: =COUNTIF('Base TOTAL'!P:P, A52) -> 13
A53: A corregir por M/C | B53: =COUNTIF('Base TOTAL'!P:P, A53) -> 13
A54: Completo OK | B54: =COUNTIF('Base TOTAL'!P:P, A54) -> 13
A55: En Evaluaciòn Jurìdico | B55: =COUNTIF('Base TOTAL'!P:P, A55) -> 1
A56: Completo OK | B56: =COUNTIF('Base TOTAL'!P:P, A56) -> 13

Sheet Contactos intendentes
A1: G | B1: LOCALIDAD | C1: CENSO 2010 | D1: 2019 - 2023 | E1: TIPO | F1: Frente | G1: TELEFONO | H1: CORREO | I1: REELECCION | J1: 2023-2027 | K1: TELEFONO | L1: MAIL | M1: GENERO | N1: PARTIDO
A2: Calamuchita | B2: AMBOY | C2: 228 | D2: DANIEL ALVAREZ | E2: C | F2: HACEMOS POR CBA | G2: 3546526127 / 03546-15526129(comuna) | H2: comunadeamboy@hotmail.com/danielalvarezamboy@gmail.com | J2: Maria Soledad Sanchez | K2: 3546 515294 | M2: F | N2: Union Vecinal Federal/HUXCBA
A3: Calamuchita | B3: CAÑADA DEL SAUCE | C3: 75 | D3: MAURICIO ACOSTA | E3: C | F3: HACEMOS POR CBA | G3: 3584368540 | H3: aleortiz_81@hotmail.com | I3: REELECCION | J3: Mauricio Acosta | K3: 3584368540 | N3: Hacemos Unidos por Córdoba
A4: Calamuchita | B4: EMBALSE | C4: 9107 | D4: EDUARDO MALDONADO (INTERINO) | E4: M | F4: HACEMOS POR CBA | G4: 3571534418/ SECRETARIA 3513266882 Estela | H4: doctormaldonado@gmail.com | J4: Rivarola Mario | K4: 3571526135 | N4: Hacemos Unidos por Córdoba
A5: Calamuchita | B5: LA CRUZ | C5: 1551 | D5: MAURICIO JAIMES | E5: M | F5: CAMBIEMOS-UCR | G5: 3515577512 / 03546-494017 | H5: municipalidaddelacruz@hotmail.com/ tsbetyrodriguez@hotmail.com | J5: Melica Fabiana Raquel | K5: 3546435663 | M5: F | N5: Juntos por el Cambio
A6: Calamuchita | B6: LA CUMBRECITA | C6: 776 | D6: DANIEL ARTURO LOPEZ | E6: C | F6: HACEMOS POR CBA | G6: 3546410650 / 03546-481051 | H6: comuna2003@htomail.com | J6: Silvana Torres | K6: 3546418707 | L6: silmatorres@hotmail.com | M6: F | N6: Somos por Cumbecita
A7: Calamuchita | B7: LAS BAJADAS | C7: 141 | D7: GABRIELA CAMPILLO | E7: C | F7: CAMBIEMOS-UCR | G7: 3547448850 | H7: labatedaga3@hotmail.com | I7: REELECCION | J7: Campilia Gabriela | K7: 3547448850 | M7: F | N7: Juntos por el Cambio
A8: Calamuchita | B8: LAS CALERAS | C8: 268 | D8: NESTOR GONZALEZ | E8: C | F8: VECINAL-HXCBA | G8: 3584284463 | H8: nestorgonzalez_03@hotmail.com | I8: REELECCION | J8: Nestor Gonzalez | K8: 3584284463 | N8: Hacemos Unidos por Córdoba
A9: Calamuchita | B9: LOS CONDORES | C9: 2964 | D9: DIEGO BLENGINO | E9: M | F9: CAMBIEMOS-UCR | G9: 3571556520 | H9: diegoblengino@gmail.com/ sole_2535@hotmail.com | J9: Mateo Gioda | K9: 3571684430 | N9: Juntos por el Cambio
A10: Calamuchita | B10: LOS MOLINOS | C10: 338 | D10: SILVIA MARTINEZ | E10: C | F10: HACEMOS POR CBA | G10: 3547578388 | H10: silviabmartinez2015@gmail.com/ comunalosmolinos@hotmail.com | J10: Quinteros Jonatan | K10: 3547468628 | N10: Hacemos Unidos por Córdoba
A11: Calamuchita | B11: LOS REARTES | C11: 1426 | D11: LUCAS MARTIN SANCHEZ | E11: C | F11: CAMBIEMOS-UCR | G11: 3546439509 / 03546-492084 | H11: lucasms6@hotmail.com/ belen_santarosa@hotmail.com | J11: Maria Ines Ramello | K11: 3546 65-1510 | M11: F | N11: Movimiento de Accion Vecinal
A12: Calamuchita | B12: LUTTI | C12: 183 | D12: JUAN ANTONIO JAIMES | E12: C | F12: CAMBIEMOS-UCR | G12: 3546476962 | H12: juanantojaimes54@hotmail.com | J12: Cejas Romina Elizabeth | K12: 3546476962 | M12: F | N12: Juntos por el Cambio
A13: Calamuchita | B13: CALMAYO | C13: 74 | D13: LUIS ALBERTO CAMANDONE | E13: C | F13: HACEMOS POR CBA | G13: 3571522973 | H13: parquecalmayo@hotmail.com / lcamandone@hotmail.com | J13: Delgado Fernando | K13: 2964532448 | N13: Juntos por el Cambio
A14: Calamuchita | B14: RIO DE LOS SAUCES | C14: 1326 | D14: FABIAN GIGENA | E14: M | F14: CAMBIEMOS-UCR | G14: 3585170382 / 3584855020 PABLO BRINGAS (SEC DE GOB) | H14: muniriodelossauces@gmail.com / pablo_bringas@hotmail.com | J14: Muñoz Gimena | K14: 3513472248 | L14: gimarribillaga@yahoo.com.ar | M14: F | N14: Juntos por el Cambio
A15: Calamuchita | B15: SAN AGUSTIN | C15: 3742 | D15: IVAN DARIO ORTEGA | E15: M | F15: HACEMOS POR CBA | G15: 3515919051//3547451411 | H15: ivanortega_77@hotmail.com | J15: Calderon Miguel Santiago | K15: 3415045902 | N15: Juntos por el Cambio
A16: Calamuchita | B16: SAN IGNACIO | C16: 247 | D16: JORGE ORDOÑEZ | E16: C | F16: HACEMOS POR CBA | G16: 3546502111 / 03546-493018 | H16: comunasanignacio@hotmail.com / jorgeordonez59@hotmail.com | J16: Adrian Urbano | K16: 3546 45-0463 | N16: Union Vecinal
A17: Calamuchita | B17: SEGUNDA USINA | C17: 170 | D17: CEFERINO LOPEZ | E17: C | F17: HACEMOS POR CBA | G17: 3571553126 | J17: Rojo Roxana | K17: 3571696164 | M17: F | N17: Hacemos Unidos por Córdoba
A18: Calamuchita | B18: SANTA ROSA DE CALAMUCHITA | C18: 12830 | D18: CLAUDIO HORACIO CHAVERO | E18: M | F18: HACEMOS POR CBA | G18: 3546482922 / 03546 - 482328 (muni) | H18: secretariaintendente@starosacalamuchita.com.a | J18: Eduardo Martin | K18: 3546476477 | N18: Juntos por el Cambio
A19: Calamuchita | B19: VILLA AMANCAY | C19: 450 | D19: JULIO CESAR MANTOVANI | F19: HACEMOS POR CBA | G19: 3546476644 | H19: vivas1@live.com.ar | J19: Yohana Rodriguez | K19: 3546401710 | M19: F | N19: Hacemos Unidos por Córdoba
A20: Calamuchita | B20: VILLA CIUDAD PARQUE | C20: 1165 | D20: PABLO JULIAN RIVEROS | E20: C | F20: VECINAL-HXCBA | G20: 3546513908 | H20: pablojriveros@gmail.com | J20: Diego Ruiz | K20: 3546 51-3916 | N20: Union Vecinal
A21: Calamuchita | B21: VILLA DEL DIQUE | C21: 3303 | D21: RICARDO SCOLES | E21: M | F21: VECINAL-HXCBA | G21: 1144050279 | H21: mgmarandino@hotmail.com | J21: Emiliano Torres | K21: 3513073324 | N21: Somos Villa del Dique (justicialistas/PRO/radicales)
A22: Calamuchita | B22: VILLA GENERAL BELGRANO | C22: 8257 | D22: OSCAR SANTARELLI | E22: M | F22: HACEMOS POR CBA | G22: 3516647848 | H22: oscarsantarelli@vgb.gob.ar/ cintiabrasca@gmail.com | I22: REELECCION | J22: Oscar Santarelli | K22: 3516647848 | N22: Hacemos Unidos por Córdoba
A23: Calamuchita | B23: VILLA QUILLINZO | C23: 79 | D23: DANILO GRAZIANO | E23: C | F23: HACEMOS POR CBA | G23: 3546659609 | H23: danilo@villaquillinzo.gob.ar | J23: Sebastian Cabral | K23: 3546418617 | N23: Juntos por el Cambio
A24: Calamuchita | B24: VILLA RUMIPAL | C24: 2663 | D24: GUSTAVO EDUARDO GANTUS | E24: M | F24: FDT-HUPC | G24: 3546514317 | H24: gegantus@hotmail.com | J24: Julio Cesar Gantus | K24: 3546477887 | N24: Hacemos Unidos por Córdoba
A25: Calamuchita | B25: VILLA YACANTO | C25: 1634 | D25: OSCAR ALFREDO MUSUMECI | E25: M | F25: FDT-HUPC | G25: 3516328444 | H25: oscarmusumeci@hotmail.com | J25: Fernando Moisó | K25: 3546520085 | N25: Juntos por el Cambio
A26: Capital | B26: CÓRDOBA CAPITAL 1 | C26: 1329604 | D26: MARTIN LLARYORA | E26: M | F26: HACEMOS POR CBA | H26: mllaryora13@gmail.com | J26: Passerini Daniel | K26: 3513 29-6549 | N26: Hacemos Unidos por Córdoba
A27: Colon | B27: AGUA DE ORO | C27: 2.111 | D27: ORLANDO OSCAR BELLI | E27: M | F27: CAMBIEMOS-MUCORA | G27: 3516615772 / 03525 49-3071 (muni) | H27: belliorlando@yahoo.com/ municipalidad@aguadeoro.gob.ar | J27: Miguel Angel Aguirre | K27: 3525646421 | N27: Hacemos Unidos por Córdoba
A28: Colon | B28: COLONIA CAROYA | C28: 20.821 | D28: GUSTAVO BRANDAN | E28: M | F28: HACEMOS POR CBA | G28: 3525438532 | H28: gustavo.brandan@yahoo.com.ar | J28: Nanini Paola | K28: 3525538313 | M28: F | N28: Hacemos Unidos por Córdoba
A29: Colon | B29: COLONIA TIROLESA | C29: 5.342 | D29: OSCAR LAURET | E29: M | F29: CAMBIEMOS-UCR | G29: 3516164961 | H29: lauretos@gmail.com | J29: Juan Panichelli | K29: 3512285554 | N29: Hacemos Unidos por Córdoba
A30: Colon | B30: COLONIA VICENTE AGÜERO | C30: 352 | D30: GUSTAVO GERMAN RIPELONI | E30: C | F30: CAMBIEMOS-UCR | G30: 3525435733 | H30: gustavoripeloni@hotmail.com | J30: Nilda Lauret | K30: 3525516738 | M30: F | N30: Encuentro Vecinal Córdoba
A31: Colon | B31: EL MANZANO | C31: 1.298 | D31: JOSE MARIA GARZON | E31: C | F31: HACEMOS POR CBA | G31: 3525641414 | H31: jmariagarzon@gmail.com | I31: REELECCION | J31: Garzon Jose Maria | K31: 3525641414 | N31: Hacemos Unidos por Córdoba
A32: Colon | B32: ESTACION GENERAL PAZ | C32: 2.253 | D32: BORGOBELLO CARLOS HECTOR | E32: M | F32: HACEMOS POR CBA | G32: 3525417542 | H32: carlosborgobello2@hotmail.com | J32: Dario Arata | K32: 3525565152 | N32: Hacemos Unidos por Córdoba
A33: Colon | B33: ESTACION JUAREZ CELMAN | C33: 12.129 | D33: MYRIAN PRUNOTTO | E33: M | F33: CAMBIEMOS-UCR | G33: 3513271941 | H33: myrianprunotto@gmail.com | J33: Reschia Fabian | K33: 3513 10-7108 | N33: Hacemos Unidos por Córdoba
A34: Colon | B34: JESUS MARIA | C34: 31.864 | D34: LUIS PICAT | E34: M | F34: VECINAL | G34: 3525535763 | H34: intendencia@jesusmaria.gov.ar/hacienda@jesusmaria.gov.ar | J34: Federico Zarate | K34: 3525416244 | N34: Juntos por el Cambio
B35: LA CALERA | C35: 32.227 | D35: FACUNDO RUFEIL | E35: M | F35: HACEMOS POR CBA | G35: 3515730833 | H35: desarrollosociallacalera@gmail.com | J35: Fernando Rambaldi | K35: 3515145928 | N35: Juntos por el Cambio
A36: Colon | B36: LA GRANJA | C36: 3.234 | D36: CARLOS AMBROCICH | E36: M | F36: HACEMOS POR CBA | G36: 3525644339 | H36: carlosambrocich@gmail.com | J36: Pittaro Miguel Angel | K36: 32525480192 | N36: Juntos por el Cambio
A37: Colon | B37: MALVINAS ARGENTINAS | C37: 12.581 | D37: GASTON MAZZALAY | E37: M | F37: HACEMOS POR CBA | G37: 3513480413 | H37: gastonmazzalay@gmail.com | I37: REELECCION | J37: Mazzalay Gaston | K37: 3513480413 | N37: Hacemos Unidos por Córdoba
A38: Colon | B38: MENDIOLAZA | C38: 10.317 | D38: NESTOR DANIEL SALIBI | E38: M | F38: CAMBIEMOS-MUCORA | G38: 3515637428 | H38: intendente@mendiolaza.gov.ar | J38: Arning Adela | K38: 3515 29-5168 | M38: F | N38: PRO
A39: Colon | B39: MI GRANJA | C39: 2.149 | D39: CLAUDIA INÉS ACOSTA | E39: C | F39: HACEMOS POR CBA | G39: 3512449400 / 3513106611 | H39: migranja_cordoba@yahoo.com.ar | I39: REELECCION | J39: Acosta Claudia | K39: 3512449400 / 3513106611 | M39: F | N39: Hacemos Unidos por Córdoba
A40: Colon | B40: RIO CEBALLOS | C40: 20.242 | D40: EDUARDO BALDASSI | E40: M | F40: HACEMOS POR CBA | G40: 3543552682/ 3543690101 | H40: baldassi62@gmail.com | J40: Lemos Ezequiel | K40: 3543600844 | N40: Juntos por el Cambio
A41: Colon | B41: SALDAN | C41: 10.606 | D41: CAYETANO CANTO | E41: M | F41: HACEMOS POR CBA | G41: 3512038129 | H41: CANTOCAYETANO@GMAIL.COM | J41: Cristori Carolina | K41: 3512251529 | M41: F | N41: Hacemos Unidos por Córdoba
A42: Colon | B42: SALSIPUEDES | C42: 9.842 | D42: MARCELO BUSTOS | E42: M | F42: CAMBIEMOS-PRO | G42: 3543510531 | H42: marcelobustos1969@gmail.com/promocionciudadanasalsipuedes@gmail.com | J42: Strasorier Mario David | K42: 3515309607 | N42: FDT-HUPC
A43: Colon | B43: TINOCO | C43: 514 | D43: HEBERTO GUSTAVO BUSTOS | E43: C | F43: HACEMOS POR CBA | G43: 3515051017 | H43: comunadetinoco@outlook.com/ todocelso@gmail.com | J43: Bustos Dalma | K43: 3525448708 | M43: F | N43: Hacemos Unidos por Córdoba
A44: Colon | B44: UNQUILLO | C44: 18.483 | D44: JORGE FABRISIN | E44: M | F44: HACEMOS POR CBA | G44: 3543616733 | H44: intendencia@unquillo.gov.ar | J44: Guillermo Valli | K44: 3543606514 | N44: Hacemos Unidos por Córdoba
A45: Colon | B45: VILLA ALLENDE | C45: 28.374 | D45: MARIA TERESA DE VELEZ EDUARDO ROMERO (LICENCIA) | E45: M | F45: CAMBIEMOS-PRO | G45: 3516377078 | H45: teredevelez@yahoo.com.ar / teresadevelez@gmail.com | J45: Pablo Cornet | K45: 3516655471 | N45: PRO - Propuesta Republicana
A46: Colon | B46: VILLA CERRO AZUL | C46: 280 | D46: MARIA LAURA WHERLI | E46: C | F46: HACEMOS POR CBA | G46: 3525512116 | H46: maruwehrli79@hotmail.com | J46: Di Pace Natalia | K46: 3516674892 | M46: F | N46: Union Vecinal
A47: Cruz Del Eje | B47: ALTO DE LOS QUEBRACHOS | C47: 268 | D47: ARIEL ATILIO ALIENDRO | E47: C | F47: CAMBIEMOS-UCR | G47: 3549417480 (secretaria elizabeth 3549459862) | H47: elizabeth_heredia2013@hotmail.com | J47: Rodrigo Aliendo | K47: 3549504128 | N47: UCR/HXCBA
A48: Cruz Del Eje | B48: BAÑADO DE SOTO | C48: 941 | D48: FABRICIO RUIZ | E48: C | F48: HACEMOS POR CBA | G48: 3549468637 | H48: banadodesotocomuna@gmail.com | I48: REELECCION | J48: Ruiz Fabricio | K48: 3549468637 | N48: Hacemos Unidos por Córdoba
A49: Cruz Del Eje | B49: CRUZ DE CAÑA | C49: 352 | D49: DAVID SANCHEZ | E49: C | F49: CAMBIEMOS-UCR | G49: 3549439248 | H49: davidflorencio.sanchez@gmail.com | J49: Matias Gallardo | K49: 3516454953 | N49: Juntos por el Cambio
A50: Cruz Del Eje | B50: CRUZ DEL EJE | C50: 30.844 | D50: CLAUDIO FARIAS | E50: M | F50: HACEMOS POR CBA | G50: 3513411368 | H50: claudiofale@hotmail.com | J50: Raschetti Renato | K50: 3549575943 | N50: Juntos por el Cambio
A51: Cruz Del Eje | B51: EL BRETE | C51: 2.327 | D51: NESTOR MAURICIO JACHULA | E51: M | F51: CAMBIEMOS-UCR | G51: 3549639794 | H51: manyy12@hotmail.com | J51: Pablo Diaz | K51: 3549502124 | N51: Juntos por el Cambio
A52: Cruz Del Eje | B52: GUANACO MUERTO | C52: 554 | D52: DOMINGO ZENON SORIA | E52: C | F52: HACEMOS POR CBA | G52: 3549531634 / 3549418528 | H52: domingozenons@gmail.com | J52: Mayco Soria | K52: 3549440455 | N52: Hacemos Unidos por Córdoba
A53: Cruz Del Eje | B53: LA BATEA | C53: 180 | D53: MANUEL BENITO FARIAS | E53: C | F53: CAMBIEMOS-UCR | G53: 3549631311 | H53: omar_luna@hotmail.com.ar | J53: Ivan Denis Farias | K53: 3549465986 | N53: Juntos por el cambio
A54: Cruz Del Eje | B54: LA HIGUERA | C54: 411 | D54: DANIEL MANZANELLI | E54: C | F54: HACEMOS POR CBA | G54: 3542470003 | H54: danielemanzanelli@gmail.com/ comunalahiguera01@gmail.com | I54: REELECCION | J54: Daniel Manzanelli | K54: 3542470003 | N54: Hacemos Unidos por Córdoba
A55: Cruz Del Eje | B55: LAS CAÑADAS | C55: 272 | D55: RAFAEL CORTEZ | E55: C | F55: CAMBIEMOS-UCR | G55: 3549464914 - 3549460632 | H55: maiasuarez2008@outlook.com | J55: Erica Cortez | K55: 3549458421 | M55: F | N55: Juntos por el Cambio
A56: Cruz Del Eje | B56: LAS PLAYAS | C56: 962 | D56: VICTOR ARCHILLA | E56: C | F56: CAMBIEMOS-PRO | G56: 3549418650 | H56: victor_archilla@hotmail.com | J56: Maria Daniela Godoy | K56: 3549468032 | M56: F | N56: Juntos por el Cambio
A57: Cruz Del Eje | B57: LOS CHAÑARITOS (CDE) | C57: 564 | D57: MARIELA GONZALEZ | E57: C | F57: VECINAL-HXCBA | G57: 3549447808 | H57: marielag_42@hotmail.com/ | J57: Bazan Ariel Alejandro | K57: 3549447808 | N57: Union Popular Federal
A58: Cruz Del Eje | B58: MEDIA NARANJA | C58: 936 | D58: JORGE CARBELO | E58: C | F58: HACEMOS POR CBA | G58: 3512103276 | H58: jorgecarbelo@gmail.com | J58: Juan Carbelo | K58: 3512838302 | N58: Hacemos Unidos por Córdoba
A59: Cruz Del Eje | B59: PASO VIEJO | C59: 1.033 | D59: DARÍO HEREDIA | E59: C | F59: HACEMOS POR CBA | G59: 3549464317 | H59: dariocomunapasoviejo@hotmail.com | J59: Mauro Tapia | K59: 3549 63-6770 | N59: Hacemos Unidos por Córdoba
A60: Cruz Del Eje | B60: SAN MARCOS SIERRAS | C60: 2.199 | D60: CÉSAR BRIGUERA | E60: M | F60: HACEMOS POR CBA | G60: 3549416291 | H60: cesarbriguera15@gmail.com | J60: Vrancic Luciano | K60: 3549 43-2081 | N60: Frente Amplio
A61: Cruz Del Eje | B61: SERREZUELA | C61: 2.678 | D61: RICARDO MARTIN | E61: M | F61: CAMBIEMOS-UCR | G61: 3549473168 | H61: ricardo25martin@gmail.com | I61: REELECCION | J61: Ricardo Martin | K61: 3549473168 | N61: Juntos por el Cambio
A62: Cruz Del Eje | B62: TUCLAME | C62: 907 | D62: HUGO OSSES | E62: C | F62: FDT-HUPC | G62: 3549430347 | H62: comunatuclame@gmail.com | J62: Graciela del Valle Gonzalez | K62: 3549537628 | M62: F | N62: Hacemos Unidos por Córdoba
A63: Cruz Del Eje | B63: VILLA DE SOTO | C63: 9.927 | D63: FERNANDO LUNA | E63: M | F63: CAMBIEMOS-UCR | G63: 3549417940 | H63: fernandojavierluna@yahoo.com.ar | J63: Maria Jose Acuña | K63: 3549455083 | L63: mariajo.turismo@hotmail.com | M63: F | N63: Juntos por el Cambio
A64: General Roca | B64: BUCHARDO | C64: 1.795 | D64: MARIA ANTONELA LAMBERTI | E64: M | F64: HACEMOS POR CBA | G64: 3365467168 | H64: antolamberti@hotmail.com | I64: REELECCION | J64: Maria Atonella Lamberti | K64: 3385467168 | M64: F | N64: Hacemos Unidos por Córdoba
A65: General Roca | B65: DEL CAMPILLO | C65: 3.508 | D65: ANA ZANOTTO | E65: M | F65: HACEMOS POR CBA | G65: 3583442356 | H65: anazanotto@yahoo.com.ar | J65: Villanova Carla | K65: 3583401420 | M65: F | N65: Hacemos Unidos por Córdoba
A66: General Roca | B66: Huinca Renanco | C66: 9.487 | D66: OSCAR ELIAS SALIBA | E66: M | F66: CAMBIEMOS-UCR | G66: 2302542830 | H66: oscarsaliba@hotmail.com | J66: Lucia Bolaño | K66: 2336497026 | M66: F | N66: Juntos por el Cambio
A67: General Roca | B67: ITALO | C67: 1.12 | D67: ARIEL VIDORET | E67: M | F67: HACEMOS POR CBA | G67: 2302543060 | H67: gustavoarielvido@hotmail.com/ municipio@italonet.com.ar | I67: REELECCION | J67: Vidoret Ariel | K67: 2302543060 | N67: Hacemos Unidos por Córdoba
A68: General Roca | B68: JOVITA | C68: 4.823 | D68: JAVIER RIBERI | E68: M | F68: CAMBIEMOS-UCR | G68: 3385447959 | H68: munijovita@yahoo.com.ar | I68: REELECCION | J68: Javier Riberi | K68: 3385447959 | N68: Juntos por el Cambio
A69: General Roca | B69: MATTALDI | C69: 1.842 | D69: DARIO RENAUDO | E69: M | F69: CAMBIEMOS-UCR | G69: 3583403987 | H69: bruno@mattaldinet.com.ar | J69: Agaccio German | K69: 3583401152 | L69: germangaccio@hotmail.com | N69: Hacemos Unidos por Córdoba
A70: General Roca | B70: NICOLAS BRUZZONE | C70: 214 | D70: CARLOS IRÚSTA | E70: C | F70: HACEMOS POR CBA | G70: 3583404177 | H70: carlitosbruzone2015@gmail.com | J70: Irusta Fabio | K70: 3585121647 | L70: irustaleonardofabio@gmail.com | N70: Hacemos Unidos por Córdoba
A71: General Roca | B71: ONAGOITY | C71: 63 | D71: JUAN CARLOS FENOGLIO | E71: C | F71: HACEMOS POR CBA | G71: 3385406721/03387-491430 muni | H71: comunaonagoity@hotmail.com | J71: Omar Fenoglio | K71: 3385406721/03387-491430 muni | L71: comunaonagoity@hotmail. com | N71: Hacemos Unidos por Córdoba
A72: General Roca | B72: PINCEN | C72: 254 | D72: MIRIAM SIGNORILE | E72: C | F72: HACEMOS POR CBA | G72: 2302597932 | H72: miriangsignorile@hotmail.com | J72: Roggia Gonzalo Heber | K72: 3584182272 | N72: Hacemos Unidos por Córdoba
A73: General Roca | B73: RANQUELES | C73: 67 | D73: GABRIELA ELIZABETH LANFRANCO | E73: C | F73: HACEMOS POR CBA | G73: 2302476720 | J73: Licera Maria Florencia | K73: 2355470168 | M73: F | N73: Juntos por el Cambio
A74: General Roca | B74: VILLA HUIDOBRO | C74: 5.658 | D74: SILVIO ADRIAN QUIROGA | E74: M | F74: HACEMOS POR CBA | G74: 2302699464 | H74: silvio.quiroga@hotmail.com | J74: Quiroga Enzo | K74: 2302453904 | N74: Hacemos Unidos por Córdoba
A75: General Roca | B75: VILLA SARMIENTO (GR) | C75: 373 | D75: OSVALDO JESUS ESTRADA | E75: C | F75: CAMBIEMOS-UCR | G75: 3583430074 | H75: comunavillasarmiento@hotmail.com | I75: REELECCION | J75: Osvaldo Estrada | K75: 3583430074 | L75: comunavillasarmiento@hotmail.com | N75: Juntos por el Cambio
A76: General Roca | B76: VILLA VALERIA | C76: 3.002 | D76: DARIO RICARDO ARDILES | E76: M | F76: HACEMOS POR CBA | G76: 3583414634 | H76: ardilesdarioricardo@yahoo.com.ar | J76: Medero Claudio | K76: 3583439116 | N76: Hacemos Unidos por Córdoba
A77: General San Martin | B77: ARROYO ALGODON | C77: 692 | D77: CRISTIAN GHIANO | E77: M | F77: HACEMOS POR CBA | G77: 3534184302 | H77: cristianestebanghiano@hotmail.com/ agueda505@gmail.com | J77: Donati Gonzalo | K77: 3534238818 | N77: Juntos por el Cambio
A78: General San Martin | B78: ARROYO CABRAL | C78: 2.793 | D78: PABLO ALCALINO | E78: M | F78: CAMBIEMOS-UCR | G78: 3534287686 | H78: municipalidadarroyocabral@hotmail.com | J78: Raul Mariscalchi | K78: 3534241413 | N78: Juntos por el Cambio
A79: General San Martin | B79: AUSONIA | C79: 1.133 | D79: MAURICIO PAJON | E79: M | F79: HACEMOS POR CBA | G79: 3534240507 | H79: gallego78_80@hotmail.com | J79: Morelatto Enzo Nicolas | K79: 3534 59-6816 | N79: Juntos por el Cambio
A80: General San Martin | B80: CHAZON | C80: 1.08 | D80: ROBERT SANTIAGO MEICHTRI | E80: M | F80: CAMBIEMOS-UCR | G80: 3534068698 | H80: rmeichtri@gmail.com | I80: REELECCION | J80: Robert Santiago Meichtri | K80: 3534068698 | L80: rmeichtri@gmail.com | N80: Juntos por el Cambio
A81: General San Martin | B81: ETRURIA | C81: 4.13 | D81: MAXIMILIANO ANDRES | E81: M | F81: CAMBIEMOS-UCR | G81: 3534271744 | H81: maxiandres1@gmail.com | I81: REELECCION | J81: Maximiliano Andres | K81: 3534271744 | L81: maxiandres1@gmail.com | N81: Juntos por el Cambio
A82: General San Martin | B82: LA LAGUNA | C82: 1.524 | D82: JULIO CASTELLANO | E82: M | F82: CAMBIEMOS-UCR | G82: 3534086930 | H82: juliohcastellano@hotmail.com | J82: Mariano Colombano | K82: 3534200619 | N82: Juntos por el Cambio
A83: General San Martin | B83: LA PALESTINA | C83: 502 | D83: CRISTIAN PORTESIO | E83: M | F83: CAMBIEMOS-UCR | G83: 3534174011 | H83: cgportesio@hotmail.com.ar | J83: Mayco Becco | K83: 3534786948 | N83: Hacemos Unidos por Córdoba
A84: General San Martin | B84: LA PLAYOSA | C84: 2.757 | D84: GABRIELA NICOLINO | E84: M | F84: HACEMOS POR CBA | G84: 3535646843 | H84: gnicolino2010@hotmail.com | J84: Villar Franco | K84: 3534201707 | N84: Hacemos Unidos por Córdoba
A85: General San Martin | B85: LUCA | C85: 563 | D85: AUGUSTO ARIETTI | E85: M | F85: HACEMOS POR CBA | G85: 3534200205 | H85: AUGUSTOARIETTIPRENSA@YAHOO.COM | I85: REELECCION | J85: Arietti Augusto | K85: 3534187503 | N85: Hacemos Unidos por Córdoba
A86: General San Martin | B86: PASCO | C86: 1.201 | D86: DANIEL NICOLAS DELBONO | E86: M | F86: HACEMOS POR CBA | G86: 3534243370 | H86: municipalidadpasco@hotmail.com | J86: Dardo Pereyra | K86: 3534088856 | N86: Juntos por Pasco/Afin HUPC
A87: General San Martin | B87: SILVIO PELLICO | C87: 405 | D87: LETICIA YUDIT ALLOCCO | E87: M | F87: CAMBIEMOS-PRO | G87: 3535630956 | H87: lallocco@hotmail.com//muni_spellico@hotmail.com//lalloco@hotmail.com | J87: Federico Quiñonez | K87: 3535632282 | N87: Hacemos Unidos por Córdoba
A88: General San Martin | B88: TICINO | C88: 2.207 | D88: LILIANA RUETSCH | E88: M | F88: CAMBIEMOS-UCR | G88: 3534823448 | H88: intendenciaticino@gmail.com | J88: Gabriel Cañas | K88: 3534 06-2645 | N88: Juntos por el Cambio
A89: General San Martin | B89: TIO PUJIO | C89: 2.676 | D89: NANCY DEL CARMEN SCHIAVI | E89: M | F89: HACEMOS POR CBA | G89: 3534231948 | H89: nancyschiavi@gmail.com | J89: Ariel Petrocchi | K89: 3534180842 | N89: Hacemos Unidos por Córdoba
A90: General San Martin | B90: VILLA MARIA | C90: 79.946 | D90: PABLO ROSSO | E90: M | F90: HACEMOS POR CBA | G90: 3534189484 | J90: Eduardo Accastello | K90: 3534110442 | N90: Hacemos Unidos por Córdoba
A91: General San Martin | B91: VILLA NUEVA | C91: 19.362 | D91: NATALIO GRAGLIA | E91: M | F91: HACEMOS POR CBA | G91: 3534286245 | H91: nat_gra@yahoo.com | J91: Tagni Ignacio Gabriel | K91: 3534128698 | N91: Juntos por el Cambio
A92: Ischilin | B92: AVELLANEDA | C92: 323 | D92: PEDRO LAURET | E92: C | F92: HACEMOS POR CBA | G92: 3521436273 | H92: pedrolauret12@gmail.com | J92: Baretto Juan Esteban | K92: 3521407254 | N92: ESTAMOS
A93: Ischilin | B93: CAÑADA DE RIO PINTO | C93: 193 | D93: EDGARDO CASTRO | E93: C | F93: HACEMOS POR CBA | G93: 3525458143 | H93: ccriopinto@gmail.com | J93: Gutierrez Ariel Hernan | K93: 3525 53-6676 | N93: Encuentro Vecinal
A94: Ischilin | B94: CHUÑA | C94: 563 | D94: ROBUSTEANO LUNA | E94: C | F94: HACEMOS POR CBA | G94: 3521417671 | H94: lunarobustiano@hotmail.com | J94: Barrera Paulo Rodolfo | K94: 3549537411 | N94: Juntos por el Cambio
A95: Ischilin | B95: COPACABANA | C95: 74 | D95: ERNESTO ENRIQUE QUINTEROS | E95: C | F95: HACEMOS POR CBA | G95: 3521417995 | H95: ernestoenriquequinteros@hotmail.com | J95: Susana del Valle Luna | K95: 3521650623/ 3521 40-4266 | M95: F | N95: Hacemos Unidos por Córdoba
A96: Ischilin | B96: DEAN FUNES | C96: 21.518 | D96: RAUL ALBERTO FIGUEROA | E96: M | F96: VECINAL | G96: Diputada Nacional | H96: raulfigue@hotmail.com | J96: Andrea Nievas | K96: 3521411244 | M96: F | N96: Vecinalismo/Candidata de Tito Figueroa
A97: Ischilin | B97: LOS POZOS | C97: 95 | D97: CLAUDIO TRIPIANA | E97: C | F97: HACEMOS POR CBA | G97: 3525517470 | J97: Claudio Tripiana | K97: 3521630065 | M97: M | N97: Hacemos Unidos por Córdoba
A98: Ischilin | B98: OLIVARES DE SAN NICOLAS | C98: 615 | D98: CARMEN ANTONIO HEREDIA | E98: C | F98: CAMBIEMOS-UCR | G98: 3549447678 | H98: herediaantonio124@gmail.com | J98: Heredia Yanina | K98: 3549500305 | M98: F | N98: Hacemos Unidos por Córdoba
A99: Ischilin | B99: QUILINO | C99: 5.262 | D99: MABEL GODOY | E99: M | F99: HACEMOS POR CBA | G99: 3521433297 | H99: godoymab@gmail.com | I99: REELECCION | J99: Godoy Mabel | K99: 3521433297 | M99: F | N99: Hacemos Unidos por Córdoba
A100: Ischilin | B100: VILLA GUTIERREZ | C100: 341 | D100: OSVALDO C. ABRAMENIA | E100: C | F100: HACEMOS POR CBA | G100: 3521418530 | H100: comunadevillagutierrez@hotmail.com | J100: Abramenia Cesar | K100: 3525 642177 | N100: Hacemos Unidos por Córdoba
...

Sheet Validaciones
A1: DEPARTAMENTOS PROVINCIA DE CORDOBA
A2: Calamuchita
A3: Capital
A4: Colón
A5: Cruz del Eje
A6: General Roca
A7: General San Martín
A8: Ischilín
A9: Juárez Celman
A10: Marcos Juárez
A11: Minas
A12: Pocho
... A398: Zanoni
