Workbook

Sheet IN x Localidad NATI
A1: Programas provinciales - Dirección General de Vivienda
A2: Ingreso de Datos
C3: LOCALIDAD: | D3: Sacanta | E3: ⬅️ solamente ELEGIR LOCALIDAD
C4: DEPARTAMENTO: | D4: =IFERROR(VLOOKUP($D$3,'Base TOTAL'!A:AU,2,0), "Sin dato") -> San Justo
C5: Datos actuales | D5: Modificar/Ingresar nuevo dato | E5: Columna ref. BASE TOTAL
B6: MUNICIPIO / COMUNA | C6: =LET(res, IFERROR(VLOOKUP($D$3,'Base TOTAL'!A:DA,5,0),""), IF(res="", "Sin datos", res)) -> M | D6: M | E6: E
B7: INTENDENTE / PRESIDENTE COMUNAL | C7: =LET(res, IFERROR(VLOOKUP($D$3,'Base TOTAL'!A:DA,6,0),""), IF(res="", "Sin datos", res)) -> Mecchia Jose Luis | E7: F
B8: N° TELÉFONO M/C | C8: =LET(res, IFERROR(VLOOKUP($D$3,'Base TOTAL'!A:DA,7,0),""), IF(res="", "Sin datos", res)) -> 3533580162 | E8: G
B9: CORREO ELECTRÓNICO | C9: =LET(res, IFERROR(VLOOKUP($D$3,'Base TOTAL'!A:DA,8,0),""), IF(res="", "Sin datos", res)) -> Secretariodegobierno@sacanta.gob.ar | E9: H
B10: CONTACTO TÉCNICO de M/C | C10: =LET(res, IFERROR(VLOOKUP($D$3,'Base TOTAL'!A:DA,9,0),""), IF(res="", "Sin datos", res)) -> jumagon82@gmail.com | E10: I
A11: PROGRAMA PROVINCIAL DE CORDÓN CUNETA Y ADOQUINES - LEY Nº 11089
B12: EXPEDIENTE N° | C12: =LET(res, IFERROR(VLOOKUP($D$3,'Base TOTAL'!A:DA,3,0),""), IF(res="", "Sin datos", res)) -> 0423-080124/2026 | E12: C
B13: N° Orden | C13: =LET(res, IFERROR(VLOOKUP($D$3,'Base TOTAL'!A:DA,4,0),""), IF(res="", "Sin datos", res)) -> 35 | E13: D
A14: CONVENIO | B14: MONTO CONVENIO | C14: =LET(res, IFERROR(VLOOKUP($D$3,'Base TOTAL'!A:DA,10,0),""), IF(res="", "Sin datos", res)) -> 70000000 | E14: J
B15: Cordón Cuneta (ml) | C15: =LET(res, IFERROR(VLOOKUP($D$3,'Base TOTAL'!A:DA,11,0),""), IF(res="", "Sin datos", res)) -> 1055 | E15: K
B16: Adoquinado (m2) | C16: =LET(res, IFERROR(VLOOKUP($D$3,'Base TOTAL'!A:DA,12,0),""), IF(res="", "Sin datos", res)) -> Sin datos | E16: L
A17: DOCUMENTACIÓN A PRESENTAR por Municipio / Comuna | B17: 1 | C17: =LET(res, IFERROR(VLOOKUP($D$3,'Base TOTAL'!A:DA,13,0),""), IF(res="", "Sin datos", res)) -> A corregir por M/C | E17: M
B18: 2 | C18: =LET(res, IFERROR(VLOOKUP($D$3,'Base TOTAL'!A:DA,14,0),""), IF(res="", "Sin datos", res)) -> Completo OK | E18: N
B19: 3 | C19: =LET(res, IFERROR(VLOOKUP($D$3,'Base TOTAL'!A:DA,15,0),""), IF(res="", "Sin datos", res)) -> Completo OK | E19: O
B20: 4 | C20: =LET(res, IFERROR(VLOOKUP($D$3,'Base TOTAL'!A:DA,16,0),""), IF(res="", "Sin datos", res)) -> A corregir por M/C | E20: P
B21: Descripción General | C21: =LET(res, IFERROR(VLOOKUP($D$3,'Base TOTAL'!A:DA,17,0),""), IF(res="", "Sin datos", res)) -> A corregir por M/C | E21: Q
B22: Memoria Técnica | C22: =LET(res, IFERROR(VLOOKUP($D$3,'Base TOTAL'!A:DA,18,0),""), IF(res="", "Sin datos", res)) -> Completo OK | E22: R
B23: Plazo de Ejecución | C23: =LET(res, IFERROR(VLOOKUP($D$3,'Base TOTAL'!A:DA,19,0),""), IF(res="", "Sin datos", res)) -> Completo OK | E23: S
B24: Cómputo y Presupuesto | C24: =LET(res, IFERROR(VLOOKUP($D$3,'Base TOTAL'!A:DA,20,0),""), IF(res="", "Sin datos", res)) -> A corregir por M/C | E24: T
B25: Cronograma Avance Obra | C25: =LET(res, IFERROR(VLOOKUP($D$3,'Base TOTAL'!A:DA,21,0),""), IF(res="", "Sin datos", res)) -> A corregir por M/C | E25: U
B26: Planimetría | C26: =LET(res, IFERROR(VLOOKUP($D$3,'Base TOTAL'!A:DA,22,0),""), IF(res="", "Sin datos", res)) -> Completo OK | E26: V
B27: Perfil Calzada | C27: =LET(res, IFERROR(VLOOKUP($D$3,'Base TOTAL'!A:DA,23,0),""), IF(res="", "Sin datos", res)) -> Completo OK | E27: W
B28: Detalle de Cordón Cuneta | C28: =LET(res, IFERROR(VLOOKUP($D$3,'Base TOTAL'!A:DA,24,0),""), IF(res="", "Sin datos", res)) -> Completo OK | E28: X
B29: Detalle de Badén | C29: =LET(res, IFERROR(VLOOKUP($D$3,'Base TOTAL'!A:DA,25,0),""), IF(res="", "Sin datos", res)) -> Completo OK | E29: Y
B30: Paquete estr. Calzada | C30: =LET(res, IFERROR(VLOOKUP($D$3,'Base TOTAL'!A:DA,26,0),""), IF(res="", "Sin datos", res)) -> A ESPERA de DOC.TÉCNICA | E30: Z
B31: 5 | C31: =LET(res, IFERROR(VLOOKUP($D$3,'Base TOTAL'!A:DA,27,0),""), IF(res="", "Sin datos", res)) -> Completo OK | E31: AA
B32: 6 | C32: =LET(res, IFERROR(VLOOKUP($D$3,'Base TOTAL'!A:DA,28,0),""), IF(res="", "Sin datos", res)) -> Completo OK | E32: AB
B33: 7 | C33: =LET(res, IFERROR(VLOOKUP($D$3,'Base TOTAL'!A:DA,29,0),""), IF(res="", "Sin datos", res)) -> Completo OK | E33: AC
B34: 8 | C34: =LET(res, IFERROR(VLOOKUP($D$3,'Base TOTAL'!A:DA,30,0),""), IF(res="", "Sin datos", res)) -> Completo OK | E34: AD
B35: 9 | C35: =LET(res, IFERROR(VLOOKUP($D$3,'Base TOTAL'!A:DA,31,0),""), IF(res="", "Sin datos", res)) -> Completo OK | E35: AE
B36: ESTADO DEL EXPEDIENTE DE LA LOCALIDAD | C36: =LET(res, IFERROR(VLOOKUP($D$3,'Base TOTAL'!A:DA,32,0),""), IF(res="", "Sin datos", res)) -> En CURSO en TÉCNICA | E36: AF
A37: OBSERVACIONES | C37: =LET(res, IFERROR(VLOOKUP($D$3,'Base TOTAL'!A:DA,33,0),""), IF(res="", "Sin datos", res)) -> 04/9/2026: Se envìan al arq. encargado las Observaciones A corregir. 20/8/2026: Se envìan por Email las Observaciones A corregir por el Munic. 03/8/2026: Se envìan correcc a intend. Secr tec e Infraestr. 29/6/2026: Se envía nuevamente al municipio (Email) el Instructivo de la documentación legal y técnica requerida. 24/6/26: El Intendente informa que el monto autorizado es de $100 mill. y no $70 como dice la autorización previa. Ya hizo la gestión para que corrijan. /// Se envía Instructivo de la documentación legal y técnica a presentar.....23/6/26: Comunicaciòn con municipio solicitando Correo electrònico. 5/6/26: Ingresa Nota Ministerio Gobierno autorizando financiamiento. | E37: AG
A38: EXPEDIENTE RADICADO EN: | B38: FECHA | C38: =LET(res, IFERROR(VLOOKUP($D$3,'Base TOTAL'!A:DA,34,0),""), IF(res="", "Sin datos", res)) -> 46178 | E38: AH
B39: REPARTICIÓN | C39: =LET(res, IFERROR(VLOOKUP($D$3,'Base TOTAL'!A:DA,35,0),""), IF(res="", "Sin datos", res)) -> DIRECCION DE JURISDICCION DE REGULARIZACION DE OBRAS Y PROYECTOS | E39: AI
B40: OBRA (En Ejecución)
B41: Estado de la obra | C41: fecha
B42: Anticipo financiero | C42: =LET(res, IFERROR(VLOOKUP($D$3,'Base TOTAL'!A:DA,39,0),""), IF(res="", "Sin datos", res)) -> Sin datos | E42: AM
B43: =LET(res, IFERROR(VLOOKUP($D$3,'Base TOTAL'!A:DA,38,0),""), IF(res="", "Sin datos", res)) -> 35000000
B44: Avance físico 40% | C44: =LET(res, IFERROR(VLOOKUP($D$3,'Base TOTAL'!A:DA,41,0),""), IF(res="", "Sin datos", res)) -> Sin datos | E44: AO
B45: =LET(res, IFERROR(VLOOKUP($D$3,'Base TOTAL'!A:DA,40,0),""), IF(res="", "Sin datos", res)) -> 17500000
B46: Avance físico 70% | C46: =LET(res, IFERROR(VLOOKUP($D$3,'Base TOTAL'!A:DA,43,0),""), IF(res="", "Sin datos", res)) -> Sin datos | E46: AQ
B47: =LET(res, IFERROR(VLOOKUP($D$3,'Base TOTAL'!A:DA,42,0),""), IF(res="", "Sin datos", res)) -> 17500000
B48: OBRA (Terminada)
B49: Estado de la obra | C49: fecha
B50: Avance físico 100% | C50: =LET(res, IFERROR(VLOOKUP($D$3,'Base TOTAL'!A:DA,45,0),""), IF(res="", "Sin datos", res)) -> Sin datos | E50: AS
B51: $0,00
A52: OBSERVACIONES | C52: =LET(res, IFERROR(VLOOKUP($D$3,'Base TOTAL'!A:DA,46,0),""), IF(res="", "Sin datos", res)) -> Sin datos | E52: AT
A53: PROGRAMA CÓRDOBA HOGAR - LEY Nº 8663
A54: CONVENIO | B54: MONTO CONVENIO | C54: =LET(res, IFERROR(VLOOKUP($D$3,'Base TOTAL'!A:DA,48,0),""), IF(res="", "Sin datos", res)) -> Sin datos | E54: AV
B55: Cantidad de Viviendas | C55: =LET(res, IFERROR(VLOOKUP($D$3,'Base TOTAL'!A:DA,49,0),""), IF(res="", "Sin datos", res)) -> Sin datos | E55: AW
B56: Nº Expediente | C56: =LET(res, IFERROR(VLOOKUP($D$3,'Base TOTAL'!A:DA,50,0),""), IF(res="", "Sin datos", res)) -> Sin datos | E56: AX
A57: DOCUMENTACIÓN A PRESENTAR por Municipio / Comuna | B57: 1- Planimetría (Ubic. Obra) | C57: =LET(res, IFERROR(VLOOKUP($D$3,'Base TOTAL'!A:DA,51,0),""), IF(res="", "Sin datos", res)) -> Sin datos | E57: AY
B58: 2- Matrìcula de cada lote | C58: =LET(res, IFERROR(VLOOKUP($D$3,'Base TOTAL'!A:DA,52,0),""), IF(res="", "Sin datos", res)) -> Sin datos | E58: AZ
B59: 3- Estudio de Suelo | C59: =LET(res, IFERROR(VLOOKUP($D$3,'Base TOTAL'!A:DA,53,0),""), IF(res="", "Sin datos", res)) -> Sin datos | E59: BA
B60: 4- Cert. de No inundabilidad | C60: =LET(res, IFERROR(VLOOKUP($D$3,'Base TOTAL'!A:DA,54,0),""), IF(res="", "Sin datos", res)) -> Sin datos | D60: A ESPERA de DOC.TÉCNICA | E60: |
B61: 5- Fact. Agua Potable | C61: =LET(res, IFERROR(VLOOKUP($D$3,'Base TOTAL'!A:DA,55,0),""), IF(res="", "Sin datos", res)) -> Sin datos | E61: BC
B62: 6- Fac. Energìa Elèctrica | C62: =LET(res, IFERROR(VLOOKUP($D$3,'Base TOTAL'!A:DA,56,0),""), IF(res="", "Sin datos", res)) -> Sin datos | E62: BD
B63: 7- Designaciòn Dir. T. Obra | C63: =LET(res, IFERROR(VLOOKUP($D$3,'Base TOTAL'!A:DA,57,0),""), IF(res="", "Sin datos", res)) -> Sin datos | E63: BE
B64: 8- Memoria Téc. descriptiva | C64: =LET(res, IFERROR(VLOOKUP($D$3,'Base TOTAL'!A:DA,58,0),""), IF(res="", "Sin datos", res)) -> Sin datos | E64: BF
B65: 9- Planos Legajo Técnico | C65: =LET(res, IFERROR(VLOOKUP($D$3,'Base TOTAL'!A:DA,59,0),""), IF(res="", "Sin datos", res)) -> Sin datos | E65: BG
B66: 10- Pliego de Especif. Técnicas | C66: =LET(res, IFERROR(VLOOKUP($D$3,'Base TOTAL'!A:DA,60,0),""), IF(res="", "Sin datos", res)) -> Sin datos | E66: BH
B67: 11- Cómputo y Presupuesto | C67: =LET(res, IFERROR(VLOOKUP($D$3,'Base TOTAL'!A:DA,61,0),""), IF(res="", "Sin datos", res)) -> Sin datos | E67: BI
B68: 12- Acta Mediciòn - Cert. | C68: =LET(res, IFERROR(VLOOKUP($D$3,'Base TOTAL'!A:DA,62,0),""), IF(res="", "Sin datos", res)) -> Sin datos | E68: BJ
B69: 13- Curva de Avance | C69: =LET(res, IFERROR(VLOOKUP($D$3,'Base TOTAL'!A:DA,63,0),""), IF(res="", "Sin datos", res)) -> Sin datos | E69: BK
B70: 14- Cronograma de Avance | C70: =LET(res, IFERROR(VLOOKUP($D$3,'Base TOTAL'!A:DA,64,0),""), IF(res="", "Sin datos", res)) -> Sin datos | E70: BL
B71: ESTADO DEL EXPEDIENTE DE LA LOCALIDAD | C71: =LET(res, IFERROR(VLOOKUP($D$3,'Base TOTAL'!A:DA,65,0),""), IF(res="", "Sin datos", res)) -> En CURSO en TÉCNICA | E71: BM
A72: OBSERVACIONES | C72: =LET(res, IFERROR(VLOOKUP($D$3,'Base TOTAL'!A:DA,66,0),""), IF(res="", "Sin datos", res)) -> 02/9/2026: Se envìa Instructivo del Programa. | E72: BN
B73: OBRA (En Ejecución)
B74: Estado de la obra | C74: fecha | D74: fecha
B75: Anticipo financiero | C75: =LET(res, IFERROR(VLOOKUP($D$3,'Base TOTAL'!A:DA,68,0),""), IF(res="", "Sin datos", res)) -> Sin datos | E75: BP
B76: =$C$14*0.5 -> 35000000
B77: Avance físico 40% | C77: =LET(res, IFERROR(VLOOKUP($D$3,'Base TOTAL'!A:DA,70,0),""), IF(res="", "Sin datos", res)) -> Sin datos | E77: BR
B78: =$C$14*0.25 -> 17500000
B79: Avance físico 70% | C79: =LET(res, IFERROR(VLOOKUP($D$3,'Base TOTAL'!A:DA,72,0),""), IF(res="", "Sin datos", res)) -> Sin datos | E79: BT
B80: =$C$14*0.25 -> 17500000
B81: OBRA (Terminada)
B82: Estado de la obra | C82: fecha
B83: Avance físico 100% | C83: =LET(res, IFERROR(VLOOKUP($D$3,'Base TOTAL'!A:DA,74,0),""), IF(res="", "Sin datos", res)) -> Sin datos | E83: BV
B84: $0,00
A85: OBSERVACIONES | C85: =LET(res, IFERROR(VLOOKUP($D$3,'Base TOTAL'!A:DA,75,0),""), IF(res="", "Sin datos", res)) -> Sin datos | E85: BW
A86: PROGRAMA MI LUGAR
A87: CONVENIO | B87: MONTO | C87: =LET(res, IFERROR(VLOOKUP($D$3,'Base TOTAL'!A:DA,77,0),""), IF(res="", "Sin datos", res)) -> Sin datos | E87: BY
B88: Cantidad de Lotes | C88: =LET(res, IFERROR(VLOOKUP($D$3,'Base TOTAL'!A:DA,78,0),""), IF(res="", "Sin datos", res)) -> Sin datos | E88: BZ
B89: Nº Expediente | C89: =LET(res, IFERROR(VLOOKUP($D$3,'Base TOTAL'!A:DA,79,0),""), IF(res="", "Sin datos", res)) -> Sin datos | E89: CA
A90: DOCUMENTACIÓN A PRESENTAR por Municipio / Comuna | B90: ='Base TOTAL'!CB2 -> 1- Planimetría General | C90: =LET(res, IFERROR(VLOOKUP($D$3,'Base TOTAL'!A:DA,80,0),""), IF(res="", "Sin datos", res)) -> Sin datos | E90: CB
B91: ='Base TOTAL'!CC2 -> 2- Plano de Altimetría | C91: =LET(res, IFERROR(VLOOKUP($D$3,'Base TOTAL'!A:DA,81,0),""), IF(res="", "Sin datos", res)) -> Sin datos | E91: CC
B92: ='Base TOTAL'!CD2 -> 3- Plancheta Catastral | C92: =LET(res, IFERROR(VLOOKUP($D$3,'Base TOTAL'!A:DA,82,0),""), IF(res="", "Sin datos", res)) -> Sin datos | E92: CD
B93: ='Base TOTAL'!CE2 -> 4-Títulos | C93: =LET(res, IFERROR(VLOOKUP($D$3,'Base TOTAL'!A:DA,83,0),""), IF(res="", "Sin datos", res)) -> Sin datos | E93: CE
B94: ='Base TOTAL'!CF2 -> 5- Certificado de No Inundabilidad | C94: =LET(res, IFERROR(VLOOKUP($D$3,'Base TOTAL'!A:DA,84,0),""), IF(res="", "Sin datos", res)) -> Sin datos | E94: CF
B95: ='Base TOTAL'!CG2 -> 6- Informe de Ministerio de Ambiente y Economía Circular | C95: =LET(res, IFERROR(VLOOKUP($D$3,'Base TOTAL'!A:DA,85,0),""), IF(res="", "Sin datos", res)) -> Sin datos | E95: CG
B96: ='Base TOTAL'!CH2 -> 7- Factibilidad de Agua Potable | C96: =LET(res, IFERROR(VLOOKUP($D$3,'Base TOTAL'!A:DA,86,0),""), IF(res="", "Sin datos", res)) -> Sin datos | E96: CH
B97: ='Base TOTAL'!CI2 -> 8- Factibilidad de Energía Eléctrica | C97: =LET(res, IFERROR(VLOOKUP($D$3,'Base TOTAL'!A:DA,87,0),""), IF(res="", "Sin datos", res)) -> Sin datos | E97: CI
B98: ='Base TOTAL'!CJ2 -> 9- Certificado de Prestación de Servicios | C98: =LET(res, IFERROR(VLOOKUP($D$3,'Base TOTAL'!A:DA,88,0),""), IF(res="", "Sin datos", res)) -> Sin datos | E98: CJ
B99: ='Base TOTAL'!CK2 -> 10- Factibilidad de Red Cloacal / Poszo Absorbente | C99: =LET(res, IFERROR(VLOOKUP($D$3,'Base TOTAL'!A:DA,89,0),""), IF(res="", "Sin datos", res)) -> Sin datos | E99: CK
B100: ='Base TOTAL'!CL2 -> 11- Designación de Representante Técnico | C100: =LET(res, IFERROR(VLOOKUP($D$3,'Base TOTAL'!A:DA,90,0),""), IF(res="", "Sin datos", res)) -> Sin datos | E100: CL
...

Sheet IN x Localidad PABLO
A1: Programas provinciales - Dirección General de Vivienda
A2: Ingreso de Datos
C3: LOCALIDAD: | D3: El Arañado | E3: ⬅️ solamente ELEGIR LOCALIDAD
C4: DEPARTAMENTO: | D4: =IFERROR(VLOOKUP($D$3,'Base TOTAL'!A:AU,2,0), "Sin da") -> San Justo
C5: Datos actuales | D5: Modificar/Ingresar nuevo dato | E5: Columna ref. BASE TOTAL
B6: MUNICIPIO / COMUNA | C6: =LET(res, IFERROR(VLOOKUP($D$3,'Base TOTAL'!A:DA,5,0),""), IF(res="", "Sin datos", res)) -> Sin datos | E6: E
B7: INTENDENTE / PRESIDENTE COMUNAL | C7: =LET(res, IFERROR(VLOOKUP($D$3,'Base TOTAL'!A:DA,6,0),""), IF(res="", "Sin datos", res)) -> Gudiño Jorge Alino | E7: F
B8: N° TELÉFONO M/C | C8: =LET(res, IFERROR(VLOOKUP($D$3,'Base TOTAL'!A:DA,7,0),""), IF(res="", "Sin datos", res)) -> 3533442747 | E8: G
B9: CORREO ELECTRÓNICO | C9: =LET(res, IFERROR(VLOOKUP($D$3,'Base TOTAL'!A:DA,8,0),""), IF(res="", "Sin datos", res)) -> Jorgegudino276@gmail.com | E9: H
B10: CONTACTO TÉCNICO de M/C | C10: =LET(res, IFERROR(VLOOKUP($D$3,'Base TOTAL'!A:DA,9,0),""), IF(res="", "Sin datos", res)) -> ab.alcantaro@gmail.com | E10: I
A11: PROGRAMA PROVINCIAL DE CORDÓN CUNETA Y ADOQUINES - LEY Nº 11089
B12: EXPEDIENTE N° | C12: =LET(res, IFERROR(VLOOKUP($D$3,'Base TOTAL'!A:DA,3,0),""), IF(res="", "Sin datos", res)) -> 0423-080121/2026 | E12: C
B13: N° Orden | C13: =LET(res, IFERROR(VLOOKUP($D$3,'Base TOTAL'!A:DA,4,0),""), IF(res="", "Sin datos", res)) -> 45 | E13: D
A14: CONVENIO | B14: MONTO CONVENIO | C14: =LET(res, IFERROR(VLOOKUP($D$3,'Base TOTAL'!A:DA,10,0),""), IF(res="", "Sin datos", res)) -> 200000000 | E14: J
B15: Cordón Cuneta (ml) | C15: =LET(res, IFERROR(VLOOKUP($D$3,'Base TOTAL'!A:DA,11,0),""), IF(res="", "Sin datos", res)) -> Sin datos | E15: K
B16: Adoquinado (m2) | C16: =LET(res, IFERROR(VLOOKUP($D$3,'Base TOTAL'!A:DA,12,0),""), IF(res="", "Sin datos", res)) -> Sin datos | E16: L
A17: DOCUMENTACIÓN A PRESENTAR por Municipio / Comuna | B17: 1 | C17: =LET(res, IFERROR(VLOOKUP($D$3,'Base TOTAL'!A:DA,13,0),""), IF(res="", "Sin datos", res)) -> A ESPERA de DOC.TÉCNICA | E17: M
B18: 2 | C18: =LET(res, IFERROR(VLOOKUP($D$3,'Base TOTAL'!A:DA,14,0),""), IF(res="", "Sin datos", res)) -> A ESPERA de DOC.TÉCNICA | E18: N
B19: 3 | C19: =LET(res, IFERROR(VLOOKUP($D$3,'Base TOTAL'!A:DA,15,0),""), IF(res="", "Sin datos", res)) -> A ESPERA de DOC.TÉCNICA | E19: O
B20: 4 | C20: =LET(res, IFERROR(VLOOKUP($D$3,'Base TOTAL'!A:DA,16,0),""), IF(res="", "Sin datos", res)) -> A corregir por M/C | E20: P
B21: Descripción General | C21: =LET(res, IFERROR(VLOOKUP($D$3,'Base TOTAL'!A:DA,17,0),""), IF(res="", "Sin datos", res)) -> A corregir por M/C | E21: Q
B22: Memoria Técnica | C22: =LET(res, IFERROR(VLOOKUP($D$3,'Base TOTAL'!A:DA,18,0),""), IF(res="", "Sin datos", res)) -> A corregir por M/C | E22: R
B23: Plazo de Ejecución | C23: =LET(res, IFERROR(VLOOKUP($D$3,'Base TOTAL'!A:DA,19,0),""), IF(res="", "Sin datos", res)) -> A corregir por M/C | E23: S
B24: Cómputo y Presupuesto | C24: =LET(res, IFERROR(VLOOKUP($D$3,'Base TOTAL'!A:DA,20,0),""), IF(res="", "Sin datos", res)) -> A corregir por M/C | E24: T
B25: Cronograma Avance Obra | C25: =LET(res, IFERROR(VLOOKUP($D$3,'Base TOTAL'!A:DA,21,0),""), IF(res="", "Sin datos", res)) -> A corregir por M/C | E25: U
B26: Planimetría | C26: =LET(res, IFERROR(VLOOKUP($D$3,'Base TOTAL'!A:DA,22,0),""), IF(res="", "Sin datos", res)) -> A corregir por M/C | E26: V
B27: Perfil Calzada | C27: =LET(res, IFERROR(VLOOKUP($D$3,'Base TOTAL'!A:DA,23,0),""), IF(res="", "Sin datos", res)) -> A corregir por M/C | E27: W
B28: Detalle de Cordón Cuneta | C28: =LET(res, IFERROR(VLOOKUP($D$3,'Base TOTAL'!A:DA,24,0),""), IF(res="", "Sin datos", res)) -> A corregir por M/C | E28: X
B29: Detalle de Badén | C29: =LET(res, IFERROR(VLOOKUP($D$3,'Base TOTAL'!A:DA,25,0),""), IF(res="", "Sin datos", res)) -> A corregir por M/C | E29: Y
B30: Paquete estr. Calzada | C30: =LET(res, IFERROR(VLOOKUP($D$3,'Base TOTAL'!A:DA,26,0),""), IF(res="", "Sin datos", res)) -> A ESPERA de DOC.TÉCNICA | E30: Z
B31: 5 | C31: =LET(res, IFERROR(VLOOKUP($D$3,'Base TOTAL'!A:DA,27,0),""), IF(res="", "Sin datos", res)) -> A ESPERA de DOC.TÉCNICA | E31: AA
B32: 6 | C32: =LET(res, IFERROR(VLOOKUP($D$3,'Base TOTAL'!A:DA,28,0),""), IF(res="", "Sin datos", res)) -> A ESPERA de DOC.TÉCNICA | E32: AB
B33: 7 | C33: =LET(res, IFERROR(VLOOKUP($D$3,'Base TOTAL'!A:DA,29,0),""), IF(res="", "Sin datos", res)) -> A ESPERA de DOC.TÉCNICA | E33: AC
B34: 8 | C34: =LET(res, IFERROR(VLOOKUP($D$3,'Base TOTAL'!A:DA,30,0),""), IF(res="", "Sin datos", res)) -> A ESPERA de DOC.TÉCNICA | E34: AD
B35: 9 | C35: =LET(res, IFERROR(VLOOKUP($D$3,'Base TOTAL'!A:DA,31,0),""), IF(res="", "Sin datos", res)) -> A ESPERA de DOC.TÉCNICA | E35: AE
B36: ESTADO DEL EXPEDIENTE DE LA LOCALIDAD | C36: =LET(res, IFERROR(VLOOKUP($D$3,'Base TOTAL'!A:DA,32,0),""), IF(res="", "Sin datos", res)) -> En CURSO en TÉCNICA | E36: AF
A37: OBSERVACIONES | C37: =LET(res, IFERROR(VLOOKUP($D$3,'Base TOTAL'!A:DA,33,0),""), IF(res="", "Sin datos", res)) -> 20/8/2026: Se envía por Email, el Instructivo con el cambio de denominación. (Hoy Secretaría) 05/8/2026: Comunicaciòn con M/C enviando correo electrònico. 24/6/26:Comunicación con el municipio. Se envía Instructivo de la documentación legal y técnica requerida. 5/6/26: Ingresa Nota Ministerio Gobierno autorizando financiamiento. | E37: AG
A38: EXPEDIENTE RADICADO EN: | B38: FECHA | C38: =LET(res, IFERROR(VLOOKUP($D$3,'Base TOTAL'!A:DA,34,0),""), IF(res="", "Sin datos", res)) -> 46178 | E38: AH
B39: REPARTICIÓN | C39: =LET(res, IFERROR(VLOOKUP($D$3,'Base TOTAL'!A:DA,35,0),""), IF(res="", "Sin datos", res)) -> DIRECCION DE JURISDICCION DE REGULARIZACION DE OBRAS Y PROYECTOS | E39: AI
B40: OBRA (En Ejecución)
B41: Estado de la obra | C41: fecha
B42: Anticipo financiero | C42: =LET(res, IFERROR(VLOOKUP($D$3,'Base TOTAL'!A:DA,39,0),""), IF(res="", "Sin datos", res)) -> Sin datos | E42: AM
B43: =LET(res, IFERROR(VLOOKUP($D$3,'Base TOTAL'!A:DA,38,0),""), IF(res="", "Sin datos", res)) -> 100000000
B44: Avance físico 40% | C44: =LET(res, IFERROR(VLOOKUP($D$3,'Base TOTAL'!A:DA,41,0),""), IF(res="", "Sin datos", res)) -> Sin datos | E44: AO
B45: =LET(res, IFERROR(VLOOKUP($D$3,'Base TOTAL'!A:DA,40,0),""), IF(res="", "Sin datos", res)) -> 50000000
B46: Avance físico 70% | C46: =LET(res, IFERROR(VLOOKUP($D$3,'Base TOTAL'!A:DA,43,0),""), IF(res="", "Sin datos", res)) -> Sin datos | E46: AQ
B47: =LET(res, IFERROR(VLOOKUP($D$3,'Base TOTAL'!A:DA,42,0),""), IF(res="", "Sin datos", res)) -> 50000000
B48: OBRA (Terminada)
B49: Estado de la obra | C49: fecha
B50: Avance físico 100% | C50: =LET(res, IFERROR(VLOOKUP($D$3,'Base TOTAL'!A:DA,45,0),""), IF(res="", "Sin datos", res)) -> Sin datos | E50: AS
B51: $0,00
A52: OBSERVACIONES | C52: =LET(res, IFERROR(VLOOKUP($D$3,'Base TOTAL'!A:DA,46,0),""), IF(res="", "Sin datos", res)) -> Sin datos | E52: AT
A53: PROGRAMA CÓRDOBA HOGAR - LEY Nº 8663
A54: CONVENIO | B54: MONTO CONVENIO | C54: =LET(res, IFERROR(VLOOKUP($D$3,'Base TOTAL'!A:DA,48,0),""), IF(res="", "Sin datos", res)) -> Sin datos | E54: AV
B55: Cantidad de Viviendas | C55: =LET(res, IFERROR(VLOOKUP($D$3,'Base TOTAL'!A:DA,49,0),""), IF(res="", "Sin datos", res)) -> Sin datos | E55: AW
B56: Nº Expediente | C56: =LET(res, IFERROR(VLOOKUP($D$3,'Base TOTAL'!A:DA,50,0),""), IF(res="", "Sin datos", res)) -> Sin datos | E56: AX
A57: DOCUMENTACIÓN A PRESENTAR por Municipio / Comuna | B57: 1- Planimetría (Ubic. Obra) | C57: =LET(res, IFERROR(VLOOKUP($D$3,'Base TOTAL'!A:DA,51,0),""), IF(res="", "Sin datos", res)) -> Sin datos | E57: AY
B58: 2- Matrìcula de cada lote | C58: =LET(res, IFERROR(VLOOKUP($D$3,'Base TOTAL'!A:DA,52,0),""), IF(res="", "Sin datos", res)) -> Sin datos | E58: AZ
B59: 3- Estudio de Suelo | C59: =LET(res, IFERROR(VLOOKUP($D$3,'Base TOTAL'!A:DA,53,0),""), IF(res="", "Sin datos", res)) -> Sin datos | E59: BA
B60: 4- Cert. de No inundabilidad | C60: =LET(res, IFERROR(VLOOKUP($D$3,'Base TOTAL'!A:DA,54,0),""), IF(res="", "Sin datos", res)) -> Sin datos | E60: |
B61: 5- Fact. Agua Potable | C61: =LET(res, IFERROR(VLOOKUP($D$3,'Base TOTAL'!A:DA,55,0),""), IF(res="", "Sin datos", res)) -> Sin datos | E61: BC
B62: 6- Fac. Energìa Elèctrica | C62: =LET(res, IFERROR(VLOOKUP($D$3,'Base TOTAL'!A:DA,56,0),""), IF(res="", "Sin datos", res)) -> Sin datos | E62: BD
B63: 7- Designaciòn Dir. T. Obra | C63: =LET(res, IFERROR(VLOOKUP($D$3,'Base TOTAL'!A:DA,57,0),""), IF(res="", "Sin datos", res)) -> Sin datos | E63: BE
B64: 8- Memoria Téc. descriptiva | C64: =LET(res, IFERROR(VLOOKUP($D$3,'Base TOTAL'!A:DA,58,0),""), IF(res="", "Sin datos", res)) -> Sin datos | E64: BF
B65: 9- Planos Legajo Técnico | C65: =LET(res, IFERROR(VLOOKUP($D$3,'Base TOTAL'!A:DA,59,0),""), IF(res="", "Sin datos", res)) -> Sin datos | E65: BG
B66: 10- Pliego de Especif. Técnicas | C66: =LET(res, IFERROR(VLOOKUP($D$3,'Base TOTAL'!A:DA,60,0),""), IF(res="", "Sin datos", res)) -> Sin datos | E66: BH
B67: 11- Cómputo y Presupuesto | C67: =LET(res, IFERROR(VLOOKUP($D$3,'Base TOTAL'!A:DA,61,0),""), IF(res="", "Sin datos", res)) -> Sin datos | E67: BI
B68: 12- Acta Mediciòn - Cert. | C68: =LET(res, IFERROR(VLOOKUP($D$3,'Base TOTAL'!A:DA,62,0),""), IF(res="", "Sin datos", res)) -> Sin datos | E68: BJ
B69: 13- Curva de Avance | C69: =LET(res, IFERROR(VLOOKUP($D$3,'Base TOTAL'!A:DA,63,0),""), IF(res="", "Sin datos", res)) -> Sin datos | E69: BK
B70: 14- Cronograma de Avance | C70: =LET(res, IFERROR(VLOOKUP($D$3,'Base TOTAL'!A:DA,64,0),""), IF(res="", "Sin datos", res)) -> Sin datos | E70: BL
B71: ESTADO DEL EXPEDIENTE DE LA LOCALIDAD | C71: =LET(res, IFERROR(VLOOKUP($D$3,'Base TOTAL'!A:DA,65,0),""), IF(res="", "Sin datos", res)) -> Sin datos | E71: BM
A72: OBSERVACIONES | C72: =LET(res, IFERROR(VLOOKUP($D$3,'Base TOTAL'!A:DA,66,0),""), IF(res="", "Sin datos", res)) -> Sin datos | E72: BN
B73: OBRA (En Ejecución)
B74: Estado de la obra | C74: fecha | D74: fecha
B75: Anticipo financiero | C75: =LET(res, IFERROR(VLOOKUP($D$3,'Base TOTAL'!A:DA,68,0),""), IF(res="", "Sin datos", res)) -> Sin datos | E75: BP
B76: =$C$14*0.5 -> 100000000
B77: Avance físico 40% | C77: =LET(res, IFERROR(VLOOKUP($D$3,'Base TOTAL'!A:DA,70,0),""), IF(res="", "Sin datos", res)) -> Sin datos | E77: BR
B78: =$C$14*0.25 -> 50000000
B79: Avance físico 70% | C79: =LET(res, IFERROR(VLOOKUP($D$3,'Base TOTAL'!A:DA,72,0),""), IF(res="", "Sin datos", res)) -> Sin datos | E79: BT
B80: =$C$14*0.25 -> 50000000
B81: OBRA (Terminada)
B82: Estado de la obra | C82: fecha
B83: Avance físico 100% | C83: =LET(res, IFERROR(VLOOKUP($D$3,'Base TOTAL'!A:DA,74,0),""), IF(res="", "Sin datos", res)) -> Sin datos | E83: BV
B84: $0,00
A85: OBSERVACIONES | C85: =LET(res, IFERROR(VLOOKUP($D$3,'Base TOTAL'!A:DA,75,0),""), IF(res="", "Sin datos", res)) -> Sin datos | E85: BW
A86: PROGRAMA MI LUGAR
A87: CONVENIO | B87: MONTO | C87: =LET(res, IFERROR(VLOOKUP($D$3,'Base TOTAL'!A:DA,77,0),""), IF(res="", "Sin datos", res)) -> Sin datos | E87: BY
B88: Cantidad de Lotes | C88: =LET(res, IFERROR(VLOOKUP($D$3,'Base TOTAL'!A:DA,78,0),""), IF(res="", "Sin datos", res)) -> Sin datos | E88: BZ
B89: Nº Expediente | C89: =LET(res, IFERROR(VLOOKUP($D$3,'Base TOTAL'!A:DA,79,0),""), IF(res="", "Sin datos", res)) -> Sin datos | E89: CA
A90: DOCUMENTACIÓN A PRESENTAR por Municipio / Comuna | B90: ='Base TOTAL'!CB2 -> 1- Planimetría General | C90: =LET(res, IFERROR(VLOOKUP($D$3,'Base TOTAL'!A:DA,80,0),""), IF(res="", "Sin datos", res)) -> Sin datos | E90: CB
B91: ='Base TOTAL'!CC2 -> 2- Plano de Altimetría | C91: =LET(res, IFERROR(VLOOKUP($D$3,'Base TOTAL'!A:DA,81,0),""), IF(res="", "Sin datos", res)) -> Sin datos | E91: CC
B92: ='Base TOTAL'!CD2 -> 3- Plancheta Catastral | C92: =LET(res, IFERROR(VLOOKUP($D$3,'Base TOTAL'!A:DA,82,0),""), IF(res="", "Sin datos", res)) -> Sin datos | E92: CD
B93: ='Base TOTAL'!CE2 -> 4-Títulos | C93: =LET(res, IFERROR(VLOOKUP($D$3,'Base TOTAL'!A:DA,83,0),""), IF(res="", "Sin datos", res)) -> Sin datos | E93: CE
B94: ='Base TOTAL'!CF2 -> 5- Certificado de No Inundabilidad | C94: =LET(res, IFERROR(VLOOKUP($D$3,'Base TOTAL'!A:DA,84,0),""), IF(res="", "Sin datos", res)) -> Sin datos | E94: CF
B95: ='Base TOTAL'!CG2 -> 6- Informe de Ministerio de Ambiente y Economía Circular | C95: =LET(res, IFERROR(VLOOKUP($D$3,'Base TOTAL'!A:DA,85,0),""), IF(res="", "Sin datos", res)) -> Sin datos | E95: CG
B96: ='Base TOTAL'!CH2 -> 7- Factibilidad de Agua Potable | C96: =LET(res, IFERROR(VLOOKUP($D$3,'Base TOTAL'!A:DA,86,0),""), IF(res="", "Sin datos", res)) -> Sin datos | E96: CH
B97: ='Base TOTAL'!CI2 -> 8- Factibilidad de Energía Eléctrica | C97: =LET(res, IFERROR(VLOOKUP($D$3,'Base TOTAL'!A:DA,87,0),""), IF(res="", "Sin datos", res)) -> Sin datos | E97: CI
B98: ='Base TOTAL'!CJ2 -> 9- Certificado de Prestación de Servicios | C98: =LET(res, IFERROR(VLOOKUP($D$3,'Base TOTAL'!A:DA,88,0),""), IF(res="", "Sin datos", res)) -> Sin datos | E98: CJ
B99: ='Base TOTAL'!CK2 -> 10- Factibilidad de Red Cloacal / Poszo Absorbente | C99: =LET(res, IFERROR(VLOOKUP($D$3,'Base TOTAL'!A:DA,89,0),""), IF(res="", "Sin datos", res)) -> Sin datos | E99: CK
B100: ='Base TOTAL'!CL2 -> 11- Designación de Representante Técnico | C100: =LET(res, IFERROR(VLOOKUP($D$3,'Base TOTAL'!A:DA,90,0),""), IF(res="", "Sin datos", res)) -> Sin datos | E100: CL
...

Sheet IN x Localidad H
A1: Programas provinciales - Dirección General de Vivienda
A2: Ingreso de Datos
C3: LOCALIDAD: | D3: Tuclame | E3: ⬅️ solamente ELEGIR LOCALIDAD
C4: DEPARTAMENTO: | D4: =IFERROR(VLOOKUP($D$3,'Base TOTAL'!A:AU,2,0), "Sin dato") -> Cruz del Eje
C5: Datos actuales | D5: Modificar/Ingresar nuevo dato | E5: Columna ref. BASE TOTAL
B6: MUNICIPIO / COMUNA | C6: =LET(res, IFERROR(VLOOKUP($D$3,'Base TOTAL'!A:DA,5,0),""), IF(res="", "Sin datos", res)) -> C | E6: E
B7: INTENDENTE / PRESIDENTE COMUNAL | C7: =LET(res, IFERROR(VLOOKUP($D$3,'Base TOTAL'!A:DA,6,0),""), IF(res="", "Sin datos", res)) -> GRACIELA DEL VALLE GONZÁLEZ | E7: F
B8: N° TELÉFONO M/C | C8: =LET(res, IFERROR(VLOOKUP($D$3,'Base TOTAL'!A:DA,7,0),""), IF(res="", "Sin datos", res)) -> (3549) 53-7628 | E8: G
B9: CORREO ELECTRÓNICO | C9: =LET(res, IFERROR(VLOOKUP($D$3,'Base TOTAL'!A:DA,8,0),""), IF(res="", "Sin datos", res)) -> gracieladelvallegonzalez20@gmail.com | E9: H
B10: CONTACTO TÉCNICO de M/C | C10: =LET(res, IFERROR(VLOOKUP($D$3,'Base TOTAL'!A:DA,9,0),""), IF(res="", "Sin datos", res)) -> ingbracamontegustavo@gmail.com | E10: I
A11: PROGRAMA PROVINCIAL DE CORDÓN CUNETA Y ADOQUINES - LEY Nº 11089
B12: EXPEDIENTE N° | C12: =LET(res, IFERROR(VLOOKUP($D$3,'Base TOTAL'!A:DA,3,0),""), IF(res="", "Sin datos", res)) -> 0423-079113/2026 | E12: C
B13: N° Orden | C13: =LET(res, IFERROR(VLOOKUP($D$3,'Base TOTAL'!A:DA,4,0),""), IF(res="", "Sin datos", res)) -> 16 | E13: D
A14: CONVENIO | B14: MONTO CONVENIO | C14: =LET(res, IFERROR(VLOOKUP($D$3,'Base TOTAL'!A:DA,10,0),""), IF(res="", "Sin datos", res)) -> 200000000 | E14: J
B15: Cordón Cuneta (ml) | C15: =LET(res, IFERROR(VLOOKUP($D$3,'Base TOTAL'!A:DA,11,0),""), IF(res="", "Sin datos", res)) -> 400 | E15: K
B16: Adoquinado (m2) | C16: =LET(res, IFERROR(VLOOKUP($D$3,'Base TOTAL'!A:DA,12,0),""), IF(res="", "Sin datos", res)) -> Sin datos | E16: L
A17: DOCUMENTACIÓN A PRESENTAR por Municipio / Comuna | B17: 1 | C17: =LET(res, IFERROR(VLOOKUP($D$3,'Base TOTAL'!A:DA,13,0),""), IF(res="", "Sin datos", res)) -> Completo OK | E17: M
B18: 2 | C18: =LET(res, IFERROR(VLOOKUP($D$3,'Base TOTAL'!A:DA,14,0),""), IF(res="", "Sin datos", res)) -> Completo OK | E18: N
B19: 3 | C19: =LET(res, IFERROR(VLOOKUP($D$3,'Base TOTAL'!A:DA,15,0),""), IF(res="", "Sin datos", res)) -> Completo OK | E19: O
B20: 4 | C20: =LET(res, IFERROR(VLOOKUP($D$3,'Base TOTAL'!A:DA,16,0),""), IF(res="", "Sin datos", res)) -> Completo OK | E20: P
B21: Descripción General | C21: =LET(res, IFERROR(VLOOKUP($D$3,'Base TOTAL'!A:DA,17,0),""), IF(res="", "Sin datos", res)) -> Completo OK | E21: Q
B22: Memoria Técnica | C22: =LET(res, IFERROR(VLOOKUP($D$3,'Base TOTAL'!A:DA,18,0),""), IF(res="", "Sin datos", res)) -> Completo OK | E22: R
B23: Plazo de Ejecución | C23: =LET(res, IFERROR(VLOOKUP($D$3,'Base TOTAL'!A:DA,19,0),""), IF(res="", "Sin datos", res)) -> Completo OK | E23: S
B24: Cómputo y Presupuesto | C24: =LET(res, IFERROR(VLOOKUP($D$3,'Base TOTAL'!A:DA,20,0),""), IF(res="", "Sin datos", res)) -> Completo OK | E24: T
B25: Cronograma Avance Obra | C25: =LET(res, IFERROR(VLOOKUP($D$3,'Base TOTAL'!A:DA,21,0),""), IF(res="", "Sin datos", res)) -> Completo OK | E25: U
B26: Planimetría | C26: =LET(res, IFERROR(VLOOKUP($D$3,'Base TOTAL'!A:DA,22,0),""), IF(res="", "Sin datos", res)) -> Completo OK | E26: V
B27: Perfil Calzada | C27: =LET(res, IFERROR(VLOOKUP($D$3,'Base TOTAL'!A:DA,23,0),""), IF(res="", "Sin datos", res)) -> Completo OK | E27: W
B28: Detalle de Cordón Cuneta | C28: =LET(res, IFERROR(VLOOKUP($D$3,'Base TOTAL'!A:DA,24,0),""), IF(res="", "Sin datos", res)) -> Completo OK | E28: X
B29: Detalle de Badén | C29: =LET(res, IFERROR(VLOOKUP($D$3,'Base TOTAL'!A:DA,25,0),""), IF(res="", "Sin datos", res)) -> Completo OK | E29: Y
B30: Paquete estr. Calzada | C30: =LET(res, IFERROR(VLOOKUP($D$3,'Base TOTAL'!A:DA,26,0),""), IF(res="", "Sin datos", res)) -> Completo OK | E30: Z
B31: 5 | C31: =LET(res, IFERROR(VLOOKUP($D$3,'Base TOTAL'!A:DA,27,0),""), IF(res="", "Sin datos", res)) -> Completo OK | E31: AA
B32: 6 | C32: =LET(res, IFERROR(VLOOKUP($D$3,'Base TOTAL'!A:DA,28,0),""), IF(res="", "Sin datos", res)) -> Completo OK | E32: AB
B33: 7 | C33: =LET(res, IFERROR(VLOOKUP($D$3,'Base TOTAL'!A:DA,29,0),""), IF(res="", "Sin datos", res)) -> Completo OK | E33: AC
B34: 8 | C34: =LET(res, IFERROR(VLOOKUP($D$3,'Base TOTAL'!A:DA,30,0),""), IF(res="", "Sin datos", res)) -> Completo OK | E34: AD
B35: 9 | C35: =LET(res, IFERROR(VLOOKUP($D$3,'Base TOTAL'!A:DA,31,0),""), IF(res="", "Sin datos", res)) -> Completo OK | E35: AE
B36: ESTADO DEL EXPEDIENTE DE LA LOCALIDAD | C36: =LET(res, IFERROR(VLOOKUP($D$3,'Base TOTAL'!A:DA,32,0),""), IF(res="", "Sin datos", res)) -> OBRA en EJECUCIÓN | E36: AF
A37: OBSERVACIONES | C37: =LET(res, IFERROR(VLOOKUP($D$3,'Base TOTAL'!A:DA,33,0),""), IF(res="", "Sin datos", res)) -> 07/8/2026: Se pagò A.F. el 5/8/2026 05/8/2026: PASA A EONOMICO-FINANCIERO para pago de A.F. 04/8/2026: Envìan Certif. y Nota a Silvia. 04/8/2026: Se envìa Modelo de Cert. A.F. A completar por la comuna y presentar. COMPLETÓ documentación. Subió a Jurídico Con V°B°. EN LA PRIVADA DESDE 19/05/26 ENVIÓ LA DOCUMENTACIÓN. ESTÁS COMPLETA, SÓLO DEBE CORREGIR CRONOGRAMA DE INVERSIONES. COMPLETO. CON V°B° DE TÉCNICA | E37: AG
A38: EXPEDIENTE RADICADO EN: | B38: FECHA | C38: =LET(res, IFERROR(VLOOKUP($D$3,'Base TOTAL'!A:DA,34,0),""), IF(res="", "Sin datos", res)) -> 46231 | E38: AH
B39: REPARTICIÓN | C39: =LET(res, IFERROR(VLOOKUP($D$3,'Base TOTAL'!A:DA,35,0),""), IF(res="", "Sin datos", res)) -> DIRECCION DE JURISDICCION ECONOMICO, FINANCIERA Y DE ADMINISTRACION | E39: AI
B40: OBRA (En Ejecución)
B41: Estado de la obra | C41: fecha
B42: Anticipo financiero | C42: =LET(res, IFERROR(VLOOKUP($D$3,'Base TOTAL'!A:DA,39,0),""), IF(res="", "Sin datos", res)) -> 46239 | E42: AM
B43: =LET(res, IFERROR(VLOOKUP($D$3,'Base TOTAL'!A:DA,38,0),""), IF(res="", "Sin datos", res)) -> 100000000
B44: Avance físico 40% | C44: =LET(res, IFERROR(VLOOKUP($D$3,'Base TOTAL'!A:DA,41,0),""), IF(res="", "Sin datos", res)) -> Sin datos | E44: AO
B45: =LET(res, IFERROR(VLOOKUP($D$3,'Base TOTAL'!A:DA,40,0),""), IF(res="", "Sin datos", res)) -> 50000000
B46: Avance físico 70% | C46: =LET(res, IFERROR(VLOOKUP($D$3,'Base TOTAL'!A:DA,43,0),""), IF(res="", "Sin datos", res)) -> Sin datos | E46: AQ
B47: =LET(res, IFERROR(VLOOKUP($D$3,'Base TOTAL'!A:DA,42,0),""), IF(res="", "Sin datos", res)) -> 50000000
B48: OBRA (Terminada)
B49: Estado de la obra | C49: fecha
B50: Avance físico 100% | C50: =LET(res, IFERROR(VLOOKUP($D$3,'Base TOTAL'!A:DA,45,0),""), IF(res="", "Sin datos", res)) -> Sin datos | E50: AS
B51: $0,00
A52: OBSERVACIONES | C52: =LET(res, IFERROR(VLOOKUP($D$3,'Base TOTAL'!A:DA,46,0),""), IF(res="", "Sin datos", res)) -> 04/9/2026: Comunicaciòn con la Pres. Com. el 2/9. Informa que la obra està avanzando. Se envìa Certificado Modelo al Ing. Bracamonte. 07/8/2026: Se pagò A.F. el 5/8/2026 | E52: AT
A53: PROGRAMA CÓRDOBA HOGAR - LEY Nº 8663
A54: CONVENIO | B54: MONTO CONVENIO | C54: =LET(res, IFERROR(VLOOKUP($D$3,'Base TOTAL'!A:DA,48,0),""), IF(res="", "Sin datos", res)) -> 102000000 | E54: AV
B55: Cantidad de Viviendas | C55: =LET(res, IFERROR(VLOOKUP($D$3,'Base TOTAL'!A:DA,49,0),""), IF(res="", "Sin datos", res)) -> 3 | E55: AW
B56: Nº Expediente | C56: =LET(res, IFERROR(VLOOKUP($D$3,'Base TOTAL'!A:DA,50,0),""), IF(res="", "Sin datos", res)) -> 0135-045042/2026 | E56: AX
A57: DOCUMENTACIÓN A PRESENTAR por Municipio / Comuna | B57: 1- Planimetría (Ubic. Obra) | C57: =LET(res, IFERROR(VLOOKUP($D$3,'Base TOTAL'!A:DA,51,0),""), IF(res="", "Sin datos", res)) -> Completo OK | E57: AY
B58: 2- Matrìcula de cada lote | C58: =LET(res, IFERROR(VLOOKUP($D$3,'Base TOTAL'!A:DA,52,0),""), IF(res="", "Sin datos", res)) -> Sin datos | E58: AZ
B59: 3- Estudio de Suelo | C59: =LET(res, IFERROR(VLOOKUP($D$3,'Base TOTAL'!A:DA,53,0),""), IF(res="", "Sin datos", res)) -> Sin datos | E59: BA
B60: 4- Cert. de No inundabilidad | C60: =LET(res, IFERROR(VLOOKUP($D$3,'Base TOTAL'!A:DA,54,0),""), IF(res="", "Sin datos", res)) -> Sin datos | E60: |
B61: 5- Fact. Agua Potable | C61: =LET(res, IFERROR(VLOOKUP($D$3,'Base TOTAL'!A:DA,55,0),""), IF(res="", "Sin datos", res)) -> Sin datos | E61: BC
B62: 6- Fac. Energìa Elèctrica | C62: =LET(res, IFERROR(VLOOKUP($D$3,'Base TOTAL'!A:DA,56,0),""), IF(res="", "Sin datos", res)) -> Sin datos | E62: BD
B63: 7- Designaciòn Dir. T. Obra | C63: =LET(res, IFERROR(VLOOKUP($D$3,'Base TOTAL'!A:DA,57,0),""), IF(res="", "Sin datos", res)) -> Sin datos | E63: BE
B64: 8- Memoria Téc. descriptiva | C64: =LET(res, IFERROR(VLOOKUP($D$3,'Base TOTAL'!A:DA,58,0),""), IF(res="", "Sin datos", res)) -> Completo OK | E64: BF
B65: 9- Planos Legajo Técnico | C65: =LET(res, IFERROR(VLOOKUP($D$3,'Base TOTAL'!A:DA,59,0),""), IF(res="", "Sin datos", res)) -> Completo OK | E65: BG
B66: 10- Pliego de Especif. Técnicas | C66: =LET(res, IFERROR(VLOOKUP($D$3,'Base TOTAL'!A:DA,60,0),""), IF(res="", "Sin datos", res)) -> Completo OK | E66: BH
B67: 11- Cómputo y Presupuesto | C67: =LET(res, IFERROR(VLOOKUP($D$3,'Base TOTAL'!A:DA,61,0),""), IF(res="", "Sin datos", res)) -> A corregir por M/C | E67: BI
B68: 12- Acta Mediciòn - Cert. | C68: =LET(res, IFERROR(VLOOKUP($D$3,'Base TOTAL'!A:DA,62,0),""), IF(res="", "Sin datos", res)) -> Completo OK | E68: BJ
B69: 13- Curva de Avance | C69: =LET(res, IFERROR(VLOOKUP($D$3,'Base TOTAL'!A:DA,63,0),""), IF(res="", "Sin datos", res)) -> Sin datos | E69: BK
B70: 14- Cronograma de Avance | C70: =LET(res, IFERROR(VLOOKUP($D$3,'Base TOTAL'!A:DA,64,0),""), IF(res="", "Sin datos", res)) -> Sin datos | E70: BL
B71: ESTADO DEL EXPEDIENTE DE LA LOCALIDAD | C71: =LET(res, IFERROR(VLOOKUP($D$3,'Base TOTAL'!A:DA,65,0),""), IF(res="", "Sin datos", res)) -> En CURSO en TÉCNICA | E71: BM
A72: OBSERVACIONES | C72: =LET(res, IFERROR(VLOOKUP($D$3,'Base TOTAL'!A:DA,66,0),""), IF(res="", "Sin datos", res)) -> 04/9/2026: Se envìan por Email las Observaciones A corregir por la comuna. 26/8/2026: Comunicaciòn con la pres. comunal . Se solicita Email para enviar PLA. Observaciones- Se envìa Email . 24/8/26: Se llama a la Pres. Com. Sin respuesta. Se deja mensaje. | E72: BN
B73: OBRA (En Ejecución)
B74: Estado de la obra | C74: fecha | D74: fecha
B75: Anticipo financiero | C75: =LET(res, IFERROR(VLOOKUP($D$3,'Base TOTAL'!A:DA,68,0),""), IF(res="", "Sin datos", res)) -> Sin datos | E75: BP
B76: =$C$14*0.5 -> 100000000
B77: Avance físico 40% | C77: =LET(res, IFERROR(VLOOKUP($D$3,'Base TOTAL'!A:DA,70,0),""), IF(res="", "Sin datos", res)) -> Sin datos | E77: BR
B78: =$C$14*0.25 -> 50000000
B79: Avance físico 70% | C79: =LET(res, IFERROR(VLOOKUP($D$3,'Base TOTAL'!A:DA,72,0),""), IF(res="", "Sin datos", res)) -> Sin datos | E79: BT
B80: =$C$14*0.25 -> 50000000
B81: OBRA (Terminada)
B82: Estado de la obra | C82: fecha
B83: Avance físico 100% | C83: =LET(res, IFERROR(VLOOKUP($D$3,'Base TOTAL'!A:DA,74,0),""), IF(res="", "Sin datos", res)) -> Sin datos | E83: BV
B84: $0,00
A85: OBSERVACIONES | C85: =LET(res, IFERROR(VLOOKUP($D$3,'Base TOTAL'!A:DA,75,0),""), IF(res="", "Sin datos", res)) -> Sin datos | E85: BW
A86: PROGRAMA MI LUGAR
A87: CONVENIO | B87: MONTO | C87: =LET(res, IFERROR(VLOOKUP($D$3,'Base TOTAL'!A:DA,77,0),""), IF(res="", "Sin datos", res)) -> Sin datos | E87: BY
B88: Cantidad de Lotes | C88: =LET(res, IFERROR(VLOOKUP($D$3,'Base TOTAL'!A:DA,78,0),""), IF(res="", "Sin datos", res)) -> Sin datos | E88: BZ
B89: Nº Expediente | C89: =LET(res, IFERROR(VLOOKUP($D$3,'Base TOTAL'!A:DA,79,0),""), IF(res="", "Sin datos", res)) -> Sin datos | E89: CA
A90: DOCUMENTACIÓN A PRESENTAR por Municipio / Comuna | B90: ='Base TOTAL'!CB2 -> 1- Planimetría General | C90: =LET(res, IFERROR(VLOOKUP($D$3,'Base TOTAL'!A:DA,80,0),""), IF(res="", "Sin datos", res)) -> Sin datos | E90: CB
B91: ='Base TOTAL'!CC2 -> 2- Plano de Altimetría | C91: =LET(res, IFERROR(VLOOKUP($D$3,'Base TOTAL'!A:DA,81,0),""), IF(res="", "Sin datos", res)) -> Sin datos | E91: CC
B92: ='Base TOTAL'!CD2 -> 3- Plancheta Catastral | C92: =LET(res, IFERROR(VLOOKUP($D$3,'Base TOTAL'!A:DA,82,0),""), IF(res="", "Sin datos", res)) -> Sin datos | E92: CD
B93: ='Base TOTAL'!CE2 -> 4-Títulos | C93: =LET(res, IFERROR(VLOOKUP($D$3,'Base TOTAL'!A:DA,83,0),""), IF(res="", "Sin datos", res)) -> Sin datos | E93: CE
B94: ='Base TOTAL'!CF2 -> 5- Certificado de No Inundabilidad | C94: =LET(res, IFERROR(VLOOKUP($D$3,'Base TOTAL'!A:DA,84,0),""), IF(res="", "Sin datos", res)) -> Sin datos | E94: CF
B95: ='Base TOTAL'!CG2 -> 6- Informe de Ministerio de Ambiente y Economía Circular | C95: =LET(res, IFERROR(VLOOKUP($D$3,'Base TOTAL'!A:DA,85,0),""), IF(res="", "Sin datos", res)) -> Sin datos | E95: CG
B96: ='Base TOTAL'!CH2 -> 7- Factibilidad de Agua Potable | C96: =LET(res, IFERROR(VLOOKUP($D$3,'Base TOTAL'!A:DA,86,0),""), IF(res="", "Sin datos", res)) -> Sin datos | E96: CH
B97: ='Base TOTAL'!CI2 -> 8- Factibilidad de Energía Eléctrica | C97: =LET(res, IFERROR(VLOOKUP($D$3,'Base TOTAL'!A:DA,87,0),""), IF(res="", "Sin datos", res)) -> Sin datos | E97: CI
B98: ='Base TOTAL'!CJ2 -> 9- Certificado de Prestación de Servicios | C98: =LET(res, IFERROR(VLOOKUP($D$3,'Base TOTAL'!A:DA,88,0),""), IF(res="", "Sin datos", res)) -> Sin datos | E98: CJ
B99: ='Base TOTAL'!CK2 -> 10- Factibilidad de Red Cloacal / Poszo Absorbente | C99: =LET(res, IFERROR(VLOOKUP($D$3,'Base TOTAL'!A:DA,89,0),""), IF(res="", "Sin datos", res)) -> Sin datos | E99: CK
B100: ='Base TOTAL'!CL2 -> 11- Designación de Representante Técnico | C100: =LET(res, IFERROR(VLOOKUP($D$3,'Base TOTAL'!A:DA,90,0),""), IF(res="", "Sin datos", res)) -> Sin datos | E100: CL
...

Sheet IN x Localidad BETINA
A1: Programas provinciales - Dirección General de Vivienda
A2: Ingreso de Datos
C3: LOCALIDAD: | D3: Del Campillo | E3: ⬅️ solamente ELEGIR LOCALIDAD
C4: DEPARTAMENTO: | D4: =IFERROR(VLOOKUP($D$3,'Base TOTAL'!A:AU,2,0), "Sin dato") -> General Roca
C5: Datos actuales | D5: Modificar/Ingresar nuevo dato | E5: Columna ref. BASE TOTAL
B6: MUNICIPIO / COMUNA | C6: =LET(res, IFERROR(VLOOKUP($D$3,'Base TOTAL'!A:DA,5,0),""), IF(res="", "Sin datos", res)) -> M | E6: E
B7: INTENDENTE / PRESIDENTE COMUNAL | C7: =LET(res, IFERROR(VLOOKUP($D$3,'Base TOTAL'!A:DA,6,0),""), IF(res="", "Sin datos", res)) -> CARLA VILLANOVA | E7: F
B8: N° TELÉFONO M/C | C8: =LET(res, IFERROR(VLOOKUP($D$3,'Base TOTAL'!A:DA,7,0),""), IF(res="", "Sin datos", res)) -> (3583) 40-1420 | E8: G
B9: CORREO ELECTRÓNICO | C9: =LET(res, IFERROR(VLOOKUP($D$3,'Base TOTAL'!A:DA,8,0),""), IF(res="", "Sin datos", res)) -> Carla.villanova480@gmail.com | E9: H
B10: CONTACTO TÉCNICO de M/C | C10: =LET(res, IFERROR(VLOOKUP($D$3,'Base TOTAL'!A:DA,9,0),""), IF(res="", "Sin datos", res)) -> Carlota.Bertorello@gmail.com | E10: I
A11: PROGRAMA PROVINCIAL DE CORDÓN CUNETA Y ADOQUINES - LEY Nº 11089
B12: EXPEDIENTE N° | C12: =LET(res, IFERROR(VLOOKUP($D$3,'Base TOTAL'!A:DA,3,0),""), IF(res="", "Sin datos", res)) -> 0423-079098/2026 | E12: C
B13: N° Orden | C13: =LET(res, IFERROR(VLOOKUP($D$3,'Base TOTAL'!A:DA,4,0),""), IF(res="", "Sin datos", res)) -> 3 | E13: D
A14: CONVENIO | B14: MONTO CONVENIO | C14: =LET(res, IFERROR(VLOOKUP($D$3,'Base TOTAL'!A:DA,10,0),""), IF(res="", "Sin datos", res)) -> 200000000 | E14: J
B15: Cordón Cuneta (ml) | C15: =LET(res, IFERROR(VLOOKUP($D$3,'Base TOTAL'!A:DA,11,0),""), IF(res="", "Sin datos", res)) -> Sin datos | E15: K
B16: Adoquinado (m2) | C16: =LET(res, IFERROR(VLOOKUP($D$3,'Base TOTAL'!A:DA,12,0),""), IF(res="", "Sin datos", res)) -> 7440 | E16: L
A17: DOCUMENTACIÓN A PRESENTAR por Municipio / Comuna | B17: 1 | C17: =LET(res, IFERROR(VLOOKUP($D$3,'Base TOTAL'!A:DA,13,0),""), IF(res="", "Sin datos", res)) -> Completo OK | E17: M
B18: 2 | C18: =LET(res, IFERROR(VLOOKUP($D$3,'Base TOTAL'!A:DA,14,0),""), IF(res="", "Sin datos", res)) -> Completo OK | E18: N
B19: 3 | C19: =LET(res, IFERROR(VLOOKUP($D$3,'Base TOTAL'!A:DA,15,0),""), IF(res="", "Sin datos", res)) -> Completo OK | E19: O
B20: 4 | C20: =LET(res, IFERROR(VLOOKUP($D$3,'Base TOTAL'!A:DA,16,0),""), IF(res="", "Sin datos", res)) -> Completo OK | E20: P
B21: Descripción General | C21: =LET(res, IFERROR(VLOOKUP($D$3,'Base TOTAL'!A:DA,17,0),""), IF(res="", "Sin datos", res)) -> Completo OK | E21: Q
B22: Memoria Técnica | C22: =LET(res, IFERROR(VLOOKUP($D$3,'Base TOTAL'!A:DA,18,0),""), IF(res="", "Sin datos", res)) -> Completo OK | E22: R
B23: Plazo de Ejecución | C23: =LET(res, IFERROR(VLOOKUP($D$3,'Base TOTAL'!A:DA,19,0),""), IF(res="", "Sin datos", res)) -> Completo OK | E23: S
B24: Cómputo y Presupuesto | C24: =LET(res, IFERROR(VLOOKUP($D$3,'Base TOTAL'!A:DA,20,0),""), IF(res="", "Sin datos", res)) -> Completo OK | E24: T
B25: Cronograma Avance Obra | C25: =LET(res, IFERROR(VLOOKUP($D$3,'Base TOTAL'!A:DA,21,0),""), IF(res="", "Sin datos", res)) -> Completo OK | E25: U
B26: Planimetría | C26: =LET(res, IFERROR(VLOOKUP($D$3,'Base TOTAL'!A:DA,22,0),""), IF(res="", "Sin datos", res)) -> Completo OK | E26: V
B27: Perfil Calzada | C27: =LET(res, IFERROR(VLOOKUP($D$3,'Base TOTAL'!A:DA,23,0),""), IF(res="", "Sin datos", res)) -> Completo OK | E27: W
B28: Detalle de Cordón Cuneta | C28: =LET(res, IFERROR(VLOOKUP($D$3,'Base TOTAL'!A:DA,24,0),""), IF(res="", "Sin datos", res)) -> A ESPERA de DOC.TÉCNICA | E28: X
B29: Detalle de Badén | C29: =LET(res, IFERROR(VLOOKUP($D$3,'Base TOTAL'!A:DA,25,0),""), IF(res="", "Sin datos", res)) -> A ESPERA de DOC.TÉCNICA | E29: Y
B30: Paquete estr. Calzada | C30: =LET(res, IFERROR(VLOOKUP($D$3,'Base TOTAL'!A:DA,26,0),""), IF(res="", "Sin datos", res)) -> Completo OK | E30: Z
B31: 5 | C31: =LET(res, IFERROR(VLOOKUP($D$3,'Base TOTAL'!A:DA,27,0),""), IF(res="", "Sin datos", res)) -> Completo OK | E31: AA
B32: 6 | C32: =LET(res, IFERROR(VLOOKUP($D$3,'Base TOTAL'!A:DA,28,0),""), IF(res="", "Sin datos", res)) -> Completo OK | E32: AB
B33: 7 | C33: =LET(res, IFERROR(VLOOKUP($D$3,'Base TOTAL'!A:DA,29,0),""), IF(res="", "Sin datos", res)) -> Completo OK | E33: AC
B34: 8 | C34: =LET(res, IFERROR(VLOOKUP($D$3,'Base TOTAL'!A:DA,30,0),""), IF(res="", "Sin datos", res)) -> Completo OK | E34: AD
B35: 9 | C35: =LET(res, IFERROR(VLOOKUP($D$3,'Base TOTAL'!A:DA,31,0),""), IF(res="", "Sin datos", res)) -> Completo OK | E35: AE
B36: ESTADO DEL EXPEDIENTE DE LA LOCALIDAD | C36: =LET(res, IFERROR(VLOOKUP($D$3,'Base TOTAL'!A:DA,32,0),""), IF(res="", "Sin datos", res)) -> COMPLETO en TÉCNICA | E36: AF
A37: OBSERVACIONES | C37: =LET(res, IFERROR(VLOOKUP($D$3,'Base TOTAL'!A:DA,33,0),""), IF(res="", "Sin datos", res)) -> 20/8/2026: PASA A LEGALES para prosecuciòn del tràmite. 11/8/2026: Se recibe doc. completa, avisa juridica que la doc. esta completa. Se envian al Email del prof. + intend. + infra. de las correcc. s/ la doc. presentada ayer 10/8/2026: Respuesta de arq: "Ya tengo todo hecho! Me falta armar los 3 pdf y pasarlosEstuve con mi bebé en Cba en el médico hasta ayer.. asique en lo que queda de la tarde no durante y el finde paso todo por mail" 30/7/2026: Se solicita a la arq. informe si pudieron avanzar con la documentaciòn. Respuesta: " estoy en Cba en el médico Asique hasta la semana que viene no voy a tener corregida la documentación /// Lunes o martes ya seguro que estoy pasando todo" 24/7/2026: Se envìa por Email las Observaciones A corregir por el municipio. 23/7/2026: La arq. envìa doc. tècnica en borrador para su evaluaciòn. 16/7/2026: Comunicaciòn con la arq. (Estuvo demorada por Maternidad) y dice que està preparando la documentaciòn para presentar. - 22-06-2026 : Comunicaciòn con int. Se espera doc. tècnica y listo para dar continuidad al tràmite. - 19-06-2026 Se solicitan a la intend. Carla los siguientes: (Faltan en Planimetria Gral. las Geo ref. sobre las diferentes ubic. de obra + ampliar sobre la misma los nombres de las calles no se visualizan + corte paquete estr. de la calzada + detalles de baden s/ modelo) - 18-06-2026 Se envian al whats de intendenta y al mail los faltantes, correcciones y Modelo --RTAS.; Se recibe toda la doc. 4/6/2026 CB - VVVVVV 4/6/2026 HS - la documentacion tecnica tiene observaciones en el computo. esperaremos la vuelta desde jurídico. COMPLETÓ documentación. Subió a Jurídico Con V°B°. ARCHIVADO EL 13/05/26 EL 14/04/26 SE CONTACTÓ A LA INTENDENTE, LA CUAL ENVIÓ POSTERIORMENTE DOCUMENTACIÓN. SE SOLICITÓ EL COMPLETAMIENTO DE ITEM 4. COMPLETÓ PASADO CON V°B° TÉCNICA | E37: AG
A38: EXPEDIENTE RADICADO EN: | B38: FECHA | C38: =LET(res, IFERROR(VLOOKUP($D$3,'Base TOTAL'!A:DA,34,0),""), IF(res="", "Sin datos", res)) -> 46227 | E38: AH
B39: REPARTICIÓN | C39: =LET(res, IFERROR(VLOOKUP($D$3,'Base TOTAL'!A:DA,35,0),""), IF(res="", "Sin datos", res)) -> AREA COORDINACION ADMINISTRATIVA | E39: AI
B40: OBRA (En Ejecución)
B41: Estado de la obra | C41: fecha
B42: Anticipo financiero | C42: =LET(res, IFERROR(VLOOKUP($D$3,'Base TOTAL'!A:DA,39,0),""), IF(res="", "Sin datos", res)) -> Sin datos | E42: AM
B43: =LET(res, IFERROR(VLOOKUP($D$3,'Base TOTAL'!A:DA,38,0),""), IF(res="", "Sin datos", res)) -> 100000000
B44: Avance físico 40% | C44: =LET(res, IFERROR(VLOOKUP($D$3,'Base TOTAL'!A:DA,41,0),""), IF(res="", "Sin datos", res)) -> Sin datos | E44: AO
B45: =LET(res, IFERROR(VLOOKUP($D$3,'Base TOTAL'!A:DA,40,0),""), IF(res="", "Sin datos", res)) -> 50000000
B46: Avance físico 70% | C46: =LET(res, IFERROR(VLOOKUP($D$3,'Base TOTAL'!A:DA,43,0),""), IF(res="", "Sin datos", res)) -> Sin datos | E46: AQ
B47: =LET(res, IFERROR(VLOOKUP($D$3,'Base TOTAL'!A:DA,42,0),""), IF(res="", "Sin datos", res)) -> 50000000
B48: OBRA (Terminada)
B49: Estado de la obra | C49: fecha
B50: Avance físico 100% | C50: =LET(res, IFERROR(VLOOKUP($D$3,'Base TOTAL'!A:DA,45,0),""), IF(res="", "Sin datos", res)) -> Sin datos | E50: AS
B51: $0,00
A52: OBSERVACIONES | C52: =LET(res, IFERROR(VLOOKUP($D$3,'Base TOTAL'!A:DA,46,0),""), IF(res="", "Sin datos", res)) -> Sin datos | E52: AT
A53: PROGRAMA CÓRDOBA HOGAR - LEY Nº 8663
A54: CONVENIO | B54: MONTO CONVENIO | C54: =LET(res, IFERROR(VLOOKUP($D$3,'Base TOTAL'!A:DA,48,0),""), IF(res="", "Sin datos", res)) -> Sin datos | E54: AV
B55: Cantidad de Viviendas | C55: =LET(res, IFERROR(VLOOKUP($D$3,'Base TOTAL'!A:DA,49,0),""), IF(res="", "Sin datos", res)) -> Sin datos | E55: AW
B56: Nº Expediente | C56: =LET(res, IFERROR(VLOOKUP($D$3,'Base TOTAL'!A:DA,50,0),""), IF(res="", "Sin datos", res)) -> Sin datos | E56: AX
A57: DOCUMENTACIÓN A PRESENTAR por Municipio / Comuna | B57: 1- Planimetría (Ubic. Obra) | C57: =LET(res, IFERROR(VLOOKUP($D$3,'Base TOTAL'!A:DA,51,0),""), IF(res="", "Sin datos", res)) -> Sin datos | E57: AY
B58: 2- Matrìcula de cada lote | C58: =LET(res, IFERROR(VLOOKUP($D$3,'Base TOTAL'!A:DA,52,0),""), IF(res="", "Sin datos", res)) -> Sin datos | E58: AZ
B59: 3- Estudio de Suelo | C59: =LET(res, IFERROR(VLOOKUP($D$3,'Base TOTAL'!A:DA,53,0),""), IF(res="", "Sin datos", res)) -> Sin datos | E59: BA
B60: 4- Cert. de No inundabilidad | C60: =LET(res, IFERROR(VLOOKUP($D$3,'Base TOTAL'!A:DA,54,0),""), IF(res="", "Sin datos", res)) -> Sin datos | E60: |
B61: 5- Fact. Agua Potable | C61: =LET(res, IFERROR(VLOOKUP($D$3,'Base TOTAL'!A:DA,55,0),""), IF(res="", "Sin datos", res)) -> Sin datos | E61: BC
B62: 6- Fac. Energìa Elèctrica | C62: =LET(res, IFERROR(VLOOKUP($D$3,'Base TOTAL'!A:DA,56,0),""), IF(res="", "Sin datos", res)) -> Sin datos | E62: BD
B63: 7- Designaciòn Dir. T. Obra | C63: =LET(res, IFERROR(VLOOKUP($D$3,'Base TOTAL'!A:DA,57,0),""), IF(res="", "Sin datos", res)) -> Sin datos | E63: BE
B64: 8- Memoria Téc. descriptiva | C64: =LET(res, IFERROR(VLOOKUP($D$3,'Base TOTAL'!A:DA,58,0),""), IF(res="", "Sin datos", res)) -> Sin datos | E64: BF
B65: 9- Planos Legajo Técnico | C65: =LET(res, IFERROR(VLOOKUP($D$3,'Base TOTAL'!A:DA,59,0),""), IF(res="", "Sin datos", res)) -> Sin datos | E65: BG
B66: 10- Pliego de Especif. Técnicas | C66: =LET(res, IFERROR(VLOOKUP($D$3,'Base TOTAL'!A:DA,60,0),""), IF(res="", "Sin datos", res)) -> Sin datos | E66: BH
B67: 11- Cómputo y Presupuesto | C67: =LET(res, IFERROR(VLOOKUP($D$3,'Base TOTAL'!A:DA,61,0),""), IF(res="", "Sin datos", res)) -> Sin datos | E67: BI
B68: 12- Acta Mediciòn - Cert. | C68: =LET(res, IFERROR(VLOOKUP($D$3,'Base TOTAL'!A:DA,62,0),""), IF(res="", "Sin datos", res)) -> Sin datos | E68: BJ
B69: 13- Curva de Avance | C69: =LET(res, IFERROR(VLOOKUP($D$3,'Base TOTAL'!A:DA,63,0),""), IF(res="", "Sin datos", res)) -> Sin datos | E69: BK
B70: 14- Cronograma de Avance | C70: =LET(res, IFERROR(VLOOKUP($D$3,'Base TOTAL'!A:DA,64,0),""), IF(res="", "Sin datos", res)) -> Sin datos | E70: BL
B71: ESTADO DEL EXPEDIENTE DE LA LOCALIDAD | C71: =LET(res, IFERROR(VLOOKUP($D$3,'Base TOTAL'!A:DA,65,0),""), IF(res="", "Sin datos", res)) -> Sin datos | E71: BM
A72: OBSERVACIONES | C72: =LET(res, IFERROR(VLOOKUP($D$3,'Base TOTAL'!A:DA,66,0),""), IF(res="", "Sin datos", res)) -> Sin datos | E72: BN
B73: OBRA (En Ejecución)
B74: Estado de la obra | C74: fecha | D74: fecha
B75: Anticipo financiero | C75: =LET(res, IFERROR(VLOOKUP($D$3,'Base TOTAL'!A:DA,68,0),""), IF(res="", "Sin datos", res)) -> Sin datos | E75: BP
B76: =$C$14*0.5 -> 100000000
B77: Avance físico 40% | C77: =LET(res, IFERROR(VLOOKUP($D$3,'Base TOTAL'!A:DA,70,0),""), IF(res="", "Sin datos", res)) -> Sin datos | E77: BR
B78: =$C$14*0.25 -> 50000000
B79: Avance físico 70% | C79: =LET(res, IFERROR(VLOOKUP($D$3,'Base TOTAL'!A:DA,72,0),""), IF(res="", "Sin datos", res)) -> Sin datos | E79: BT
B80: =$C$14*0.25 -> 50000000
B81: OBRA (Terminada)
B82: Estado de la obra | C82: fecha
B83: Avance físico 100% | C83: =LET(res, IFERROR(VLOOKUP($D$3,'Base TOTAL'!A:DA,74,0),""), IF(res="", "Sin datos", res)) -> Sin datos | E83: BV
B84: $0,00
A85: OBSERVACIONES | C85: =LET(res, IFERROR(VLOOKUP($D$3,'Base TOTAL'!A:DA,75,0),""), IF(res="", "Sin datos", res)) -> Sin datos | E85: BW
A86: PROGRAMA MI LUGAR
A87: CONVENIO | B87: MONTO | C87: =LET(res, IFERROR(VLOOKUP($D$3,'Base TOTAL'!A:DA,77,0),""), IF(res="", "Sin datos", res)) -> Sin datos | E87: BY
B88: Cantidad de Lotes | C88: =LET(res, IFERROR(VLOOKUP($D$3,'Base TOTAL'!A:DA,78,0),""), IF(res="", "Sin datos", res)) -> Sin datos | E88: BZ
B89: Nº Expediente | C89: =LET(res, IFERROR(VLOOKUP($D$3,'Base TOTAL'!A:DA,79,0),""), IF(res="", "Sin datos", res)) -> Sin datos | E89: CA
A90: DOCUMENTACIÓN A PRESENTAR por Municipio / Comuna | B90: ='Base TOTAL'!CB2 -> 1- Planimetría General | C90: =LET(res, IFERROR(VLOOKUP($D$3,'Base TOTAL'!A:DA,80,0),""), IF(res="", "Sin datos", res)) -> Sin datos | E90: CB
B91: ='Base TOTAL'!CC2 -> 2- Plano de Altimetría | C91: =LET(res, IFERROR(VLOOKUP($D$3,'Base TOTAL'!A:DA,81,0),""), IF(res="", "Sin datos", res)) -> Sin datos | E91: CC
B92: ='Base TOTAL'!CD2 -> 3- Plancheta Catastral | C92: =LET(res, IFERROR(VLOOKUP($D$3,'Base TOTAL'!A:DA,82,0),""), IF(res="", "Sin datos", res)) -> Sin datos | E92: CD
B93: ='Base TOTAL'!CE2 -> 4-Títulos | C93: =LET(res, IFERROR(VLOOKUP($D$3,'Base TOTAL'!A:DA,83,0),""), IF(res="", "Sin datos", res)) -> Sin datos | E93: CE
B94: ='Base TOTAL'!CF2 -> 5- Certificado de No Inundabilidad | C94: =LET(res, IFERROR(VLOOKUP($D$3,'Base TOTAL'!A:DA,84,0),""), IF(res="", "Sin datos", res)) -> Sin datos | E94: CF
B95: ='Base TOTAL'!CG2 -> 6- Informe de Ministerio de Ambiente y Economía Circular | C95: =LET(res, IFERROR(VLOOKUP($D$3,'Base TOTAL'!A:DA,85,0),""), IF(res="", "Sin datos", res)) -> Sin datos | E95: CG
B96: ='Base TOTAL'!CH2 -> 7- Factibilidad de Agua Potable | C96: =LET(res, IFERROR(VLOOKUP($D$3,'Base TOTAL'!A:DA,86,0),""), IF(res="", "Sin datos", res)) -> Sin datos | E96: CH
B97: ='Base TOTAL'!CI2 -> 8- Factibilidad de Energía Eléctrica | C97: =LET(res, IFERROR(VLOOKUP($D$3,'Base TOTAL'!A:DA,87,0),""), IF(res="", "Sin datos", res)) -> Sin datos | E97: CI
B98: ='Base TOTAL'!CJ2 -> 9- Certificado de Prestación de Servicios | C98: =LET(res, IFERROR(VLOOKUP($D$3,'Base TOTAL'!A:DA,88,0),""), IF(res="", "Sin datos", res)) -> Sin datos | E98: CJ
B99: ='Base TOTAL'!CK2 -> 10- Factibilidad de Red Cloacal / Poszo Absorbente | C99: =LET(res, IFERROR(VLOOKUP($D$3,'Base TOTAL'!A:DA,89,0),""), IF(res="", "Sin datos", res)) -> Sin datos | E99: CK
B100: ='Base TOTAL'!CL2 -> 11- Designación de Representante Técnico | C100: =LET(res, IFERROR(VLOOKUP($D$3,'Base TOTAL'!A:DA,90,0),""), IF(res="", "Sin datos", res)) -> Sin datos | E100: CL
...

Sheet IN x Localidad GREGORAT
A1: Programas provinciales - Dirección General de Vivienda
A2: Ingreso de Datos
C3: LOCALIDAD: | D3: San Joaquín | E3: ⬅️ solamente ELEGIR LOCALIDAD
C4: DEPARTAMENTO: | D4: =IFERROR(VLOOKUP($D$3,'Base TOTAL'!A:AU,2,0), "Sin dato") -> Presidente Roque Sáenz Peña
C5: Datos actuales | D5: Modificar/Ingresar nuevo dato | E5: Columna ref. BASE TOTAL
B6: MUNICIPIO / COMUNA | C6: =LET(res, IFERROR(VLOOKUP($D$3,'Base TOTAL'!A:DA,5,0),""), IF(res="", "Sin datos", res)) -> C | E6: E
B7: INTENDENTE / PRESIDENTE COMUNAL | C7: =LET(res, IFERROR(VLOOKUP($D$3,'Base TOTAL'!A:DA,6,0),""), IF(res="", "Sin datos", res)) -> DANIEL PICCO | E7: F
B8: N° TELÉFONO M/C | C8: =LET(res, IFERROR(VLOOKUP($D$3,'Base TOTAL'!A:DA,7,0),""), IF(res="", "Sin datos", res)) -> (3385) 43-5407 | E8: G
B9: CORREO ELECTRÓNICO | C9: =LET(res, IFERROR(VLOOKUP($D$3,'Base TOTAL'!A:DA,8,0),""), IF(res="", "Sin datos", res)) -> Danielpicco66@hotmail.com | E9: H
B10: CONTACTO TÉCNICO de M/C | C10: =LET(res, IFERROR(VLOOKUP($D$3,'Base TOTAL'!A:DA,9,0),""), IF(res="", "Sin datos", res)) -> mafer76_4@hotmail.com | E10: I
A11: PROGRAMA PROVINCIAL DE CORDÓN CUNETA Y ADOQUINES - LEY Nº 11089
B12: EXPEDIENTE N° | C12: =LET(res, IFERROR(VLOOKUP($D$3,'Base TOTAL'!A:DA,3,0),""), IF(res="", "Sin datos", res)) -> 043-079116/2026 | E12: C
B13: N° Orden | C13: =LET(res, IFERROR(VLOOKUP($D$3,'Base TOTAL'!A:DA,4,0),""), IF(res="", "Sin datos", res)) -> 1 | E13: D
A14: CONVENIO | B14: MONTO CONVENIO | C14: =LET(res, IFERROR(VLOOKUP($D$3,'Base TOTAL'!A:DA,10,0),""), IF(res="", "Sin datos", res)) -> 30000000 | E14: J
B15: Cordón Cuneta (ml) | C15: =LET(res, IFERROR(VLOOKUP($D$3,'Base TOTAL'!A:DA,11,0),""), IF(res="", "Sin datos", res)) -> 206 | E15: K
B16: Adoquinado (m2) | C16: =LET(res, IFERROR(VLOOKUP($D$3,'Base TOTAL'!A:DA,12,0),""), IF(res="", "Sin datos", res)) -> Sin datos | E16: L
A17: DOCUMENTACIÓN A PRESENTAR por Municipio / Comuna | B17: 1 | C17: =LET(res, IFERROR(VLOOKUP($D$3,'Base TOTAL'!A:DA,13,0),""), IF(res="", "Sin datos", res)) -> Completo OK | E17: M
B18: 2 | C18: =LET(res, IFERROR(VLOOKUP($D$3,'Base TOTAL'!A:DA,14,0),""), IF(res="", "Sin datos", res)) -> Completo OK | E18: N
B19: 3 | C19: =LET(res, IFERROR(VLOOKUP($D$3,'Base TOTAL'!A:DA,15,0),""), IF(res="", "Sin datos", res)) -> Completo OK | E19: O
B20: 4 | C20: =LET(res, IFERROR(VLOOKUP($D$3,'Base TOTAL'!A:DA,16,0),""), IF(res="", "Sin datos", res)) -> Completo OK | E20: P
B21: Descripción General | C21: =LET(res, IFERROR(VLOOKUP($D$3,'Base TOTAL'!A:DA,17,0),""), IF(res="", "Sin datos", res)) -> Completo OK | E21: Q
B22: Memoria Técnica | C22: =LET(res, IFERROR(VLOOKUP($D$3,'Base TOTAL'!A:DA,18,0),""), IF(res="", "Sin datos", res)) -> Completo OK | E22: R
B23: Plazo de Ejecución | C23: =LET(res, IFERROR(VLOOKUP($D$3,'Base TOTAL'!A:DA,19,0),""), IF(res="", "Sin datos", res)) -> Completo OK | E23: S
B24: Cómputo y Presupuesto | C24: =LET(res, IFERROR(VLOOKUP($D$3,'Base TOTAL'!A:DA,20,0),""), IF(res="", "Sin datos", res)) -> Completo OK | E24: T
B25: Cronograma Avance Obra | C25: =LET(res, IFERROR(VLOOKUP($D$3,'Base TOTAL'!A:DA,21,0),""), IF(res="", "Sin datos", res)) -> Completo OK | E25: U
B26: Planimetría | C26: =LET(res, IFERROR(VLOOKUP($D$3,'Base TOTAL'!A:DA,22,0),""), IF(res="", "Sin datos", res)) -> Completo OK | E26: V
B27: Perfil Calzada | C27: =LET(res, IFERROR(VLOOKUP($D$3,'Base TOTAL'!A:DA,23,0),""), IF(res="", "Sin datos", res)) -> Completo OK | E27: W
B28: Detalle de Cordón Cuneta | C28: =LET(res, IFERROR(VLOOKUP($D$3,'Base TOTAL'!A:DA,24,0),""), IF(res="", "Sin datos", res)) -> Completo OK | E28: X
B29: Detalle de Badén | C29: =LET(res, IFERROR(VLOOKUP($D$3,'Base TOTAL'!A:DA,25,0),""), IF(res="", "Sin datos", res)) -> Completo OK | E29: Y
B30: Paquete estr. Calzada | C30: =LET(res, IFERROR(VLOOKUP($D$3,'Base TOTAL'!A:DA,26,0),""), IF(res="", "Sin datos", res)) -> Completo OK | E30: Z
B31: 5 | C31: =LET(res, IFERROR(VLOOKUP($D$3,'Base TOTAL'!A:DA,27,0),""), IF(res="", "Sin datos", res)) -> Completo OK | E31: AA
B32: 6 | C32: =LET(res, IFERROR(VLOOKUP($D$3,'Base TOTAL'!A:DA,28,0),""), IF(res="", "Sin datos", res)) -> Completo OK | E32: AB
B33: 7 | C33: =LET(res, IFERROR(VLOOKUP($D$3,'Base TOTAL'!A:DA,29,0),""), IF(res="", "Sin datos", res)) -> Completo OK | E33: AC
B34: 8 | C34: =LET(res, IFERROR(VLOOKUP($D$3,'Base TOTAL'!A:DA,30,0),""), IF(res="", "Sin datos", res)) -> Completo OK | E34: AD
B35: 9 | C35: =LET(res, IFERROR(VLOOKUP($D$3,'Base TOTAL'!A:DA,31,0),""), IF(res="", "Sin datos", res)) -> DIR. JUR. LEGAL Y NOTARIAL | E35: AE
B36: ESTADO DEL EXPEDIENTE DE LA LOCALIDAD | C36: =LET(res, IFERROR(VLOOKUP($D$3,'Base TOTAL'!A:DA,32,0),""), IF(res="", "Sin datos", res)) -> En CURSO en TÉCNICA | E36: AF
A37: OBSERVACIONES | C37: =LET(res, IFERROR(VLOOKUP($D$3,'Base TOTAL'!A:DA,33,0),""), IF(res="", "Sin datos", res)) -> 28/8/2026: Se reciben actualizac. 21/8/2026: Se re-envian por whatss las Observac. a correg a la nva profes. 21/08/2026: Se reciben actualiz. x el Presid. Comunal x whatss del A.Legal y se confecciona la planilla de Observ. para anexar cuando la nva prof. envie actualiz. Tecnicas. 20/8/2026: Se envìa mensaje al Int. preguntando si pudieron corregir las Observaciones para presentar la documentaciòn. 29/7/2026: Se envìa Planilla de Observ. a corregir por la comuna , al nvo profesional y a Infraestr. 28/7/2026: El municipio cambiò de profesional. Se le envìa el instructivo a la nueva arq. 22/7/2026: Se envìa nuevamente al Email las observaciones A corregir por la comuna 22/7/2026: El 14/7/2026 presentan documentaciòn a corregir nuevamente. 25/6/26: Comunicación con int. solicitando presenten correcciones. Se espera respuesta de la ing. a cargo. 19/6/26: Comunicaciòn con la ing. a cargo . Se solcita la presentaciòn a la mayor brevedad posible . 12-06-2026 Solicitar P Georef en Planim. + demas doc.Tec y leg 11/6/26: Se solicita nuevamente la correcciòn de Documentaciòn tècnica.Tiene todos los Items completos, salvo por el 4 (documentación técnica). El 29/5/26 se reclama la documentación firmada EL 19/05/26 PRESENTA PROYECTO CORREGIDO (A EVALUAR). EL 30/4 PRESENTAN NUEVO PRESUPUESTO, A VALOR $30.000.000. DEBE FUNDAMENTAR EL INCREMENTO EN EL MONTO TOTAL EL CÓMPUTO. El 30/04 se recibe y el monto que presenta es menor que el que se le da. Se pide que lo haga llegar al monto asignado El 28/04/26 se le envía documentación técnica modelo. EL 20/04/2026 LA COMUNA ENVÍA DOCUMENTACIÓN. FALTA INFO TÉCNICA. PRESENTA PRESUPUESTO, DE $21.969.370 - FALTA FIRMAS DE ÉSTE. EL 14/04/26 SE CONTACTÓ AL PRESIDENTE COMUNAL - | E37: AG
A38: EXPEDIENTE RADICADO EN: | B38: FECHA | C38: =LET(res, IFERROR(VLOOKUP($D$3,'Base TOTAL'!A:DA,34,0),""), IF(res="", "Sin datos", res)) -> 46199 | E38: AH
B39: REPARTICIÓN | C39: =LET(res, IFERROR(VLOOKUP($D$3,'Base TOTAL'!A:DA,35,0),""), IF(res="", "Sin datos", res)) -> DIRECCION DE JURISDICCION ECONOMICO, FINANCIERA Y DE ADMINISTRACION | E39: AI
B40: OBRA (En Ejecución)
B41: Estado de la obra | C41: fecha
B42: Anticipo financiero | C42: =LET(res, IFERROR(VLOOKUP($D$3,'Base TOTAL'!A:DA,39,0),""), IF(res="", "Sin datos", res)) -> Sin datos | E42: AM
B43: =LET(res, IFERROR(VLOOKUP($D$3,'Base TOTAL'!A:DA,38,0),""), IF(res="", "Sin datos", res)) -> 15000000
B44: Avance físico 40% | C44: =LET(res, IFERROR(VLOOKUP($D$3,'Base TOTAL'!A:DA,41,0),""), IF(res="", "Sin datos", res)) -> Sin datos | E44: AO
B45: =LET(res, IFERROR(VLOOKUP($D$3,'Base TOTAL'!A:DA,40,0),""), IF(res="", "Sin datos", res)) -> 7500000
B46: Avance físico 70% | C46: =LET(res, IFERROR(VLOOKUP($D$3,'Base TOTAL'!A:DA,43,0),""), IF(res="", "Sin datos", res)) -> Sin datos | E46: AQ
B47: =LET(res, IFERROR(VLOOKUP($D$3,'Base TOTAL'!A:DA,42,0),""), IF(res="", "Sin datos", res)) -> 7500000
B48: OBRA (Terminada)
B49: Estado de la obra | C49: fecha
B50: Avance físico 100% | C50: =LET(res, IFERROR(VLOOKUP($D$3,'Base TOTAL'!A:DA,45,0),""), IF(res="", "Sin datos", res)) -> Sin datos | E50: AS
B51: $0,00
A52: OBSERVACIONES | C52: =LET(res, IFERROR(VLOOKUP($D$3,'Base TOTAL'!A:DA,46,0),""), IF(res="", "Sin datos", res)) -> Sin datos | E52: AT
A53: PROGRAMA CÓRDOBA HOGAR - LEY Nº 8663
A54: CONVENIO | B54: MONTO CONVENIO | C54: =LET(res, IFERROR(VLOOKUP($D$3,'Base TOTAL'!A:DA,48,0),""), IF(res="", "Sin datos", res)) -> Sin datos | E54: AV
B55: Cantidad de Viviendas | C55: =LET(res, IFERROR(VLOOKUP($D$3,'Base TOTAL'!A:DA,49,0),""), IF(res="", "Sin datos", res)) -> Sin datos | E55: AW
B56: Nº Expediente | C56: =LET(res, IFERROR(VLOOKUP($D$3,'Base TOTAL'!A:DA,50,0),""), IF(res="", "Sin datos", res)) -> Sin datos | E56: AX
A57: DOCUMENTACIÓN A PRESENTAR por Municipio / Comuna | B57: 1- Planimetría (Ubic. Obra) | C57: =LET(res, IFERROR(VLOOKUP($D$3,'Base TOTAL'!A:DA,51,0),""), IF(res="", "Sin datos", res)) -> A ESPERA de DOC.TÉCNICA | E57: AY
B58: 2- Matrìcula de cada lote | C58: =LET(res, IFERROR(VLOOKUP($D$3,'Base TOTAL'!A:DA,52,0),""), IF(res="", "Sin datos", res)) -> A ESPERA de DOC.TÉCNICA | E58: AZ
B59: 3- Estudio de Suelo | C59: =LET(res, IFERROR(VLOOKUP($D$3,'Base TOTAL'!A:DA,53,0),""), IF(res="", "Sin datos", res)) -> A ESPERA de DOC.TÉCNICA | E59: BA
B60: 4- Cert. de No inundabilidad | C60: =LET(res, IFERROR(VLOOKUP($D$3,'Base TOTAL'!A:DA,54,0),""), IF(res="", "Sin datos", res)) -> A ESPERA de DOC.TÉCNICA | E60: |
B61: 5- Fact. Agua Potable | C61: =LET(res, IFERROR(VLOOKUP($D$3,'Base TOTAL'!A:DA,55,0),""), IF(res="", "Sin datos", res)) -> A ESPERA de DOC.TÉCNICA | E61: BC
B62: 6- Fac. Energìa Elèctrica | C62: =LET(res, IFERROR(VLOOKUP($D$3,'Base TOTAL'!A:DA,56,0),""), IF(res="", "Sin datos", res)) -> A ESPERA de DOC.TÉCNICA | E62: BD
B63: 7- Designaciòn Dir. T. Obra | C63: =LET(res, IFERROR(VLOOKUP($D$3,'Base TOTAL'!A:DA,57,0),""), IF(res="", "Sin datos", res)) -> A ESPERA de DOC.TÉCNICA | E63: BE
B64: 8- Memoria Téc. descriptiva | C64: =LET(res, IFERROR(VLOOKUP($D$3,'Base TOTAL'!A:DA,58,0),""), IF(res="", "Sin datos", res)) -> A ESPERA de DOC.TÉCNICA | E64: BF
B65: 9- Planos Legajo Técnico | C65: =LET(res, IFERROR(VLOOKUP($D$3,'Base TOTAL'!A:DA,59,0),""), IF(res="", "Sin datos", res)) -> A ESPERA de DOC.TÉCNICA | E65: BG
B66: 10- Pliego de Especif. Técnicas | C66: =LET(res, IFERROR(VLOOKUP($D$3,'Base TOTAL'!A:DA,60,0),""), IF(res="", "Sin datos", res)) -> A ESPERA de DOC.TÉCNICA | E66: BH
B67: 11- Cómputo y Presupuesto | C67: =LET(res, IFERROR(VLOOKUP($D$3,'Base TOTAL'!A:DA,61,0),""), IF(res="", "Sin datos", res)) -> A ESPERA de DOC.TÉCNICA | E67: BI
B68: 12- Acta Mediciòn - Cert. | C68: =LET(res, IFERROR(VLOOKUP($D$3,'Base TOTAL'!A:DA,62,0),""), IF(res="", "Sin datos", res)) -> A ESPERA de DOC.TÉCNICA | E68: BJ
B69: 13- Curva de Avance | C69: =LET(res, IFERROR(VLOOKUP($D$3,'Base TOTAL'!A:DA,63,0),""), IF(res="", "Sin datos", res)) -> A ESPERA de DOC.TÉCNICA | E69: BK
B70: 14- Cronograma de Avance | C70: =LET(res, IFERROR(VLOOKUP($D$3,'Base TOTAL'!A:DA,64,0),""), IF(res="", "Sin datos", res)) -> A ESPERA de DOC.TÉCNICA | E70: BL
B71: ESTADO DEL EXPEDIENTE DE LA LOCALIDAD | C71: =LET(res, IFERROR(VLOOKUP($D$3,'Base TOTAL'!A:DA,65,0),""), IF(res="", "Sin datos", res)) -> Sin datos | E71: BM
A72: OBSERVACIONES | C72: =LET(res, IFERROR(VLOOKUP($D$3,'Base TOTAL'!A:DA,66,0),""), IF(res="", "Sin datos", res)) -> Sin datos | E72: BN
B73: OBRA (En Ejecución)
B74: Estado de la obra | C74: fecha | D74: fecha
B75: Anticipo financiero | C75: =LET(res, IFERROR(VLOOKUP($D$3,'Base TOTAL'!A:DA,68,0),""), IF(res="", "Sin datos", res)) -> Sin datos | E75: BP
B76: =$C$14*0.5 -> 15000000
B77: Avance físico 40% | C77: =LET(res, IFERROR(VLOOKUP($D$3,'Base TOTAL'!A:DA,70,0),""), IF(res="", "Sin datos", res)) -> Sin datos | E77: BR
B78: =$C$14*0.25 -> 7500000
B79: Avance físico 70% | C79: =LET(res, IFERROR(VLOOKUP($D$3,'Base TOTAL'!A:DA,72,0),""), IF(res="", "Sin datos", res)) -> Sin datos | E79: BT
B80: =$C$14*0.25 -> 7500000
B81: OBRA (Terminada)
B82: Estado de la obra | C82: fecha
B83: Avance físico 100% | C83: =LET(res, IFERROR(VLOOKUP($D$3,'Base TOTAL'!A:DA,74,0),""), IF(res="", "Sin datos", res)) -> Sin datos | E83: BV
B84: $0,00
A85: OBSERVACIONES | C85: =LET(res, IFERROR(VLOOKUP($D$3,'Base TOTAL'!A:DA,75,0),""), IF(res="", "Sin datos", res)) -> Sin datos | E85: BW
A86: PROGRAMA MI LUGAR
A87: CONVENIO | B87: MONTO | C87: =LET(res, IFERROR(VLOOKUP($D$3,'Base TOTAL'!A:DA,77,0),""), IF(res="", "Sin datos", res)) -> Sin datos | E87: BY
B88: Cantidad de Lotes | C88: =LET(res, IFERROR(VLOOKUP($D$3,'Base TOTAL'!A:DA,78,0),""), IF(res="", "Sin datos", res)) -> Sin datos | E88: BZ
B89: Nº Expediente | C89: =LET(res, IFERROR(VLOOKUP($D$3,'Base TOTAL'!A:DA,79,0),""), IF(res="", "Sin datos", res)) -> Sin datos | E89: CA
A90: DOCUMENTACIÓN A PRESENTAR por Municipio / Comuna | B90: ='Base TOTAL'!CB2 -> 1- Planimetría General | C90: =LET(res, IFERROR(VLOOKUP($D$3,'Base TOTAL'!A:DA,80,0),""), IF(res="", "Sin datos", res)) -> A ESPERA de DOC.TÉCNICA | E90: CB
B91: ='Base TOTAL'!CC2 -> 2- Plano de Altimetría | C91: =LET(res, IFERROR(VLOOKUP($D$3,'Base TOTAL'!A:DA,81,0),""), IF(res="", "Sin datos", res)) -> A ESPERA de DOC.TÉCNICA | E91: CC
B92: ='Base TOTAL'!CD2 -> 3- Plancheta Catastral | C92: =LET(res, IFERROR(VLOOKUP($D$3,'Base TOTAL'!A:DA,82,0),""), IF(res="", "Sin datos", res)) -> A ESPERA de DOC.TÉCNICA | E92: CD
B93: ='Base TOTAL'!CE2 -> 4-Títulos | C93: =LET(res, IFERROR(VLOOKUP($D$3,'Base TOTAL'!A:DA,83,0),""), IF(res="", "Sin datos", res)) -> A ESPERA de DOC.TÉCNICA | E93: CE
B94: ='Base TOTAL'!CF2 -> 5- Certificado de No Inundabilidad | C94: =LET(res, IFERROR(VLOOKUP($D$3,'Base TOTAL'!A:DA,84,0),""), IF(res="", "Sin datos", res)) -> A ESPERA de DOC.TÉCNICA | E94: CF
B95: ='Base TOTAL'!CG2 -> 6- Informe de Ministerio de Ambiente y Economía Circular | C95: =LET(res, IFERROR(VLOOKUP($D$3,'Base TOTAL'!A:DA,85,0),""), IF(res="", "Sin datos", res)) -> A ESPERA de DOC.TÉCNICA | E95: CG
B96: ='Base TOTAL'!CH2 -> 7- Factibilidad de Agua Potable | C96: =LET(res, IFERROR(VLOOKUP($D$3,'Base TOTAL'!A:DA,86,0),""), IF(res="", "Sin datos", res)) -> A ESPERA de DOC.TÉCNICA | E96: CH
B97: ='Base TOTAL'!CI2 -> 8- Factibilidad de Energía Eléctrica | C97: =LET(res, IFERROR(VLOOKUP($D$3,'Base TOTAL'!A:DA,87,0),""), IF(res="", "Sin datos", res)) -> A ESPERA de DOC.TÉCNICA | E97: CI
B98: ='Base TOTAL'!CJ2 -> 9- Certificado de Prestación de Servicios | C98: =LET(res, IFERROR(VLOOKUP($D$3,'Base TOTAL'!A:DA,88,0),""), IF(res="", "Sin datos", res)) -> A ESPERA de DOC.TÉCNICA | E98: CJ
B99: ='Base TOTAL'!CK2 -> 10- Factibilidad de Red Cloacal / Poszo Absorbente | C99: =LET(res, IFERROR(VLOOKUP($D$3,'Base TOTAL'!A:DA,89,0),""), IF(res="", "Sin datos", res)) -> A ESPERA de DOC.TÉCNICA | E99: CK
B100: ='Base TOTAL'!CL2 -> 11- Designación de Representante Técnico | C100: =LET(res, IFERROR(VLOOKUP($D$3,'Base TOTAL'!A:DA,90,0),""), IF(res="", "Sin datos", res)) -> A ESPERA de DOC.TÉCNICA | E100: CL
...

Sheet REP CC estado exp.
A1: OBRA: "EJECUCIÒN DE CORDÒN CUNETA Y ADOQUINADO"
A2: PROGRAMA: "PROVINCIAL DE CORDÒN CUNETA Y ADOQUINES" - LEY Nº 11.089
A3: REPORTE | B3: =TODAY() -> 46269
A4: ='Base TOTAL'!AF2 -> ESTADO DEL EXPEDIENTE DE LA LOCALIDAD | C4: En CURSO en TÉCNICA
C5: =COUNTIF(C7:C400, "<>-") -> 12 | D5: ='Base TOTAL'!AH2 -> EXP en FECHA
A6: Localidad | B6: Departamento | C6: ='Base TOTAL'!AG2 -> OBSERVACIONES | D6: ='Base TOTAL'!AH2 -> EXP en FECHA | E6: ='Base TOTAL'!AI2 -> EXP en REPARTICIÓN
A7: =IFERROR(__xludf.DUMMYFUNCTION("SORT(FILTER('Base TOTAL'!A:A, 'Base TOTAL'!AF:AF = C4))"),"Calchín") -> Calchín | B7: =IFERROR(VLOOKUP($A7,'Base TOTAL'!A:AU,2,0), "-") -> Río Segundo | C7: =IFERROR(VLOOKUP($A7,'Base TOTAL'!A:AU,33,0), "-") -> 31/8/2026: EL INT. RESPONDE que ya tiene todo para firmar y enviarnos. 31/8/2026: Comunicaciòn telefònica con Int. Sin respuesta. Se envìa mensaje por wahtsapp. 14/8/2026: Se envìan Observac. p/ corregir por Email al munic. e infra. RTA.: Ok, ya me fijo para preparar las correcciones enseguida 28/7/2026: Se envìa por Email, las Observaciones a corregir por el municipio. 17/7/2026: Se solicita informen si pudieron avanzar con la documentaciòn. Respuesta: me faltan unos datos técnicos que tiene q mandar el ingeniero y le enviamos todo juntos 19/6/26: El municipio presenta documentación a corregir y completar. Se envía INSTRUCTIVO de la documentación legal y técnica requerida.El 26/05/2026 se logra la comunicación telefónica con el Intendente. Se le envía documentación modelo por WhatsApp | D7: =IFERROR(VLOOKUP($A7,'Base TOTAL'!A:AU,34,0), "-") -> 46168 | E7: =IFERROR(VLOOKUP($A7,'Base TOTAL'!A:AU,35,0), "-") -> DIRECCION DE JURISDICCION DE REGULARIZACION DE OBRAS Y PROYECTOS
A8: =IFERROR(__xludf.DUMMYFUNCTION("""COMPUTED_VALUE"""),"Capitán General Bernardo O'Higgins") -> Capitán General Bernardo O'Higgins | B8: =IFERROR(VLOOKUP($A8,'Base TOTAL'!A:AU,2,0), "-") -> Marcos Juárez | C8: =IFERROR(VLOOKUP($A8,'Base TOTAL'!A:AU,33,0), "-") -> 20/8/2026: Se envìa mensaje a la Int. preguntando si pudieron completar la documentaciòn. 28/7/2026: Se envìan por Email Observaciones a corregir por la comuna, al arq. e infra. RTA de arq. P. Lapentta: Hola... Bien! Habia visto esos detalles pero pense que con lo que presentaba era suficiente. Ya los completaré. 23/7/2026: Comunicaciòn con el arq. para corregir las observaciones. Se envìa Email con Instructivo. 22/7/2026: Se envìan por Email las observaciones a corregir por el M-C 13/7/2026: Presentan nuevamente la documentaciòn En evaluaciòn areas legal y tècnica. 25-6-26: Comunicaciòn con int. y arq. para completen Georeferencia. 19/6/2026 se envian observaciones por email para corregir y completar. 18/6/26: Comunicación con el municipio para enviar Instructivo. EL 16/04/26 SE CONTACTÓ A LA INTENDENTE. EL 29/04/26 NOS VISITÓ Y CONSULTÓ. VA A ENVIAR DOCUMENTACIÓN | D8: =IFERROR(VLOOKUP($A8,'Base TOTAL'!A:AU,34,0), "-") -> 46126 | E8: =IFERROR(VLOOKUP($A8,'Base TOTAL'!A:AU,35,0), "-") -> DIRECCION DE JURISDICCION DE REGULARIZACION DE OBRAS Y PROYECTOS
A9: =IFERROR(__xludf.DUMMYFUNCTION("""COMPUTED_VALUE"""),"El Arañado") -> El Arañado | B9: =IFERROR(VLOOKUP($A9,'Base TOTAL'!A:AU,2,0), "-") -> San Justo | C9: =IFERROR(VLOOKUP($A9,'Base TOTAL'!A:AU,33,0), "-") -> 20/8/2026: Se envía por Email, el Instructivo con el cambio de denominación. (Hoy Secretaría) 05/8/2026: Comunicaciòn con M/C enviando correo electrònico. 24/6/26:Comunicación con el municipio. Se envía Instructivo de la documentación legal y técnica requerida. 5/6/26: Ingresa Nota Ministerio Gobierno autorizando financiamiento. | D9: =IFERROR(VLOOKUP($A9,'Base TOTAL'!A:AU,34,0), "-") -> 46178 | E9: =IFERROR(VLOOKUP($A9,'Base TOTAL'!A:AU,35,0), "-") -> DIRECCION DE JURISDICCION DE REGULARIZACION DE OBRAS Y PROYECTOS
A10: =IFERROR(__xludf.DUMMYFUNCTION("""COMPUTED_VALUE"""),"General Baldissera") -> General Baldissera | B10: =IFERROR(VLOOKUP($A10,'Base TOTAL'!A:AU,2,0), "-") -> Marcos Juárez | C10: =IFERROR(VLOOKUP($A10,'Base TOTAL'!A:AU,33,0), "-") -> 27/8/2026: Se envian Observaciones a corregir x mail al intend.+ profes. + infra. 26/8/2026: Se recibe doc. 24/8/2026: Se re envian Observac. para corregir por Mail al int + profes + Infra 20/8/2026: Se envìa mensaje al Int. preguntando si pudieron corregir la documentaciòn para presentar. 05/8/2026: Se envían por Email Observaciones a corregir por el municipio. 24/6/26: Se envía Instructivo de documentación legal y técnica requerida. 22/6/26: Se solicitan correos electrònicos del municipio y profesional a cargo. El 11/5/26 se logra comunicación con municipalidad. Se pasa por whatsapp la documentación modelo | D10: =IFERROR(VLOOKUP($A10,'Base TOTAL'!A:AU,34,0), "-") -> 46150 | E10: =IFERROR(VLOOKUP($A10,'Base TOTAL'!A:AU,35,0), "-") -> DIRECCION DE JURISDICCION DE REGULARIZACION DE OBRAS Y PROYECTOS
A11: =IFERROR(__xludf.DUMMYFUNCTION("""COMPUTED_VALUE"""),"Guanaco Muerto") -> Guanaco Muerto | B11: =IFERROR(VLOOKUP($A11,'Base TOTAL'!A:AU,2,0), "-") -> Cruz del Eje | C11: =IFERROR(VLOOKUP($A11,'Base TOTAL'!A:AU,33,0), "-") -> 03/9/2026: Se reciben actualiz. por mail del presid. comunal (se avisa x whatss que el monto del computo debe coincidir con el monto total autoriz) 31/8/2026: Se re envian correcc al Presid. Com + prof. + infra x mail 26/8/2026: Se reitera nuevamente al ing. Bracamonte x mail la la correccion antes solicitada de agregar el ITems pto. 1,3 al computo y demas doc. derivadas del mismo 25/8/2026: Presentan actualiz. 21/8/2026: Se reitera el pedido de correcciones. 14/8/2026: Se responde Mail al ing. solicitando item1.3 en Computo y Avance.. 10/8/2026: Se envìa x mail Observaciones a corregir por presid. Comunal + profes. + infra 07/8/2026: Presentan nuevamente docum. a evaluar 05/8/2026: La Comuna tenìa una consulta para el àrea Legal, se les pregunto y se enviò la respuesta. Se aguarda la documentaciòn corregida. 04/8/2026: Se solicita a la comuna informen si pudieron corregir la documentaciòn. 22/7/2026: Se envìan Observaciones A corregir por Comuna 20/7/2026: Se recibe documentaciòn el 17/7. En evaluaciòn area Legales. 18/6/26: Se envìa Instructivo de documentaciòn legal y tècnica a presentar por M-C. EL 29/04/26 SE LE ENVÍA LOS REQUISITOS, VA A ENVIAR DOCUMENTACIÓN Completó el punto 4. Se le envió el 29/04/26 los restantes items para completar Expte. | D11: =IFERROR(VLOOKUP($A11,'Base TOTAL'!A:AU,34,0), "-") -> 46126 | E11: =IFERROR(VLOOKUP($A11,'Base TOTAL'!A:AU,35,0), "-") -> DIRECCION DE JURISDICCION DE REGULARIZACION DE OBRAS Y PROYECTOS
A12: =IFERROR(__xludf.DUMMYFUNCTION("""COMPUTED_VALUE"""),"Los Reartes") -> Los Reartes | B12: =IFERROR(VLOOKUP($A12,'Base TOTAL'!A:AU,2,0), "-") -> Calamuchita | C12: =IFERROR(VLOOKUP($A12,'Base TOTAL'!A:AU,33,0), "-") -> 31/8/2026: Se recibe doc. actualiz. x mail 24/8/2026: Se envìan Observac. p/compl. o correg. por Mail a la Presid. Com. + prof. + infra. 11/8/2026: Se recibem actualiz. por mail 07/8/2026: Se envian por Email Observaciones a corregir por intend. + prof. + Infra. Se reciben doc. 04/8/2026: Se envìan x mail correcc. al intend. + profes + infra Se recibe doc. Tècn. 03/8/2026: El ing. de la Comuna solicita Instructivo para hacer las correcciones en la doc. presentada. 27/7/2026: Se les consulto por email sobre las observaciones a la documentacion presentada. 17/7/2026: Se envìan por Email las observaciones A corregir por la comuna 15/7/2026: Fri Jul 03 2026 04:00:00 GMT-0300 (Argentina Standard Time) 03/7/2026: Presentan documentación en evaluaciòn. 22/6/26:Comunicaciòn con la pres. comunal. Se envìa Instructivo de la documentaciòn legal y tècnica requerida al munic. y al profesional. . 5/6/26: Ingresa Nota Ministerio Gobierno autorizando financiamiento. | D12: =IFERROR(VLOOKUP($A12,'Base TOTAL'!A:AU,34,0), "-") -> 46178 | E12: =IFERROR(VLOOKUP($A12,'Base TOTAL'!A:AU,35,0), "-") -> DIRECCION DE JURISDICCION DE REGULARIZACION DE OBRAS Y PROYECTOS
A13: =IFERROR(__xludf.DUMMYFUNCTION("""COMPUTED_VALUE"""),"Manfredi") -> Manfredi | B13: =IFERROR(VLOOKUP($A13,'Base TOTAL'!A:AU,2,0), "-") -> Río Segundo | C13: =IFERROR(VLOOKUP($A13,'Base TOTAL'!A:AU,33,0), "-") -> 02/9/2026: Se envian Observaciones a corregir al Intendente + Profes. + infra. 20/8/2026: Se envìan por Email las Observaciones A corregir por M. 20/8/2026: Se envìan por Email las Observaciones A corregir por M. 19/8/2026: El int. envìa documentaciòn tècnica por wathsapp. En evaluaciòn. 05/8/2026: Comunicaciòn con M/C enviando correo electrònico. 23/7/2026: Se envìa Email con la Notificaciòn ya enviada por Cidi el 3/7/2026. 23/7/2026: Comunicaciòn con el int. se solicita correos electrònicos para enviar Instructivo. | D13: =IFERROR(VLOOKUP($A13,'Base TOTAL'!A:AU,34,0), "-") | E13: =IFERROR(VLOOKUP($A13,'Base TOTAL'!A:AU,35,0), "-")
A14: =IFERROR(__xludf.DUMMYFUNCTION("""COMPUTED_VALUE"""),"Rosales") -> Rosales | B14: =IFERROR(VLOOKUP($A14,'Base TOTAL'!A:AU,2,0), "-") -> Presidente Roque Sáenz Peña | C14: =IFERROR(VLOOKUP($A14,'Base TOTAL'!A:AU,33,0), "-") -> 04/9/2026: Se re envian Observaciones p/corregir x mail a intend. + prof. + infra. 20/08/2026 Se solicita por Whatss, actualiz. doc. al ing. Rodrigues -RTAS.: ....... 04/8/2026: Se reitera el pedido de documetnaciòn al ing. encargado. 28/7/2026: Respuesta: "estamos a la espera de que el ingeniero pueda realizar las observaciones. Apenas lo tengamos se lo pasamos." 27/7/2026: se consulto por email el estado de las observaciones al legajo técnico. 16/7/2026: El municipio corrige la doc. legal pero falta que corrija la doc. tècnica. 15/7/2026: Se envían al municipio y profesional, las Observaciones a corregir. 07/7/2026: Envìan contacto y correo electrònico del ing. a cargo de la obra. 24/6/26: Se enviò Instructivo .El 8/05/26 se envió documentación modelo para participar. El 11/ envió documentación a analizar | D14: =IFERROR(VLOOKUP($A14,'Base TOTAL'!A:AU,34,0), "-") -> 46126 | E14: =IFERROR(VLOOKUP($A14,'Base TOTAL'!A:AU,35,0), "-") -> DIRECCION DE JURISDICCION DE REGULARIZACION DE OBRAS Y PROYECTOS
A15: =IFERROR(__xludf.DUMMYFUNCTION("""COMPUTED_VALUE"""),"Sacanta") -> Sacanta | B15: =IFERROR(VLOOKUP($A15,'Base TOTAL'!A:AU,2,0), "-") -> San Justo | C15: =IFERROR(VLOOKUP($A15,'Base TOTAL'!A:AU,33,0), "-") -> 04/9/2026: Se envìan al arq. encargado las Observaciones A corregir. 20/8/2026: Se envìan por Email las Observaciones A corregir por el Munic. 03/8/2026: Se envìan correcc a intend. Secr tec e Infraestr. 29/6/2026: Se envía nuevamente al municipio (Email) el Instructivo de la documentación legal y técnica requerida. 24/6/26: El Intendente informa que el monto autorizado es de $100 mill. y no $70 como dice la autorización previa. Ya hizo la gestión para que corrijan. /// Se envía Instructivo de la documentación legal y técnica a presentar.....23/6/26: Comunicaciòn con municipio solicitando Correo electrònico. 5/6/26: Ingresa Nota Ministerio Gobierno autorizando financiamiento. | D15: =IFERROR(VLOOKUP($A15,'Base TOTAL'!A:AU,34,0), "-") -> 46178 | E15: =IFERROR(VLOOKUP($A15,'Base TOTAL'!A:AU,35,0), "-") -> DIRECCION DE JURISDICCION DE REGULARIZACION DE OBRAS Y PROYECTOS
A16: =IFERROR(__xludf.DUMMYFUNCTION("""COMPUTED_VALUE"""),"San Joaquín") -> San Joaquín | B16: =IFERROR(VLOOKUP($A16,'Base TOTAL'!A:AU,2,0), "-") -> Presidente Roque Sáenz Peña | C16: =IFERROR(VLOOKUP($A16,'Base TOTAL'!A:AU,33,0), "-") -> 28/8/2026: Se reciben actualizac. 21/8/2026: Se re-envian por whatss las Observac. a correg a la nva profes. 21/08/2026: Se reciben actualiz. x el Presid. Comunal x whatss del A.Legal y se confecciona la planilla de Observ. para anexar cuando la nva prof. envie actualiz. Tecnicas. 20/8/2026: Se envìa mensaje al Int. preguntando si pudieron corregir las Observaciones para presentar la documentaciòn. 29/7/2026: Se envìa Planilla de Observ. a corregir por la comuna , al nvo profesional y a Infraestr. 28/7/2026: El municipio cambiò de profesional. Se le envìa el instructivo a la nueva arq. 22/7/2026: Se envìa nuevamente al Email las observaciones A corregir por la comuna 22/7/2026: El 14/7/2026 presentan documentaciòn a corregir nuevamente. 25/6/26: Comunicación con int. solicitando presenten correcciones. Se espera respuesta de la ing. a cargo. 19/6/26: Comunicaciòn con la ing. a cargo . Se solcita la presentaciòn a la mayor brevedad posible . 12-06-2026 Solicitar P Georef en Planim. + demas doc.Tec y leg 11/6/26: Se solicita nuevamente la correcciòn de Documentaciòn tècnica.Tiene todos los Items completos, salvo por el 4 (documentación técnica). El 29/5/26 se reclama la documentación firmada EL 19/05/26 PRESENTA PROYECTO CORREGIDO (A EVALUAR). EL 30/4 PRESENTAN NUEVO PRESUPUESTO, A VALOR $30.000.000. DEBE FUNDAMENTAR EL INCREMENTO EN EL MONTO TOTAL EL CÓMPUTO. El 30/04 se recibe y el monto que presenta es menor que el que se le da. Se pide que lo haga llegar al monto asignado El 28/04/26 se le envía documentación técnica modelo. EL 20/04/2026 LA COMUNA ENVÍA DOCUMENTACIÓN. FALTA INFO TÉCNICA. PRESENTA PRESUPUESTO, DE $21.969.370 - FALTA FIRMAS DE ÉSTE. EL 14/04/26 SE CONTACTÓ AL PRESIDENTE COMUNAL - | D16: =IFERROR(VLOOKUP($A16,'Base TOTAL'!A:AU,34,0), "-") -> 46199 | E16: =IFERROR(VLOOKUP($A16,'Base TOTAL'!A:AU,35,0), "-") -> DIRECCION DE JURISDICCION ECONOMICO, FINANCIERA Y DE ADMINISTRACION
A17: =IFERROR(__xludf.DUMMYFUNCTION("""COMPUTED_VALUE"""),"Tío Pujio") -> Tío Pujio | B17: =IFERROR(VLOOKUP($A17,'Base TOTAL'!A:AU,2,0), "-") -> General San Martín | C17: =IFERROR(VLOOKUP($A17,'Base TOTAL'!A:AU,33,0), "-") -> 02/9/2026: Se enviaron Observac. p/ corregir a Munic. + profes. + infra 01/09/2026: Se reciben actualiz. x mail 25/8/2026: Se envìan por Email las Observaciones tècnicas A corregir por el M. 24/8/2026: Se esperan observaciones del area legales para enviar al m. 18/8/2026: Presentan documetnaciòn por Email En evaluaciòn. 13/8/2026: Se recibe doc. y se responden por whatss consultas s/ la prosecuc. de los mismos 03/8/2026: Comunicaciòn con el encargado de la obra. Se envìa Instructivo para preparar toda la documentaciòn. 24/7/2026: Comunicaciòn con int. Se enviò Instructivo . | D17: =IFERROR(VLOOKUP($A17,'Base TOTAL'!A:AU,34,0), "-") | E17: =IFERROR(VLOOKUP($A17,'Base TOTAL'!A:AU,35,0), "-")
A18: =IFERROR(__xludf.DUMMYFUNCTION("""COMPUTED_VALUE"""),"Villa del Prado") -> Villa del Prado | B18: =IFERROR(VLOOKUP($A18,'Base TOTAL'!A:AU,2,0), "-") -> Santa María | C18: =IFERROR(VLOOKUP($A18,'Base TOTAL'!A:AU,33,0), "-") -> 02/9/2026: Se envìa a la comuna las Observaciones A corregir. 20/8/2026: Se envìa por Email, el Instructivo con el cambio de denominaciòn. (Hoy Secretarìa) 22/6/26: Se envìa Instructivo de la documentaciòn legal y tècnica requerida. 19/6/25/6/26: Comunicaciòn con el int. Se solicita correo electrònico para enviar instructivo. 5/6/26: Ingresa Nota Ministerio Gobierno autorizando financiamiento. | D18: =IFERROR(VLOOKUP($A18,'Base TOTAL'!A:AU,34,0), "-") -> 46178 | E18: =IFERROR(VLOOKUP($A18,'Base TOTAL'!A:AU,35,0), "-") -> DIRECCION DE JURISDICCION DE REGULARIZACION DE OBRAS Y PROYECTOS
B19: =IFERROR(VLOOKUP($A19,'Base TOTAL'!A:AU,2,0), "-") -> - | C19: =IFERROR(VLOOKUP($A19,'Base TOTAL'!A:AU,33,0), "-") -> - | D19: =IFERROR(VLOOKUP($A19,'Base TOTAL'!A:AU,34,0), "-") -> - | E19: =IFERROR(VLOOKUP($A19,'Base TOTAL'!A:AU,35,0), "-") -> -
B20: =IFERROR(VLOOKUP($A20,'Base TOTAL'!A:AU,2,0), "-") -> - | C20: =IFERROR(VLOOKUP($A20,'Base TOTAL'!A:AU,33,0), "-") -> - | D20: =IFERROR(VLOOKUP($A20,'Base TOTAL'!A:AU,34,0), "-") -> - | E20: =IFERROR(VLOOKUP($A20,'Base TOTAL'!A:AU,35,0), "-") -> -
B21: =IFERROR(VLOOKUP($A21,'Base TOTAL'!A:AU,2,0), "-") -> - | C21: =IFERROR(VLOOKUP($A21,'Base TOTAL'!A:AU,33,0), "-") -> - | D21: =IFERROR(VLOOKUP($A21,'Base TOTAL'!A:AU,34,0), "-") -> - | E21: =IFERROR(VLOOKUP($A21,'Base TOTAL'!A:AU,35,0), "-") -> -
B22: =IFERROR(VLOOKUP($A22,'Base TOTAL'!A:AU,2,0), "-") -> - | C22: =IFERROR(VLOOKUP($A22,'Base TOTAL'!A:AU,33,0), "-") -> - | D22: =IFERROR(VLOOKUP($A22,'Base TOTAL'!A:AU,34,0), "-") -> - | E22: =IFERROR(VLOOKUP($A22,'Base TOTAL'!A:AU,35,0), "-") -> -
B23: =IFERROR(VLOOKUP($A23,'Base TOTAL'!A:AU,2,0), "-") -> - | C23: =IFERROR(VLOOKUP($A23,'Base TOTAL'!A:AU,33,0), "-") -> - | D23: =IFERROR(VLOOKUP($A23,'Base TOTAL'!A:AU,34,0), "-") -> - | E23: =IFERROR(VLOOKUP($A23,'Base TOTAL'!A:AU,35,0), "-") -> -
B24: =IFERROR(VLOOKUP($A24,'Base TOTAL'!A:AU,2,0), "-") -> - | C24: =IFERROR(VLOOKUP($A24,'Base TOTAL'!A:AU,33,0), "-") -> - | D24: =IFERROR(VLOOKUP($A24,'Base TOTAL'!A:AU,34,0), "-") -> - | E24: =IFERROR(VLOOKUP($A24,'Base TOTAL'!A:AU,35,0), "-") -> -
B25: =IFERROR(VLOOKUP($A25,'Base TOTAL'!A:AU,2,0), "-") -> - | C25: =IFERROR(VLOOKUP($A25,'Base TOTAL'!A:AU,33,0), "-") -> - | D25: =IFERROR(VLOOKUP($A25,'Base TOTAL'!A:AU,34,0), "-") -> - | E25: =IFERROR(VLOOKUP($A25,'Base TOTAL'!A:AU,35,0), "-") -> -
B26: =IFERROR(VLOOKUP($A26,'Base TOTAL'!A:AU,2,0), "-") -> - | C26: =IFERROR(VLOOKUP($A26,'Base TOTAL'!A:AU,33,0), "-") -> - | D26: =IFERROR(VLOOKUP($A26,'Base TOTAL'!A:AU,34,0), "-") -> - | E26: =IFERROR(VLOOKUP($A26,'Base TOTAL'!A:AU,35,0), "-") -> -
B27: =IFERROR(VLOOKUP($A27,'Base TOTAL'!A:AU,2,0), "-") -> - | C27: =IFERROR(VLOOKUP($A27,'Base TOTAL'!A:AU,33,0), "-") -> - | D27: =IFERROR(VLOOKUP($A27,'Base TOTAL'!A:AU,34,0), "-") -> - | E27: =IFERROR(VLOOKUP($A27,'Base TOTAL'!A:AU,35,0), "-") -> -
B28: =IFERROR(VLOOKUP($A28,'Base TOTAL'!A:AU,2,0), "-") -> - | C28: =IFERROR(VLOOKUP($A28,'Base TOTAL'!A:AU,33,0), "-") -> - | D28: =IFERROR(VLOOKUP($A28,'Base TOTAL'!A:AU,34,0), "-") -> - | E28: =IFERROR(VLOOKUP($A28,'Base TOTAL'!A:AU,35,0), "-") -> -
B29: =IFERROR(VLOOKUP($A29,'Base TOTAL'!A:AU,2,0), "-") -> - | C29: =IFERROR(VLOOKUP($A29,'Base TOTAL'!A:AU,33,0), "-") -> - | D29: =IFERROR(VLOOKUP($A29,'Base TOTAL'!A:AU,34,0), "-") -> - | E29: =IFERROR(VLOOKUP($A29,'Base TOTAL'!A:AU,35,0), "-") -> -
B30: =IFERROR(VLOOKUP($A30,'Base TOTAL'!A:AU,2,0), "-") -> - | C30: =IFERROR(VLOOKUP($A30,'Base TOTAL'!A:AU,33,0), "-") -> - | D30: =IFERROR(VLOOKUP($A30,'Base TOTAL'!A:AU,34,0), "-") -> - | E30: =IFERROR(VLOOKUP($A30,'Base TOTAL'!A:AU,35,0), "-") -> -
... B501: =IFERROR(VLOOKUP($A501,'Base TOTAL'!A:AU,2,0), "-") -> - | C501: =IFERROR(VLOOKUP($A501,'Base TOTAL'!A:AU,33,0), "-") -> - | D501: =IFERROR(VLOOKUP($A501,'Base TOTAL'!A:AU,34,0), "-") -> - | E501: =IFERROR(VLOOKUP($A501,'Base TOTAL'!A:AU,35,0), "-") -> -

Sheet REP CH estado exp.
A1: OBRA: "CÓRDOBA HOGAR"
A2: PROGRAMA: "CÓRDOBA HOGAR"
A3: REPORTE | B3: =TODAY() -> 46269
A4: ='Base TOTAL'!AF2 -> ESTADO DEL EXPEDIENTE DE LA LOCALIDAD | C4: COMPLETO en TÉCNICA
C5: =COUNTIF(C7:C400, "<>-") -> 2 | D5: ='Base TOTAL'!AH2 -> EXP en FECHA
A6: Localidad | B6: Departamento | C6: ='Base TOTAL'!AG2 -> OBSERVACIONES | D6: ='Base TOTAL'!AH2 -> EXP en FECHA | E6: ='Base TOTAL'!AI2 -> EXP en REPARTICIÓN
A7: =IFERROR(__xludf.DUMMYFUNCTION("SORT(FILTER('Base TOTAL'!A:A, 'Base TOTAL'!BM:BM = C4))"),"Charras") -> Charras | B7: =IFERROR(VLOOKUP($A7,'Base TOTAL'!A:AU,2,0), "-") -> Juárez Celman | C7: =IFERROR(VLOOKUP($A7,'Base TOTAL'!A:AU,33,0), "-") -> 20/7/2026: PASA A LEGALES para prosecuciòn del tràmite. 16/7/2026: Presentan otra correcciòn observada por legales. 03/7/2026: Presentan documentaciòn nuevamente. 01/7/2026: Se envìan al municipio /profesional las Observaciones a corregir. 30-06-2026 Avisa el int. que envìo doc. por mail 18/6/26: Se envìa Instructivo de documentaciòn legal y tècnica a presentar por M-C. P -17-06-2026 Se corrige envio y se envia por whats al Intend. Emiliano p/ su completam. -RTAS.: 12/6/26: Comunicaciòn con Intendente para dar inicio al tràmite. 5/6/26: Ingresa Nota Ministerio Gobierno autorizando financiamiento. | D7: =IFERROR(VLOOKUP($A7,'Base TOTAL'!A:AU,34,0), "-") -> 46224 | E7: =IFERROR(VLOOKUP($A7,'Base TOTAL'!A:AU,35,0), "-") -> DIRECCION DE JURISDICCION LEGAL Y NOTARIAL
A8: =IFERROR(__xludf.DUMMYFUNCTION("""COMPUTED_VALUE"""),"El Fortín") -> El Fortín | B8: =IFERROR(VLOOKUP($A8,'Base TOTAL'!A:AU,2,0), "-") -> San Justo | C8: =IFERROR(VLOOKUP($A8,'Base TOTAL'!A:AU,33,0), "-") -> 20/8/2026: Se envía por Email, el Instructivo con el cambio de denominación. (Hoy Secretaría) 05/8/2026: Comunicaciòn con M/C enviando correo electrònico. 29/6/2026: Comunicación con el intendenten. Se envía el Instructivo al arquitecto a cargo 18/6/26: Se envìa Instructivo de documentaciòn legal y tècnica a presentar por M-C. 8/6/26: Se envía Instructivo (Doc. Requerida) a la localidad. 5/6/26: Ingresa Nota Ministerio Gobierno | D8: =IFERROR(VLOOKUP($A8,'Base TOTAL'!A:AU,34,0), "-") -> 46178 | E8: =IFERROR(VLOOKUP($A8,'Base TOTAL'!A:AU,35,0), "-") -> DIRECCION DE JURISDICCION DE REGULARIZACION DE OBRAS Y PROYECTOS
B9: =IFERROR(VLOOKUP($A9,'Base TOTAL'!A:AU,2,0), "-") -> - | C9: =IFERROR(VLOOKUP($A9,'Base TOTAL'!A:AU,33,0), "-") -> - | D9: =IFERROR(VLOOKUP($A9,'Base TOTAL'!A:AU,34,0), "-") -> - | E9: =IFERROR(VLOOKUP($A9,'Base TOTAL'!A:AU,35,0), "-") -> -
B10: =IFERROR(VLOOKUP($A10,'Base TOTAL'!A:AU,2,0), "-") -> - | C10: =IFERROR(VLOOKUP($A10,'Base TOTAL'!A:AU,33,0), "-") -> - | D10: =IFERROR(VLOOKUP($A10,'Base TOTAL'!A:AU,34,0), "-") -> - | E10: =IFERROR(VLOOKUP($A10,'Base TOTAL'!A:AU,35,0), "-") -> -
B11: =IFERROR(VLOOKUP($A11,'Base TOTAL'!A:AU,2,0), "-") -> - | C11: =IFERROR(VLOOKUP($A11,'Base TOTAL'!A:AU,33,0), "-") -> - | D11: =IFERROR(VLOOKUP($A11,'Base TOTAL'!A:AU,34,0), "-") -> - | E11: =IFERROR(VLOOKUP($A11,'Base TOTAL'!A:AU,35,0), "-") -> -
B12: =IFERROR(VLOOKUP($A12,'Base TOTAL'!A:AU,2,0), "-") -> - | C12: =IFERROR(VLOOKUP($A12,'Base TOTAL'!A:AU,33,0), "-") -> - | D12: =IFERROR(VLOOKUP($A12,'Base TOTAL'!A:AU,34,0), "-") -> - | E12: =IFERROR(VLOOKUP($A12,'Base TOTAL'!A:AU,35,0), "-") -> -
B13: =IFERROR(VLOOKUP($A13,'Base TOTAL'!A:AU,2,0), "-") -> - | C13: =IFERROR(VLOOKUP($A13,'Base TOTAL'!A:AU,33,0), "-") -> - | D13: =IFERROR(VLOOKUP($A13,'Base TOTAL'!A:AU,34,0), "-") -> - | E13: =IFERROR(VLOOKUP($A13,'Base TOTAL'!A:AU,35,0), "-") -> -
B14: =IFERROR(VLOOKUP($A14,'Base TOTAL'!A:AU,2,0), "-") -> - | C14: =IFERROR(VLOOKUP($A14,'Base TOTAL'!A:AU,33,0), "-") -> - | D14: =IFERROR(VLOOKUP($A14,'Base TOTAL'!A:AU,34,0), "-") -> - | E14: =IFERROR(VLOOKUP($A14,'Base TOTAL'!A:AU,35,0), "-") -> -
B15: =IFERROR(VLOOKUP($A15,'Base TOTAL'!A:AU,2,0), "-") -> - | C15: =IFERROR(VLOOKUP($A15,'Base TOTAL'!A:AU,33,0), "-") -> - | D15: =IFERROR(VLOOKUP($A15,'Base TOTAL'!A:AU,34,0), "-") -> - | E15: =IFERROR(VLOOKUP($A15,'Base TOTAL'!A:AU,35,0), "-") -> -
B16: =IFERROR(VLOOKUP($A16,'Base TOTAL'!A:AU,2,0), "-") -> - | C16: =IFERROR(VLOOKUP($A16,'Base TOTAL'!A:AU,33,0), "-") -> - | D16: =IFERROR(VLOOKUP($A16,'Base TOTAL'!A:AU,34,0), "-") -> - | E16: =IFERROR(VLOOKUP($A16,'Base TOTAL'!A:AU,35,0), "-") -> -
B17: =IFERROR(VLOOKUP($A17,'Base TOTAL'!A:AU,2,0), "-") -> - | C17: =IFERROR(VLOOKUP($A17,'Base TOTAL'!A:AU,33,0), "-") -> - | D17: =IFERROR(VLOOKUP($A17,'Base TOTAL'!A:AU,34,0), "-") -> - | E17: =IFERROR(VLOOKUP($A17,'Base TOTAL'!A:AU,35,0), "-") -> -
B18: =IFERROR(VLOOKUP($A18,'Base TOTAL'!A:AU,2,0), "-") -> - | C18: =IFERROR(VLOOKUP($A18,'Base TOTAL'!A:AU,33,0), "-") -> - | D18: =IFERROR(VLOOKUP($A18,'Base TOTAL'!A:AU,34,0), "-") -> - | E18: =IFERROR(VLOOKUP($A18,'Base TOTAL'!A:AU,35,0), "-") -> -
B19: =IFERROR(VLOOKUP($A19,'Base TOTAL'!A:AU,2,0), "-") -> - | C19: =IFERROR(VLOOKUP($A19,'Base TOTAL'!A:AU,33,0), "-") -> - | D19: =IFERROR(VLOOKUP($A19,'Base TOTAL'!A:AU,34,0), "-") -> - | E19: =IFERROR(VLOOKUP($A19,'Base TOTAL'!A:AU,35,0), "-") -> -
B20: =IFERROR(VLOOKUP($A20,'Base TOTAL'!A:AU,2,0), "-") -> - | C20: =IFERROR(VLOOKUP($A20,'Base TOTAL'!A:AU,33,0), "-") -> - | D20: =IFERROR(VLOOKUP($A20,'Base TOTAL'!A:AU,34,0), "-") -> - | E20: =IFERROR(VLOOKUP($A20,'Base TOTAL'!A:AU,35,0), "-") -> -
... B501: =IFERROR(VLOOKUP($A501,'Base TOTAL'!A:AU,2,0), "-") -> - | C501: =IFERROR(VLOOKUP($A501,'Base TOTAL'!A:AU,33,0), "-") -> - | D501: =IFERROR(VLOOKUP($A501,'Base TOTAL'!A:AU,34,0), "-") -> - | E501: =IFERROR(VLOOKUP($A501,'Base TOTAL'!A:AU,35,0), "-") -> -

Sheet REP CC ubicacion exp.
A1: OBRA: "EJECUCIÒN DE CORDÒN CUNETA Y ADOQUINADO"
A2: PROGRAMA: "PROVINCIAL DE CORDÒN CUNETA Y ADOQUINES" - LEY Nº 11.089
A3: REPORTE | B3: =TODAY() -> 46269
A4: =#REF! -> #REF! | C4: DIRECCION DE JURISDICCION ECONOMICO, FINANCIERA Y DE ADMINISTRACION
C5: =COUNTIF(C7:C400, "<>-") -> 3 | D5: INGRESO | E5: ='Base TOTAL'!AF2 -> ESTADO DEL EXPEDIENTE DE LA LOCALIDAD
A6: Localidad | B6: Departamento | D6: ='Base TOTAL'!AH2 -> EXP en FECHA | E6: ESTADO
A7: =IFERROR(__xludf.DUMMYFUNCTION("SORT(FILTER('Base TOTAL'!A:A, 'Base TOTAL'!AI:AI = C4))"),"La Higuera") -> La Higuera | B7: =IFERROR(VLOOKUP($A7,'Base TOTAL'!A:AU,2,0), "-") -> Cruz del Eje | C7: =IFERROR(VLOOKUP($A7,'Base TOTAL'!A:AU,33,0), "-") -> 12/8/2026: El Secretario consulta s/la doc. enviada y se avisa que PASO A LEGALES el 29-07 para su prosecuciòn 29/7/2026: PASA A LEGALES para prosecuciòn del tràmite. 22/7/2026: Se envìa PLA. Observaciones a corregir. 22/7/2026: Presentan documentaciòn a evaluar. 21/7/2026: Escriben consultando por el Email. Se solicita Correo electrònico 13-07-2026 Se llamo al ing. quien avisa que hoy envia doc. a la firma de la comuna y mañana nos envian por mail. 13/7/2026: Se solicita a la comuna y al ing. informen si puedieron avanzar con la documentaciòn. 13/7/2026: Se solicita a la comuna y al ing. informen si puedieron avanzar con la documentaciòn. 30-06-2026 Se reitera actualiz y completar docum. s/ instr. 26/6/2026: holaaaaaa 26/6/26: Se solicita al Ing. que complete la documentaciòn requerida conforme al Instructivo. 24/6/26: Se insiste y se hace un llamado al pres. comunal. Envìa datos por wathsapp. 22/6/26: Se solicita correo electrònico y datos del profesional para enviar instructivo. Sin respuesta 12-05-2026 Se envia las correcciones de la documentac. tecnica y la nota inial ( via whatsapp a Gonzalo Guzman El 30/04/2026 envían documentación de los items 1 a 5 para ver EL MARTES 28/04/26 SE HABLÓ POR TELÉFONO Y POR WHATSAPP, DONDE SE LE ENVIÓ LOS 9 PUNTOS Y SE COMPROMETIÓ EN DAR RESPUESTA. | D7: =IFERROR(VLOOKUP($A7,'Base TOTAL'!A:AU,34,0), "-") -> 46245 | E7: =IFERROR(VLOOKUP($A7,'Base TOTAL'!A:AU,32,0), "-") -> COMPLETO en TÉCNICA
A8: =IFERROR(__xludf.DUMMYFUNCTION("""COMPUTED_VALUE"""),"San Joaquín") -> San Joaquín | B8: =IFERROR(VLOOKUP($A8,'Base TOTAL'!A:AU,2,0), "-") -> Presidente Roque Sáenz Peña | C8: =IFERROR(VLOOKUP($A8,'Base TOTAL'!A:AU,33,0), "-") -> 28/8/2026: Se reciben actualizac. 21/8/2026: Se re-envian por whatss las Observac. a correg a la nva profes. 21/08/2026: Se reciben actualiz. x el Presid. Comunal x whatss del A.Legal y se confecciona la planilla de Observ. para anexar cuando la nva prof. envie actualiz. Tecnicas. 20/8/2026: Se envìa mensaje al Int. preguntando si pudieron corregir las Observaciones para presentar la documentaciòn. 29/7/2026: Se envìa Planilla de Observ. a corregir por la comuna , al nvo profesional y a Infraestr. 28/7/2026: El municipio cambiò de profesional. Se le envìa el instructivo a la nueva arq. 22/7/2026: Se envìa nuevamente al Email las observaciones A corregir por la comuna 22/7/2026: El 14/7/2026 presentan documentaciòn a corregir nuevamente. 25/6/26: Comunicación con int. solicitando presenten correcciones. Se espera respuesta de la ing. a cargo. 19/6/26: Comunicaciòn con la ing. a cargo . Se solcita la presentaciòn a la mayor brevedad posible . 12-06-2026 Solicitar P Georef en Planim. + demas doc.Tec y leg 11/6/26: Se solicita nuevamente la correcciòn de Documentaciòn tècnica.Tiene todos los Items completos, salvo por el 4 (documentación técnica). El 29/5/26 se reclama la documentación firmada EL 19/05/26 PRESENTA PROYECTO CORREGIDO (A EVALUAR). EL 30/4 PRESENTAN NUEVO PRESUPUESTO, A VALOR $30.000.000. DEBE FUNDAMENTAR EL INCREMENTO EN EL MONTO TOTAL EL CÓMPUTO. El 30/04 se recibe y el monto que presenta es menor que el que se le da. Se pide que lo haga llegar al monto asignado El 28/04/26 se le envía documentación técnica modelo. EL 20/04/2026 LA COMUNA ENVÍA DOCUMENTACIÓN. FALTA INFO TÉCNICA. PRESENTA PRESUPUESTO, DE $21.969.370 - FALTA FIRMAS DE ÉSTE. EL 14/04/26 SE CONTACTÓ AL PRESIDENTE COMUNAL - | D8: =IFERROR(VLOOKUP($A8,'Base TOTAL'!A:AU,34,0), "-") -> 46199 | E8: =IFERROR(VLOOKUP($A8,'Base TOTAL'!A:AU,32,0), "-") -> En CURSO en TÉCNICA
A9: =IFERROR(__xludf.DUMMYFUNCTION("""COMPUTED_VALUE"""),"Tuclame") -> Tuclame | B9: =IFERROR(VLOOKUP($A9,'Base TOTAL'!A:AU,2,0), "-") -> Cruz del Eje | C9: =IFERROR(VLOOKUP($A9,'Base TOTAL'!A:AU,33,0), "-") -> 07/8/2026: Se pagò A.F. el 5/8/2026 05/8/2026: PASA A EONOMICO-FINANCIERO para pago de A.F. 04/8/2026: Envìan Certif. y Nota a Silvia. 04/8/2026: Se envìa Modelo de Cert. A.F. A completar por la comuna y presentar. COMPLETÓ documentación. Subió a Jurídico Con V°B°. EN LA PRIVADA DESDE 19/05/26 ENVIÓ LA DOCUMENTACIÓN. ESTÁS COMPLETA, SÓLO DEBE CORREGIR CRONOGRAMA DE INVERSIONES. COMPLETO. CON V°B° DE TÉCNICA | D9: =IFERROR(VLOOKUP($A9,'Base TOTAL'!A:AU,34,0), "-") -> 46231 | E9: =IFERROR(VLOOKUP($A9,'Base TOTAL'!A:AU,32,0), "-") -> OBRA en EJECUCIÓN
B10: =IFERROR(VLOOKUP($A10,'Base TOTAL'!A:AU,2,0), "-") -> - | C10: =IFERROR(VLOOKUP($A10,'Base TOTAL'!A:AU,33,0), "-") -> - | D10: =IFERROR(VLOOKUP($A10,'Base TOTAL'!A:AU,34,0), "-") -> - | E10: =IFERROR(VLOOKUP($A10,'Base TOTAL'!A:AU,32,0), "-") -> -
B11: =IFERROR(VLOOKUP($A11,'Base TOTAL'!A:AU,2,0), "-") -> - | C11: =IFERROR(VLOOKUP($A11,'Base TOTAL'!A:AU,33,0), "-") -> - | D11: =IFERROR(VLOOKUP($A11,'Base TOTAL'!A:AU,34,0), "-") -> - | E11: =IFERROR(VLOOKUP($A11,'Base TOTAL'!A:AU,32,0), "-") -> -
B12: =IFERROR(VLOOKUP($A12,'Base TOTAL'!A:AU,2,0), "-") -> - | C12: =IFERROR(VLOOKUP($A12,'Base TOTAL'!A:AU,33,0), "-") -> - | D12: =IFERROR(VLOOKUP($A12,'Base TOTAL'!A:AU,34,0), "-") -> - | E12: =IFERROR(VLOOKUP($A12,'Base TOTAL'!A:AU,32,0), "-") -> -
B13: =IFERROR(VLOOKUP($A13,'Base TOTAL'!A:AU,2,0), "-") -> - | C13: =IFERROR(VLOOKUP($A13,'Base TOTAL'!A:AU,33,0), "-") -> - | D13: =IFERROR(VLOOKUP($A13,'Base TOTAL'!A:AU,34,0), "-") -> - | E13: =IFERROR(VLOOKUP($A13,'Base TOTAL'!A:AU,32,0), "-") -> -
B14: =IFERROR(VLOOKUP($A14,'Base TOTAL'!A:AU,2,0), "-") -> - | C14: =IFERROR(VLOOKUP($A14,'Base TOTAL'!A:AU,33,0), "-") -> - | D14: =IFERROR(VLOOKUP($A14,'Base TOTAL'!A:AU,34,0), "-") -> - | E14: =IFERROR(VLOOKUP($A14,'Base TOTAL'!A:AU,32,0), "-") -> -
B15: =IFERROR(VLOOKUP($A15,'Base TOTAL'!A:AU,2,0), "-") -> - | C15: =IFERROR(VLOOKUP($A15,'Base TOTAL'!A:AU,33,0), "-") -> - | D15: =IFERROR(VLOOKUP($A15,'Base TOTAL'!A:AU,34,0), "-") -> - | E15: =IFERROR(VLOOKUP($A15,'Base TOTAL'!A:AU,32,0), "-") -> -
B16: =IFERROR(VLOOKUP($A16,'Base TOTAL'!A:AU,2,0), "-") -> - | C16: =IFERROR(VLOOKUP($A16,'Base TOTAL'!A:AU,33,0), "-") -> - | D16: =IFERROR(VLOOKUP($A16,'Base TOTAL'!A:AU,34,0), "-") -> - | E16: =IFERROR(VLOOKUP($A16,'Base TOTAL'!A:AU,32,0), "-") -> -
B17: =IFERROR(VLOOKUP($A17,'Base TOTAL'!A:AU,2,0), "-") -> - | C17: =IFERROR(VLOOKUP($A17,'Base TOTAL'!A:AU,33,0), "-") -> - | D17: =IFERROR(VLOOKUP($A17,'Base TOTAL'!A:AU,34,0), "-") -> - | E17: =IFERROR(VLOOKUP($A17,'Base TOTAL'!A:AU,32,0), "-") -> -
B18: =IFERROR(VLOOKUP($A18,'Base TOTAL'!A:AU,2,0), "-") -> - | C18: =IFERROR(VLOOKUP($A18,'Base TOTAL'!A:AU,33,0), "-") -> - | D18: =IFERROR(VLOOKUP($A18,'Base TOTAL'!A:AU,34,0), "-") -> - | E18: =IFERROR(VLOOKUP($A18,'Base TOTAL'!A:AU,32,0), "-") -> -
B19: =IFERROR(VLOOKUP($A19,'Base TOTAL'!A:AU,2,0), "-") -> - | C19: =IFERROR(VLOOKUP($A19,'Base TOTAL'!A:AU,33,0), "-") -> - | D19: =IFERROR(VLOOKUP($A19,'Base TOTAL'!A:AU,34,0), "-") -> - | E19: =IFERROR(VLOOKUP($A19,'Base TOTAL'!A:AU,32,0), "-") -> -
B20: =IFERROR(VLOOKUP($A20,'Base TOTAL'!A:AU,2,0), "-") -> - | C20: =IFERROR(VLOOKUP($A20,'Base TOTAL'!A:AU,33,0), "-") -> - | D20: =IFERROR(VLOOKUP($A20,'Base TOTAL'!A:AU,34,0), "-") -> - | E20: =IFERROR(VLOOKUP($A20,'Base TOTAL'!A:AU,32,0), "-") -> -
B21: =IFERROR(VLOOKUP($A21,'Base TOTAL'!A:AU,2,0), "-") -> - | C21: =IFERROR(VLOOKUP($A21,'Base TOTAL'!A:AU,33,0), "-") -> - | D21: =IFERROR(VLOOKUP($A21,'Base TOTAL'!A:AU,34,0), "-") -> - | E21: =IFERROR(VLOOKUP($A21,'Base TOTAL'!A:AU,32,0), "-") -> -
... B501: =IFERROR(VLOOKUP($A501,'Base TOTAL'!A:AU,2,0), "-") -> - | C501: =IFERROR(VLOOKUP($A501,'Base TOTAL'!A:AU,33,0), "-") -> - | D501: =IFERROR(VLOOKUP($A501,'Base TOTAL'!A:AU,34,0), "-") -> - | E501: =IFERROR(VLOOKUP($A501,'Base TOTAL'!A:AU,32,0), "-") -> -

Sheet REP CC Depart.
A1: OBRA: "EJECUCIÒN DE CORDÒN CUNETA Y ADOQUINADO"
A2: PROGRAMA: "PROVINCIAL DE CORDÒN CUNETA Y ADOQUINES" - LEY Nº 11.089
A3: INFORME DEPARTAMENTO | B3: =TODAY() -> 46269
A4: DEPARTAMENTO: | B4: Marcos Juárez
A5: Cantidad de localidades afectadas | B5: =COUNTIF('Base TOTAL'!B:B, $B$4) -> 12
A6: TRAMITE PRE-OBRA
A7: MONTO TOTAL: | B7: =SUMIF('Base TOTAL'!B:B, $B$4, 'Base TOTAL'!J:J) -> 1720000000
A8: ='Base TOTAL'!K2 -> CONVENIO - Cordón Cuneta (ml) | B8: =SUMIF('Base TOTAL'!B:B, $B$4, 'Base TOTAL'!K:K) -> 4523
A9: ='Base TOTAL'!L2 -> CONVENIO - Adoquinado (m2) | B9: =SUMIF('Base TOTAL'!B:B, $B$4, 'Base TOTAL'!L:L) -> 24796.2
A10: ='Base TOTAL'!AF2 -> ESTADO DEL EXPEDIENTE DE LA LOCALIDAD
A11: =IFERROR(__xludf.DUMMYFUNCTION("SORT(FILTER('Base TOTAL'!A:A, 'Base TOTAL'!B:B = B4))"),"Alejo Ledesma") -> Alejo Ledesma | B11: =IFERROR(VLOOKUP($A11,'Base TOTAL'!A:AU,32,0), "-")
A12: =IFERROR(__xludf.DUMMYFUNCTION("""COMPUTED_VALUE"""),"Arias") -> Arias | B12: =IFERROR(VLOOKUP($A12,'Base TOTAL'!A:AU,32,0), "-") -> COMPLETO en TÉCNICA
A13: =IFERROR(__xludf.DUMMYFUNCTION("""COMPUTED_VALUE"""),"Camilo Aldao") -> Camilo Aldao | B13: =IFERROR(VLOOKUP($A13,'Base TOTAL'!A:AU,32,0), "-") -> COMPLETO en TÉCNICA
A14: =IFERROR(__xludf.DUMMYFUNCTION("""COMPUTED_VALUE"""),"Capitán General Bernardo O'Higgins") -> Capitán General Bernardo O'Higgins | B14: =IFERROR(VLOOKUP($A14,'Base TOTAL'!A:AU,32,0), "-") -> En CURSO en TÉCNICA
A15: =IFERROR(__xludf.DUMMYFUNCTION("""COMPUTED_VALUE"""),"Cavanagh") -> Cavanagh | B15: =IFERROR(VLOOKUP($A15,'Base TOTAL'!A:AU,32,0), "-") -> COMPLETO en TÉCNICA
A16: =IFERROR(__xludf.DUMMYFUNCTION("""COMPUTED_VALUE"""),"Colonia Barge") -> Colonia Barge | B16: =IFERROR(VLOOKUP($A16,'Base TOTAL'!A:AU,32,0), "-") -> A ESPERA de DOC.TÉCNICA
A17: =IFERROR(__xludf.DUMMYFUNCTION("""COMPUTED_VALUE"""),"Colonia Italiana") -> Colonia Italiana | B17: =IFERROR(VLOOKUP($A17,'Base TOTAL'!A:AU,32,0), "-") -> COMPLETO en TÉCNICA
A18: =IFERROR(__xludf.DUMMYFUNCTION("""COMPUTED_VALUE"""),"Cruz Alta") -> Cruz Alta | B18: =IFERROR(VLOOKUP($A18,'Base TOTAL'!A:AU,32,0), "-") -> COMPLETO en TÉCNICA
A19: =IFERROR(__xludf.DUMMYFUNCTION("""COMPUTED_VALUE"""),"General Baldissera") -> General Baldissera | B19: =IFERROR(VLOOKUP($A19,'Base TOTAL'!A:AU,32,0), "-") -> En CURSO en TÉCNICA
A20: =IFERROR(__xludf.DUMMYFUNCTION("""COMPUTED_VALUE"""),"General Roca") -> General Roca | B20: =IFERROR(VLOOKUP($A20,'Base TOTAL'!A:AU,32,0), "-") -> OBRA en EJECUCIÓN
A21: =IFERROR(__xludf.DUMMYFUNCTION("""COMPUTED_VALUE"""),"Guatimozín") -> Guatimozín | B21: =IFERROR(VLOOKUP($A21,'Base TOTAL'!A:AU,32,0), "-")
A22: =IFERROR(__xludf.DUMMYFUNCTION("""COMPUTED_VALUE"""),"Saira") -> Saira | B22: =IFERROR(VLOOKUP($A22,'Base TOTAL'!A:AU,32,0), "-") -> COMPLETO en TÉCNICA
B23: =IFERROR(VLOOKUP($A23,'Base TOTAL'!A:AU,32,0), "-") -> -
B24: =IFERROR(VLOOKUP($A24,'Base TOTAL'!A:AU,32,0), "-") -> -
B25: =IFERROR(VLOOKUP($A25,'Base TOTAL'!A:AU,32,0), "-") -> -
B26: =IFERROR(VLOOKUP($A26,'Base TOTAL'!A:AU,32,0), "-") -> -
B27: =IFERROR(VLOOKUP($A27,'Base TOTAL'!A:AU,32,0), "-") -> -
B28: =IFERROR(VLOOKUP($A28,'Base TOTAL'!A:AU,32,0), "-") -> -
B29: =IFERROR(VLOOKUP($A29,'Base TOTAL'!A:AU,32,0), "-") -> -
B30: =IFERROR(VLOOKUP($A30,'Base TOTAL'!A:AU,32,0), "-") -> -
B31: =IFERROR(VLOOKUP($A31,'Base TOTAL'!A:AU,32,0), "-") -> -
B32: =IFERROR(VLOOKUP($A32,'Base TOTAL'!A:AU,32,0), "-") -> -
B33: =IFERROR(VLOOKUP($A33,'Base TOTAL'!A:AU,32,0), "-") -> -
B34: =IFERROR(VLOOKUP($A34,'Base TOTAL'!A:AU,32,0), "-") -> -
... B50: =IFERROR(VLOOKUP($A50,'Base TOTAL'!A:AU,32,0), "-") -> -
A51: fin del listado

Sheet REP Loc.
A1: Programas provinciales - Dirección General de Vivienda
A2: Reporte
A3: INFORME LOCALIDAD | B3: =TODAY() -> 46269
A4: LOCALIDAD: | B4: Tuclame
A5: DEPARTAMENTO: | B5: =IFERROR(VLOOKUP($B$4,'Base TOTAL'!A:DA,2,0), "Sin dato") -> Cruz del Eje
A6: PROGRAMA PROVINCIAL DE CORDÓN CUNETA Y ADOQUINES - LEY Nº 11089
A7: TRAMITE PRE-OBRA (Obra Proyectada)
A8: Nº EXPEDIENTE 0135- : | B8: =IFERROR(VLOOKUP($B$4,'Base TOTAL'!A:DA,3,0), "Sin dato") -> 0423-079113/2026
A9: MONTO TOTAL: | B9: =IFERROR(VLOOKUP($B$4,'Base TOTAL'!A:DA,10,0), "Sin dato") -> 200000000
A10: ='Base TOTAL'!K2 -> CONVENIO - Cordón Cuneta (ml) | B10: 440
A11: ='Base TOTAL'!L2 -> CONVENIO - Adoquinado (m2) | B11: =IFERROR(VLOOKUP($B$4,'Base TOTAL'!A:DA,12,0), "Sin dato")
A12: Estado de la documentación
A13: 1- Nota Solicitud de Financiamiento | B13: =IFERROR(VLOOKUP($B$4,'Base TOTAL'!A:DA,13,0), "Sin dato") -> Completo OK
A14: 2- Ordenanza y Decreto/ Resolución comunal | B14: =IFERROR(VLOOKUP($B$4,'Base TOTAL'!A:DA,14,0), "Sin dato") -> Completo OK
A15: 3- DDJJ compromiso de ejecuciòn obra | B15: =IFERROR(VLOOKUP($B$4,'Base TOTAL'!A:DA,15,0), "Sin dato") -> Completo OK
A16: 4- Proyecto, Planos, Còmputo y Presupuesto | B16: =IFERROR(VLOOKUP($B$4,'Base TOTAL'!A:DA,16,0), "Sin dato") -> Completo OK
A17: Descripción General | B17: =IFERROR(VLOOKUP($B$4,'Base TOTAL'!A:DA,17,0), "Sin dato") -> Completo OK
A18: Memoria Técnica | B18: =IFERROR(VLOOKUP($B$4,'Base TOTAL'!A:DA,18,0), "Sin dato") -> Completo OK
A19: Plazo de Ejecución | B19: =IFERROR(VLOOKUP($B$4,'Base TOTAL'!A:DA,19,0), "Sin dato") -> Completo OK
A20: Cómputo y Presupuesto | B20: =IFERROR(VLOOKUP($B$4,'Base TOTAL'!A:DA,20,0), "Sin dato") -> Completo OK
A21: Cronograma Avance Obra | B21: =IFERROR(VLOOKUP($B$4,'Base TOTAL'!A:DA,21,0), "Sin dato") -> Completo OK
A22: Planimetría | B22: =IFERROR(VLOOKUP($B$4,'Base TOTAL'!A:DA,22,0), "Sin dato") -> Completo OK
A23: Perfil Calzada | B23: =IFERROR(VLOOKUP($B$4,'Base TOTAL'!A:DA,23,0), "Sin dato") -> Completo OK
A24: Detalle de Cordón Cuneta | B24: =IFERROR(VLOOKUP($B$4,'Base TOTAL'!A:DA,24,0), "Sin dato") -> Completo OK
A25: Detalle de Badén | B25: =IFERROR(VLOOKUP($B$4,'Base TOTAL'!A:DA,25,0), "Sin dato") -> Completo OK
A26: Paquete estr. Calzada | B26: =IFERROR(VLOOKUP($B$4,'Base TOTAL'!A:DA,26,0), "Sin dato") -> Completo OK
A27: 5- Nota a Contaduría Cesiòn Coparticipaciòn | B27: =IFERROR(VLOOKUP($B$4,'Base TOTAL'!A:DA,27,0), "Sin dato") -> Completo OK
A28: 6- Nº CBU de M/C especial para depòsito de fondos | B28: =IFERROR(VLOOKUP($B$4,'Base TOTAL'!A:DA,28,0), "Sin dato") -> Completo OK
A29: 7- Nº CUIT Municipal / Comunal | B29: =IFERROR(VLOOKUP($B$4,'Base TOTAL'!A:DA,29,0), "Sin dato") -> Completo OK
A30: 8- DNI Intendente / Jefe Comunal | B30: =IFERROR(VLOOKUP($B$4,'Base TOTAL'!A:DA,30,0), "Sin dato") -> Completo OK
A31: 9- Acta de Proclamación Int./Pres. Com. | B31: =IFERROR(VLOOKUP($B$4,'Base TOTAL'!A:DA,31,0), "Sin dato") -> Completo OK
A32: ='Base TOTAL'!AG2 -> OBSERVACIONES
A33: =IFERROR(VLOOKUP($B$4,'Base TOTAL'!A:DA,33,0), "Sin dato") -> 07/8/2026: Se pagò A.F. el 5/8/2026 05/8/2026: PASA A EONOMICO-FINANCIERO para pago de A.F. 04/8/2026: Envìan Certif. y Nota a Silvia. 04/8/2026: Se envìa Modelo de Cert. A.F. A completar por la comuna y presentar. COMPLETÓ documentación. Subió a Jurídico Con V°B°. EN LA PRIVADA DESDE 19/05/26 ENVIÓ LA DOCUMENTACIÓN. ESTÁS COMPLETA, SÓLO DEBE CORREGIR CRONOGRAMA DE INVERSIONES. COMPLETO. CON V°B° DE TÉCNICA
A34: ='Base TOTAL'!AF2 -> ESTADO DEL EXPEDIENTE DE LA LOCALIDAD | B34: =IFERROR(VLOOKUP($B$4,'Base TOTAL'!A:DA,32,0), "Sin dato") -> OBRA en EJECUCIÓN
A35: EXPEDIENTE RADICADO EN:
A36: ='Base TOTAL'!AH2 -> EXP en FECHA | B36: ='Base TOTAL'!AI2 -> EXP en REPARTICIÓN
A37: =IFERROR(VLOOKUP($B$4,'Base TOTAL'!A:DA,34,0), "Sin dato") -> 46231 | B37: =IFERROR(VLOOKUP($B$4,'Base TOTAL'!A:DA,35,0), "Sin dato") -> DIRECCION DE JURISDICCION ECONOMICO, FINANCIERA Y DE ADMINISTRACION
A38: OBRA (En Ejecución)
A39: Estado de la obra | B39: fecha
A40: Anticipo financiero | B40: =LET(res, IFERROR(VLOOKUP($B$4,'Base TOTAL'!A:DA,39,0),""), IF(res="", "Sin datos", res)) -> 46239
A41: =LET(res, IFERROR(VLOOKUP($B$4,'Base TOTAL'!A:DA,38,0),""), IF(res="", "Sin datos", res)) -> 100000000
A42: Avance físico 40% | B42: =LET(res, IFERROR(VLOOKUP($B$4,'Base TOTAL'!A:DA,41,0),""), IF(res="", "Sin datos", res)) -> Sin datos
A43: =LET(res, IFERROR(VLOOKUP($B$4,'Base TOTAL'!A:DA,40,0),""), IF(res="", "Sin datos", res)) -> 50000000
A44: Avance físico 70% | B44: =LET(res, IFERROR(VLOOKUP($B$4,'Base TOTAL'!A:DA,43,0),""), IF(res="", "Sin datos", res)) -> Sin datos
A45: =LET(res, IFERROR(VLOOKUP($B$4,'Base TOTAL'!A:DA,42,0),""), IF(res="", "Sin datos", res)) -> 50000000
A46: OBRA (Terminada)
A47: Estado de la obra | B47: fecha
A48: Avance físico 100% | B48: =LET(res, IFERROR(VLOOKUP($B$4,'Base TOTAL'!A:DA,45,0),""), IF(res="", "Sin datos", res)) -> Sin datos
A49: $0,00
A50: OBSERVACIONES
A51: =LET(res, IFERROR(VLOOKUP($B$4,'Base TOTAL'!A:DA,46,0),""), IF(res="", "Sin datos", res)) -> 04/9/2026: Comunicaciòn con la Pres. Com. el 2/9. Informa que la obra està avanzando. Se envìa Certificado Modelo al Ing. Bracamonte. 07/8/2026: Se pagò A.F. el 5/8/2026
A52: PROGRAMA CÓRDOBA HOGAR - LEY Nº 8663
A53: TRAMITE PRE-OBRA (Obra Proyectada)
A54: MONTO CONVENIO | B54: =LET(res, IFERROR(VLOOKUP($B$4,'Base TOTAL'!A:DA,48,0),""), IF(res="", "Sin datos", res)) -> 102000000
A55: Cantidad de Viviendas | B55: =LET(res, IFERROR(VLOOKUP($B$4,'Base TOTAL'!A:DA,49,0),""), IF(res="", "Sin datos", res)) -> 3
A56: Nº Expediente | B56: =LET(res, IFERROR(VLOOKUP($B$4,'Base TOTAL'!A:DA,50,0),""), IF(res="", "Sin datos", res)) -> 0135-045042/2026
A57: DOCUMENTACIÓN A PRESENTAR por Municipio / Comuna
A58: 1- Planimetría (Ubic. Obra) | B58: =LET(res, IFERROR(VLOOKUP($B$4,'Base TOTAL'!A:DA,51,0),""), IF(res="", "Sin datos", res)) -> Completo OK
A59: 2- Matrìcula de cada lote | B59: =LET(res, IFERROR(VLOOKUP($B$4,'Base TOTAL'!A:DA,52,0),""), IF(res="", "Sin datos", res)) -> Sin datos
A60: 3- Estudio de Suelo | B60: =LET(res, IFERROR(VLOOKUP($B$4,'Base TOTAL'!A:DA,53,0),""), IF(res="", "Sin datos", res)) -> Sin datos
A61: 4- Cert. de No inundabilidad | B61: =LET(res, IFERROR(VLOOKUP($B$4,'Base TOTAL'!A:DA,54,0),""), IF(res="", "Sin datos", res)) -> Sin datos
A62: 5- Fact. Agua Potable | B62: =LET(res, IFERROR(VLOOKUP($B$4,'Base TOTAL'!A:DA,55,0),""), IF(res="", "Sin datos", res)) -> Sin datos
A63: 6- Fac. Energìa Elèctrica | B63: =LET(res, IFERROR(VLOOKUP($B$4,'Base TOTAL'!A:DA,56,0),""), IF(res="", "Sin datos", res)) -> Sin datos
A64: 7- Designaciòn Dir. T. Obra | B64: =LET(res, IFERROR(VLOOKUP($B$4,'Base TOTAL'!A:DA,57,0),""), IF(res="", "Sin datos", res)) -> Sin datos
A65: 8- Memoria Téc. descriptiva | B65: =LET(res, IFERROR(VLOOKUP($B$4,'Base TOTAL'!A:DA,58,0),""), IF(res="", "Sin datos", res)) -> Completo OK
A66: 9- Planos Legajo Técnico | B66: =LET(res, IFERROR(VLOOKUP($B$4,'Base TOTAL'!A:DA,59,0),""), IF(res="", "Sin datos", res)) -> Completo OK
A67: 10- Pliego de Especif. Técnicas | B67: =LET(res, IFERROR(VLOOKUP($B$4,'Base TOTAL'!A:DA,60,0),""), IF(res="", "Sin datos", res)) -> Completo OK
A68: 11- Cómputo y Presupuesto | B68: =LET(res, IFERROR(VLOOKUP($B$4,'Base TOTAL'!A:DA,61,0),""), IF(res="", "Sin datos", res)) -> A corregir por M/C
A69: 12- Acta Mediciòn - Cert. | B69: =LET(res, IFERROR(VLOOKUP($B$4,'Base TOTAL'!A:DA,62,0),""), IF(res="", "Sin datos", res)) -> Completo OK
A70: 13- Curva de Avance | B70: =LET(res, IFERROR(VLOOKUP($B$4,'Base TOTAL'!A:DA,63,0),""), IF(res="", "Sin datos", res)) -> Sin datos
A71: 14- Cronograma de Avance | B71: =LET(res, IFERROR(VLOOKUP($B$4,'Base TOTAL'!A:DA,64,0),""), IF(res="", "Sin datos", res)) -> Sin datos
A72: ESTADO DEL EXPEDIENTE DE LA LOCALIDAD | B72: =LET(res, IFERROR(VLOOKUP($B$4,'Base TOTAL'!A:DA,65,0),""), IF(res="", "Sin datos", res)) -> En CURSO en TÉCNICA
A73: OBSERVACIONES
A74: =LET(res, IFERROR(VLOOKUP($B$4,'Base TOTAL'!A:DA,66,0),""), IF(res="", "Sin datos", res)) -> 04/9/2026: Se envìan por Email las Observaciones A corregir por la comuna. 26/8/2026: Comunicaciòn con la pres. comunal . Se solicita Email para enviar PLA. Observaciones- Se envìa Email . 24/8/26: Se llama a la Pres. Com. Sin respuesta. Se deja mensaje.
A75: OBRA (En Ejecución)
A76: Estado de la obra | B76: fecha
A77: Anticipo financiero | B77: =LET(res, IFERROR(VLOOKUP($B$4,'Base TOTAL'!A:DA,68,0),""), IF(res="", "Sin datos", res)) -> Sin datos
A78: =$B$54*0.5 -> 51000000
A79: Avance físico 40% | B79: =LET(res, IFERROR(VLOOKUP($B$4,'Base TOTAL'!A:DA,70,0),""), IF(res="", "Sin datos", res)) -> Sin datos
A80: =$B$54*0.25 -> 25500000
A81: Avance físico 70% | B81: =LET(res, IFERROR(VLOOKUP($B$4,'Base TOTAL'!A:DA,72,0),""), IF(res="", "Sin datos", res)) -> Sin datos
A82: =$B$54*0.25 -> 25500000
A83: OBRA (Terminada)
A84: Estado de la obra | B84: fecha
A85: Avance físico 100% | B85: =LET(res, IFERROR(VLOOKUP($B$4,'Base TOTAL'!A:DA,74,0),""), IF(res="", "Sin datos", res)) -> Sin datos
A86: $0,00
A87: OBSERVACIONES
A88: =LET(res, IFERROR(VLOOKUP($B$4,'Base TOTAL'!A:DA,75,0),""), IF(res="", "Sin datos", res)) -> Sin datos
A89: PROGRAMA MI LUGAR
A90: MONTO | B90: =LET(res, IFERROR(VLOOKUP($B$4,'Base TOTAL'!A:DA,77,0),""), IF(res="", "Sin datos", res)) -> Sin datos
A91: Cantidad de Lotes | B91: =LET(res, IFERROR(VLOOKUP($B$4,'Base TOTAL'!A:DA,78,0),""), IF(res="", "Sin datos", res)) -> Sin datos
A92: Nº Expediente | B92: =LET(res, IFERROR(VLOOKUP($B$4,'Base TOTAL'!A:DA,79,0),""), IF(res="", "Sin datos", res)) -> Sin datos
A93: DOCUMENTACIÓN A PRESENTAR por Municipio / Comuna
A94: 1- Planimetría General | B94: =LET(res, IFERROR(VLOOKUP($B$4,'Base TOTAL'!A:DA,80,0),""), IF(res="", "Sin datos", res)) -> Sin datos
A95: 2- Plano de Altimetría | B95: =LET(res, IFERROR(VLOOKUP($B$4,'Base TOTAL'!A:DA,81,0),""), IF(res="", "Sin datos", res)) -> Sin datos
A96: 3- Plancheta Catastral | B96: =LET(res, IFERROR(VLOOKUP($B$4,'Base TOTAL'!A:DA,82,0),""), IF(res="", "Sin datos", res)) -> Sin datos
A97: 4-Títulos | B97: =LET(res, IFERROR(VLOOKUP($B$4,'Base TOTAL'!A:DA,83,0),""), IF(res="", "Sin datos", res)) -> Sin datos
A98: 5- Certificado de No Inundabilidad | B98: =LET(res, IFERROR(VLOOKUP($B$4,'Base TOTAL'!A:DA,84,0),""), IF(res="", "Sin datos", res)) -> Sin datos
A99: 6- Informe de Ministerio de Ambiente y Economía Circular | B99: =LET(res, IFERROR(VLOOKUP($B$4,'Base TOTAL'!A:DA,85,0),""), IF(res="", "Sin datos", res)) -> Sin datos
A100: 7- Factibilidad de Agua Potable | B100: =LET(res, IFERROR(VLOOKUP($B$4,'Base TOTAL'!A:DA,86,0),""), IF(res="", "Sin datos", res)) -> Sin datos
...

Sheet Resumen
B2: CC Presupuesto destinado por Localidad | I2: CC | L2: CC
I3: =IFERROR(__xludf.DUMMYFUNCTION("QUERY('Base TOTAL'!A2:J1030, ""SELECT A, J WHERE J IS NOT NULL ORDER BY J DESC"", 1)"),"LOCALIDAD / PROYECTO") -> LOCALIDAD / PROYECTO | J3: =IFERROR(__xludf.DUMMYFUNCTION("""COMPUTED_VALUE"""),"CONVENIO - MONTO") -> CONVENIO - MONTO | L3: =IFERROR(__xludf.DUMMYFUNCTION("QUERY('Base TOTAL'!A2:J1030, ""SELECT B, COUNT(A), SUM(J) WHERE B IS NOT NULL AND B <> '' GROUP BY B ORDER BY SUM(J) DESC LABEL B 'Departamento', COUNT(A) 'Cant. Localidades', SUM(J) 'Monto Total Convenios ($)'"", 1)"),"Departamento") -> Departamento | M3: =IFERROR(__xludf.DUMMYFUNCTION("""COMPUTED_VALUE"""),"Cant. Localidades") -> Cant. Localidades | N3: =IFERROR(__xludf.DUMMYFUNCTION("""COMPUTED_VALUE"""),"Monto Total Convenios ($)") -> Monto Total Convenios ($)
I4: =IFERROR(__xludf.DUMMYFUNCTION("""COMPUTED_VALUE"""),"Las Varillas") -> Las Varillas | J4: =IFERROR(__xludf.DUMMYFUNCTION("""COMPUTED_VALUE"""),4.0E8) -> 400000000 | L4: =IFERROR(__xludf.DUMMYFUNCTION("""COMPUTED_VALUE"""),"Marcos Juárez") -> Marcos Juárez | M4: =IFERROR(__xludf.DUMMYFUNCTION("""COMPUTED_VALUE"""),12.0) -> 12 | N4: =IFERROR(__xludf.DUMMYFUNCTION("""COMPUTED_VALUE"""),1.72E9) -> 1720000000
I5: =IFERROR(__xludf.DUMMYFUNCTION("""COMPUTED_VALUE"""),"Cruz Alta") -> Cruz Alta | J5: =IFERROR(__xludf.DUMMYFUNCTION("""COMPUTED_VALUE"""),4.0E8) -> 400000000 | L5: =IFERROR(__xludf.DUMMYFUNCTION("""COMPUTED_VALUE"""),"San Justo") -> San Justo | M5: =IFERROR(__xludf.DUMMYFUNCTION("""COMPUTED_VALUE"""),6.0) -> 6 | N5: =IFERROR(__xludf.DUMMYFUNCTION("""COMPUTED_VALUE"""),1.32E9) -> 1320000000
I6: =IFERROR(__xludf.DUMMYFUNCTION("""COMPUTED_VALUE"""),"Villa Valeria") -> Villa Valeria | J6: =IFERROR(__xludf.DUMMYFUNCTION("""COMPUTED_VALUE"""),3.5E8) -> 350000000 | L6: =IFERROR(__xludf.DUMMYFUNCTION("""COMPUTED_VALUE"""),"General Roca") -> General Roca | M6: =IFERROR(__xludf.DUMMYFUNCTION("""COMPUTED_VALUE"""),4.0) -> 4 | N6: =IFERROR(__xludf.DUMMYFUNCTION("""COMPUTED_VALUE"""),9.6E8) -> 960000000
I7: =IFERROR(__xludf.DUMMYFUNCTION("""COMPUTED_VALUE"""),"Cavanagh") -> Cavanagh | J7: =IFERROR(__xludf.DUMMYFUNCTION("""COMPUTED_VALUE"""),3.0E8) -> 300000000 | L7: =IFERROR(__xludf.DUMMYFUNCTION("""COMPUTED_VALUE"""),"San Javier") -> San Javier | M7: =IFERROR(__xludf.DUMMYFUNCTION("""COMPUTED_VALUE"""),6.0) -> 6 | N7: =IFERROR(__xludf.DUMMYFUNCTION("""COMPUTED_VALUE"""),8.75E8) -> 875000000
I8: =IFERROR(__xludf.DUMMYFUNCTION("""COMPUTED_VALUE"""),"La Paz") -> La Paz | J8: =IFERROR(__xludf.DUMMYFUNCTION("""COMPUTED_VALUE"""),3.0E8) -> 300000000 | L8: =IFERROR(__xludf.DUMMYFUNCTION("""COMPUTED_VALUE"""),"Cruz del Eje") -> Cruz del Eje | M8: =IFERROR(__xludf.DUMMYFUNCTION("""COMPUTED_VALUE"""),6.0) -> 6 | N8: =IFERROR(__xludf.DUMMYFUNCTION("""COMPUTED_VALUE"""),6.0E8) -> 600000000
I9: =IFERROR(__xludf.DUMMYFUNCTION("""COMPUTED_VALUE"""),"El Fortín") -> El Fortín | J9: =IFERROR(__xludf.DUMMYFUNCTION("""COMPUTED_VALUE"""),3.0E8) -> 300000000 | L9: =IFERROR(__xludf.DUMMYFUNCTION("""COMPUTED_VALUE"""),"General San Martín") -> General San Martín | M9: =IFERROR(__xludf.DUMMYFUNCTION("""COMPUTED_VALUE"""),5.0) -> 5 | N9: =IFERROR(__xludf.DUMMYFUNCTION("""COMPUTED_VALUE"""),5.8E8) -> 580000000
I10: =IFERROR(__xludf.DUMMYFUNCTION("""COMPUTED_VALUE"""),"General Roca") -> General Roca | J10: =IFERROR(__xludf.DUMMYFUNCTION("""COMPUTED_VALUE"""),2.4E8) -> 240000000 | L10: =IFERROR(__xludf.DUMMYFUNCTION("""COMPUTED_VALUE"""),"Presidente Roque Sáenz Peña") -> Presidente Roque Sáenz Peña | M10: =IFERROR(__xludf.DUMMYFUNCTION("""COMPUTED_VALUE"""),4.0) -> 4 | N10: =IFERROR(__xludf.DUMMYFUNCTION("""COMPUTED_VALUE"""),5.3E8) -> 530000000
I11: =IFERROR(__xludf.DUMMYFUNCTION("""COMPUTED_VALUE"""),"Villa Sarmiento") -> Villa Sarmiento | J11: =IFERROR(__xludf.DUMMYFUNCTION("""COMPUTED_VALUE"""),2.1E8) -> 210000000 | L11: =IFERROR(__xludf.DUMMYFUNCTION("""COMPUTED_VALUE"""),"Río Segundo") -> Río Segundo | M11: =IFERROR(__xludf.DUMMYFUNCTION("""COMPUTED_VALUE"""),5.0) -> 5 | N11: =IFERROR(__xludf.DUMMYFUNCTION("""COMPUTED_VALUE"""),4.8E8) -> 480000000
I12: =IFERROR(__xludf.DUMMYFUNCTION("""COMPUTED_VALUE"""),"Del Campillo") -> Del Campillo | J12: =IFERROR(__xludf.DUMMYFUNCTION("""COMPUTED_VALUE"""),2.0E8) -> 200000000 | L12: =IFERROR(__xludf.DUMMYFUNCTION("""COMPUTED_VALUE"""),"Juárez Celman") -> Juárez Celman | M12: =IFERROR(__xludf.DUMMYFUNCTION("""COMPUTED_VALUE"""),5.0) -> 5 | N12: =IFERROR(__xludf.DUMMYFUNCTION("""COMPUTED_VALUE"""),4.3E8) -> 430000000
I13: =IFERROR(__xludf.DUMMYFUNCTION("""COMPUTED_VALUE"""),"San Javier y Yacanto") -> San Javier y Yacanto | J13: =IFERROR(__xludf.DUMMYFUNCTION("""COMPUTED_VALUE"""),2.0E8) -> 200000000 | L13: =IFERROR(__xludf.DUMMYFUNCTION("""COMPUTED_VALUE"""),"Calamuchita") -> Calamuchita | M13: =IFERROR(__xludf.DUMMYFUNCTION("""COMPUTED_VALUE"""),3.0) -> 3 | N13: =IFERROR(__xludf.DUMMYFUNCTION("""COMPUTED_VALUE"""),3.0E8) -> 300000000
I14: =IFERROR(__xludf.DUMMYFUNCTION("""COMPUTED_VALUE"""),"Capitán General Bernardo O'Higgins") -> Capitán General Bernardo O'Higgins | J14: =IFERROR(__xludf.DUMMYFUNCTION("""COMPUTED_VALUE"""),2.0E8) -> 200000000 | L14: =IFERROR(__xludf.DUMMYFUNCTION("""COMPUTED_VALUE"""),"Santa María") -> Santa María | M14: =IFERROR(__xludf.DUMMYFUNCTION("""COMPUTED_VALUE"""),3.0) -> 3 | N14: =IFERROR(__xludf.DUMMYFUNCTION("""COMPUTED_VALUE"""),2.0E8) -> 200000000
I15: =IFERROR(__xludf.DUMMYFUNCTION("""COMPUTED_VALUE"""),"Las Playas") -> Las Playas | J15: =IFERROR(__xludf.DUMMYFUNCTION("""COMPUTED_VALUE"""),2.0E8) -> 200000000 | L15: =IFERROR(__xludf.DUMMYFUNCTION("""COMPUTED_VALUE"""),"Ischilín") -> Ischilín | M15: =IFERROR(__xludf.DUMMYFUNCTION("""COMPUTED_VALUE"""),1.0) -> 1
I16: =IFERROR(__xludf.DUMMYFUNCTION("""COMPUTED_VALUE"""),"Villa Huidobro") -> Villa Huidobro | J16: =IFERROR(__xludf.DUMMYFUNCTION("""COMPUTED_VALUE"""),2.0E8) -> 200000000 | L16: =IFERROR(__xludf.DUMMYFUNCTION("""COMPUTED_VALUE"""),"Pocho") -> Pocho | M16: =IFERROR(__xludf.DUMMYFUNCTION("""COMPUTED_VALUE"""),4.0) -> 4
I17: =IFERROR(__xludf.DUMMYFUNCTION("""COMPUTED_VALUE"""),"Tuclame") -> Tuclame | J17: =IFERROR(__xludf.DUMMYFUNCTION("""COMPUTED_VALUE"""),2.0E8) -> 200000000 | L17: =IFERROR(__xludf.DUMMYFUNCTION("""COMPUTED_VALUE"""),"Río Cuarto") -> Río Cuarto | M17: =IFERROR(__xludf.DUMMYFUNCTION("""COMPUTED_VALUE"""),1.0) -> 1
I18: =IFERROR(__xludf.DUMMYFUNCTION("""COMPUTED_VALUE"""),"La Cesira") -> La Cesira | J18: =IFERROR(__xludf.DUMMYFUNCTION("""COMPUTED_VALUE"""),2.0E8) -> 200000000 | L18: =IFERROR(__xludf.DUMMYFUNCTION("""COMPUTED_VALUE"""),"Tercero Arriba") -> Tercero Arriba | M18: =IFERROR(__xludf.DUMMYFUNCTION("""COMPUTED_VALUE"""),1.0) -> 1
I19: =IFERROR(__xludf.DUMMYFUNCTION("""COMPUTED_VALUE"""),"Embalse") -> Embalse | J19: =IFERROR(__xludf.DUMMYFUNCTION("""COMPUTED_VALUE"""),2.0E8) -> 200000000 | L19: =IFERROR(__xludf.DUMMYFUNCTION("""COMPUTED_VALUE"""),"Unión") -> Unión | M19: =IFERROR(__xludf.DUMMYFUNCTION("""COMPUTED_VALUE"""),1.0) -> 1
I20: =IFERROR(__xludf.DUMMYFUNCTION("""COMPUTED_VALUE"""),"Pozo del Molle") -> Pozo del Molle | J20: =IFERROR(__xludf.DUMMYFUNCTION("""COMPUTED_VALUE"""),2.0E8) -> 200000000
I21: =IFERROR(__xludf.DUMMYFUNCTION("""COMPUTED_VALUE"""),"Laboulaye") -> Laboulaye | J21: =IFERROR(__xludf.DUMMYFUNCTION("""COMPUTED_VALUE"""),2.0E8) -> 200000000
I22: =IFERROR(__xludf.DUMMYFUNCTION("""COMPUTED_VALUE"""),"Alicia") -> Alicia | J22: =IFERROR(__xludf.DUMMYFUNCTION("""COMPUTED_VALUE"""),2.0E8) -> 200000000
I23: =IFERROR(__xludf.DUMMYFUNCTION("""COMPUTED_VALUE"""),"El Arañado") -> El Arañado | J23: =IFERROR(__xludf.DUMMYFUNCTION("""COMPUTED_VALUE"""),2.0E8) -> 200000000
I24: =IFERROR(__xludf.DUMMYFUNCTION("""COMPUTED_VALUE"""),"Olaeta") -> Olaeta | J24: =IFERROR(__xludf.DUMMYFUNCTION("""COMPUTED_VALUE"""),1.8E8) -> 180000000
I25: =IFERROR(__xludf.DUMMYFUNCTION("""COMPUTED_VALUE"""),"Luyaba") -> Luyaba | J25: =IFERROR(__xludf.DUMMYFUNCTION("""COMPUTED_VALUE"""),1.5E8) -> 150000000
I26: =IFERROR(__xludf.DUMMYFUNCTION("""COMPUTED_VALUE"""),"Los Hornillos") -> Los Hornillos | J26: =IFERROR(__xludf.DUMMYFUNCTION("""COMPUTED_VALUE"""),1.5E8) -> 150000000
I27: =IFERROR(__xludf.DUMMYFUNCTION("""COMPUTED_VALUE"""),"Saira") -> Saira | J27: =IFERROR(__xludf.DUMMYFUNCTION("""COMPUTED_VALUE"""),1.5E8) -> 150000000
I28: =IFERROR(__xludf.DUMMYFUNCTION("""COMPUTED_VALUE"""),"Villa Parque Santa Ana") -> Villa Parque Santa Ana | J28: =IFERROR(__xludf.DUMMYFUNCTION("""COMPUTED_VALUE"""),1.5E8) -> 150000000
I29: =IFERROR(__xludf.DUMMYFUNCTION("""COMPUTED_VALUE"""),"Santa Eufemia") -> Santa Eufemia | J29: =IFERROR(__xludf.DUMMYFUNCTION("""COMPUTED_VALUE"""),1.5E8) -> 150000000
I30: =IFERROR(__xludf.DUMMYFUNCTION("""COMPUTED_VALUE"""),"Las Varas") -> Las Varas | J30: =IFERROR(__xludf.DUMMYFUNCTION("""COMPUTED_VALUE"""),1.5E8) -> 150000000
I31: =IFERROR(__xludf.DUMMYFUNCTION("""COMPUTED_VALUE"""),"La Laguna") -> La Laguna | J31: =IFERROR(__xludf.DUMMYFUNCTION("""COMPUTED_VALUE"""),1.5E8) -> 150000000
I32: =IFERROR(__xludf.DUMMYFUNCTION("""COMPUTED_VALUE"""),"Tío Pujio") -> Tío Pujio | J32: =IFERROR(__xludf.DUMMYFUNCTION("""COMPUTED_VALUE"""),1.5E8) -> 150000000
I33: =IFERROR(__xludf.DUMMYFUNCTION("""COMPUTED_VALUE"""),"La Higuera") -> La Higuera | J33: =IFERROR(__xludf.DUMMYFUNCTION("""COMPUTED_VALUE"""),1.0E8) -> 100000000
I34: =IFERROR(__xludf.DUMMYFUNCTION("""COMPUTED_VALUE"""),"Rosales") -> Rosales | J34: =IFERROR(__xludf.DUMMYFUNCTION("""COMPUTED_VALUE"""),1.0E8) -> 100000000
I35: =IFERROR(__xludf.DUMMYFUNCTION("""COMPUTED_VALUE"""),"Camilo Aldao") -> Camilo Aldao | J35: =IFERROR(__xludf.DUMMYFUNCTION("""COMPUTED_VALUE"""),1.0E8) -> 100000000
I36: =IFERROR(__xludf.DUMMYFUNCTION("""COMPUTED_VALUE"""),"Arias") -> Arias | J36: =IFERROR(__xludf.DUMMYFUNCTION("""COMPUTED_VALUE"""),1.0E8) -> 100000000
I37: =IFERROR(__xludf.DUMMYFUNCTION("""COMPUTED_VALUE"""),"General Baldissera") -> General Baldissera | J37: =IFERROR(__xludf.DUMMYFUNCTION("""COMPUTED_VALUE"""),1.0E8) -> 100000000
I38: =IFERROR(__xludf.DUMMYFUNCTION("""COMPUTED_VALUE"""),"Capilla del Carmen") -> Capilla del Carmen | J38: =IFERROR(__xludf.DUMMYFUNCTION("""COMPUTED_VALUE"""),1.0E8) -> 100000000
I39: =IFERROR(__xludf.DUMMYFUNCTION("""COMPUTED_VALUE"""),"Los Reartes") -> Los Reartes | J39: =IFERROR(__xludf.DUMMYFUNCTION("""COMPUTED_VALUE"""),1.0E8) -> 100000000
I40: =IFERROR(__xludf.DUMMYFUNCTION("""COMPUTED_VALUE"""),"Charras") -> Charras | J40: =IFERROR(__xludf.DUMMYFUNCTION("""COMPUTED_VALUE"""),1.0E8) -> 100000000
I41: =IFERROR(__xludf.DUMMYFUNCTION("""COMPUTED_VALUE"""),"Etruria") -> Etruria | J41: =IFERROR(__xludf.DUMMYFUNCTION("""COMPUTED_VALUE"""),1.0E8) -> 100000000
I42: =IFERROR(__xludf.DUMMYFUNCTION("""COMPUTED_VALUE"""),"Chazón") -> Chazón | J42: =IFERROR(__xludf.DUMMYFUNCTION("""COMPUTED_VALUE"""),1.0E8) -> 100000000
I43: =IFERROR(__xludf.DUMMYFUNCTION("""COMPUTED_VALUE"""),"Colonia Italiana") -> Colonia Italiana | J43: =IFERROR(__xludf.DUMMYFUNCTION("""COMPUTED_VALUE"""),8.0E7) -> 80000000
I44: =IFERROR(__xludf.DUMMYFUNCTION("""COMPUTED_VALUE"""),"Matorrales") -> Matorrales | J44: =IFERROR(__xludf.DUMMYFUNCTION("""COMPUTED_VALUE"""),8.0E7) -> 80000000
I45: =IFERROR(__xludf.DUMMYFUNCTION("""COMPUTED_VALUE"""),"Ausonia") -> Ausonia | J45: =IFERROR(__xludf.DUMMYFUNCTION("""COMPUTED_VALUE"""),8.0E7) -> 80000000
I46: =IFERROR(__xludf.DUMMYFUNCTION("""COMPUTED_VALUE"""),"La Población") -> La Población | J46: =IFERROR(__xludf.DUMMYFUNCTION("""COMPUTED_VALUE"""),7.5E7) -> 75000000
I47: =IFERROR(__xludf.DUMMYFUNCTION("""COMPUTED_VALUE"""),"Sacanta") -> Sacanta | J47: =IFERROR(__xludf.DUMMYFUNCTION("""COMPUTED_VALUE"""),7.0E7) -> 70000000
I48: =IFERROR(__xludf.DUMMYFUNCTION("""COMPUTED_VALUE"""),"Guanaco Muerto") -> Guanaco Muerto | J48: =IFERROR(__xludf.DUMMYFUNCTION("""COMPUTED_VALUE"""),5.0E7) -> 50000000
I49: =IFERROR(__xludf.DUMMYFUNCTION("""COMPUTED_VALUE"""),"La Batea") -> La Batea | J49: =IFERROR(__xludf.DUMMYFUNCTION("""COMPUTED_VALUE"""),5.0E7) -> 50000000
I50: =IFERROR(__xludf.DUMMYFUNCTION("""COMPUTED_VALUE"""),"Colonia Barge") -> Colonia Barge | J50: =IFERROR(__xludf.DUMMYFUNCTION("""COMPUTED_VALUE"""),5.0E7) -> 50000000
I51: =IFERROR(__xludf.DUMMYFUNCTION("""COMPUTED_VALUE"""),"Calchín") -> Calchín | J51: =IFERROR(__xludf.DUMMYFUNCTION("""COMPUTED_VALUE"""),5.0E7) -> 50000000
I52: =IFERROR(__xludf.DUMMYFUNCTION("""COMPUTED_VALUE"""),"Villa del Prado") -> Villa del Prado | J52: =IFERROR(__xludf.DUMMYFUNCTION("""COMPUTED_VALUE"""),5.0E7) -> 50000000
I53: =IFERROR(__xludf.DUMMYFUNCTION("""COMPUTED_VALUE"""),"Manfredi") -> Manfredi | J53: =IFERROR(__xludf.DUMMYFUNCTION("""COMPUTED_VALUE"""),5.0E7) -> 50000000
I54: =IFERROR(__xludf.DUMMYFUNCTION("""COMPUTED_VALUE"""),"San Joaquín") -> San Joaquín | J54: =IFERROR(__xludf.DUMMYFUNCTION("""COMPUTED_VALUE"""),3.0E7) -> 30000000
B56: CORDON CUNETA
B57: ='Base TOTAL'!AF2 -> ESTADO DEL EXPEDIENTE DE LA LOCALIDAD
B59: A ESPERA de DOC.TÉCNICA | C59: =COUNTIF('Base TOTAL'!AF:AF, B59) -> 11
B60: En CURSO en TÉCNICA | C60: =COUNTIF('Base TOTAL'!AF:AF, B60) -> 12
B61: COMPLETO en TÉCNICA | C61: =COUNTIF('Base TOTAL'!AF:AF, B61) -> 22
B62: En CURSO en TRIB.C | C62: =COUNTIF('Base TOTAL'!AF:AF, B62) -> 0
B63: APROBADO por TRIB.C | C63: =COUNTIF('Base TOTAL'!AF:AF, B63) -> 1
B64: OBRA en EJECUCIÓN | C64: =COUNTIF('Base TOTAL'!AF:AF, B64) -> 5
B65: OBRA TERMINADA | C65: =COUNTIF('Base TOTAL'!AF:AF, B65) -> 0
B70: CC Donde esta radicado el expediente por áreas dentro de la repartición
B71: Jurídico DGV | C71: =COUNTIF('Base TOTAL'!AI:AI, B71) -> 0
B72: DIRECCION DE JURISDICCION DE REGULARIZACION DE OBRAS Y PROYECTOS | C72: =COUNTIF('Base TOTAL'!AI:AI, B72) -> 20
B73: DIRECCION DE CONTADURIA - TRIBUNAL DE CUENTAS | C73: =COUNTIF('Base TOTAL'!AI:AI, B73) -> 0
B74: VOCALIA POR LA MINORIA - TRIBUNAL DE CUENTAS | C74: =COUNTIF('Base TOTAL'!AI:AI, B74) -> 1
B75: SUBDIR DE JUR. REGULARIZACION DE OBRAS URBANO HABITACIONALES | C75: =COUNTIF('Base TOTAL'!AI:AI, B75) -> 1
B76: DIRECCION DE JURISDICCION LEGAL Y NOTARIAL | C76: =COUNTIF('Base TOTAL'!AI:AI, B76) -> 17
B78: CC Proyecto, Planos, Còmputo y Presupuesto - Estado
B79: A ESPERA de DOC.TÉCNICA | C79: =COUNTIF('Base TOTAL'!P:P, B79) -> 8
B80: En Evaluación TÉCNICA | C80: =COUNTIF('Base TOTAL'!P:P, B80) -> 1
B81: A corregir por M/C | C81: =COUNTIF('Base TOTAL'!P:P, B81) -> 10
B82: A corregir por M/C | C82: =COUNTIF('Base TOTAL'!P:P, B82) -> 10
B83: Completo OK | C83: =COUNTIF('Base TOTAL'!P:P, B83) -> 30
B84: DIR. JUR. LEGAL Y NOTARIAL | C84: =COUNTIF('Base TOTAL'!P:P, B84) -> 0
B85: Completo OK | C85: =COUNTIF('Base TOTAL'!P:P, B85) -> 30
B90: CORDOBA HOGAR
B91: ='Base TOTAL'!BM2 -> CH ESTADO DEL EXPEDIENTE DE LA LOCALIDAD
B93: A ESPERA de DOC.TÉCNICA | C93: =COUNTIF('Base TOTAL'!BM:BM, B93) -> 4
B94: En CURSO en TÉCNICA | C94: =COUNTIF('Base TOTAL'!BM:BM, B94) -> 15
B95: COMPLETO en TÉCNICA | C95: =COUNTIF('Base TOTAL'!BM:BM, B95) -> 2
B96: En CURSO en TRIB.C | C96: =COUNTIF('Base TOTAL'!BM:BM, B96) -> 0
B97: APROBADO por TRIB.C | C97: =COUNTIF('Base TOTAL'!BM:BM, B97) -> 0
B98: OBRA en EJECUCIÓN | C98: =COUNTIF('Base TOTAL'!BM:BM, B98) -> 0
B99: OBRA TERMINADA | C99: =COUNTIF('Base TOTAL'!BM:BM, B99) -> 0
B101: TOTAL | C101: =SUM(C93:C99) -> 21

Sheet Base TOTAL
A2: LOCALIDAD / PROYECTO | B2: DEPARTAMENTO | C2: EXPEDIENTE N° | D2: N° Orden | E2: MUNICIPIO / COMUNA | F2: INTENDENTE / PRESIDENTE COMUNAL | G2: N° TELÉFONO M/C | H2: CORREO ELECTRÓNICO | I2: CONTACTO TÉCNICO de M/C | J2: CONVENIO - MONTO | K2: CONVENIO - Cordón Cuneta (ml) | L2: CONVENIO - Adoquinado (m2) | M2: DOC - Item 1 | N2: DOC - Item 2 | O2: DOC - Item 3 | P2: DOC - Item 4 | Q2: Descripción General | R2: Memoria Técnica | S2: Plazo de Ejecución | T2: Cómputo y Presupuesto | U2: Cronograma Avance Obra | V2: Planimetría | W2: Perfil Calzada | X2: Detalle de Cordón Cuneta | Y2: Detalle de Badén | Z2: Paquete estr. Calzada | AA2: DOC - Item 5 | AB2: DOC - Item 6 | AC2: DOC - Item 7 | AD2: DOC - Item 8 | AE2: DOC - Item 9 | AF2: ESTADO DEL EXPEDIENTE DE LA LOCALIDAD | AG2: OBSERVACIONES | AH2: EXP en FECHA | AI2: EXP en REPARTICIÓN | AJ2: Precio m2 cordon cuneta | AK2: Precio m2 adoquinado | AL2: OBRA Ant.Fin. Valor | AM2: OBRA Ant.Fin. fecha | AN2: OBRA Av.Fisico 40% Valor | AO2: OBRA Av.Fisico 40% Fecha | AP2: OBRA Av.Fisico 70% Valor | AQ2: OBRA Av.Fisico 70% Fecha | AR2: OBRA Av.Fisico 100% Valor | AS2: OBRA Av.Fisico 100% Fecha | AT2: OBRA OBSERVACIONES | AU2: CORDON CUNETA y ADOQUINES | AV2: CH CONVENIO MONTO | AW2: CH CONVENIO Cant. de Viv. | AX2: CH CONVENIO Nº Expediente | AY2: 1- Planimetría (Ubic. Obra) | AZ2: 2- Matrìcula de cada lote | BA2: 3- Estudio de Suelo | BB2: 4- Cert. de No inundabilidad | BC2: 5- Fact. Agua Potable | BD2: 6- Fac. Energìa Elèctrica | BE2: 7- Designaciòn Dir. T. Obra | BF2: 8- Memoria Téc. descriptiva | BG2: 9- Planos Legajo Técnico | BH2: 10- Pliego de Especif. Técnicas | BI2: 11- Cómputo y Presupuesto | BJ2: 12- Acta Mediciòn - Cert. | BK2: 13- Curva de Avance | BL2: 14- Cronograma de Avance | BM2: CH ESTADO DEL EXPEDIENTE DE LA LOCALIDAD | BN2: CH Observaciones | BO2: EST OBRA Anticipo financiero | BQ2: EST OBRA Avance físico 40% | BS2: EST OBRA Avance físico 70% | BU2: EST OBRA Avance físico 100% | BW2: EST OBRA OBSERVACIONES | BX2: CORDOBA HOGAR | BY2: ML CONVENIO MONTO | BZ2: ML CONVENIO Cantidad de Lotes | CA2: ML CONVENIO Nº Expediente | CB2: 1- Planimetría General | CC2: 2- Plano de Altimetría | CD2: 3- Plancheta Catastral | CE2: 4-Títulos | CF2: 5- Certificado de No Inundabilidad | CG2: 6- Informe de Ministerio de Ambiente y Economía Circular | CH2: 7- Factibilidad de Agua Potable | CI2: 8- Factibilidad de Energía Eléctrica | CJ2: 9- Certificado de Prestación de Servicios | CK2: 10- Factibilidad de Red Cloacal / Poszo Absorbente | CL2: 11- Designación de Representante Técnico | CM2: 12- Plano de Loteo Aprobado y Protocolizado | CN2: 13- Ordenanza / Resolución | CO2: 14- Proyectos de infraestructura a realizar | CP2: 14 RED VIAL | CQ2: 14 RED DE AGUA POTABLE | CR2: 14 RED ENERGÍA ELÉCTRICA - MEDIA Y BAJA TENSIÓN | CS2: 14 RED DE ALUMBRADO PÚBLICO | CT2: 14 NEXO DE AGUA | CU2: 14 NEXO ELÉCTRICO | CV2: ML ESTADO DEL EXPEDIENTE DE LA LOCALIDAD | CW2: ML OBSERVACIONES | CX2: MI LUGAR
A3: San Joaquín | B3: Presidente Roque Sáenz Peña | C3: 043-079116/2026 | D3: 1 | E3: C | F3: DANIEL PICCO | G3: (3385) 43-5407 | H3: Danielpicco66@hotmail.com | I3: mafer76_4@hotmail.com | J3: 30000000 | K3: 206 | M3: Completo OK | N3: Completo OK | O3: Completo OK | P3: Completo OK | Q3: Completo OK | R3: Completo OK | S3: Completo OK | T3: Completo OK | U3: Completo OK | V3: Completo OK | W3: Completo OK | X3: Completo OK | Y3: Completo OK | Z3: Completo OK | AA3: Completo OK | AB3: Completo OK | AC3: Completo OK | AD3: Completo OK | AE3: DIR. JUR. LEGAL Y NOTARIAL | AF3: En CURSO en TÉCNICA | AG3: 28/8/2026: Se reciben actualizac. 21/8/2026: Se re-envian por whatss las Observac. a correg a la nva profes. 21/08/2026: Se reciben actualiz. x el Presid. Comunal x whatss del A.Legal y se confecciona la planilla de Observ. para anexar cuando la nva prof. envie actualiz. Tecnicas. 20/8/2026: Se envìa mensaje al Int. preguntando si pudieron corregir las Observaciones para presentar la documentaciòn. 29/7/2026: Se envìa Planilla de Observ. a corregir por la comuna , al nvo profesional y a Infraestr. 28/7/2026: El municipio cambiò de profesional. Se le envìa el instructivo a la nueva arq. 22/7/2026: Se envìa nuevamente al Email las observaciones A corregir por la comuna 22/7/2026: El 14/7/2026 presentan documentaciòn a corregir nuevamente. 25/6/26: Comunicación con int. solicitando presenten correcciones. Se espera respuesta de la ing. a cargo. 19/6/26: Comunicaciòn con la ing. a cargo . Se solcita la presentaciòn a la mayor brevedad posible . 12-06-2026 Solicitar P Georef en Planim. + demas doc.Tec y leg 11/6/26: Se solicita nuevamente la correcciòn de Documentaciòn tècnica.Tiene todos los Items completos, salvo por el 4 (documentación técnica). El 29/5/26 se reclama la documentación firmada EL 19/05/26 PRESENTA PROYECTO CORREGIDO (A EVALUAR). EL 30/4 PRESENTAN NUEVO PRESUPUESTO, A VALOR $30.000.000. DEBE FUNDAMENTAR EL INCREMENTO EN EL MONTO TOTAL EL CÓMPUTO. El 30/04 se recibe y el monto que presenta es menor que el que se le da. Se pide que lo haga llegar al monto asignado El 28/04/26 se le envía documentación técnica modelo. EL 20/04/2026 LA COMUNA ENVÍA DOCUMENTACIÓN. FALTA INFO TÉCNICA. PRESENTA PRESUPUESTO, DE $21.969.370 - FALTA FIRMAS DE ÉSTE. EL 14/04/26 SE CONTACTÓ AL PRESIDENTE COMUNAL - | AH3: 46199 | AI3: DIRECCION DE JURISDICCION ECONOMICO, FINANCIERA Y DE ADMINISTRACION | AL3: =$J3*0.5 -> 15000000 | AN3: =$J3*0.25 -> 7500000 | AP3: =$J3*0.25 -> 7500000 | AR3: =$J3*0 -> 0 | AU3: TRUE | AY3: A ESPERA de DOC.TÉCNICA | AZ3: A ESPERA de DOC.TÉCNICA | BA3: A ESPERA de DOC.TÉCNICA | BB3: A ESPERA de DOC.TÉCNICA | BC3: A ESPERA de DOC.TÉCNICA | BD3: A ESPERA de DOC.TÉCNICA | BE3: A ESPERA de DOC.TÉCNICA | BF3: A ESPERA de DOC.TÉCNICA | BG3: A ESPERA de DOC.TÉCNICA | BH3: A ESPERA de DOC.TÉCNICA | BI3: A ESPERA de DOC.TÉCNICA | BJ3: A ESPERA de DOC.TÉCNICA | BK3: A ESPERA de DOC.TÉCNICA | BL3: A ESPERA de DOC.TÉCNICA | BO3: =$AV3*0.5 -> 0 | BQ3: =$AV3*0.25 -> 0 | BS3: =$AV3*0.25 -> 0 | BU3: =$AV3*0 -> 0 | BX3: FALSE | CB3: A ESPERA de DOC.TÉCNICA | CC3: A ESPERA de DOC.TÉCNICA | CD3: A ESPERA de DOC.TÉCNICA | CE3: A ESPERA de DOC.TÉCNICA | CF3: A ESPERA de DOC.TÉCNICA | CG3: A ESPERA de DOC.TÉCNICA | CH3: A ESPERA de DOC.TÉCNICA | CI3: A ESPERA de DOC.TÉCNICA | CJ3: A ESPERA de DOC.TÉCNICA | CK3: A ESPERA de DOC.TÉCNICA | CL3: A ESPERA de DOC.TÉCNICA | CM3: A ESPERA de DOC.TÉCNICA | CN3: A ESPERA de DOC.TÉCNICA | CO3: A ESPERA de DOC.TÉCNICA | CP3: A ESPERA de DOC.TÉCNICA | CQ3: A ESPERA de DOC.TÉCNICA | CR3: A ESPERA de DOC.TÉCNICA | CS3: A ESPERA de DOC.TÉCNICA | CT3: A ESPERA de DOC.TÉCNICA | CU3: A ESPERA de DOC.TÉCNICA | CV3: A ESPERA de DOC.TÉCNICA | CX3: FALSE
A4: La Población | B4: San Javier | C4: 0423-079121/2026 | D4: 2 | E4: C | F4: EDUARDO ROMERO | G4: (3544) 58-0485 | H4: _ | I4: Arq. Adriàn Heredia (3544) 434500 Alejandra Castro (011) 6185-9307 | J4: 75000000 | K4: 440 | L4: 870 | M4: Completo OK | N4: Completo OK | O4: Completo OK | P4: Completo OK | Q4: Completo OK | R4: Completo OK | S4: Completo OK | T4: Completo OK | U4: Completo OK | V4: Completo OK | W4: Completo OK | X4: Completo OK | Y4: Completo OK | Z4: Completo OK | AA4: Completo OK | AB4: Completo OK | AC4: Completo OK | AD4: Completo OK | AE4: Completo OK | AF4: COMPLETO en TÉCNICA | AG4: 14/8/2026: PASA A LEGALES con obser. corregidas. 13/8/2026: Se envian correcciones s/ la Ddjj por whatss al arq. 16/7/2026: PASA A LEGALES 14/7/2026: PASA A Coordinaciòn Administrativa 14-07-2026 Se solicito al arq. A. Heredia la presentac. s/ instr. de toda la doc. completa. 08-07-2026 Se solicita al arq. la Present. de toda la doc. corregida completa s/ intructivo (Como iniciar el tram.) 03-07-2026 Se reciben correcciones 03/7/2026: Se solicita al arq. corregir las observaciones (Faltan Georeferencias) 2026-07-01 Se solicito al arq. el complet. de geo ref en nota 3 y la firma del intend. en nota de ampliac. de doc. de georef. 2026-06-30 Se recibe modificacion parrafo Nota 5 solicitado al arq. --EXP. COMPLETO- 2026-06-30 Se recibe envio de Geo ref y se solicita modif. parrafo en nota 5 29/6/2026: Se reitera pedido de Geo-Ref. en Planim. Gral. 8/6/26 PASA DE AREA TECNICA A LEGALES // S-3-6-2026 Se observò desde Jurìdica falta en Punto Nª2 (son 3 firmas y falta..+ monto en la parte escrita) 3/6/2026 Se envió documentacion completa digital por email y lo recibiò Jurídica. COMPLETÓ documentación. Subió a Jurídico. Está en la Privada desde el 28/05/26 EL 20/05/26 SE APRUEBA LA PARTE TÉCNICA. SE SUBE A JURÍDICO PARA SU PROSECUCIÓN. EL 20/04/2026 LA COMUNA ENVÍA DOCUMENTACIÓN. FALTA INFO TÉCNICA. SE SOLICITA COMPLETAR LA MISMA. EL 14/04/26 SE CONTACTÓ AL PRESIDENTE COMUNAL - | AH4: 46254 | AI4: DIRECCION DE JURISDICCION LEGAL Y NOTARIAL | AL4: =$J4*0.5 -> 37500000 | AN4: =$J4*0.25 -> 18750000 | AP4: =$J4*0.25 -> 18750000 | AR4: =$J4*0 -> 0 | AU4: TRUE | BO4: =$AV4*0.5 -> 0 | BQ4: =$AV4*0.25 -> 0 | BS4: =$AV4*0.25 -> 0 | BU4: =$AV4*0 -> 0 | BX4: FALSE | CV4: A ESPERA de DOC.TÉCNICA | CX4: FALSE
A5: Del Campillo | B5: General Roca | C5: 0423-079098/2026 | D5: 3 | E5: M | F5: CARLA VILLANOVA | G5: (3583) 40-1420 | H5: Carla.villanova480@gmail.com | I5: Carlota.Bertorello@gmail.com | J5: 200000000 | L5: 7440 | M5: Completo OK | N5: Completo OK | O5: Completo OK | P5: Completo OK | Q5: Completo OK | R5: Completo OK | S5: Completo OK | T5: Completo OK | U5: Completo OK | V5: Completo OK | W5: Completo OK | X5: A ESPERA de DOC.TÉCNICA | Y5: A ESPERA de DOC.TÉCNICA | Z5: Completo OK | AA5: Completo OK | AB5: Completo OK | AC5: Completo OK | AD5: Completo OK | AE5: Completo OK | AF5: COMPLETO en TÉCNICA | AG5: 20/8/2026: PASA A LEGALES para prosecuciòn del tràmite. 11/8/2026: Se recibe doc. completa, avisa juridica que la doc. esta completa. Se envian al Email del prof. + intend. + infra. de las correcc. s/ la doc. presentada ayer 10/8/2026: Respuesta de arq: "Ya tengo todo hecho! Me falta armar los 3 pdf y pasarlosEstuve con mi bebé en Cba en el médico hasta ayer.. asique en lo que queda de la tarde no durante y el finde paso todo por mail" 30/7/2026: Se solicita a la arq. informe si pudieron avanzar con la documentaciòn. Respuesta: " estoy en Cba en el médico Asique hasta la semana que viene no voy a tener corregida la documentación /// Lunes o martes ya seguro que estoy pasando todo" 24/7/2026: Se envìa por Email las Observaciones A corregir por el municipio. 23/7/2026: La arq. envìa doc. tècnica en borrador para su evaluaciòn. 16/7/2026: Comunicaciòn con la arq. (Estuvo demorada por Maternidad) y dice que està preparando la documentaciòn para presentar. - 22-06-2026 : Comunicaciòn con int. Se espera doc. tècnica y listo para dar continuidad al tràmite. - 19-06-2026 Se solicitan a la intend. Carla los siguientes: (Faltan en Planimetria Gral. las Geo ref. sobre las diferentes ubic. de obra + ampliar sobre la misma los nombres de las calles no se visualizan + corte paquete estr. de la calzada + detalles de baden s/ modelo) - 18-06-2026 Se envian al whats de intendenta y al mail los faltantes, correcciones y Modelo --RTAS.; Se recibe toda la doc. 4/6/2026 CB - VVVVVV 4/6/2026 HS - la documentacion tecnica tiene observaciones en el computo. esperaremos la vuelta desde jurídico. COMPLETÓ documentación. Subió a Jurídico Con V°B°. ARCHIVADO EL 13/05/26 EL 14/04/26 SE CONTACTÓ A LA INTENDENTE, LA CUAL ENVIÓ POSTERIORMENTE DOCUMENTACIÓN. SE SOLICITÓ EL COMPLETAMIENTO DE ITEM 4. COMPLETÓ PASADO CON V°B° TÉCNICA | AH5: 46227 | AI5: AREA COORDINACION ADMINISTRATIVA | AL5: =$J5*0.5 -> 100000000 | AN5: =$J5*0.25 -> 50000000 | AP5: =$J5*0.25 -> 50000000 | AR5: =$J5*0 -> 0 | AU5: TRUE | BO5: =$AV5*0.5 -> 0 | BQ5: =$AV5*0.25 -> 0 | BS5: =$AV5*0.25 -> 0 | BU5: =$AV5*0 -> 0 | BX5: FALSE | CV5: A ESPERA de DOC.TÉCNICA | CX5: FALSE
A6: San Javier y Yacanto | B6: San Javier | C6: 0423-079118/2026 | D6: 4 | E6: M | F6: SEGUNDO MARTÍN GARCÍA | G6: (3544) 53-4283 | H6: garciam.s078@gmail.com | I6: Arq. Adriàn Heredia (3544) 434500 | J6: 200000000 | L6: 1823 | M6: Completo OK | N6: Completo OK | O6: Completo OK | P6: Completo OK | Q6: Completo OK | R6: Completo OK | S6: Completo OK | T6: Completo OK | U6: Completo OK | V6: Completo OK | W6: Completo OK | X6: Completo OK | Y6: Completo OK | Z6: Completo OK | AA6: Completo OK | AB6: Completo OK | AC6: Completo OK | AD6: Completo OK | AE6: Completo OK | AF6: COMPLETO en TÉCNICA | AG6: 14/8/2026: PASA A LEGALES con las obs. corregidas. 13/8/2026: Se envìan por whatss al arq. correcc sobre DDJJ 17/7/2026: PASA A LEGALES 16/7/2026: Se solicitò al arq. que corrijan y se dio aviso al int. Presentan por Email y se da curso al tràmite. 16/7/2026: Se pidio al arq. modif. solo geo ref. en Declarac. Jurada y re envie todo s/ instr. 15/7/2026: PASO A Coordinaciòn administrativa 14/7/26 14/7/2026: Se insiste al arq. que envìen la documentacion requerida. 03/7/2026: Se solicita al arq. y por Email municipio, corregir las observaciones (Faltan Georeferencias) 01-07-2026 - Se solicita al arq. Las Geo-Referenc. y la modicific. de la Nota Pto. 5 sacar ante ult. parrafo. 9/6/26 PASA DE AREA TECNICA A LEGALES. -04-06-2026 -(En Pto. 1 Nota Financ sacar la expres. vereda peinada y colocar tambien medida del cordòn en ml + en el Pto. 4 en el Comp. Metr. poner la medida del cordòn cunet. en ml) 3/6/2026 Se envió documentacion completa digital por email y fue recibida por Jurídica. COMPLETÓ documentación. Subió a Jurídico. Está en la Privada desde el 28/05/26 El 05/05/26 presentó la documentación, se exede en el montoasignado de $200.000.000 en $304.840 (se lo llama para que cambie) EL 16/04/26 VINO PERSONALMENTE EL INTENDENTE, MOSTRANDO INTERÉS. EL 14/04/26 SE CONTACTÓ AL INTENDENTE. | AH6: 46254 | AI6: DIRECCION DE JURISDICCION LEGAL Y NOTARIAL | AL6: =$J6*0.5 -> 100000000 | AN6: =$J6*0.25 -> 50000000 | AP6: =$J6*0.25 -> 50000000 | AR6: =$J6*0 -> 0 | AU6: TRUE | BO6: =$AV6*0.5 -> 0 | BQ6: =$AV6*0.25 -> 0 | BS6: =$AV6*0.25 -> 0 | BU6: =$AV6*0 -> 0 | BX6: FALSE | CV6: A ESPERA de DOC.TÉCNICA | CX6: FALSE
A7: Cavanagh | B7: Marcos Juárez | C7: 0423-079101/2026 | D7: 5 | E7: M | F7: GUSTAVO DAL BO | G7: (3468) 64-7760 | H7: municavanagh@alejotv.com.ar | I7: richardquinn68@hotmail.com | J7: 300000000 | L7: 9635.3 | M7: Completo OK | N7: Completo OK | O7: Completo OK | P7: Completo OK | Q7: Completo OK | R7: Completo OK | S7: Completo OK | T7: Completo OK | U7: Completo OK | V7: Completo OK | W7: Completo OK | X7: A ESPERA de DOC.TÉCNICA | Y7: A ESPERA de DOC.TÉCNICA | Z7: Completo OK | AA7: Completo OK | AB7: Completo OK | AC7: Completo OK | AD7: Completo OK | AE7: Completo OK | AF7: COMPLETO en TÉCNICA | AG7: 21/7/2026: Pregunta la secretaria del int. por el tràmite. Se informa que se le diò curso. 20/7/2026: PASA A LEGALES para prosecuciòn del tràmite. 20/7/2026: El Viernes se solicitò al int. y al ing. a cargo que completen la parte tècnica para dar curso al expte. 25-6-26: Comunicaciòn con Int. Solicita el Instructivo, se envìa. 10/6/2026: Se envìa doc. al arq. R. Quin para su correcc. x whatss P-10/6/2026: Se solicita al Municipio el contacto del ingeniero para enviar nuevamente lo que deben corregir P- 09-6-2026 Hablar con el intendente para avisar que este Progr. no contempla el asfaltado......-Pto. 1 -corregir nombre del Programa y plazo de ejecucion a 6 meses + Pto. 2 - No tiene el sello y firma de tesorero + Pto. 3 - corregir la denominaciòn del Programa + Pto. 7 el cuil presentado fue el del intend. No de la municipal. ? + 4/6/26:Presentan documentaciòn por Cidi- En Evaluación TÉCNICA. EL 14/04/2026 SE CONTACTÓ AL INTENDENTE… QUEDÓ EN HABLAR, NO LO HIZOº | AH7: 46224 | AI7: DIRECCION DE JURISDICCION LEGAL Y NOTARIAL | AJ7: 44521.2 | AK7: 30927.5 | AL7: =$J7*0.5 -> 150000000 | AN7: =$J7*0.25 -> 75000000 | AP7: =$J7*0.25 -> 75000000 | AR7: =$J7*0 -> 0 | AU7: TRUE | BO7: =$AV7*0.5 -> 0 | BQ7: =$AV7*0.25 -> 0 | BS7: =$AV7*0.25 -> 0 | BU7: =$AV7*0 -> 0 | BX7: FALSE | CV7: A ESPERA de DOC.TÉCNICA | CX7: FALSE
A8: Capitán General Bernardo O'Higgins | B8: Marcos Juárez | C8: 0423-079103/2026 | D8: 6 | E8: M | F8: NORA BESSONE | G8: (3468) 56-1281 | H8: nora_bessone@hotmail.com | I8: muniohiggins@hotmail.com | J8: 200000000 | M8: Completo OK | N8: Completo OK | O8: Completo OK | P8: A corregir por M/C | Q8: Completo OK | R8: Completo OK | S8: A corregir por M/C | T8: Completo OK | U8: Completo OK | V8: Completo OK | W8: Completo OK | X8: Completo OK | Y8: A ESPERA de DOC.TÉCNICA | Z8: A ESPERA de DOC.TÉCNICA | AA8: Completo OK | AB8: A corregir por M/C | AC8: Completo OK | AD8: Completo OK | AE8: Completo OK | AF8: En CURSO en TÉCNICA | AG8: 20/8/2026: Se envìa mensaje a la Int. preguntando si pudieron completar la documentaciòn. 28/7/2026: Se envìan por Email Observaciones a corregir por la comuna, al arq. e infra. RTA de arq. P. Lapentta: Hola... Bien! Habia visto esos detalles pero pense que con lo que presentaba era suficiente. Ya los completaré. 23/7/2026: Comunicaciòn con el arq. para corregir las observaciones. Se envìa Email con Instructivo. 22/7/2026: Se envìan por Email las observaciones a corregir por el M-C 13/7/2026: Presentan nuevamente la documentaciòn En evaluaciòn areas legal y tècnica. 25-6-26: Comunicaciòn con int. y arq. para completen Georeferencia. 19/6/2026 se envian observaciones por email para corregir y completar. 18/6/26: Comunicación con el municipio para enviar Instructivo. EL 16/04/26 SE CONTACTÓ A LA INTENDENTE. EL 29/04/26 NOS VISITÓ Y CONSULTÓ. VA A ENVIAR DOCUMENTACIÓN | AH8: 46126 | AI8: DIRECCION DE JURISDICCION DE REGULARIZACION DE OBRAS Y PROYECTOS | AJ8: 76420.22 | AK8: 47876.29 | AL8: =$J8*0.5 -> 100000000 | AN8: =$J8*0.25 -> 50000000 | AP8: =$J8*0.25 -> 50000000 | AR8: =$J8*0 -> 0 | AU8: TRUE | BO8: =$AV8*0.5 -> 0 | BQ8: =$AV8*0.25 -> 0 | BS8: =$AV8*0.25 -> 0 | BU8: =$AV8*0 -> 0 | BX8: FALSE | CV8: A ESPERA de DOC.TÉCNICA | CX8: FALSE
A9: La Higuera | B9: Cruz del Eje | C9: 0423-079115/2026 | D9: 7 | E9: C | F9: DANIEL MANZANELLI | G9: (3542) 47-0003 | H9: Comunalahiguera01@gmail.com | I9: Ing. Bracamonte 3521401659 ---ingbracamontegustavo@gmail.com | J9: 100000000 | K9: 313.3 | L9: 704.93 | M9: Completo OK | N9: Completo OK | O9: Completo OK | P9: Completo OK | Q9: Completo OK | R9: Completo OK | S9: Completo OK | T9: Completo OK | U9: Completo OK | V9: Completo OK | W9: Completo OK | X9: Completo OK | Y9: Completo OK | Z9: Completo OK | AA9: Completo OK | AB9: Completo OK | AC9: Completo OK | AD9: Completo OK | AE9: Completo OK | AF9: COMPLETO en TÉCNICA | AG9: 12/8/2026: El Secretario consulta s/la doc. enviada y se avisa que PASO A LEGALES el 29-07 para su prosecuciòn 29/7/2026: PASA A LEGALES para prosecuciòn del tràmite. 22/7/2026: Se envìa PLA. Observaciones a corregir. 22/7/2026: Presentan documentaciòn a evaluar. 21/7/2026: Escriben consultando por el Email. Se solicita Correo electrònico 13-07-2026 Se llamo al ing. quien avisa que hoy envia doc. a la firma de la comuna y mañana nos envian por mail. 13/7/2026: Se solicita a la comuna y al ing. informen si puedieron avanzar con la documentaciòn. 13/7/2026: Se solicita a la comuna y al ing. informen si puedieron avanzar con la documentaciòn. 30-06-2026 Se reitera actualiz y completar docum. s/ instr. 26/6/2026: holaaaaaa 26/6/26: Se solicita al Ing. que complete la documentaciòn requerida conforme al Instructivo. 24/6/26: Se insiste y se hace un llamado al pres. comunal. Envìa datos por wathsapp. 22/6/26: Se solicita correo electrònico y datos del profesional para enviar instructivo. Sin respuesta 12-05-2026 Se envia las correcciones de la documentac. tecnica y la nota inial ( via whatsapp a Gonzalo Guzman El 30/04/2026 envían documentación de los items 1 a 5 para ver EL MARTES 28/04/26 SE HABLÓ POR TELÉFONO Y POR WHATSAPP, DONDE SE LE ENVIÓ LOS 9 PUNTOS Y SE COMPROMETIÓ EN DAR RESPUESTA. | AH9: 46245 | AI9: DIRECCION DE JURISDICCION ECONOMICO, FINANCIERA Y DE ADMINISTRACION | AJ9: 53000 | AK9: 67000 | AL9: =$J9*0.5 -> 50000000 | AN9: =$J9*0.25 -> 25000000 | AP9: =$J9*0.25 -> 25000000 | AR9: =$J9*0 -> 0 | AU9: TRUE | BO9: =$AV9*0.5 -> 0 | BQ9: =$AV9*0.25 -> 0 | BS9: =$AV9*0.25 -> 0 | BU9: =$AV9*0 -> 0 | BX9: FALSE | CV9: A ESPERA de DOC.TÉCNICA | CX9: FALSE
A10: Las Playas | B10: Cruz del Eje | C10: 0423-079112/2026 | D10: 8 | E10: C | F10: MARÍA DANIELA GODOY | G10: (3549) 46-8032 | H10: Danielagodoy79@gmail.com | I10: Ing. Bracamonte 3521401659 ---ingbracamontegustavo@gmail.com | J10: 200000000 | L10: 3922.22 | M10: Completo OK | N10: Completo OK | O10: Completo OK | P10: Completo OK | Q10: Completo OK | R10: Completo OK | S10: Completo OK | T10: Completo OK | U10: Completo OK | V10: Completo OK | W10: Completo OK | X10: A ESPERA de DOC.TÉCNICA | Y10: Completo OK | Z10: Completo OK | AA10: Completo OK | AB10: Completo OK | AC10: Completo OK | AD10: Completo OK | AE10: Completo OK | AF10: COMPLETO en TÉCNICA | AG10: 23/7/2026: PASA A Coor. Adm. para prosecuciòn del tràmite. 17/7/2026: Se recibe doc. por Email 14/7/2026: Se envìa por Email a la comuna y profesional a cargo, las observaciones a corregir nuevamente. 13-7-2026: Se recibe de la intend. doc. por whast y se solicita que se envie en base a instructivo y por E mail. A evaluar por àreas legal y tècnica. 13-7-2026: Se llamo al ing. quien avisa que el viernes enviò la doc. a la municip y mañana la envian firmada 13/7/2026: Se solicita informen còmo van con la documentaciòn a presentar. 29/6/2026: Se enviaron por Email las observaciones A corregir por la comuna 26/6/26: Se envían las observaciones a corregir por el ing. Se aguardan las observaciones del area Legales........22/6/26: El ing. se comunica con el àrea tècnica: Se le envìa el Instructivo de la documentaciòn legal y tècnica a presentar. 19/6/26: Sin respuesta del ing. a cargo, se envìa nuevamente el instructivo a la Pres. comunal. 11/6/26: Se solicita corregir documentación presentada. SE LE ENVIÓ LOS 9 REQUISITOS PARA PARTICIPAR EN EL PROGRAMA | AH10: 46227 | AI10: DIRECCION DE JURISDICCION LEGAL Y NOTARIAL | AL10: =$J10*0.5 -> 100000000 | AN10: =$J10*0.25 -> 50000000 | AP10: =$J10*0.25 -> 50000000 | AR10: =$J10*0 -> 0 | AU10: TRUE | BO10: =$AV10*0.5 -> 0 | BQ10: =$AV10*0.25 -> 0 | BS10: =$AV10*0.25 -> 0 | BU10: =$AV10*0 -> 0 | BX10: FALSE | CV10: A ESPERA de DOC.TÉCNICA | CX10: FALSE
A11: Luyaba | B11: San Javier | C11: 0423-079120/2026 | D11: 9 | E11: C | F11: MAXIMILIANO PEREYRA | G11: (3544) 56-7381 | H11: Hectormaximilianopereyra@gmail.com | I11: Arq. Adriàn Heredia (3544) 434500 | J11: 150000000 | K11: 300 | L11: 2050 | M11: Completo OK | N11: Completo OK | O11: Completo OK | P11: Completo OK | Q11: Completo OK | R11: Completo OK | S11: Completo OK | T11: Completo OK | U11: Completo OK | V11: Completo OK | W11: Completo OK | X11: Completo OK | Y11: Completo OK | Z11: Completo OK | AA11: Completo OK | AB11: Completo OK | AC11: Completo OK | AD11: Completo OK | AE11: Completo OK | AF11: OBRA en EJECUCIÓN | AG11: 07/8/2026: Se pagò A.F. 30/7/26 27/7/2026: PASA A Economico para pago de Cert. A. F. 15/7/2026: Se envió a la comuna Modelos de NOTA y CERT. para cobro de ANT. FINANCIERO y dar inicio a la Obra. 8/6/26 PASA DE AREA TECNICA A LEGALES // P -04-06-2026 -(En el Pto. 4 en el Comp. Metr. poner la medida del cordòn cunet. en ml) 3/6/2026 Se envió documentacion completa digital por email y lo recibiò Jurídica. 2/6/2026 corregido pasa a juridico El 27/05/2026 el municipio presentó el total de la información. APROBADA LA PARTE TÉCNICA. Debe corregir y presentar la Nota a Contaduría Gral y la DDJJ con firma clara 19/05/26 se aprueba la Parte Técnica. El 27/05/26 se recibe nueva documentación. 28/05/26 se pide que cambie nota a la contaduría y se le envía la nueva para que firme El 8/5/26 se le envió documentación modelo. Se recibió documenación de parte de la Comuna. La misma está en proceso de estudio y análisis. El | AH11: 46217 | AI11: DIRECCION DE JURISDICCION DE REGULARIZACION DE OBRAS Y PROYECTOS | AL11: =$J11*0.5 -> 75000000 | AM11: 46233 | AN11: =$J11*0.25 -> 37500000 | AP11: =$J11*0.25 -> 37500000 | AR11: =$J11*0 -> 0 | AT11: 19/8/2026: Comunicaciòn telefònica con Pres.Com. Informa que estàn por comprar los adoquines. Tambièn informa que el Gobernador anunciò una obra para la Plaza principal para inaugurarse en las Fiestas patronales (24/9). La misma empresa que està trabajando en la plaza, realizarà el adoquinado. | AU11: TRUE | BO11: =$AV11*0.5 -> 0 | BQ11: =$AV11*0.25 -> 0 | BS11: =$AV11*0.25 -> 0 | BU11: =$AV11*0 -> 0 | BX11: FALSE | CV11: A ESPERA de DOC.TÉCNICA | CX11: FALSE
A12: Villa Valeria | B12: General Roca | C12: 0423-079095/2026 | D12: 10 | E12: M | F12: CLAUDIO MELERO | G12: (3583) 43-9116 | H12: munivvaleria@yahoo.com.ar | I12: daihana.toledano11@gmail.com | J12: 350000000 | L12: 5000 | M12: Completo OK | N12: Completo OK | O12: Completo OK | P12: Completo OK | Q12: Completo OK | R12: Completo OK | S12: Completo OK | T12: Completo OK | U12: Completo OK | V12: Completo OK | W12: Completo OK | X12: Completo OK | Y12: Completo OK | Z12: Completo OK | AA12: Completo OK | AB12: Completo OK | AC12: Completo OK | AD12: Completo OK | AE12: Completo OK | AF12: OBRA en EJECUCIÓN | AG12: 16/7/2026: Se envían Modelos de NOTA y CERT. cobro de ANT. FINANCIERO y dar inicio a la Obra. 03/7/2026: PASO A LEGALES 10/6/2026 COMPLETÓ documentación. Subió a Jurídico Con V°B°. ARCHIVADO EL 13/05/26 El 12/5/26 se le envía "devolución" con correcciones de la documentación técnica presentada. COMPLETO. PASADO CON V°B° DE TÉCNICA. EL 30/04/26, EL INTENDENTE ENVÍA DOCUMENTACIÓN, QUE ESTÁ SIENDO ANALIZADA. DEBE COMPLETAR PUNTO 4, DE DOC. TÉCN. | AH12: 46217 | AI12: SUBDIR DE JUR. REGULARIZACION DE OBRAS URBANO HABITACIONALES | AL12: =$J12*0.5 -> 175000000 | AM12: 46238 | AN12: =$J12*0.25 -> 87500000 | AP12: =$J12*0.25 -> 87500000 | AR12: =$J12*0 -> 0 | AT12: 04/9/2026: Està previsto viajar el Martes 8/9/2026 a Villa Valeria para constatar el Avance. (El Municipio avisa que casi ya terminaron) La nueva arq. solicita colaboraciòn y se elabora la Certificaciòn en esta Area Tècnia. Se consulta a Silvia còmo se debe presentar la Certificaciòn (Estàn realizados dos certificados: 40 % y 70%) 01/9/2026: Se envían nuevamente a la arq. las Observaciones A Corregir . 31/8/2026: Se llama a la arq. para saber si ya corrigieron el Certificado. Dice: En media hora lo envìo. 28/8/2026: Se envìa al Munic. las Correciones sobre el Cert. Nº 1 y el modelo de DDJJ designaciòn de profesional (Hay una nueva arq. ) 26/8/2026: Ayer se le explicò a la nueva arquitecta còmo debe hacer el certificado de Avance (40%) , dijo que hoy lo presentaba. Se le envìa mensaje de wahtsapp para preguntar si pudo hacerlo. 07/8/2026: Se pagò A.F. el 4/8/2026 19/8/2026: Comunicaciòn telefònica con el Int. Informa que ya avanzaron con 4 cuadras de adoquines y continuan con otras tareas. | AU12: TRUE | BO12: =$AV12*0.5 -> 0 | BQ12: =$AV12*0.25 -> 0 | BS12: =$AV12*0.25 -> 0 | BU12: =$AV12*0 -> 0 | BX12: FALSE | CV12: A ESPERA de DOC.TÉCNICA | CX12: FALSE
A13: Villa Huidobro | B13: General Roca | C13: 0423-079097/2026 | D13: 11 | E13: M | F13: ENZO QUIROGA | G13: (2302) 45-3904 | H13: mvhuidobro@gmail.com | I13: arqmariasolcastelli2024@gmail.com | J13: 200000000 | K13: 1100 | M13: Completo OK | N13: Completo OK | O13: Completo OK | P13: Completo OK | Q13: Completo OK | R13: Completo OK | S13: Completo OK | T13: Completo OK | U13: Completo OK | V13: Completo OK | W13: Completo OK | X13: Completo OK | Y13: Completo OK | Z13: A ESPERA de DOC.TÉCNICA | AA13: Completo OK | AB13: Completo OK | AC13: Completo OK | AD13: Completo OK | AE13: Completo OK | AF13: COMPLETO en TÉCNICA | AG13: 23/7/2026: PASA A Coor. Adm. para prosecuciòn del tràmite. 22/7/2026: presentan nuevamente la dcoumnetacion. 08-7-2026 Se recibe por mail la doc. solicitada (solo el Cuil sale borroso mientras que en presentac. ant. sale bien) y se eleva a legales para su revisiòn 07-07-2026 Se tomo contacto con la arqta. Sol Castelli para acordar la presentac. de toda la doc. actualiz de manera ordenada 30-06-26 Se Responde a las dudas planteadas x el profes. x whatss 29/6/2026: Se recibe documentacion y se re envìan las correcciones 24-06-2026 -- Nos desarrollan consultas y se re envian por whats datos a completar y corregir 23-06-26 Se envian correc. 19-06-2026 Pto 6 -Re enviar CBU esta cortada la imag. + TECnica adecuar cronogr. de avance de Ob. a 6 meses y en todo escrito de la memoria que mencione plazos + nota 1 en los datos del pavimento articulado colocar medida en ML Y el Plazo de ejecucion de obra llevarlo a 6 meses + llevar los 6 meses al desarrollo de la planilla del cronogra de avances de obras + en Planim. Gral. colocar las Geo refer. y cotas ancho y largo de calles en desarr. de obra ) 9/6/26: Presentan documentación nuevamente a evaluar . 8/6/26: Se envía Instructivo (Doc. Requerida) a la localidad. El 05/05/26 se envía documentación Modelo que ayuda al completamiento y corrección de la misma. SI BIEN EL MUNPICIPIO CORRIGIÓ Y ENVIÓ CON AJUSTES EL PRESUPUESTO, DEBE ACLARAR ITEMS DE LA PARTE TÉCNICA PARA ADECUAR A MONTO CONFORMADO. | AH13: 46227 | AI13: DIRECCION DE JURISDICCION LEGAL Y NOTARIAL | AL13: =$J13*0.5 -> 100000000 | AN13: =$J13*0.25 -> 50000000 | AP13: =$J13*0.25 -> 50000000 | AR13: =$J13*0 -> 0 | AU13: TRUE | BO13: =$AV13*0.5 -> 0 | BQ13: =$AV13*0.25 -> 0 | BS13: =$AV13*0.25 -> 0 | BU13: =$AV13*0 -> 0 | BX13: FALSE | CV13: A ESPERA de DOC.TÉCNICA | CX13: FALSE
A14: La Paz | B14: San Javier | C14: 0423-079119/2026 | D14: 12 | E14: M | F14: RAMÓN RUFINO FUNES | G14: (3544) 44-0352 | H14: secgoblapaz@gmail.com | I14: Arq. Adriàn Heredia (3544) 434500 | J14: 300000000 | K14: 930 | L14: 2795 | M14: Completo OK | N14: Completo OK | O14: Completo OK | P14: Completo OK | Q14: Completo OK | R14: Completo OK | S14: Completo OK | T14: Completo OK | U14: Completo OK | V14: Completo OK | W14: Completo OK | X14: Completo OK | Y14: Completo OK | Z14: Completo OK | AA14: Completo OK | AB14: Completo OK | AC14: Completo OK | AD14: Completo OK | AE14: Completo OK | AF14: COMPLETO en TÉCNICA | AG14: 03/8/2026: Se agregaron las georeferencias solicitadas. PASA A LEGALES 23/7/2026: Comunicaciòn con el municipio explicando còmo deben corregir lo observado. 22/7/2026: NO corrigen, y presentan lo mismo - 22/7/2026: Presentan documentaciòn nuevamente. 17/7/2026: Se recibe docum. segun instruct. 15/7/2026: Se solicita al arq. completar nuevas correcc. 08-07-2026 Se solicita al arq. la Present. de toda la doc. corregida completa s/ intructivo (Como iniciar el tram.) y Se resaltan completar detalles en esta present. ( Pto 2 que lleve ademas las firmas y sellos del tesorero e intend. + en Ptol 3 En la declar. Jurada si es el domic. real esquina sacar el S/N si no colocar las georef del mismo + en la Memoria Pto 3 plazo colocar s/ instruc. ) 30/6/2026: Expte. PASA A LEGALES 29/6/2026: Documentaciòn en orden para anexar al Expte. y dar curso. /// 23-06-2026 - Completo toda la doc. ( se recibe detalle de baden) 22-06-2026 - Solo falta detalle de baden se lo pedimos y le enviamos modelo al arq. Adrian RTA.: Enviado 19/6/26: Se solicita al arq. que presenta la documentaciòn a la mayor brevedad. 12-06-2026 -- Se solicita al arq. Adrian actualiz. correcc. -RTAS.: 11-06-2026 TEC.: ( solo falta det. baden ancho + paquete estruct. de calz + Geo ref. en Pl.gral) 04-06-2026 - Se tilda al Pto. Nª 4 (para que se modifique la unidad del cordon cun. a ml en el CM) EL 28/04/26 SE LE ENVÍA LOS REQUISITOS, VA A ENVIAR DOCUMENTACIÓN | AH14: 46245 | AI14: DIRECCION DE JURISDICCION LEGAL Y NOTARIAL | AL14: =$J14*0.5 -> 150000000 | AN14: =$J14*0.25 -> 75000000 | AP14: =$J14*0.25 -> 75000000 | AR14: =$J14*0 -> 0 | AU14: TRUE | BO14: =$AV14*0.5 -> 0 | BQ14: =$AV14*0.25 -> 0 | BS14: =$AV14*0.25 -> 0 | BU14: =$AV14*0 -> 0 | BX14: FALSE | CV14: A ESPERA de DOC.TÉCNICA | CX14: FALSE
A15: Guanaco Muerto | B15: Cruz del Eje | C15: 0423-079111/2026 | D15: 13 | E15: C | F15: MAYCO SORIA | G15: (3549) 44-0455 | H15: maycosoria19@gmail.com | I15: ingbracamontegustavo@gmail.com | J15: 50000000 | K15: 100 | L15: 390 | M15: Completo OK | N15: Completo OK | O15: A corregir por M/C | P15: A corregir por M/C | Q15: A corregir por M/C | R15: Completo OK | S15: Completo OK | T15: A corregir por M/C | U15: A corregir por M/C | V15: Completo OK | W15: Completo OK | X15: Completo OK | Y15: A ESPERA de DOC.TÉCNICA | Z15: Completo OK | AA15: Completo OK | AB15: Completo OK | AC15: A corregir por M/C | AD15: A corregir por M/C | AE15: Completo OK | AF15: En CURSO en TÉCNICA | AG15: 03/9/2026: Se reciben actualiz. por mail del presid. comunal (se avisa x whatss que el monto del computo debe coincidir con el monto total autoriz) 31/8/2026: Se re envian correcc al Presid. Com + prof. + infra x mail 26/8/2026: Se reitera nuevamente al ing. Bracamonte x mail la la correccion antes solicitada de agregar el ITems pto. 1,3 al computo y demas doc. derivadas del mismo 25/8/2026: Presentan actualiz. 21/8/2026: Se reitera el pedido de correcciones. 14/8/2026: Se responde Mail al ing. solicitando item1.3 en Computo y Avance.. 10/8/2026: Se envìa x mail Observaciones a corregir por presid. Comunal + profes. + infra 07/8/2026: Presentan nuevamente docum. a evaluar 05/8/2026: La Comuna tenìa una consulta para el àrea Legal, se les pregunto y se enviò la respuesta. Se aguarda la documentaciòn corregida. 04/8/2026: Se solicita a la comuna informen si pudieron corregir la documentaciòn. 22/7/2026: Se envìan Observaciones A corregir por Comuna 20/7/2026: Se recibe documentaciòn el 17/7. En evaluaciòn area Legales. 18/6/26: Se envìa Instructivo de documentaciòn legal y tècnica a presentar por M-C. EL 29/04/26 SE LE ENVÍA LOS REQUISITOS, VA A ENVIAR DOCUMENTACIÓN Completó el punto 4. Se le envió el 29/04/26 los restantes items para completar Expte. | AH15: 46126 | AI15: DIRECCION DE JURISDICCION DE REGULARIZACION DE OBRAS Y PROYECTOS | AL15: =$J15*0.5 -> 25000000 | AN15: =$J15*0.25 -> 12500000 | AP15: =$J15*0.25 -> 12500000 | AR15: =$J15*0 -> 0 | AU15: TRUE | BO15: =$AV15*0.5 -> 0 | BQ15: =$AV15*0.25 -> 0 | BS15: =$AV15*0.25 -> 0 | BU15: =$AV15*0 -> 0 | BX15: FALSE | CV15: A ESPERA de DOC.TÉCNICA | CX15: FALSE
A16: Villa Sarmiento | B16: General Roca | C16: 0423-079096/2026 | D16: 14 | E16: C | F16: OSVALDO ESTRADA | G16: (3583) 43-0074 | H16: oestradacomunavillasarmiento@gmail.com | I16: rojobufa@gmail.com | J16: 210000000 | K16: 1530 | L16: 1575 | M16: Completo OK | N16: Completo OK | O16: Completo OK | P16: Completo OK | Q16: Completo OK | R16: Completo OK | S16: Completo OK | T16: Completo OK | U16: Completo OK | V16: Completo OK | W16: Completo OK | X16: Completo OK | Y16: Completo OK | Z16: Completo OK | AA16: Completo OK | AB16: Completo OK | AC16: Completo OK | AD16: Completo OK | AE16: Completo OK | AF16: COMPLETO en TÉCNICA | AG16: 06/8/2026: PASA A LEGALES para prosecuciòn del tràmite. 30/7/2026: Se recibe completamiento 30/7/2026: Se envìan detalles a completar x whatss al profes + mail al prof., al intend. e infra. Se recibe doc. corregida 27-07-2026 Se re envian correcc. al arq. por mail y whatss y mail al int e infra 17/7/2026: Se recibe doc y se envia a legales 15/7/2026: Se solicita al arq. nuevas correc y completam. 03-07-2026 Completar: - Pto. 3 en Declarac. Jurada y.... Se deberà colocar las Geo Referenc. en los domicilios que figuren como (calle Publica sin Numero y tambien en los de Zona Rural) - En la Memoria pto. 3 colocar PLAZO de OBRA (Ver instruct.) -En ambas PLANIM. Generales colocar (Geo Referenc. y Medidas generales Largo y ancho de las calles del proyecto). - Presentar DETALLE Perfil Transversal de Calzada) Ver instructivo. - 30/6/2026: Se solicito por email envien imagen de DNI y CBU con mas definicion. el resto de la documentación esta completa. 19-06-2026- Se solicita al arq. Buffa ( 1CBU Y2 DNI borrosos + 3Sobre las Planim. Gral coloque las Geo Refer de los 3 sectores de obra + 4 faltan Perfil transv de calzada ) 12-06-2026 Se pidio al arq. R.Buffa estos faltantes + Georef. en pl. gral. --RTA.: 11-06-2026 de esta correc. solo faltan en TECNICA (agregar cortes transv. de calz. + detalle de paquete estr. de calz + detalles de cordones cun y badenes lo demas correcto) + en LEG ( en Nota contad pto 5 cambiar el plazo a 180 dias) -22-06-2026 - 04-06-2026 - Deben completar (Pto 4- graficos Detalles de Perfiles transv. de calzada + detalle graf. de cordon cuneta + secc transv. de de vaden + Pto. Nª 9 Acta de proclamac cantidad de votos?..Preguntar a Natalia) Ya ajustó los montos… Pasó $236.529.986,60 y debe ser de $210.000.000 - Debe cambiar Nota Inicial, dice plazo obra 365 días y debe decir 180 días El 29/05/26 ingresa nva. Nota digi 0697832111-126 (La parte técnica ya está ok - Pero falta cambiar: Plazo de Obra, en Nota inicial) YA LO CAMBIÓ Y ENVIÓ 29/5/26 El 26/05/26 se recibe nueva documentación. ¡Se excede del monto estipulado! Debe calcular ENVIÓ DOCUMENTACIÓN PARA SER ANALIZADA. El 12/5/26 se envía correcciones técnicas y documentación gráfica y planillas modelo, para realizar nueva presentación. | AH16: 46241 | AI16: DIRECCION DE JURISDICCION LEGAL Y NOTARIAL | AL16: =$J16*0.5 -> 105000000 | AN16: =$J16*0.25 -> 52500000 | AP16: =$J16*0.25 -> 52500000 | AR16: =$J16*0 -> 0 | AU16: TRUE | BO16: =$AV16*0.5 -> 0 | BQ16: =$AV16*0.25 -> 0 | BS16: =$AV16*0.25 -> 0 | BU16: =$AV16*0 -> 0 | BX16: FALSE | CV16: A ESPERA de DOC.TÉCNICA | CX16: FALSE
A17: La Batea | B17: Cruz del Eje | C17: 0423-079110/026 | D17: 15 | E17: C | F17: IVÁN DENIS FARÍAS | G17: (3549) 46-5986 | H17: fariasivandenis@gmail.com | J17: 50000000 | M17: A ESPERA de DOC.TÉCNICA | N17: A ESPERA de DOC.TÉCNICA | O17: A ESPERA de DOC.TÉCNICA | P17: A ESPERA de DOC.TÉCNICA | Q17: A ESPERA de DOC.TÉCNICA | R17: A ESPERA de DOC.TÉCNICA | S17: A ESPERA de DOC.TÉCNICA | T17: A ESPERA de DOC.TÉCNICA | U17: A ESPERA de DOC.TÉCNICA | V17: A ESPERA de DOC.TÉCNICA | W17: A ESPERA de DOC.TÉCNICA | X17: A ESPERA de DOC.TÉCNICA | Y17: A ESPERA de DOC.TÉCNICA | Z17: A ESPERA de DOC.TÉCNICA | AA17: A ESPERA de DOC.TÉCNICA | AB17: A ESPERA de DOC.TÉCNICA | AC17: A ESPERA de DOC.TÉCNICA | AD17: A ESPERA de DOC.TÉCNICA | AE17: A ESPERA de DOC.TÉCNICA | AF17: RECHAZADO por M/C | AG17: 26/6/26: Silvia informa que la localidad NO quiere adherir al Convenio, NO CONTINUAR EL TRÀMITE. 24/6/26:Comunicación con el pres. comunal. Se envía Instructivo de la documentación legal y técnica requerida. El 8/5/26 se le envía documentación modelo para participar en el Programa. Presentó decumentación que está siendo estudiada. | AH17: 46126 | AI17: DIRECCION DE JURISDICCION DE REGULARIZACION DE OBRAS Y PROYECTOS | AL17: =$J17*0.5 -> 25000000 | AN17: =$J17*0.25 -> 12500000 | AP17: =$J17*0.25 -> 12500000 | AR17: =$J17*0 -> 0 | AU17: TRUE | BO17: =$AV17*0.5 -> 0 | BQ17: =$AV17*0.25 -> 0 | BS17: =$AV17*0.25 -> 0 | BU17: =$AV17*0 -> 0 | BX17: FALSE | CV17: A ESPERA de DOC.TÉCNICA | CX17: FALSE
A18: Tuclame | B18: Cruz del Eje | C18: 0423-079113/2026 | D18: 16 | E18: C | F18: GRACIELA DEL VALLE GONZÁLEZ | G18: (3549) 53-7628 | H18: gracieladelvallegonzalez20@gmail.com | I18: ingbracamontegustavo@gmail.com | J18: 200000000 | K18: 400 | M18: Completo OK | N18: Completo OK | O18: Completo OK | P18: Completo OK | Q18: Completo OK | R18: Completo OK | S18: Completo OK | T18: Completo OK | U18: Completo OK | V18: Completo OK | W18: Completo OK | X18: Completo OK | Y18: Completo OK | Z18: Completo OK | AA18: Completo OK | AB18: Completo OK | AC18: Completo OK | AD18: Completo OK | AE18: Completo OK | AF18: OBRA en EJECUCIÓN | AG18: 07/8/2026: Se pagò A.F. el 5/8/2026 05/8/2026: PASA A EONOMICO-FINANCIERO para pago de A.F. 04/8/2026: Envìan Certif. y Nota a Silvia. 04/8/2026: Se envìa Modelo de Cert. A.F. A completar por la comuna y presentar. COMPLETÓ documentación. Subió a Jurídico Con V°B°. EN LA PRIVADA DESDE 19/05/26 ENVIÓ LA DOCUMENTACIÓN. ESTÁS COMPLETA, SÓLO DEBE CORREGIR CRONOGRAMA DE INVERSIONES. COMPLETO. CON V°B° DE TÉCNICA | AH18: 46231 | AI18: DIRECCION DE JURISDICCION ECONOMICO, FINANCIERA Y DE ADMINISTRACION | AL18: =$J18*0.5 -> 100000000 | AM18: 46239 | AN18: =$J18*0.25 -> 50000000 | AP18: =$J18*0.25 -> 50000000 | AR18: =$J18*0 -> 0 | AT18: 04/9/2026: Comunicaciòn con la Pres. Com. el 2/9. Informa que la obra està avanzando. Se envìa Certificado Modelo al Ing. Bracamonte. 07/8/2026: Se pagò A.F. el 5/8/2026 | AU18: TRUE | AV18: 102000000 | AW18: 3 | AX18: 0135-045042/2026 | AY18: Completo OK | BF18: Completo OK | BG18: Completo OK | BH18: Completo OK | BI18: A corregir por M/C | BJ18: Completo OK | BM18: En CURSO en TÉCNICA | BN18: 04/9/2026: Se envìan por Email las Observaciones A corregir por la comuna. 26/8/2026: Comunicaciòn con la pres. comunal . Se solicita Email para enviar PLA. Observaciones- Se envìa Email . 24/8/26: Se llama a la Pres. Com. Sin respuesta. Se deja mensaje. | BO18: =$AV18*0.5 -> 51000000 | BQ18: =$AV18*0.25 -> 25500000 | BS18: =$AV18*0.25 -> 25500000 | BU18: =$AV18*0 -> 0 | BX18: TRUE | CV18: A ESPERA de DOC.TÉCNICA | CX18: FALSE
A19: Colonia Italiana | B19: Marcos Juárez | C19: 0423-079102/2026 | D19: 17 | E19: M | F19: ALEJANDRA SOLEDAD ITA | G19: (3468) 50-1628 | H19: alejandraita26@hotmail.com | J19: 80000000 | K19: 889 | M19: Completo OK | N19: Completo OK | O19: Completo OK | P19: Completo OK | Q19: Completo OK | R19: Completo OK | S19: Completo OK | T19: Completo OK | U19: Completo OK | V19: Completo OK | W19: Completo OK | X19: Completo OK | Y19: Completo OK | Z19: Completo OK | AA19: Completo OK | AB19: Completo OK | AC19: Completo OK | AD19: Completo OK | AE19: Completo OK | AF19: COMPLETO en TÉCNICA | AG19: 17/7/2026: PASA A LEGALES adjuntando la geolocalización requerida en DDJJ para prosecución del trámite. 30/6/2026: Expte. PASA A LEGALES 29/6/2026: Documentaciòn en orden para anexar al Expte. y dar curso. 29/6/2026: Documentaciòn en orden para anexar al Expte. y dar curso. 19/6/26: Deben completar y corregir. 18/06/2026 enviaron memoria y doc tecnica corregida segun obervaciones. P- 17-06-2026 Se envìan correg/completar: ( firma y sello del prof. en cada hoja grafic.+ falta perfil transversal de calzada aunque no tenga paq. estr. determinando mat. de relleno) + pto.6 no se enviò imagen, del CBU el enviado tiene imagen parcial cortada) P- 11-06-2026 TEC.:( Faltan Memoria + Planim. con cotas + todos los detalles cortes + Cronogr. de Avances en 6 mese + todo sellado y firm x profes.) 11/6/26: Se solicita nuevamente la documentaciòn tècnica faltante. La arq. completará. P- 08-06-2026 - Pto. Nª 2 Falta Sello y firma del Tesorero o esta borroza Secr. tesor. + Pto. Nª 4 ( Faltan cotas grales de cada manz. en la planialtim. + cortes transv. + detalles + Planilla de avances cronograma de obra + Ubica y Memoria) El 30/04/26 vino la intendente Alejandra Ita a consultar por el Programa. Pregunta por el descuento por copa posterior. | AH19: 46223 | AI19: DIRECCION DE JURISDICCION LEGAL Y NOTARIAL | AJ19: 76420.22 | AL19: =$J19*0.5 -> 40000000 | AN19: =$J19*0.25 -> 20000000 | AP19: =$J19*0.25 -> 20000000 | AR19: =$J19*0 -> 0 | AU19: TRUE | BO19: =$AV19*0.5 -> 0 | BQ19: =$AV19*0.25 -> 0 | BS19: =$AV19*0.25 -> 0 | BU19: =$AV19*0 -> 0 | BX19: FALSE | CV19: A ESPERA de DOC.TÉCNICA | CX19: FALSE
A20: Los Hornillos | B20: San Javier | C20: 0423-079117/2026 | D20: 18 | E20: C | F20: CAROLINA CABALLERO | G20: (3544) 41-0108 | H20: loshornilloscomuna@gmail.com comunalh@gmail.com | I20: Arq. Adriàn Heredia (3544) 434500 Noelia Del Aguila (3544) 40-6139 | J20: 150000000 | K20: 913.3 | L20: 534 | M20: Completo OK | N20: Completo OK | O20: Completo OK | P20: Completo OK | Q20: Completo OK | R20: Completo OK | S20: Completo OK | T20: Completo OK | U20: Completo OK | V20: Completo OK | W20: Completo OK | X20: Completo OK | Y20: Completo OK | Z20: Completo OK | AA20: Completo OK | AB20: Completo OK | AC20: Completo OK | AD20: Completo OK | AE20: Completo OK | AF20: APROBADO por TRIB.C | AG20: 07/8/2026: PASA A ECON. FINANC. Cert. A.F. para pago. 05/8/2026: Presentan Cert. A.F. Con errores A corregir por la comuna. 29/7/2026: Se envìa Modelo de Cert. A.F. A completar por la comuna y presentar. 28/7/2026: Se deja mensaje a la pres. com. para enviales modelos de Nota y Cert. A.F. 8/6/26 PASA DE AREA TECNICA A LEGALES // P- 04-06-2026 - Se tilda al Pto. Nª 4 (para que se modifique la unidad del cordon cun. a ml en el Comp Metrico) EL 28/04/26 SE LE ENVÍA LOS REQUISITOS, VA A ENVIAR DOCUMENTACIÓNP- 3/6/2026 Se envió documentacion completa digital por email y lo recibiò Jurídica. EN CONDICIONES. EN LA PRIVADA DESDE 28/05/26 El 26/05/2026 se envía toda la Documentación completa con las correcciones ya corregidas por parte de la Comuna. El 26/5/26 se envía a Jurídico todo completo El 20/05/26 se aprueba la parte técnica, sube a jurídico. El 7/5/26 se envía escaneo de docum. Técnica para corregir, también se envía modelo de avance de obra por 6 meses. El 7/5/26 se solicitó corregir el punto 4 (doc. técnica) y se solicita cambio y corrección de Nota inicial. Presentó el 30/04/26 toda la documentación. El cómputo y presupuesto se pasa en $240.991-Se pide que se corrija. | AH20: 46217 | AI20: VOCALIA POR LA MINORIA - TRIBUNAL DE CUENTAS | AL20: =$J20*0.5 -> 75000000 | AN20: =$J20*0.25 -> 37500000 | AP20: =$J20*0.25 -> 37500000 | AR20: =$J20*0 -> 0 | AU20: TRUE | BO20: =$AV20*0.5 -> 0 | BQ20: =$AV20*0.25 -> 0 | BS20: =$AV20*0.25 -> 0 | BU20: =$AV20*0 -> 0 | BX20: FALSE | CV20: A ESPERA de DOC.TÉCNICA | CX20: FALSE
A21: General Roca | B21: Marcos Juárez | C21: 0423-079133/2026 | D21: 19 | E21: M | F21: Iser Francisco Facundo | G21: (3472) 63-7614 | H21: iserfrancisco92@gmail.com | I21: mrcostamagna@hotmail.com | J21: 240000000 | K21: 2600 | M21: Completo OK | N21: Completo OK | O21: Completo OK | P21: Completo OK | Q21: Completo OK | R21: Completo OK | S21: Completo OK | T21: Completo OK | U21: Completo OK | V21: Completo OK | W21: Completo OK | X21: Completo OK | Y21: Completo OK | Z21: A ESPERA de DOC.TÉCNICA | AA21: Completo OK | AB21: Completo OK | AC21: Completo OK | AD21: Completo OK | AE21: Completo OK | AF21: OBRA en EJECUCIÓN | AG21: 29/7/2026: PASA A Economico para pago de Cert. A. F. 16/7/2026: Se envían Modelos de NOTA y CERT. cobro de ANT. FINANCIERO y dar inicio a la Obra. Completó documentación y se elevó a jurídica para su estudio. COMPLETO. CON V°B° DE TÉCNICA. | AH21: 46217 | AI21: AREA COORDINACION ADMINISTRATIVA | AL21: =$J21*0.5 -> 120000000 | AM21: 46233 | AN21: =$J21*0.25 -> 60000000 | AP21: =$J21*0.25 -> 60000000 | AR21: =$J21*0 -> 0 | AT21: 04/9/2026: El arq. solicita explicaciòn para la elaboraciòn del certificado. Envìa fotografìas de la obra. 01/9/2026: Envìa certificado y se lo devuelve con las observaciones A Corregir. 01/9/2026: Se pregunta al arq. si pudo hacer el Certificado, si tiene alguna consulta respecto a la elaboración del mismo. Envìa borrador A corregir. 26/8/2026: Se envìa modelo de Certificaciòn al arquitecto para que prepare el Certificado de avance (40%) 19/8/2026: El Arq. de la localidad se comunica solicitando informaciòn respecto a la Certificaciòn. 07/8/2026: Se pagò A.F. el 30/7/2026 19/8/2026: Comunicaciòn telefònica con el Int. Informa que ya tienen ejecutadas varias cuadras de cordòn cuneta. | AU21: TRUE | BO21: =$AV21*0.5 -> 0 | BQ21: =$AV21*0.25 -> 0 | BS21: =$AV21*0.25 -> 0 | BU21: =$AV21*0 -> 0 | BX21: FALSE | CV21: A ESPERA de DOC.TÉCNICA | CX21: FALSE
A22: Rosales | B22: Presidente Roque Sáenz Peña | C22: 0423-079114/2026 | D22: 20 | E22: M | F22: ARIEL GUSTAVO PANICHELLI | G22: (3385) 43-0090 | H22: munirosales.cba@gmail.com | I22: Perezrodrigomiguel@gmail.com | J22: 100000000 | M22: Completo OK | N22: Completo OK | O22: Completo OK | P22: A corregir por M/C | Q22: A corregir por M/C | R22: A corregir por M/C | S22: A corregir por M/C | T22: A corregir por M/C | U22: A corregir por M/C | V22: A corregir por M/C | W22: A corregir por M/C | X22: A corregir por M/C | Y22: A corregir por M/C | Z22: A corregir por M/C | AA22: Completo OK | AB22: Completo OK | AC22: Completo OK | AD22: Completo OK | AE22: Completo OK | AF22: En CURSO en TÉCNICA | AG22: 04/9/2026: Se re envian Observaciones p/corregir x mail a intend. + prof. + infra. 20/08/2026 Se solicita por Whatss, actualiz. doc. al ing. Rodrigues -RTAS.: ....... 04/8/2026: Se reitera el pedido de documetnaciòn al ing. encargado. 28/7/2026: Respuesta: "estamos a la espera de que el ingeniero pueda realizar las observaciones. Apenas lo tengamos se lo pasamos." 27/7/2026: se consulto por email el estado de las observaciones al legajo técnico. 16/7/2026: El municipio corrige la doc. legal pero falta que corrija la doc. tècnica. 15/7/2026: Se envían al municipio y profesional, las Observaciones a corregir. 07/7/2026: Envìan contacto y correo electrònico del ing. a cargo de la obra. 24/6/26: Se enviò Instructivo .El 8/05/26 se envió documentación modelo para participar. El 11/ envió documentación a analizar | AH22: 46126 | AI22: DIRECCION DE JURISDICCION DE REGULARIZACION DE OBRAS Y PROYECTOS | AL22: =$J22*0.5 -> 50000000 | AN22: =$J22*0.25 -> 25000000 | AP22: =$J22*0.25 -> 25000000 | AR22: =$J22*0 -> 0 | AU22: TRUE | BO22: =$AV22*0.5 -> 0 | BQ22: =$AV22*0.25 -> 0 | BS22: =$AV22*0.25 -> 0 | BU22: =$AV22*0 -> 0 | BX22: FALSE | CV22: A ESPERA de DOC.TÉCNICA | CX22: FALSE
A23: La Cesira | B23: Presidente Roque Sáenz Peña | C23: 0423-079809/2026 | D23: 21 | E23: M | F23: GUILLERMO LEGORBURU | G23: (3382) 672961 | H23: guillermolegorburu@gmail.com | I23: municesira@gmail | J23: 200000000 | K23: 260 | L23: 3440 | M23: Completo OK | N23: Completo OK | O23: Completo OK | P23: Completo OK | Q23: Completo OK | R23: Completo OK | S23: Completo OK | T23: Completo OK | U23: Completo OK | V23: Completo OK | W23: Completo OK | X23: Completo OK | Y23: Completo OK | Z23: Completo OK | AA23: Completo OK | AB23: Completo OK | AC23: Completo OK | AD23: Completo OK | AE23: Completo OK | AF23: OBRA en EJECUCIÓN | AG23: 07/8/2026: Se pagò A.F. el 27/7/2026 20/7/2026: PASA A ECON- FINANC. el CERT. A.F. presentado por localidad. 15/7/2026: Se envió a la comuna Modelos de NOTA y CERT. ANT. FINANCIERO para DAR inicio a la Obra. 8/6/26 PASA DE AREA TECNICA A LEGALES //3/6/2026 Se envió documentacion completa digital por email y lo recibiò Jurídica. SUBIDA EL 29-05-26 28/5/26, debe cambiar la nota de pedido a la contaduría Gral. y no se ve firma en la declaracion jurada. El 27/05/26 presentó toda la documentación (completa la parte técnica). Debe cambiar la Nota de inicio, corregir Monto y Plazo de Obra. LISTO, Pero ahora, El 27/05/2026 el municipio presentó el total de la información, se solicita que cambie la Nota inicial, con el momto de obra y el plazo de la misma.. EN CONDICIONES Se presentó nuevo Expte. con nuevo monto asignado - Pasó a $200.000.000. | AH23: 46217 | AI23: DIRECCION DE JURISDICCION DE REGULARIZACION DE OBRAS Y PROYECTOS | AL23: =$J23*0.5 -> 100000000 | AM23: 46230 | AN23: =$J23*0.25 -> 50000000 | AP23: =$J23*0.25 -> 50000000 | AR23: =$J23*0 -> 0 | AT23: 19/8/2026: Comunicaciòn telefònica con el Int. Informa que ya compraron los materiales. Que estàn empezando con la apertura del cajero porque tuvieron varios dìas de lluvia. | AU23: TRUE | BO23: =$AV23*0.5 -> 0 | BQ23: =$AV23*0.25 -> 0 | BS23: =$AV23*0.25 -> 0 | BU23: =$AV23*0 -> 0 | BX23: FALSE | CV23: A ESPERA de DOC.TÉCNICA | CX23: FALSE
A24: Las Perdices | B24: Tercero Arriba | D24: 22 | E24: M | F24: SERGIO AVALIS | G24: (3534) 234615 | J24: _ | M24: A ESPERA de DOC.TÉCNICA | N24: A ESPERA de DOC.TÉCNICA | O24: A ESPERA de DOC.TÉCNICA | P24: A ESPERA de DOC.TÉCNICA | Q24: A ESPERA de DOC.TÉCNICA | R24: A ESPERA de DOC.TÉCNICA | S24: A ESPERA de DOC.TÉCNICA | T24: A ESPERA de DOC.TÉCNICA | U24: A ESPERA de DOC.TÉCNICA | V24: A ESPERA de DOC.TÉCNICA | W24: A ESPERA de DOC.TÉCNICA | X24: A ESPERA de DOC.TÉCNICA | Y24: A ESPERA de DOC.TÉCNICA | Z24: A ESPERA de DOC.TÉCNICA | AA24: A ESPERA de DOC.TÉCNICA | AB24: A ESPERA de DOC.TÉCNICA | AC24: A ESPERA de DOC.TÉCNICA | AD24: A ESPERA de DOC.TÉCNICA | AE24: A ESPERA de DOC.TÉCNICA | AF24: SIN AUTORIZACION MIN.GOB | AG24: 20-7-2026: Ingresa nota GOBDIGI -0541650111-426 pero sin Autorizaciòn de Gobierno aùn.25-6-26: Comunicación con int. Se espera autirización Ministerio Gobierno. El 08/05/26 se realia comunicación telefónica con el intendente. Va a enviar su documentación. SIN EXPEDIENTE. | AL24: =$J24*0.5 -> #VALUE! | AN24: =$J24*0.25 -> #VALUE! | AP24: =$J24*0.25 -> #VALUE! | AR24: =$J24*0 -> #VALUE! | AU24: TRUE | BO24: =$AV24*0.5 -> 0 | BQ24: =$AV24*0.25 -> 0 | BS24: =$AV24*0.25 -> 0 | BU24: =$AV24*0 -> 0 | BX24: FALSE | CV24: A ESPERA de DOC.TÉCNICA | CX24: FALSE
A25: Colonia Barge | B25: Marcos Juárez | C25: 0423-079784/2026 | D25: 23 | E25: M | F25: SERGIO RODRIGUEZ | G25: (3468) 569782 | H25: Mnina@ccbarge.gob.ar /// nvrodriguez@ccbarge.gob.ar | I25: emanuelmartinatto@gmail.com | J25: 50000000 | M25: A ESPERA de DOC.TÉCNICA | N25: A ESPERA de DOC.TÉCNICA | O25: A ESPERA de DOC.TÉCNICA | P25: A ESPERA de DOC.TÉCNICA | Q25: A ESPERA de DOC.TÉCNICA | R25: A ESPERA de DOC.TÉCNICA | S25: A ESPERA de DOC.TÉCNICA | T25: A ESPERA de DOC.TÉCNICA | U25: A ESPERA de DOC.TÉCNICA | V25: A ESPERA de DOC.TÉCNICA | W25: A ESPERA de DOC.TÉCNICA | X25: A ESPERA de DOC.TÉCNICA | Y25: A ESPERA de DOC.TÉCNICA | Z25: A ESPERA de DOC.TÉCNICA | AA25: A ESPERA de DOC.TÉCNICA | AB25: A ESPERA de DOC.TÉCNICA | AC25: A ESPERA de DOC.TÉCNICA | AD25: A ESPERA de DOC.TÉCNICA | AE25: A ESPERA de DOC.TÉCNICA | AF25: A ESPERA de DOC.TÉCNICA | AG25: 20/8/2026: Se envía por Email, el Instructivo con el cambio de denominación. (Hoy Secretaría) 05/8/2026: Comunicaciòn con la comuna para saber si pudieron avanzar con la documentaciòn. 24/6/26: Comunicaciòn con la comuna. Se enviò Instructivo. El 11/5/26 se logra comunicación con municipalidad. Se pasa por whatsapp la documentación modelo | AH25: 46150 | AI25: DIRECCION DE JURISDICCION DE REGULARIZACION DE OBRAS Y PROYECTOS | AL25: =$J25*0.5 -> 25000000 | AN25: =$J25*0.25 -> 12500000 | AP25: =$J25*0.25 -> 12500000 | AR25: =$J25*0 -> 0 | AU25: TRUE | BO25: =$AV25*0.5 -> 0 | BQ25: =$AV25*0.25 -> 0 | BS25: =$AV25*0.25 -> 0 | BU25: =$AV25*0 -> 0 | BX25: FALSE | CV25: A ESPERA de DOC.TÉCNICA | CX25: FALSE
A26: Saira | B26: Marcos Juárez | C26: 0423-079781/2026 | D26: 24 | E26: M | F26: EDGAR JORDÁN | G26: (3472) 502676 | H26: edgarfyordan@hotmail.com | I26: caraimar@hotmail.com | J26: 150000000 | L26: 2160 | M26: Completo OK | N26: Completo OK | O26: Completo OK | P26: Completo OK | Q26: Completo OK | R26: Completo OK | S26: Completo OK | T26: Completo OK | U26: Completo OK | V26: Completo OK | W26: Completo OK | X26: A ESPERA de DOC.TÉCNICA | Y26: A ESPERA de DOC.TÉCNICA | Z26: Completo OK | AA26: Completo OK | AB26: Completo OK | AC26: Completo OK | AD26: Completo OK | AE26: Completo OK | AF26: COMPLETO en TÉCNICA | AG26: 26/8/2026: Se Recibe mail con anexo A pero la solicitud es por el ptol 9 A.A. C del int., por lo que se vuelve a enviar por whats informando dicho error a corregir 26/8/2026: Se avisa por whatss a la secr. municip. que enviaron solo el A.P. de Autoridades y NO la doc. A.A. del Cargo 25/8/2026: Avisa Jurìdica que falta Acta de A. C. del Intend. - Se informa x whatss a la int. responde que ya fue env. antes 21/8/2026: PASA A LEGALES para prosecuciòn del tràmite. 19/8/2026: Se solicita nos envien los 3 PDF incluyendo en el A. Legal el Acta de Proclam. 18/8/2026: Doc. Completa, Se recibe Acta de Aceptaciòn de Cargo Intende. 14/08/2026 Se envia Observac. a Completar por Mail al prof. e infra (Acta de Acept. Cargo Intend.) 03/08/2026 Avisa Legales que falta Acta de Acept. Cargo Intend. 30/7/2026: Se recibe Documentaciòn Completa 29/7/2026: Se enviò Planilla para completam. al intend. e Infraest. carecemos por el mto. del mail del prof. 29/7/2026: Se recibe completam. por mail 22/7/2026: Se enviaron por Email Observaciones A corregir por M-C 16/7/2026: Presentan documentaciòn en evaluaciòn legal y tècnica. 22/6/26: Se envìa Instructivo. 12/6/26: Se envìa Modelos de doc. tecnica y se avisa que en breve se enviarà el instructivo total del Programa. 10/6/26: Comunicaciòn con municipio para enviar Instructivo de Documentaciòn A presentar. El 11/5/26 se logra comunicación con municipalidad. Se pasa por whatsapp la documentación modelo. Envió documentación pero pide para PAVIMENTO | AH26: 46254 | AI26: AREA COORDINACION ADMINISTRATIVA | AL26: =$J26*0.5 -> 75000000 | AN26: =$J26*0.25 -> 37500000 | AP26: =$J26*0.25 -> 37500000 | AR26: =$J26*0 -> 0 | AU26: TRUE | BM26: En CURSO en TÉCNICA | BN26: 02/9/2026: Se envìa Instructivo por Email al int. | BO26: =$AV26*0.5 -> 0 | BQ26: =$AV26*0.25 -> 0 | BS26: =$AV26*0.25 -> 0 | BU26: =$AV26*0 -> 0 | BX26: TRUE | CV26: A ESPERA de DOC.TÉCNICA | CX26: FALSE
A27: Camilo Aldao | B27: Marcos Juárez | C27: 0423-079782/2026 | D27: 25 | E27: M | F27: MARIO DOMINGO BACELLI | G27: (3468) 644516 | H27: munca@nodosud.com.ar munca@futurnet.com.ar mariobacelli@hotmail.com | I27: ARQ. GISELA MIRIANI (3468)51-6292 | J27: 100000000 | L27: 3600 | M27: Completo OK | N27: Completo OK | O27: Completo OK | P27: Completo OK | Q27: Completo OK | R27: Completo OK | S27: Completo OK | T27: Completo OK | U27: Completo OK | V27: Completo OK | W27: Completo OK | X27: A ESPERA de DOC.TÉCNICA | Y27: A ESPERA de DOC.TÉCNICA | Z27: Completo OK | AA27: Completo OK | AB27: Completo OK | AC27: Completo OK | AD27: Completo OK | AE27: Completo OK | AF27: COMPLETO en TÉCNICA | AG27: 30/7/2026: Se recibe Documentaciòn Completa 29/7/2026: Se enviò Planilla para completam. al intend. e Infraest. carecemos por el mto. del mail del prof. 29/7/2026: Se recibe completam. por mail 22/7/2026: Se enviaron por Email Observaciones A corregir por M-C 16/7/2026: Presentan documentaciòn en evaluaciòn legal y tècnica. 22/6/26: Se envìa Instructivo. 12/6/26: Se envìa Modelos de doc. tecnica y se avisa que en breve se enviarà el instructivo total del Programa. 10/6/26: Comunicaciòn con municipio para enviar Instructivo de Documentaciòn A presentar. El 11/5/26 se logra comunicación con municipalidad. Se pasa por whatsapp la documentación modelo. Envió documentación pero pide para PAVIMENTO | AH27: 46223 | AI27: DIRECCION DE JURISDICCION LEGAL Y NOTARIAL | AK27: 18904 | AL27: =$J27*0.5 -> 50000000 | AN27: =$J27*0.25 -> 25000000 | AP27: =$J27*0.25 -> 25000000 | AR27: =$J27*0 -> 0 | AU27: TRUE | BO27: =$AV27*0.5 -> 0 | BQ27: =$AV27*0.25 -> 0 | BS27: =$AV27*0.25 -> 0 | BU27: =$AV27*0 -> 0 | BX27: FALSE | CV27: A ESPERA de DOC.TÉCNICA | CX27: FALSE
A28: Arias | B28: Marcos Juárez | C28: 0423-079785/2026 | D28: 26 | E28: M | F28: NÉSTOR DEFAGOT DIAZ | G28: (3468) 512149 | H28: njdefagot@hotmail.com.ar | I28: ing.jmaldonado@gmail.com | J28: 100000000 | L28: 920.9 | M28: Completo OK | N28: Completo OK | O28: Completo OK | P28: Completo OK | Q28: Completo OK | R28: Completo OK | S28: Completo OK | T28: Completo OK | U28: Completo OK | V28: Completo OK | W28: Completo OK | X28: Completo OK | Y28: Completo OK | Z28: Completo OK | AA28: Completo OK | AB28: Completo OK | AC28: Completo OK | AD28: Completo OK | AE28: Completo OK | AF28: COMPLETO en TÉCNICA | AG28: 02/9/2026: PASA A LEGALES para prosecuciòn del tràmite. 01/9/2026: Documentaciòn completa, lista para pasar a legales. 31/8/2026: Damos aviso al int. que re envie toda la doc en una carpeta con los 3 pdf RTA.: Perfecto,a la brevedad lo estamos enviando 21/8/2026: Avisa el ing. que nos enviò por mail la doc. pero los 3 ult. pl. falta la firma del int. y tambien enviò a la municip. para que firmen y nos lo re envien 21/8/2026: Se envian Observaciones a corregir x mail al intend. + ing. + infra. 07/08/2026 Se recibe doc. 05/8/2026: Se envian por Email Observaciones a corregir por intend. + profes. + Infra. Se recibiò document. 29/7/2026: Se envìa msj al ing. ante cualquier necesidad s/la doc. a completar, habiendose este profes. acercado semanas antes, a ntra. repartic. p/aclarar completam. 08/7/2026: Se enviaron observaciones (Email) al municipio y profesional responsable para corregir.. 25-06-2026 - Se enviaron imagenes de las correcc. y re envio del instructivo p/ whats al ing. 24-06-2026 - Se enviaron correcciones por whats al ing. 23/6/2026: la nota de pedido tiene un valor mayor cotizado, 4to parrafo del considerando y art, 4,debe decir:seis meses (6) a partir de efectivizado el primer desembolso, nota a contaduria completar, falta DDJJ y acta de aceptacion del cargo, 22/6/26: Comunicaciòn con Int. y profesional para corregir documentaciòn conforme al instructivo. 19/6/26: Comunicación con Municipio. Docuemtación En Evaluación. 4/6/26:Presentan documentaciòn por Cidi- En Evaluación TÉCNICA - El 11/5/26 se logra comunicación con municipalidad. Se pasa por whatsapp la documentación modelo | AH28: 46150 | AI28: DIRECCION DE JURISDICCION DE REGULARIZACION DE OBRAS Y PROYECTOS | AJ28: 51000 | AK28: 43000 | AL28: =$J28*0.5 -> 50000000 | AN28: =$J28*0.25 -> 25000000 | AP28: =$J28*0.25 -> 25000000 | AR28: =$J28*0 -> 0 | AU28: TRUE | BO28: =$AV28*0.5 -> 0 | BQ28: =$AV28*0.25 -> 0 | BS28: =$AV28*0.25 -> 0 | BU28: =$AV28*0 -> 0 | BX28: FALSE | CV28: A ESPERA de DOC.TÉCNICA | CX28: FALSE
A29: General Baldissera | B29: Marcos Juárez | C29: 0423-079783/2026 | D29: 27 | E29: M | F29: LUCAS PERASSI | G29: (3468) 512117 | H29: munigbaldissera@gmail.com | I29: ebigi@hotmail.com | J29: 100000000 | L29: 1953 | M29: Completo OK | N29: Completo OK | O29: Completo OK | P29: A corregir por M/C | Q29: Completo OK | R29: Completo OK | S29: A corregir por M/C | T29: A corregir por M/C | U29: A corregir por M/C | V29: A corregir por M/C | W29: Completo OK | X29: A ESPERA de DOC.TÉCNICA | Y29: A ESPERA de DOC.TÉCNICA | Z29: Completo OK | AA29: Completo OK | AB29: Completo OK | AC29: Completo OK | AD29: Completo OK | AE29: Completo OK | AF29: En CURSO en TÉCNICA | AG29: 27/8/2026: Se envian Observaciones a corregir x mail al intend.+ profes. + infra. 26/8/2026: Se recibe doc. 24/8/2026: Se re envian Observac. para corregir por Mail al int + profes + Infra 20/8/2026: Se envìa mensaje al Int. preguntando si pudieron corregir la documentaciòn para presentar. 05/8/2026: Se envían por Email Observaciones a corregir por el municipio. 24/6/26: Se envía Instructivo de documentación legal y técnica requerida. 22/6/26: Se solicitan correos electrònicos del municipio y profesional a cargo. El 11/5/26 se logra comunicación con municipalidad. Se pasa por whatsapp la documentación modelo | AH29: 46150 | AI29: DIRECCION DE JURISDICCION DE REGULARIZACION DE OBRAS Y PROYECTOS | AL29: =$J29*0.5 -> 50000000 | AN29: =$J29*0.25 -> 25000000 | AP29: =$J29*0.25 -> 25000000 | AR29: =$J29*0 -> 0 | AU29: TRUE | BO29: =$AV29*0.5 -> 0 | BQ29: =$AV29*0.25 -> 0 | BS29: =$AV29*0.25 -> 0 | BU29: =$AV29*0 -> 0 | BX29: FALSE | CV29: A ESPERA de DOC.TÉCNICA | CX29: FALSE
A30: Matorrales | B30: Río Segundo | C30: 0423-079944/2026 | D30: 28 | E30: M | F30: FRANCO CINGOLANI | G30: (3573) 513735 | H30: Munimatorrales@hotmail.com | I30: germangarino@gmail.com | J30: 80000000 | K30: 1450 | M30: Completo OK | N30: Completo OK | O30: Completo OK | P30: A corregir por M/C | Q30: Completo OK | R30: Completo OK | S30: A corregir por M/C | T30: A corregir por M/C | U30: Completo OK | V30: A corregir por M/C | W30: Completo OK | X30: Completo OK | Y30: A corregir por M/C | Z30: A ESPERA de DOC.TÉCNICA | AA30: Completo OK | AB30: Completo OK | AC30: Completo OK | AD30: Completo OK | AE30: Completo OK | AF30: A ESPERA de DOC.TÉCNICA | AG30: 01/9/2026: Se envìan Observaciones a corregir por mail al Munic + profes. + Infra 31/8/2026: Avisa el Secret. de Gob. que enviaron la doc. 20/8/2026: Se envía por Email, el Instructivo con el cambio de denominación. (Hoy Secretaría) 05/8/2026: Comunicaciòn con M/C enviando correo electrònico. 24/7/2026: Comunicaciòn con el ing. a cargo , responde lo siguiente: "me falta aún calculo en unos días tenerlo listo" 23/7/2026: Comunicaciòn con el municipio, se solicita informen si pudieron preparar la documentaciòn. 07/7/2026: Se solicita verifiquen el correo de la municipalidad porque NO se puede entregar. El municipio dice que enviaron con error. Se envìa nuevamente el Instructivo al correo correcto. 01/7/2026: Se envìa Instructivo de la documentaciòn legal y tècnica requerida por el Programa. 22/6/26: Comunicaciòn con el municipio para enviar Instructivo. El 26/05/2026 se envía WhatsApp a intendente. El 27/05/2026 se logra la comunicación telefónica. | AH30: 46168 | AI30: DIRECCION DE JURISDICCION DE REGULARIZACION DE OBRAS Y PROYECTOS | AL30: =$J30*0.5 -> 40000000 | AN30: =$J30*0.25 -> 20000000 | AP30: =$J30*0.25 -> 20000000 | AR30: =$J30*0 -> 0 | AU30: TRUE | BO30: =$AV30*0.5 -> 0 | BQ30: =$AV30*0.25 -> 0 | BS30: =$AV30*0.25 -> 0 | BU30: =$AV30*0 -> 0 | BX30: FALSE | CV30: A ESPERA de DOC.TÉCNICA | CX30: FALSE
A31: Embalse | B31: Calamuchita | C31: 0423-079932/2026 | D31: 29 | E31: M | F31: MARIO RIVAROLA | G31: (3571) 526135 | H31: crayanes@gmail.com | I31: jjorgeaquiroga@gmail.com | J31: 200000000 | L31: 5500 | M31: Completo OK | N31: Completo OK | O31: Completo OK | P31: Completo OK | Q31: Completo OK | R31: Completo OK | S31: Completo OK | T31: Completo OK | U31: Completo OK | V31: Completo OK | W31: Completo OK | X31: A ESPERA de DOC.TÉCNICA | Y31: A ESPERA de DOC.TÉCNICA | Z31: Completo OK | AA31: Completo OK | AB31: Completo OK | AC31: Completo OK | AD31: Completo OK | AE31: Completo OK | AF31: COMPLETO en TÉCNICA | AG31: 20/7/2026: PASA A LEGALES para prosecuciòn del tràmite. 16/7/2026: Envìan nuevamente documentaciòn. En evaluaciòn legal y tècnica. 15/7/2026: Nos contactamos con el contador para explicar bien cómo deben presentar la documentación. 15/7/2026: Se envía mensaje al contador Nahuel...se espera respuesta. 13/7/2026: Se solicita contacto de contador municipio (a cargo del tràmite). 01/7/2026: Se enviaron al municipio y profesional a cargo, las Observaciones A corregir. 01/7/2026: Comunicación con el municipio, presentan documentaciòn A evaluar. 29/6/2026: Comunicaciòn con la Contadora del municipio. Se solicitò la documentaciòn y dijeron que Hoy presentaban. Se aguarda la misma. 19/6/26: Se envía Instructivo de documentación legal y técnica requerida. 11/6/26: Se envìa nuevamente el instructivo Area Tècnica para que corrijan documentaciòn presentada. 10/6/26: Comunicaciòn con municipio para enviar Instructivo de Documentaciòn A presentar. P- Corregir a: $ 200.000.000- en todo lugar donde se denomine el Monto de Obra. + Agregar (cotas) a la Planimetria El 26/05/2026 nos comunicamos telefónicamente con intendente. Se le envía WhatsApp documentación modelo. El 27/05/2026 se recibe documentación de parte de la Municipalidad. El 28/05/26 se envían las correcciones de la parte técnica | AH31: 46224 | AI31: DIRECCION DE JURISDICCION LEGAL Y NOTARIAL | AL31: =$J31*0.5 -> 100000000 | AN31: =$J31*0.25 -> 50000000 | AP31: =$J31*0.25 -> 50000000 | AR31: =$J31*0 -> 0 | AU31: TRUE | BO31: =$AV31*0.5 -> 0 | BQ31: =$AV31*0.25 -> 0 | BS31: =$AV31*0.25 -> 0 | BU31: =$AV31*0 -> 0 | BX31: FALSE | CV31: A ESPERA de DOC.TÉCNICA | CX31: FALSE
